Workbook

Sheet Resumen
A1: Base de prospectos B2B – Valparaíso / San Antonio / Casablanca / Curacaví
A2: Fuente: 22 exportaciones de Google Maps (mapsscraper.ai, plan gratuito) del 05-10-2026. Totales calculados con fórmulas sobre la hoja Base_limpia.
A4: Indicador | B4: Valor
A5: Filas brutas (sin pies de página) | B5: 296 | C5: Dato fijo: 344 filas leídas − 48 filas de pie de página del scraper
A6: Empresas únicas | B6: =COUNTA(Base_limpia!$A$2:$A$196) -> 195
A7: Con teléfono | B7: =COUNTIF(Base_limpia!$J$2:$J$196,"+*") -> 144
A8: Con web propia | B8: =COUNTIF(Base_limpia!$N$2:$N$196,"Sí") -> 109
A9: Score de completitud promedio | B9: =ROUND(AVERAGE(Base_limpia!$I$2:$I$196),1) -> 66.7
A11: Relevancia | B11: Empresas | C11: % del total
A12: Alta | B12: =COUNTIF(Base_limpia!$G$2:$G$196,A12) -> 126 | C12: =B12/$B$6 -> 0.64615385
A13: Media | B13: =COUNTIF(Base_limpia!$G$2:$G$196,A13) -> 44 | C13: =B13/$B$6 -> 0.22564103
A14: Baja | B14: =COUNTIF(Base_limpia!$G$2:$G$196,A14) -> 19 | C14: =B14/$B$6 -> 0.097435897
A15: Descartar | B15: =COUNTIF(Base_limpia!$G$2:$G$196,A15) -> 6 | C15: =B15/$B$6 -> 0.030769231
A17: Segmento | B17: Total | C17: Alta | D17: Media | E17: Score promedio
A18: Transporte de carga | B18: =COUNTIF(Base_limpia!$F$2:$F$196,A18) -> 57 | C18: =COUNTIFS(Base_limpia!$F$2:$F$196,A18,Base_limpia!$G$2:$G$196,"Alta") -> 39 | D18: =COUNTIFS(Base_limpia!$F$2:$F$196,A18,Base_limpia!$G$2:$G$196,"Media") -> 16 | E18: =IFERROR(ROUND(AVERAGEIF(Base_limpia!$F$2:$F$196,A18,Base_limpia!$I$2:$I$196),1),0) -> 57.5
A19: Maquinaria / Industrial | B19: =COUNTIF(Base_limpia!$F$2:$F$196,A19) -> 34 | C19: =COUNTIFS(Base_limpia!$F$2:$F$196,A19,Base_limpia!$G$2:$G$196,"Alta") -> 26 | D19: =COUNTIFS(Base_limpia!$F$2:$F$196,A19,Base_limpia!$G$2:$G$196,"Media") -> 5 | E19: =IFERROR(ROUND(AVERAGEIF(Base_limpia!$F$2:$F$196,A19,Base_limpia!$I$2:$I$196),1),0) -> 78.2
A20: Logística / Almacenaje | B20: =COUNTIF(Base_limpia!$F$2:$F$196,A20) -> 30 | C20: =COUNTIFS(Base_limpia!$F$2:$F$196,A20,Base_limpia!$G$2:$G$196,"Alta") -> 17 | D20: =COUNTIFS(Base_limpia!$F$2:$F$196,A20,Base_limpia!$G$2:$G$196,"Media") -> 8 | E20: =IFERROR(ROUND(AVERAGEIF(Base_limpia!$F$2:$F$196,A20,Base_limpia!$I$2:$I$196),1),0) -> 54.2
A21: Frío / Alimentos | B21: =COUNTIF(Base_limpia!$F$2:$F$196,A21) -> 22 | C21: =COUNTIFS(Base_limpia!$F$2:$F$196,A21,Base_limpia!$G$2:$G$196,"Alta") -> 7 | D21: =COUNTIFS(Base_limpia!$F$2:$F$196,A21,Base_limpia!$G$2:$G$196,"Media") -> 8 | E21: =IFERROR(ROUND(AVERAGEIF(Base_limpia!$F$2:$F$196,A21,Base_limpia!$I$2:$I$196),1),0) -> 83.9
A22: Otros / Servicios empresariales | B22: =COUNTIF(Base_limpia!$F$2:$F$196,A22) -> 20 | C22: =COUNTIFS(Base_limpia!$F$2:$F$196,A22,Base_limpia!$G$2:$G$196,"Alta") -> 14 | D22: =COUNTIFS(Base_limpia!$F$2:$F$196,A22,Base_limpia!$G$2:$G$196,"Media") -> 3 | E22: =IFERROR(ROUND(AVERAGEIF(Base_limpia!$F$2:$F$196,A22,Base_limpia!$I$2:$I$196),1),0) -> 67.5
A23: Vitivinícola / Agrícola | B23: =COUNTIF(Base_limpia!$F$2:$F$196,A23) -> 15 | C23: =COUNTIFS(Base_limpia!$F$2:$F$196,A23,Base_limpia!$G$2:$G$196,"Alta") -> 8 | D23: =COUNTIFS(Base_limpia!$F$2:$F$196,A23,Base_limpia!$G$2:$G$196,"Media") -> 4 | E23: =IFERROR(ROUND(AVERAGEIF(Base_limpia!$F$2:$F$196,A23,Base_limpia!$I$2:$I$196),1),0) -> 69.7
A24: Portuario / Contenedores | B24: =COUNTIF(Base_limpia!$F$2:$F$196,A24) -> 12 | C24: =COUNTIFS(Base_limpia!$F$2:$F$196,A24,Base_limpia!$G$2:$G$196,"Alta") -> 11 | D24: =COUNTIFS(Base_limpia!$F$2:$F$196,A24,Base_limpia!$G$2:$G$196,"Media") -> 0 | E24: =IFERROR(ROUND(AVERAGEIF(Base_limpia!$F$2:$F$196,A24,Base_limpia!$I$2:$I$196),1),0) -> 75
A25: Química / Energía | B25: =COUNTIF(Base_limpia!$F$2:$F$196,A25) -> 5 | C25: =COUNTIFS(Base_limpia!$F$2:$F$196,A25,Base_limpia!$G$2:$G$196,"Alta") -> 4 | D25: =COUNTIFS(Base_limpia!$F$2:$F$196,A25,Base_limpia!$G$2:$G$196,"Media") -> 0 | E25: =IFERROR(ROUND(AVERAGEIF(Base_limpia!$F$2:$F$196,A25,Base_limpia!$I$2:$I$196),1),0) -> 59
A27: Comuna | B27: Total | C27: Alta
A28: San Antonio | B28: =COUNTIF(Base_limpia!$O$2:$O$196,A28) -> 63 | C28: =COUNTIFS(Base_limpia!$O$2:$O$196,A28,Base_limpia!$G$2:$G$196,"Alta") -> 43
A29: Viña del Mar | B29: =COUNTIF(Base_limpia!$O$2:$O$196,A29) -> 40 | C29: =COUNTIFS(Base_limpia!$O$2:$O$196,A29,Base_limpia!$G$2:$G$196,"Alta") -> 34
A30: Valparaíso | B30: =COUNTIF(Base_limpia!$O$2:$O$196,A30) -> 38 | C30: =COUNTIFS(Base_limpia!$O$2:$O$196,A30,Base_limpia!$G$2:$G$196,"Alta") -> 27
A31: Casablanca | B31: =COUNTIF(Base_limpia!$O$2:$O$196,A31) -> 12 | C31: =COUNTIFS(Base_limpia!$O$2:$O$196,A31,Base_limpia!$G$2:$G$196,"Alta") -> 7
A32: Curacaví | B32: =COUNTIF(Base_limpia!$O$2:$O$196,A32) -> 11 | C32: =COUNTIFS(Base_limpia!$O$2:$O$196,A32,Base_limpia!$G$2:$G$196,"Alta") -> 5
A33: Concón | B33: =COUNTIF(Base_limpia!$O$2:$O$196,A33) -> 4 | C33: =COUNTIFS(Base_limpia!$O$2:$O$196,A33,Base_limpia!$G$2:$G$196,"Alta") -> 3
A34: Cartagena | B34: =COUNTIF(Base_limpia!$O$2:$O$196,A34) -> 3 | C34: =COUNTIFS(Base_limpia!$O$2:$O$196,A34,Base_limpia!$G$2:$G$196,"Alta") -> 3
A35: Pudahuel | B35: =COUNTIF(Base_limpia!$O$2:$O$196,A35) -> 3 | C35: =COUNTIFS(Base_limpia!$O$2:$O$196,A35,Base_limpia!$G$2:$G$196,"Alta") -> 0
A36: Quilpué | B36: =COUNTIF(Base_limpia!$O$2:$O$196,A36) -> 2 | C36: =COUNTIFS(Base_limpia!$O$2:$O$196,A36,Base_limpia!$G$2:$G$196,"Alta") -> 1
A37: Quillota | B37: =COUNTIF(Base_limpia!$O$2:$O$196,A37) -> 2 | C37: =COUNTIFS(Base_limpia!$O$2:$O$196,A37,Base_limpia!$G$2:$G$196,"Alta") -> 2
A38: Santiago | B38: =COUNTIF(Base_limpia!$O$2:$O$196,A38) -> 2 | C38: =COUNTIFS(Base_limpia!$O$2:$O$196,A38,Base_limpia!$G$2:$G$196,"Alta") -> 0
A39: San Bernardo | B39: =COUNTIF(Base_limpia!$O$2:$O$196,A39) -> 2 | C39: =COUNTIFS(Base_limpia!$O$2:$O$196,A39,Base_limpia!$G$2:$G$196,"Alta") -> 0
... A47: Algarrobo | B47: =COUNTIF(Base_limpia!$O$2:$O$196,A47) -> 1 | C47: =COUNTIFS(Base_limpia!$O$2:$O$196,A47,Base_limpia!$G$2:$G$196,"Alta") -> 0

Sheet Base_limpia
A1: Place_Id | B1: Empresa | C1: Nombre_original | D1: Grupo_empresa | E1: N_sedes_grupo | F1: Segmento | G1: Relevancia | H1: Motivo_relevancia | I1: Score_completitud | J1: Telefono | K1: Tipo_telefono | L1: Sitio_web | M1: Dominio | N1: Web_propia | O1: Comuna | P1: Region | Q1: Codigo_postal | R1: Direccion | S1: Precision_direccion | T1: Latitud | U1: Longitud | V1: Categoria_principal | W1: Categorias | X1: N_resenas | Y1: Rating | Z1: Horario | AA1: Google_Maps_URL | AB1: Busquedas_origen | AC1: N_apariciones | AD1: Flags_calidad
A2: ChIJZ4iHJyfPYpYR_t_bNE6g844 | B2: Viña Casas del Bosque | C2: Viña Casas del Bosque | E2: 1 | F2: Vitivinícola / Agrícola | G2: Alta | H2: Viña de gran escala (enoturismo + producción) | I2: 100 | J2: +56 2 2480 6941 | K2: Fijo | L2: http://casasdelbosque.cl/ | M2: casasdelbosque.cl | N2: Sí | O2: Casablanca | P2: Valparaíso | R2: Ex Fundo Santa Rosa - Hijuela Nº 2, Casablanca, Valparaíso | S2: Con número | T2: -33.318621 | U2: -71.43545 | V2: Bodega | W2: Bodega, Recinto para eventos, Restaurante, Atracción turística, Tienda de vinos | X2: 1688 | Y2: 4.6 | Z2: lunes:10 am–5:30 pm | martes:10 am–5:30 pm | miércoles:10 am–5:30 pm | jueves:10 am–5:30 pm | viernes:10 am–5:30 pm | sábado:10 am–6 pm | domingo:10 am–6 pm | AA2: https://www.google.com/maps?cid=10300753030481174526 | AB2: Bodegas, Valparaíso - Chile; Viña*, Casablanca, Chile | AC2: 3
A3: ChIJU5_yCuBuYpYRLQPLGWUBG6s | B3: Casa Viñamar | C3: Casa Viñamar | E3: 1 | F3: Vitivinícola / Agrícola | G3: Alta | H3: Empresa industrial/logística en zona objetivo con canal de contacto | I3: 100 | J3: +56 9 8242 3349 | K3: Móvil | L3: https://vsptwinegroup.com/tours-and-events/es/holidays/vinamar/ | M3: vsptwinegroup.com | N3: Sí | O3: Casablanca | P3: Valparaíso | R3: Ruta 68, km 72, Casablanca, Valparaíso | S3: Con número | T3: -33.358489 | U3: -71.353124 | V3: Viñedo | W3: Viñedo, Restaurante, Atracción turística, Tienda de vinos | X3: 1636 | Y3: 4.7 | Z3: lunes:10 am–5:30 pm | martes:10 am–5:30 pm | miércoles:10 am–5:30 pm | jueves:10 am–5:30 pm | viernes:10 am–5:30 pm | sábado:10 am–5:30 pm | domingo:10 am–5:30 pm | AA3: https://www.google.com/maps?cid=12329449938592924461 | AB3: Viña*, Casablanca, Chile | AC3: 1
A4: ChIJU-puoGdmYpYRlseXs0fRl0E | B4: Viña Indómita | C4: Viña Indómita | E4: 1 | F4: Vitivinícola / Agrícola | G4: Alta | H4: Empresa industrial/logística en zona objetivo con canal de contacto | I4: 100 | J4: +56 32 215 3902 | K4: Fijo | L4: http://www.indomita.cl/ | M4: indomita.cl | N4: Sí | O4: Casablanca | P4: Valparaíso | R4: Ruta 68, Casablanca, Valparaíso | S4: Con número | T4: -33.359765 | U4: -71.343837 | V4: Viñedo | W4: Viñedo, Tienda de vinos | X4: 1294 | Y4: 4.5 | Z4: lunes:10 am–4:30 pm | martes:10 am–5:30 pm | miércoles:10 am–5:30 pm | jueves:10 am–5:30 pm | viernes:10 am–5:30 pm | sábado:Cerrado | domingo:Cerrado | AA4: https://www.google.com/maps?cid=4726476439834576790 | AB4: Viña*, Casablanca, Chile | AC4: 1
A5: ChIJTwDjYuQ4YpYRQ807Bo5Ehvg | B5: STI – San Antonio Terminal Internacional | C5: . | E5: 1 | F5: Portuario / Contenedores | G5: Alta | H5: Empresa industrial/logística en zona objetivo con canal de contacto | I5: 100 | J5: +56 35 220 1600 | K5: Fijo | L5: http://www.stiport.com/ | M5: stiport.com | N5: Sí | O5: San Antonio | P5: Valparaíso | R5: Bernardo O'Higgins Riquelme 2263, San Antonio, Valparaíso | S5: Con número | T5: -33.588561 | U5: -71.614453 | V5: Empresa portuaria | W5: Empresa portuaria, Proveedor de contenedores | X5: 928 | Y5: 4 | Z5: lunes:8:30 am–6 pm | martes:8:30 am–6 pm | miércoles:8:30 am–6 pm | jueves:8:30 am–6 pm | viernes:8:30 am–6 pm | sábado:8:30 am–6 pm | domingo:8:30 am–6 pm | AA5: https://www.google.com/maps?cid=17908076345065983299 | AB5: Empresa, San Antonio, Chile | AC5: 1 | AD5: nombre_corregido
A6: ChIJNwHdaVlHYpYR6J0IpChNBgo | B6: Seaport | C6: Seaport | E6: 1 | F6: Portuario / Contenedores | G6: Alta | H6: Empresa industrial/logística en zona objetivo con canal de contacto | I6: 100 | J6: +56 35 220 1500 | K6: Fijo | L6: http://www.seaport.cl/ | M6: seaport.cl | N6: Sí | O6: San Antonio | P6: Valparaíso | Q6: 2660000 | R6: Ruta G86, Aguas Buenas N° 6729, Cruce a Cartagena, 2660000 San Antonio, Valparaíso | S6: Con número | T6: -33.563936 | U6: -71.57017 | V6: Terminal de contenedores | W6: Terminal de contenedores | X6: 775 | Y6: 4 | Z6: lunes:9 am–5 pm | martes:9 am–5 pm | miércoles:9 am–5 pm | jueves:9 am–5 pm | viernes:9 am–5 pm | sábado:9:30–11:30 am | domingo:Cerrado | AA6: https://www.google.com/maps?cid=722349627185602024 | AB6: Empresa, San Antonio, Chile | AC6: 1
A7: ChIJCTijh51vYpYRgdNHBt8McYg | B7: Bodegas RE | C7: Bodegas RE | E7: 1 | F7: Vitivinícola / Agrícola | G7: Alta | H7: Empresa industrial/logística en zona objetivo con canal de contacto | I7: 100 | J7: +56 9 9345 9114 | K7: Móvil | L7: http://www.bodegasre.cl/ | M7: bodegasre.cl | N7: Sí | O7: Casablanca | P7: Valparaíso | R7: F-850 1380, Casablanca, Valparaíso | S7: Con número | T7: -33.304382 | U7: -71.397881 | V7: Bodega | W7: Bodega, Atracción turística | X7: 378 | Y7: 4.8 | Z7: lunes:10 am–6 pm | martes:10 am–6 pm | miércoles:10 am–6 pm | jueves:10 am–6 pm | viernes:10 am–6 pm | sábado:10 am–6 pm | domingo:11 am–5 pm | AA7: https://www.google.com/maps?cid=9831653613549114241 | AB7: Bodegas, Valparaíso - Chile | AC7: 3
A8: ChIJwfWdZmE4YpYRWcnQ83BNQSg | B8: Puerto Columbo San Antonio | C8: Puerto Columbo San Antonio | E8: 1 | F8: Otros / Servicios empresariales | G8: Alta | H8: Empresa industrial/logística en zona objetivo con canal de contacto | I8: 100 | J8: +56 35 220 3701 | K8: Fijo | L8: http://www.puertocolumbo.com/ | M8: puertocolumbo.com | N8: Sí | O8: San Antonio | P8: Valparaíso | R8: Ruta Nacional 78, Barrio Industrial # 2375, San Antonio, Valparaíso | S8: Con número | T8: -33.596729 | U8: -71.590718 | V8: Oficinas de empresa | W8: Oficinas de empresa | X8: 260 | Y8: 4.1 | Z8: lunes:8:30 am–6 pm | martes:8:30 am–6 pm | miércoles:8:30 am–6 pm | jueves:8:30 am–6 pm | viernes:8:30 am–6 pm | sábado:8:30 am–12:45 pm | domingo:Cerrado | AA8: https://www.google.com/maps?cid=2900684782525532505 | AB8: Empresa, San Antonio, Chile | AC8: 1
A9: ChIJqf97jz91YpYR3MnNt5Ur0aQ | B9: Terminal y Servicios Logísticos Las Cadenas Ltda. | C9: Terminal y Servicios Logísticos Las Cadenas Ltda. | E9: 1 | F9: Logística / Almacenaje | G9: Alta | H9: Empresa industrial/logística en zona objetivo con canal de contacto | I9: 100 | J9: +56 9 6122 2911 | K9: Móvil | L9: http://www.tlogisticolascadenas.cl/ | M9: tlogisticolascadenas.cl | N9: Sí | O9: Valparaíso | P9: Valparaíso | R9: 2821, Placilla, Cerro El Altar, Valparaíso | S9: Con número | T9: -33.134111 | U9: -71.548821 | V9: Gran superficie | W9: Gran superficie | X9: 174 | Y9: 4.3 | Z9: lunes:8 am–11 pm | martes:8 am–11 pm | miércoles:8 am–11 pm | jueves:8 am–11 pm | viernes:8 am–11 pm | sábado:8 am–5 pm | domingo:Cerrado | AA9: https://www.google.com/maps?cid=11876321614386547164 | AB9: Servicios logísticos, Valparaiso - Chile; Servicios logísticos, Valparaiso, Chile | AC9: 2
A10: ChIJaQpqAFI4YpYRZfGI7BTASjw | B10: Ferretería Industrial METALMAR | C10: Ferretería Industrial METALMAR | E10: 1 | F10: Maquinaria / Industrial | G10: Alta | H10: Empresa industrial/logística en zona objetivo con canal de contacto | I10: 100 | J10: +56 35 237 5110 | K10: Fijo | L10: http://www.metalmarchile.cl/ | M10: metalmarchile.cl | N10: Sí | O10: San Antonio | P10: Valparaíso | Q10: 2663592 | R10: Barros Luco 3058, 2663592 San Antonio, Valparaíso | S10: Con número | T10: -33.608233 | U10: -71.613862 | V10: Ferretería | W10: Ferretería, Centro comercial | X10: 147 | Y10: 4.6 | Z10: lunes:9 am–5 pm | martes:9 am–5 pm | miércoles:9 am–5 pm | jueves:9 am–5 pm | viernes:9 am–5 pm | sábado:9:30 am–1:30 pm | domingo:Cerrado | AA10: https://www.google.com/maps?cid=4344495986652541285 | AB10: Maquinaria industrial, San Antonio -Chile; Maquinaria industrial, San Antonio, Chile | AC10: 2
A11: ChIJDVf_dxPciZYRdQiz4oh22k4 | B11: Tranvial | C11: Tranvial | E11: 1 | F11: Transporte de carga | G11: Alta | H11: Empresa industrial/logística en zona objetivo con canal de contacto | I11: 100 | J11: +56 600 006 0060 | K11: 600 (call center) | L11: https://www.tranvial.com/ | M11: tranvial.com | N11: Sí | O11: Viña del Mar | P11: Valparaíso | R11: Edificio Reitz III - C. Limache 3437, Viña del Mar, Valparaíso | S11: Con número | T11: -33.04325 | U11: -71.517542 | V11: Servicio de transporte | W11: Servicio de transporte, Servicio de lanzadera, Servicio de logística, Servicio de transporte refrigerado, Empresa de transporte por camión | X11: 112 | Y11: 4.3 | Z11: lunes:Abierto las 24 horas | martes:Abierto las 24 horas | miércoles:Abierto las 24 horas | jueves:Abierto las 24 horas | viernes:Abierto las 24 horas | sábado:Abierto las 24 horas | domingo:Abierto las 24 horas | AA11: https://www.google.com/maps?cid=5681984210172315765 | AB11: Empresa, Viña del Mar, Chile; Transporte de carga, Viña del Mar, Chile | AC11: 3
A12: ChIJWdtkvBNvYpYRnhth1EiS96g | B12: Calca | C12: Calca | D12: Calca | E12: 2 | F12: Otros / Servicios empresariales | G12: Alta | H12: Empresa industrial/logística en zona objetivo con canal de contacto | I12: 100 | J12: +56 32 274 1652 | K12: Fijo | L12: http://www.calca.cl/ | M12: calca.cl | N12: Sí | O12: Casablanca | P12: Valparaíso | Q12: 2480505 | R12: Av. Portales 90, 2480505 Casablanca, Valparaíso | S12: Con número | T12: -33.321134 | U12: -71.410031 | V12: Comercio | W12: Comercio | X12: 56 | Y12: 4.6 | Z12: lunes:9 am–2 pm | martes:9 am–2 pm | miércoles:9 am–2 pm | jueves:9 am–2 pm | viernes:9 am–2 pm | sábado:9 am–12:30 pm | domingo:Cerrado | AA12: https://www.google.com/maps?cid=12175360959117859742 | AB12: Calca | AC12: 1
A13: ChIJIxwuEtNvYpYRa8XHXQiKrXA | B13: Emergent Cold LatAm | C13: Emergent Cold LatAm | E13: 1 | F13: Logística / Almacenaje | G13: Alta | H13: Empresa industrial/logística en zona objetivo con canal de contacto | I13: 100 | J13: +56 600 656 0030 | K13: 600 (call center) | L13: https://emergentcoldlatam.com/ | M13: emergentcoldlatam.com | N13: Sí | O13: Casablanca | P13: Valparaíso | R13: F-852 4621, Lo Vásquez, Casablanca, Valparaíso | S13: Con número | T13: -33.27258 | U13: -71.428276 | V13: Servicio de logística | W13: Servicio de logística | X13: 55 | Y13: 4 | Z13: lunes:Abierto las 24 horas | martes:Abierto las 24 horas | miércoles:Abierto las 24 horas | jueves:Abierto las 24 horas | viernes:Abierto las 24 horas | sábado:Abierto las 24 horas | domingo:Abierto las 24 horas | AA13: https://www.google.com/maps?cid=8119297471756617067 | AB13: Frigoríficos, Casablanca, Chile | AC13: 1
A14: ChIJt8G2SvLeiZYR9dWQP36S5DU | B14: Empresas Demaria S.A. | C14: Empresas Demaria S.A. | D14: Empresas Demaria S.A. | E14: 2 | F14: Otros / Servicios empresariales | G14: Alta | H14: Empresa industrial/logística en zona objetivo con canal de contacto | I14: 100 | J14: +56 32 226 7000 | K14: Fijo | L14: https://demaria.cl/ | M14: demaria.cl | N14: Sí | O14: Viña del Mar | P14: Valparaíso | Q14: 2562126 | R14: C. Limache 3535, 2562126 Viña del Mar, Valparaíso | S14: Con número | T14: -33.044418 | U14: -71.515894 | V14: Oficinas de empresa | W14: Oficinas de empresa | X14: 55 | Y14: 4.4 | Z14: lunes:9 am–6 pm | martes:9 am–6 pm | miércoles:9 am–6 pm | jueves:9 am–6 pm | viernes:9 am–6 pm | sábado:Cerrado | domingo:Cerrado | AA14: https://www.google.com/maps?cid=3883389849630201333 | AB14: Empresa, Viña del Mar, Chile | AC14: 1
A15: ChIJ9ckcCEfhiZYReWhuBcEBD7A | B15: Egido Empresas | C15: Egido Empresas | E15: 1 | F15: Transporte de carga | G15: Alta | H15: Empresa industrial/logística en zona objetivo con canal de contacto | I15: 100 | J15: +56 9 7450 5347 | K15: Móvil | L15: http://www.egido.cl/ | M15: egido.cl | N15: Sí | O15: Valparaíso | P15: Valparaíso | R15: Camino La Pólvora 4, La Polvora, Valparaíso | S15: Con número | T15: -33.094393 | U15: -71.588863 | V15: Empresa de transporte por camión | W15: Empresa de transporte por camión, Servicio de grúa, Tienda general, Almacén | X15: 51 | Y15: 4.3 | Z15: lunes:8 am–10 pm | martes:8 am–10 pm | miércoles:8 am–10 pm | jueves:8 am–10 pm | viernes:8 am–10 pm | sábado:8 am–2 pm | domingo:Cerrado | AA15: https://www.google.com/maps?cid=12686360603857414265 | AB15: Transporte de carga, Valparaiso, Chile | AC15: 1
A16: ChIJJ9ygp2l1YpYRz2k8P5b3_-E | B16: SERVIEX Ltda | C16: SERVIEX Ltda | E16: 1 | F16: Logística / Almacenaje | G16: Alta | H16: Empresa industrial/logística en zona objetivo con canal de contacto | I16: 95 | J16: +56 9 4173 7193 | K16: Móvil | L16: https://serviexltda.cl/ | M16: serviexltda.cl | N16: Sí | O16: Valparaíso | P16: Valparaíso | Q16: 2340000 | R16: Undécima Avenida 1730, Pc 384 Placilla, 2340000 Valparaíso | S16: Con número | T16: -33.124745 | U16: -71.545804 | V16: Servicio de logística | W16: Servicio de logística, Tienda general, Asesor en comercio internacional, Almacén, Bodega | X16: 49 | Y16: 5 | Z16: lunes:9 am–6 pm | martes:9 am–6 pm | miércoles:9 am–6 pm | jueves:9 am–6 pm | viernes:9 am–6 pm | sábado:Cerrado | domingo:Cerrado | AA16: https://www.google.com/maps?cid=16285007002273081807 | AB16: Servicios logísticos, Valparaiso - Chile | AC16: 1
A17: ChIJAXDu37PgiZYRZHTn5UC-ITM | B17: Frigorífico Víctor Mancilla y Cía Ltda. | C17: Frigorífico Víctor Mancilla y Cía Ltda. | E17: 1 | F17: Frío / Alimentos | G17: Alta | H17: Empresa industrial/logística en zona objetivo con canal de contacto | I17: 95 | J17: +56 32 262 7464 | K17: Fijo | L17: http://www.pesqueramancilla.cl/ | M17: pesqueramancilla.cl | N17: Sí | O17: Valparaíso | P17: Valparaíso | Q17: 2391272 | R17: R. Philippi 195, 2391272 Valparaíso | S17: Con número | T17: -33.035152 | U17: -71.588425 | V17: Comercio | W17: Comercio | X17: 42 | Y17: 4.2 | Z17: lunes:9 am–5 pm | martes:9 am–5 pm | miércoles:9 am–5 pm | jueves:9 am–5 pm | viernes:9 am–5 pm | sábado:9:30 am–1 pm | domingo:Cerrado | AA17: https://www.google.com/maps?cid=3684435156110111844 | AB17: Frigoríficos, Casablanca, Chile; Frigoríficos, V Región, Chile | AC17: 2
A18: ChIJ66xAzl9HYpYR7X2_s30nfzo | B18: SL TRANSPORTE LTDA | C18: SL TRANSPORTE LTDA | E18: 1 | F18: Transporte de carga | G18: Alta | H18: Empresa industrial/logística en zona objetivo con canal de contacto | I18: 95 | J18: +56 9 4008 8368 | K18: Móvil | L18: http://www.sltransporte.cl/ | M18: sltransporte.cl | N18: Sí | O18: San Antonio | P18: Valparaíso | Q18: 2660000 | R18: Los Eucaliptus, Av. Aguas Buenas 597, 2660000 San Antonio, Valparaíso | S18: Con número | T18: -33.569049 | U18: -71.570103 | V18: Empresa de transporte por camión | W18: Empresa de transporte por camión, Servicio de logística | X18: 41 | Y18: 4 | Z18: lunes:8:30 am–8 pm | martes:8:30 am–8 pm | miércoles:8:30 am–8 pm | jueves:8:30 am–8 pm | viernes:8:30 am–8 pm | sábado:8:30 am–3 pm | domingo:Cerrado | AA18: https://www.google.com/maps?cid=4215131197082140141 | AB18: Logística en San Antonio, Chile; Servicios logísticos, San Antonio, Chile; Transporte de carga, San Antonio, Chile | AC18: 3
A19: ChIJ9bP4ZR9HYpYRf9Ne0tjkdas | B19: FRIGORIFICO FRIOMOR S.A | C19: FRIGORIFICO FRIOMOR S.A | E19: 1 | F19: Frío / Alimentos | G19: Alta | H19: Empresa industrial/logística en zona objetivo con canal de contacto | I19: 95 | J19: +56 9 9619 6628 | K19: Móvil | L19: http://www.friomor.cl/ | M19: friomor.cl | N19: Sí | O19: Cartagena | P19: Valparaíso | R19: Las Majadas Lote 2 y 3 s/n, Cartagena, San Antonio, Cartagena, Valparaíso | S19: Con número | T19: -33.563029 | U19: -71.528961 | V19: Almacén | W19: Almacén, Instalación de almacenamiento en frío | X19: 26 | Y19: 4.5 | Z19: lunes:8 am–6 pm | martes:8 am–6 pm | miércoles:8 am–6 pm | jueves:8 am–6 pm | viernes:8 am–6 pm | sábado:9 am–12 pm | domingo:Cerrado | AA19: https://www.google.com/maps?cid=12355032772654322559 | AB19: Frigoríficos, Casablanca, Chile; Frigoríficos, V Región, Chile | AC19: 2
A20: ChIJOdzSlWTciZYRIK3x7MPWBs8 | B20: OSKUPACK | C20: OSKUPACK | E20: 1 | F20: Maquinaria / Industrial | G20: Alta | H20: Empresa industrial/logística en zona objetivo con canal de contacto | I20: 95 | J20: +56 9 9822 4595 | K20: Móvil | L20: https://oskupack.cl/ | M20: oskupack.cl | N20: Sí | O20: Viña del Mar | P20: Valparaíso | Q20: 2520000 | R20: Camino Lajarilla 744, 2520000 Viña del Mar, Valparaíso | S20: Con número | T20: -32.97771 | U20: -71.489106 | V20: Empresa de embalaje | W20: Empresa de embalaje, Empresa de fabricación de plástico | X20: 25 | Y20: 4.4 | Z20: lunes:9 am–5:30 pm | martes:9 am–5:30 pm | miércoles:9 am–5:30 pm | jueves:9 am–5:30 pm | viernes:9 am–5:30 pm | sábado:Cerrado | domingo:Cerrado | AA20: https://www.google.com/maps?cid=14917846952693574944 | AB20: Empresa, Viña del Mar, Chile | AC20: 1
A21: ChIJDZauyu_ciZYRzf5sek8mtt8 | B21: INDUSTRIAL COSTA SPA | C21: INDUSTRIAL COSTA SPA | E21: 1 | F21: Maquinaria / Industrial | G21: Alta | H21: Empresa industrial/logística en zona objetivo con canal de contacto | I21: 95 | J21: +56 9 8888 4772 | K21: Móvil | L21: http://industrialcostaspa.com/ | M21: industrialcostaspa.com | N21: Sí | O21: Viña del Mar | P21: Valparaíso | R21: Camino internacional 5465 Galpón F3, 1, Viña del Mar, Valparaíso | S21: Con número | T21: -32.962128 | U21: -71.510179 | V21: Taller de maquinaria | W21: Taller de maquinaria, Ingeniero mecánico, Empresa de construcciones metálicas, Servicio de reparación | X21: 23 | Y21: 4.1 | Z21: lunes:8 am–5:30 pm | martes:8 am–5:30 pm | miércoles:8 am–5:30 pm | jueves:8 am–5:30 pm | viernes:8 am–4:30 pm | sábado:Cerrado | domingo:Cerrado | AA21: https://www.google.com/maps?cid=16120114039017504461 | AB21: Empresa, Viña del Mar, Chile; Maquinaria industrial, Viña del Mar-Chile | AC21: 2
A22: ChIJh8dGG8PgiZYR9GB0wf0-N5s | B22: ROLIMAQ - VENTUS | C22: ROLIMAQ - VENTUS | E22: 1 | F22: Maquinaria / Industrial | G22: Alta | H22: Empresa industrial/logística en zona objetivo con canal de contacto | I22: 95 | J22: +56 9 5908 1452 | K22: Móvil | L22: http://www.rolimaq.cl/ | M22: rolimaq.cl | N22: Sí | O22: Viña del Mar | P22: Valparaíso | R22: 5 ORIENTE 608 VIÑA DEL MAR, Av. Colón 2877, Valparaíso, Viña del Mar, Valparaíso | S22: Con número | T22: -33.017182 | U22: -71.543249 | V22: Empresa de suministros industriales | W22: Empresa de suministros industriales | X22: 20 | Y22: 4.6 | Z22: lunes:9 am–6 pm | martes:9 am–6 pm | miércoles:9 am–6 pm | jueves:9 am–6 pm | viernes:9 am–6 pm | sábado:Cerrado | domingo:Cerrado | AA22: https://www.google.com/maps?cid=11184477459191193844 | AB22: Maquinaria industrial, Viña del Mar-Chile | AC22: 1
A23: ChIJe4q_Blp1YpYRjtN4sW_ahZs | B23: Delfrio Frigorífico de Valparaiso S.A. | C23: Delfrio Frigorífico de Valparaiso S.A. | D23: Delfrio Frigorífico de Valparaiso S.A. | E23: 2 | F23: Frío / Alimentos | G23: Alta | H23: Empresa industrial/logística en zona objetivo con canal de contacto | I23: 95 | J23: +56 32 229 1166 | K23: Fijo | L23: http://www.delfrio.cl/ | M23: delfrio.cl | N23: Sí | O23: Valparaíso | P23: Valparaíso | R23: Ruta 68 1240, Placilla, Valparaíso | S23: Con número | T23: -33.117636 | U23: -71.559892 | V23: Servicios de empresa a empresa | W23: Servicios de empresa a empresa | X23: 19 | Y23: 4.3 | Z23: lunes:8:30 am–5:30 pm | martes:8:30 am–5:30 pm | miércoles:8:30 am–5:30 pm | jueves:8:30 am–5:30 pm | viernes:8:30 am–5:30 pm | sábado:Cerrado | domingo:Cerrado | AA23: https://www.google.com/maps?cid=11206603421035058062 | AB23: Frigoríficos, Casablanca, Chile; Frigoríficos, V Región, Chile | AC23: 2
A24: ChIJ2UzWJj45YpYRxzMGbrKQI58 | B24: Distribuidor Autorizado Stihl San Antonio AGROMAR | C24: Distribuidor Autorizado Stihl San Antonio AGROMAR | E24: 1 | F24: Maquinaria / Industrial | G24: Alta | H24: Empresa industrial/logística en zona objetivo con canal de contacto | I24: 95 | J24: +56 9 8814 2767 | K24: Móvil | L24: https://redstihl.cl/productos/aceite-de-mezcla-premium-stihl-1l/ | M24: redstihl.cl | N24: Sí | O24: San Antonio | P24: Valparaíso | Q24: 2660750 | R24: Av. Chile 402, 2660750 San Antonio, Valparaíso | S24: Con número | T24: -33.61324 | U24: -71.60837 | V24: Cuarto de herramientas | W24: Cuarto de herramientas | X24: 15 | Y24: 4.1 | Z24: lunes:9 am–1:30 pm | martes:9 am–1:30 pm | miércoles:9 am–1:30 pm | jueves:9 am–1:30 pm | viernes:9 am–1:30 pm | sábado:Cerrado | domingo:Cerrado | AA24: https://www.google.com/maps?cid=11467168172239893447 | AB24: Maquinaria industrial, San Antonio -Chile; Maquinaria industrial, San Antonio, Chile | AC24: 2
A25: ChIJyU3YuwZHYpYR-gzSQD783YI | B25: Logistica el Cardal LOGEC, Malvilla | C25: Logistica el Cardal LOGEC, Malvilla | E25: 1 | F25: Logística / Almacenaje | G25: Alta | H25: Empresa industrial/logística en zona objetivo con canal de contacto | I25: 95 | J25: +56 9 5534 0864 | K25: Móvil | L25: http://www.logec.cl/ | M25: logec.cl | N25: Sí | O25: San Antonio | P25: Valparaíso | R25: Camino Malvilla 1378, Ruta G974, San Antonio, Valparaíso | S25: Con número | T25: -33.581295 | U25: -71.531363 | V25: Almacén | W25: Almacén, Oficinas de empresa | X25: 15 | Y25: 4.5 | Z25: lunes:8 am–1 pm | martes:8 am–1 pm | miércoles:8 am–1 pm | jueves:8 am–1 pm | viernes:8 am–1 pm | sábado:Cerrado | domingo:Cerrado | AA25: https://www.google.com/maps?cid=9429970539089366266 | AB25: Bodegas y almacenaje, San Antonio; Logística en San Antonio, Chile | AC25: 2
A26: ChIJK-5LjLLZiZYRavnzJYEFO28 | B26: Mibodega | C26: Mibodega | E26: 1 | F26: Logística / Almacenaje | G26: Alta | H26: Empresa industrial/logística en zona objetivo con canal de contacto | I26: 95 | J26: +56 9 3391 9144 | K26: Móvil | L26: https://mibodega.cl/ | M26: mibodega.cl | N26: Sí | O26: Quilpué | P26: Valparaíso | Q26: 2430000 | R26: Baquedano 1475, 2430000 Quilpué, Valparaíso | S26: Con número | T26: -33.042551 | U26: -71.416834 | V26: Bodega | W26: Bodega | X26: 15 | Y26: 4.3 | Z26: lunes:Abierto las 24 horas | martes:Abierto las 24 horas | miércoles:Abierto las 24 horas | jueves:Abierto las 24 horas | viernes:Abierto las 24 horas | sábado:Abierto las 24 horas | domingo:Abierto las 24 horas | AA26: https://www.google.com/maps?cid=8015006014081595754 | AB26: Bodegas, Valparaíso - Chile | AC26: 3
A27: ChIJ1d4Y2OXdiZYRXhgUpPYHODY | B27: Empresas Tuxpan | C27: Empresas Tuxpan | E27: 1 | F27: Otros / Servicios empresariales | G27: Alta | H27: Empresa industrial/logística en zona objetivo con canal de contacto | I27: 95 | J27: +56 32 268 0906 | K27: Fijo | L27: http://www.tuxpan.com/ | M27: tuxpan.com | N27: Sí | O27: Viña del Mar | P27: Valparaíso | Q27: 2520696 | R27: 7 Nte. 360, 2520696 Viña del Mar, Valparaíso | S27: Con número | T27: -33.016011 | U27: -71.554638 | V27: Oficinas de empresa | W27: Oficinas de empresa | X27: 14 | Y27: 5 | Z27: lunes:9 am–1 pm | martes:9 am–1 pm | miércoles:9 am–1 pm | jueves:9 am–1 pm | viernes:9 am–1 pm | sábado:Cerrado | domingo:Cerrado | AA27: https://www.google.com/maps?cid=3906881432640034910 | AB27: Empresa, Viña del Mar, Chile | AC27: 1
A28: ChIJ_VAVpefeiZYR4lFQkH6LgZU | B28: VIRGINIA - Empresas Demaria S.A. | C28: VIRGINIA - Empresas Demaria S.A. | D28: Empresas Demaria S.A. | E28: 2 | F28: Maquinaria / Industrial | G28: Alta | H28: Empresa industrial/logística en zona objetivo con canal de contacto | I28: 95 | J28: +56 32 226 7000 | K28: Fijo | L28: http://www.virginia.cl/ | M28: virginia.cl | N28: Sí | O28: Viña del Mar | P28: Valparaíso | Q28: 2562126 | R28: C. Limache 3535, 2562126 Viña del Mar, Valparaíso | S28: Con número | T28: -33.044718 | U28: -71.515161 | V28: Proveedor de productos de limpieza | W28: Proveedor de productos de limpieza | X28: 12 | Y28: 4.8 | Z28: lunes:8 am–6 pm | martes:8 am–6 pm | miércoles:8 am–6 pm | jueves:8 am–6 pm | viernes:8 am–6 pm | sábado:Cerrado | domingo:Cerrado | AA28: https://www.google.com/maps?cid=10773045159350260194 | AB28: Empresa, Viña del Mar, Chile | AC28: 1
A29: ChIJi5H3-nXbiZYRReEyOV_Qz3Y | B29: Bodegas Mauco | C29: Bodegas Mauco | Arriendo MiniBodegas | Galpones | Concón Viña del Mar Valparaíso Quilpué Quillota | E29: 1 | F29: Logística / Almacenaje | G29: Alta | H29: Empresa industrial/logística en zona objetivo con canal de contacto | I29: 95 | J29: +56 9 9779 1746 | K29: Móvil | L29: http://www.bodegasmauco.cl/ | M29: bodegasmauco.cl | N29: Sí | O29: Quillota | P29: Valparaíso | Q29: 2260000 | R29: RUTA f 360 KM1 Quillota, 2260000 Valparaíso, Quillota, Valparaíso | S29: Con número | T29: -32.917767 | U29: -71.434898 | V29: Bodega | W29: Bodega | X29: 11 | Y29: 4.5 | Z29: lunes:Abierto las 24 horas | martes:Abierto las 24 horas | miércoles:Abierto las 24 horas | jueves:Abierto las 24 horas | viernes:Abierto las 24 horas | sábado:Abierto las 24 horas | domingo:Abierto las 24 horas | AA29: https://www.google.com/maps?cid=8561290524054708549 | AB29: Bodegas, Valparaíso - Chile | AC29: 2 | AD29: nombre_corregido
A30: ChIJzeDAEPY5YpYRU7mFPUjuCbM | B30: Puerto San Antonio | C30: Puerto San Antonio | D30: PUERTO SAN ANTONIO | E30: 2 | F30: Portuario / Contenedores | G30: Alta | H30: Empresa industrial/logística en zona objetivo con canal de contacto | I30: 90 | J30: +56 35 258 6000 | K30: Fijo | L30: https://puertosanantonio.com/ | M30: puertosanantonio.com | N30: Sí | O30: San Antonio | P30: Valparaíso | Q30: 2660000 | R30: Antonio Núñez de Fonseca 1552, 2660000 San Antonio, Valparaíso | S30: Con número | T30: -33.574501 | U30: -71.626755 | V30: Empresa portuaria | W30: Empresa portuaria | X30: 521 | Y30: 4.5 | AA30: https://www.google.com/maps?cid=12901104601616726355 | AB30: Empresa, San Antonio, Chile | AC30: 1 | AD30: sin_horario
A31: ChIJz5AzAYY4YpYReXQuinPOZSI | B31: D&C San Antonio, patio principal | C31: D&C San Antonio, patio principal | E31: 1 | F31: Portuario / Contenedores | G31: Alta | H31: Empresa industrial/logística en zona objetivo con canal de contacto | I31: 90 | J31: +56 32 251 3302 | K31: Fijo | L31: http://www.dycsa.cl/ | M31: dycsa.cl | N31: Sí | O31: San Antonio | P31: Valparaíso | R31: Ruta G 94 F Nuevo Acceso al Puerto 3559 Barrio Industrial San Antonio, San Antonio, Valparaíso | S31: Con número | T31: -33.58876 | U31: -71.584752 | V31: Servicio de contenedores | W31: Servicio de contenedores, Proveedor de contenedores | X31: 464 | Y31: 3.2 | Z31: lunes:8:30 am–9 pm | martes:8:30 am–9 pm | miércoles:8:30 am–9 pm | jueves:8:30 am–9 pm | viernes:8:30 am–9 pm | sábado:8:30 am–3 pm | domingo:Cerrado | AA31: https://www.google.com/maps?cid=2478614165572187257 | AB31: Maquinaria industrial, San Antonio, Chile | AC31: 1
A32: ChIJsyA89Q9HYpYRmf5pd7-I9Lc | B32: Maersk Logistics and Service Chile SpA | C32: Maersk Logistics and Service Chile SpA | D32: Maersk Logistics and Service Chile SpA | E32: 2 | F32: Portuario / Contenedores | G32: Alta | H32: Empresa industrial/logística en zona objetivo con canal de contacto | I32: 90 | J32: +56 35 220 2700 | K32: Fijo | L32: http://www.maersk.com/ | M32: maersk.com | N32: Sí | O32: San Antonio | P32: Valparaíso | R32: Avenida Las Factorías 8150, San Antonio, Valparaíso | S32: Con número | T32: -33.576092 | U32: -71.536746 | V32: Terminal de contenedores | W32: Terminal de contenedores | X32: 292 | Y32: 3.9 | Z32: lunes:8 am–10 pm | martes:8 am–10 pm | miércoles:8 am–10 pm | jueves:8 am–10 pm | viernes:8 am–10 pm | sábado:8 am–6 pm | domingo:Cerrado | AA32: https://www.google.com/maps?cid=13255369959181778585 | AB32: Empresa, San Antonio, Chile; Logística en San Antonio, Chile | AC32: 2
A33: ChIJm3jkdoluYpYRGRGsx282Lfk | B33: Kingston Family Vineyards | C33: Kingston Family Vineyards | E33: 1 | F33: Vitivinícola / Agrícola | G33: Alta | H33: Empresa industrial/logística en zona objetivo con canal de contacto | I33: 90 | J33: +56 32 332 0150 | K33: Fijo | L33: http://www.kingstonvineyards.com/ | M33: kingstonvineyards.com | N33: Sí | O33: Casablanca | P33: Valparaíso | R33: Hijuela El Maitén S/N, Casablanca, Valparaíso | S33: Sin número | T33: -33.317081 | U33: -71.460571 | V33: Bodega | W33: Bodega, Atracción turística, Viñedo | X33: 216 | Y33: 4.8 | Z33: lunes:10 am–6 pm | martes:10 am–6 pm | miércoles:10 am–6 pm | jueves:10 am–6 pm | viernes:10 am–6 pm | sábado:10 am–6 pm | domingo:10 am–6 pm | AA33: https://www.google.com/maps?cid=17955067143115247897 | AB33: Bodegas, Valparaíso - Chile | AC33: 3 | AD33: direccion_imprecisa
A34: ChIJlbjaulVHYpYRQbbSWmVsH2A | B34: TLS Terminal Logistico San Antonio LTDA. | C34: TLS Terminal Logistico San Antonio LTDA. | E34: 1 | F34: Portuario / Contenedores | G34: Alta | H34: Empresa industrial/logística en zona objetivo con canal de contacto | I34: 90 | J34: +56 35 245 0146 | K34: Fijo | L34: http://www.tls.cl/ | M34: tls.cl | N34: Sí | O34: Cartagena | P34: Valparaíso | R34: Camino antiguo a Santiago SN, Cartagena, Valparaíso | S34: Sin número | T34: -33.551105 | U34: -71.569975 | V34: Servicio de contenedores | W34: Servicio de contenedores, Servicios de empresa a empresa | X34: 158 | Y34: 4.1 | Z34: lunes:7 am–11 pm | martes:7 am–11 pm | miércoles:7 am–11 pm | jueves:7 am–11 pm | viernes:7 am–11 pm | sábado:7 am–11 pm | domingo:Cerrado | AA34: https://www.google.com/maps?cid=6926373934490367553 | AB34: Logística en San Antonio, Chile | AC34: 1 | AD34: direccion_imprecisa
A35: ChIJe1d2vUZHYpYR1Qtvf2Vs_o0 | B35: Transportes Olivares | C35: Transportes Olivares | D35: Transportes Olivares | E35: 2 | F35: Transporte de carga | G35: Alta | H35: Empresa industrial/logística en zona objetivo con canal de contacto | I35: 90 | J35: +56 9 9637 6297 | K35: Móvil | L35: http://www.transportesolivares.cl/ | M35: transportesolivares.cl | N35: Sí | O35: San Antonio | P35: Valparaíso | Q35: 2660885 | R35: José Miguel Carrera Verdugo 830, of.6, 2660885 San Antonio, Valparaíso | S35: Con número | T35: -33.609401 | U35: -71.605023 | V35: Empresa de transporte por camión | W35: Empresa de transporte por camión | X35: 9 | Y35: 4 | Z35: lunes:9 am–7 pm | martes:9 am–7 pm | miércoles:9 am–7 pm | jueves:9 am–7 pm | viernes:9 am–6 pm | sábado:Cerrado | domingo:Cerrado | AA35: https://www.google.com/maps?cid=10231734586617826261 | AB35: Transporte de carga, San Antonio, Chile | AC35: 1
A36: ChIJKRr43uLdiZYROrcftBGiDMI | B36: TopMachine | C36: TopMachine | E36: 1 | F36: Maquinaria / Industrial | G36: Alta | H36: Empresa industrial/logística en zona objetivo con canal de contacto | I36: 90 | J36: +56 9 9222 6713 | K36: Móvil | L36: http://www.topmachine.cl/ | M36: topmachine.cl | N36: Sí | O36: Viña del Mar | P36: Valparaíso | R36: 1 - Calle Viana 837 Local 1, Viña del Mar, Valparaíso | S36: Con número | T36: -33.02606 | U36: -71.550078 | V36: Empresa de suministros industriales | W36: Empresa de suministros industriales | X36: 6 | Y36: 5 | Z36: lunes:9 am–2 pm | martes:9 am–2 pm | miércoles:9 am–2 pm | jueves:9 am–2 pm | viernes:9 am–2 pm | sábado:Cerrado | domingo:Cerrado | AA36: https://www.google.com/maps?cid=13982729139998668602 | AB36: Maquinaria industrial, Viña del Mar-Chile | AC36: 1
A37: ChIJyU-2Vd05YpYRTY3Hjq0as3w | B37: Forza Industrial | C37: Forza Industrial I HERRAMIENTAS I GENERADORES I SOLDADORAS I COMPRESORES I HIDROLAVADORAS I MOTOR ESTACIONARIOS | E37: 1 | F37: Maquinaria / Industrial | G37: Alta | H37: Empresa industrial/logística en zona objetivo con canal de contacto | I37: 90 | J37: +56 9 6629 5814 | K37: Móvil | L37: https://www.forzaindustrial.cl/ | M37: forzaindustrial.cl | N37: Sí | O37: San Antonio | P37: Valparaíso | Q37: 2660000 | R37: Av. Chile 55, Loc B, 2660000 Llolleo, San Antonio, Valparaíso | S37: Con número | T37: -33.61014 | U37: -71.608832 | V37: Tienda de herramientas y troqueles | W37: Tienda de herramientas y troqueles, Taller de maquinaria | X37: 5 | Y37: 5 | Z37: lunes:9 am–6 pm | martes:9 am–6 pm | miércoles:9 am–6 pm | jueves:9 am–6 pm | viernes:9 am–6 pm | sábado:Cerrado | domingo:Cerrado | AA37: https://www.google.com/maps?cid=8985555014261378381 | AB37: Maquinaria industrial, San Antonio -Chile; Maquinaria industrial, San Antonio, Chile | AC37: 2 | AD37: nombre_corregido
A38: ChIJCa2d-6vhiZYRdD4ps24G0NE | B38: Comercializadora de Carnes Gutiérrez y Gutiérrez | C38: Comercializadora de Carnes Gutiérrez y Gutiérrez | E38: 1 | F38: Frío / Alimentos | G38: Alta | H38: Empresa industrial/logística en zona objetivo con canal de contacto | I38: 90 | J38: +56 32 221 3124 | K38: Fijo | L38: https://www.carnesag.cl/ | M38: carnesag.cl | N38: Sí | O38: Valparaíso | P38: Valparaíso | Q38: 2340168 | R38: Juana Ross 155, 2340168 Valparaíso | S38: Con número | T38: -33.049856 | U38: -71.605408 | V38: Proveedor mayorista de alimentos | W38: Proveedor mayorista de alimentos | X38: 5 | Y38: 5 | Z38: lunes:8 am–2 pm | martes:8 am–2 pm | miércoles:8 am–2 pm | jueves:8 am–2 pm | viernes:8 am–2 pm | sábado:Cerrado | domingo:Cerrado | AA38: https://www.google.com/maps?cid=15118591021604748916 | AB38: Frigoríficos, V Región, Chile | AC38: 1
A39: ChIJiX4WM4veiZYRsQ5pBIXFnuw | B39: CER Chile | C39: CER Chile | E39: 1 | F39: Otros / Servicios empresariales | G39: Alta | H39: Empresa industrial/logística en zona objetivo con canal de contacto | I39: 90 | J39: +56 9 9745 4023 | K39: Móvil | L39: http://www.cer-chile.cl/ | M39: cer-chile.cl | N39: Sí | O39: Viña del Mar | P39: Valparaíso | R39: C. Limache 3437, Ofi 520, Viña del Mar, Valparaíso | S39: Con número | T39: -33.04325 | U39: -71.517542 | V39: Oficinas de empresa | W39: Oficinas de empresa | X39: 5 | Y39: 5 | Z39: lunes:8:30 am–5:30 pm | martes:8:30 am–5:30 pm | miércoles:8:30 am–5:30 pm | jueves:8:30 am–5:30 pm | viernes:8:30 am–5:30 pm | sábado:Cerrado | domingo:Cerrado | AA39: https://www.google.com/maps?cid=17050282414366592689 | AB39: Empresa, Viña del Mar, Chile | AC39: 1
A40: ChIJf-0CUiw5YpYRlKtqkW09qxo | B40: Transportes Olivares | C40: Transportes Olivares | D40: Transportes Olivares | E40: 2 | F40: Transporte de carga | G40: Alta | H40: Empresa industrial/logística en zona objetivo con canal de contacto | I40: 90 | J40: +56 9 9637 6297 | K40: Móvil | L40: http://www.transportesolivares.cl/ | M40: transportesolivares.cl | N40: Sí | O40: San Antonio | P40: Valparaíso | Q40: 2662776 | R40: Barros Luco 1814, 6, 2662776 Barrancas, San Antonio, Valparaíso | S40: Con número | T40: -33.596141 | U40: -71.613047 | V40: Empresa de transporte por camión | W40: Empresa de transporte por camión | X40: 3 | Y40: 5 | Z40: lunes:9 am–6:30 pm | martes:9 am–6:30 pm | miércoles:9 am–6:30 pm | jueves:9 am–6:30 pm | viernes:9 am–6:30 pm | sábado:Cerrado | domingo:Cerrado | AA40: https://www.google.com/maps?cid=1921697206804065172 | AB40: Transporte de carga, San Antonio, Chile | AC40: 1
A41: ChIJ_3c7OSnhiZYRXn7zp_cMfCk | B41: Compañía de Servicios Aduaneros y Transportes SPA | C41: Compañía de Servicios Aduaneros y Transportes SPA | E41: 1 | F41: Transporte de carga | G41: Alta | H41: Empresa industrial/logística en zona objetivo con canal de contacto | I41: 90 | J41: +56 9 6434 9141 | K41: Móvil | L41: http://www.transporteinternacional.cl/ | M41: transporteinternacional.cl | N41: Sí | O41: Valparaíso | P41: Valparaíso | Q41: 2361897 | R41: Esmeralda 1074, 2361897 Valparaíso | S41: Con número | T41: -33.042323 | U41: -71.624764 | V41: Empresa de transporte por camión | W41: Empresa de transporte por camión | X41: 2 | Y41: 5 | Z41: lunes:Abierto las 24 horas | martes:Abierto las 24 horas | miércoles:Abierto las 24 horas | jueves:Abierto las 24 horas | viernes:Abierto las 24 horas | sábado:Abierto las 24 horas | domingo:Abierto las 24 horas | AA41: https://www.google.com/maps?cid=2989278510481374814 | AB41: Servicios logísticos, Valparaiso - Chile; Servicios logísticos, Valparaiso, Chile; Transporte de carga, Valparaiso, Chile | AC41: 3
A42: ChIJ61VU6z91YpYRVoOEYZGHclU | B42: Imperio Transportes | C42: Imperio Transportes | E42: 1 | F42: Transporte de carga | G42: Alta | H42: Empresa industrial/logística en zona objetivo con canal de contacto | I42: 90 | J42: +56 9 8157 1998 | K42: Móvil | L42: http://www.imperiotransportes.com/ | M42: imperiotransportes.com | N42: Sí | O42: Valparaíso | P42: Valparaíso | R42: Cerro El Altar 2821, Valparaíso | S42: Con número | T42: -33.133244 | U42: -71.550866 | V42: Empresa de transporte por camión | W42: Empresa de transporte por camión, Servicio de transporte | X42: 2 | Y42: 4 | Z42: lunes:9 am–6 pm | martes:9 am–6 pm | miércoles:9 am–6 pm | jueves:9 am–6 pm | viernes:9 am–6 pm | sábado:Cerrado | domingo:Cerrado | AA42: https://www.google.com/maps?cid=6157132699044971350 | AB42: Transporte de carga, Valparaiso, Chile | AC42: 1
A43: ChIJC75NpkZ1YpYRsnJ5GyZX4SA | B43: THM Transporte Humberto Morales | C43: THM Transporte Humberto Morales | E43: 1 | F43: Transporte de carga | G43: Alta | H43: Empresa industrial/logística en zona objetivo con canal de contacto | I43: 85 | J43: +56 32 213 1200 | K43: Fijo | L43: http://www.thm.cl/ | M43: thm.cl | N43: Sí | O43: Valparaíso | P43: Valparaíso | Q43: 0002222 | R43: Novena Avenida 2225, 0002222 Valparaíso | S43: Con número | T43: -33.128277 | U43: -71.555152 | V43: Empresa de transporte por camión | W43: Empresa de transporte por camión | X43: 41 | Y43: 3.9 | Z43: lunes:9 am–6:30 pm | martes:9 am–6:30 pm | miércoles:9 am–6:30 pm | jueves:9 am–6:30 pm | viernes:9 am–6:30 pm | sábado:Cerrado | domingo:Cerrado | AA43: https://www.google.com/maps?cid=2369270700154909362 | AB43: Transporte de carga, Valparaiso, Chile | AC43: 1
A44: ChIJPUVdtVt1YpYRe4HinK-elOk | B44: Bodegas Kochifas | C44: Bodegas Kochifas | E44: 1 | F44: Logística / Almacenaje | G44: Alta | H44: Empresa industrial/logística en zona objetivo con canal de contacto | I44: 85 | J44: +56 9 8901 8446 | K44: Móvil | L44: http://www.bodegaskochifas.cl/ | M44: bodegaskochifas.cl | N44: Sí | O44: Valparaíso | P44: Valparaíso | Q44: 2340000 | R44: Fundo los Perales - Cuesta Balmaceda, Cam. La Pólvora, 2340000 Valparaíso | S44: Sin número | T44: -33.060528 | U44: -71.647527 | V44: Almacén | W44: Almacén | X44: 30 | Y44: 4.3 | Z44: lunes:9 am–6 pm | martes:9 am–6 pm | miércoles:9 am–6 pm | jueves:9 am–6 pm | viernes:9 am–6 pm | sábado:9 am–5 pm | domingo:Cerrado | AA44: https://www.google.com/maps?cid=16831252184478941563 | AB44: Bodegas, Valparaíso - Chile | AC44: 3 | AD44: direccion_imprecisa
A45: ChIJ-c9_U_DdiZYRsg96-XJm3W4 | B45: Endopack Chile | C45: Endopack Chile | E45: 1 | F45: Maquinaria / Industrial | G45: Alta | H45: Empresa industrial/logística en zona objetivo con canal de contacto | I45: 85 | J45: +56 9 8797 0197 | K45: Móvil | L45: http://www.endopackchile.cl/ | M45: endopackchile.cl | N45: Sí | O45: Viña del Mar | P45: Valparaíso | Q45: 2520000 | R45: Etchevers 185, Loc 67-A, 2520000 Viña del Mar, Valparaíso | S45: Con número | T45: -33.024083 | U45: -71.55537 | V45: Empresa de embalaje | W45: Empresa de embalaje | X45: 22 | Y45: 3.6 | Z45: lunes:9:30 am–2:30 pm | martes:9:30 am–2:30 pm | miércoles:9:30 am–2:30 pm | jueves:9:30 am–2:30 pm | viernes:9:30 am–2:30 pm | sábado:10 am–2:30 pm | domingo:Cerrado | AA45: https://www.google.com/maps?cid=7988653958022959026 | AB45: Empresa, Viña del Mar, Chile | AC45: 1
A46: ChIJR1CGMfk4YpYRsM7SwWbQDqA | B46: Maersk Chile | C46: Maersk Chile | D46: Maersk Logistics and Service Chile SpA | E46: 2 | F46: Otros / Servicios empresariales | G46: Alta | H46: Empresa industrial/logística en zona objetivo con canal de contacto | I46: 85 | J46: +56 35 221 1289 | K46: Fijo | L46: https://www.maersk.com/ | M46: maersk.com | N46: Sí | O46: San Antonio | P46: Valparaíso | Q46: 2662756 | R46: Barros Luco 1613, P 12 San Antoni, 2662756 San Antonio, Valparaíso | S46: Con número | T46: -33.593856 | U46: -71.613261 | V46: Servicios de empresa a empresa | W46: Servicios de empresa a empresa, Empresa | X46: 16 | Y46: 3.8 | Z46: lunes:9 am–6 pm | martes:9 am–6 pm | miércoles:9 am–6 pm | jueves:9 am–6 pm | viernes:9 am–6 pm | sábado:Cerrado | domingo:Cerrado | AA46: https://www.google.com/maps?cid=11533384835499478704 | AB46: Empresa, San Antonio, Chile | AC46: 1
A47: ChIJy5pXI-7eiZYRB3ovfXTOXo4 | B47: Reno Chile SA | C47: Reno Chile SA | E47: 1 | F47: Química / Energía | G47: Alta | H47: Empresa industrial/logística en zona objetivo con canal de contacto | I47: 85 | J47: +56 2 2460 1000 | K47: Fijo | L47: http://www.reno.cl/ | M47: reno.cl | N47: Sí | O47: Viña del Mar | P47: Valparaíso | R47: C. Limache 3730, Viña del Mar, Valparaíso | S47: Con número | T47: -33.047233 | U47: -71.513347 | V47: Planta química | W47: Planta química | X47: 13 | Y47: 3.6 | Z47: lunes:8 am–5:30 pm | martes:8 am–5:30 pm | miércoles:8 am–5:30 pm | jueves:8 am–5:30 pm | viernes:8 am–4:30 pm | sábado:Cerrado | domingo:Cerrado | AA47: https://www.google.com/maps?cid=10258864000908360199 | AB47: Empresa, Viña del Mar, Chile | AC47: 1
A48: ChIJoc6Vucp1YpYRAWniB2Mxz8I | B48: TFL TRANSPORTES | C48: TFL TRANSPORTES | E48: 1 | F48: Transporte de carga | G48: Alta | H48: Empresa industrial/logística en zona objetivo con canal de contacto | I48: 85 | J48: +56 9 9879 8720 | K48: Móvil | L48: http://www.tfltransportes.cl/ | M48: tfltransportes.cl | N48: Sí | O48: Valparaíso | P48: Valparaíso | Q48: 3100000 | R48: NOVENA AVENIDA 2315 PLACILLA, ORIENTE, 3100000 Valparaíso | S48: Con número | T48: -33.129352 | U48: -71.55559 | V48: Empresa de transporte por camión | W48: Empresa de transporte por camión | X48: 12 | Y48: 3.6 | Z48: lunes:8:30 am–5:30 pm | martes:8:30 am–5:30 pm | miércoles:8:30 am–5:30 pm | jueves:8:30 am–5:30 pm | viernes:8:30 am–5:30 pm | sábado:Cerrado | domingo:Cerrado | AA48: https://www.google.com/maps?cid=14037492864940927233 | AB48: Transporte de carga, Valparaiso, Chile | AC48: 1
A49: ChIJnTvDu1Q4YpYRSFPQap_n-68 | B49: HGT Extraportuarios S.A. | C49: HGT Extraportuarios S.A. | E49: 1 | F49: Portuario / Contenedores | G49: Alta | H49: Empresa industrial/logística en zona objetivo con canal de contacto | I49: 80 | J49: +56 32 232 4200 | K49: Fijo | L49: http://www.aep.cl/ | M49: aep.cl | N49: Sí | O49: San Antonio | P49: Valparaíso | R49: Pablo Neruda 289, Barrancas, San Antonio, Valparaíso | S49: Con número | T49: -33.602529 | U49: -71.619701 | V49: Almacén | W49: Almacén | X49: 336 | Y49: 3.8 | AA49: https://www.google.com/maps?cid=12680983847669617480 | AB49: Empresa, San Antonio, Chile; Logística en San Antonio, Chile | AC49: 2 | AD49: sin_horario
A50: ChIJiYtgwP_hiZYRODe7AjkNryc | B50: Transportes TRG | C50: Transportes TRG | E50: 1 | F50: Transporte de carga | G50: Alta | H50: Empresa industrial/logística en zona objetivo con canal de contacto | I50: 80 | J50: +56 32 276 8062 | K50: Fijo | L50: http://www.trg.cl/ | M50: trg.cl | N50: Sí | O50: Valparaíso | P50: Valparaíso | R50: Camino Antiguo S/N Esquina La Pólvora, Valparaíso | S50: Solo comuna | T50: -33.094456 | U50: -71.58416 | V50: Empresa de transporte por camión | W50: Empresa de transporte por camión | X50: 20 | Y50: 4.4 | Z50: lunes:9 am–7 pm | martes:9 am–7 pm | miércoles:9 am–7 pm | jueves:9 am–7 pm | viernes:9 am–7 pm | sábado:9 am–1:30 pm | domingo:Cerrado | AA50: https://www.google.com/maps?cid=2859518826913675064 | AB50: Servicios logísticos, Valparaiso - Chile; Servicios logísticos, Valparaiso, Chile; Transporte de carga, Valparaiso, Chile | AC50: 3 | AD50: direccion_imprecisa
A51: ChIJb1_j0XbeiZYRcM2JlVTgF2Q | B51: Servicemaq Ltda | C51: Servicemaq Ltda | E51: 1 | F51: Maquinaria / Industrial | G51: Alta | H51: Empresa industrial/logística en zona objetivo con canal de contacto | I51: 80 | J51: +56 9 6544 1511 | K51: Móvil | L51: http://www.servicemaq.cl/servicios | M51: servicemaq.cl | N51: Sí | O51: Viña del Mar | P51: Valparaíso | Q51: 2520000 | R51: Cancha 106, 2520000 Viña del Mar, Valparaíso | S51: Con número | T51: -33.027546 | U51: -71.540489 | V51: Proveedor de maquinaria de construcción | W51: Proveedor de maquinaria de construcción | X51: 6 | Y51: 2 | Z51: lunes:8 am–6 pm | martes:8 am–6 pm | miércoles:8 am–6 pm | jueves:8 am–6 pm | viernes:8 am–6 pm | sábado:Cerrado | domingo:Cerrado | AA51: https://www.google.com/maps?cid=7212479982147849584 | AB51: Maquinaria industrial, Viña del Mar-Chile | AC51: 1
A52: ChIJESF5OeXgiZYRylgHi9rPRyc | B52: Mger Industrial Ltda | C52: Mger Industrial Ltda | E52: 1 | F52: Maquinaria / Industrial | G52: Alta | H52: Empresa industrial/logística en zona objetivo con canal de contacto | I52: 80 | J52: +56 9 6206 0733 | K52: Móvil | L52: http://www.mger.cl/ | M52: mger.cl | N52: Sí | O52: Viña del Mar | P52: Valparaíso | R52: Camino lajarilla 744 bodega 3A, Viña del Mar, Valparaíso | S52: Con número | T52: -32.977817 | U52: -71.489483 | V52: Proveedor de maquinaria de construcción | W52: Proveedor de maquinaria de construcción | X52: 5 | Y52: 3.4 | Z52: lunes:9 am–1 pm | martes:9 am–1 pm | miércoles:9 am–1 pm | jueves:9 am–1 pm | viernes:9 am–1 pm | sábado:Cerrado | domingo:Cerrado | AA52: https://www.google.com/maps?cid=2830459428367980746 | AB52: Maquinaria industrial, Viña del Mar-Chile | AC52: 1
A53: ChIJe1rznE04YpYR_akn6Hkop-k | B53: Transportes CaboVerde | C53: Transportes CaboVerde | E53: 1 | F53: Transporte de carga | G53: Alta | H53: Empresa industrial/logística en zona objetivo con canal de contacto | I53: 80 | J53: +56 9 8297 9433 | K53: Móvil | L53: http://www.transportescaboverde.cl/ | M53: transportescaboverde.cl | N53: Sí | O53: San Antonio | P53: Valparaíso | Q53: 2660897 | R53: San Pedro 2130, 2660897 San Antonio, Valparaíso | S53: Con número | T53: -33.60938 | U53: -71.616533 | V53: Empresa de transporte por camión | W53: Empresa de transporte por camión | X53: 4 | Y53: 3.3 | Z53: lunes:8 am–8 pm | martes:8 am–8 pm | miércoles:8 am–8 pm | jueves:8 am–8 pm | viernes:8 am–8 pm | sábado:8 am–8 pm | domingo:8 am–8 pm | AA53: https://www.google.com/maps?cid=16836470235998956029 | AB53: Transporte de carga, San Antonio, Chile | AC53: 1
A54: ChIJ9QouB5_fiZYRvyARZGumRSg | B54: Maquintec | C54: Maquintec | E54: 1 | F54: Maquinaria / Industrial | G54: Alta | H54: Empresa industrial/logística en zona objetivo con canal de contacto | I54: 80 | J54: +56 9 3545 4670 | K54: Móvil | L54: https://maquintec.cl/ | M54: maquintec.cl | N54: Sí | O54: Viña del Mar | P54: Valparaíso | R54: Agua Santa 2455, Viña del Mar, Valparaíso | S54: Con número | T54: -33.039203 | U54: -71.569748 | V54: Oficinas de empresa | W54: Oficinas de empresa, Alquiler de maquinaria y equipos industriales, Cuarto de herramientas | X54: 3 | Y54: 3.7 | Z54: lunes:8:30 am–6 pm | martes:8:30 am–6:30 pm | miércoles:8:30 am–6:30 pm | jueves:8:30 am–6:30 pm | viernes:8:30 am–6:30 pm | sábado:Cerrado | domingo:Cerrado | AA54: https://www.google.com/maps?cid=2901908515080708287 | AB54: Maquinaria industrial, Viña del Mar-Chile | AC54: 1
A55: ChIJ02c5Wzc4YpYRMihqhMsnUzs | B55: ICA Transportes | C55: ICA Transportes | E55: 1 | F55: Transporte de carga | G55: Alta | H55: Empresa industrial/logística en zona objetivo con canal de contacto | I55: 80 | J55: +56 35 228 0179 | K55: Fijo | L55: http://www.icatransportes.cl/ | M55: icatransportes.cl | N55: Sí | O55: San Antonio | P55: Valparaíso | Q55: 2661191 | R55: El Paico 1202, 2661191 San Antonio, Valparaíso | S55: Con número | T55: -33.622683 | U55: -71.608396 | V55: Empresa de transporte por camión | W55: Empresa de transporte por camión | X55: 3 | Y55: 3.7 | Z55: lunes:8:30 am–6 pm | martes:8:30 am–6 pm | miércoles:8:30 am–6 pm | jueves:8:30 am–6 pm | viernes:8:30 am–6 pm | sábado:8:30 am–6 pm | domingo:Cerrado | AA55: https://www.google.com/maps?cid=4274804226358126642 | AB55: Transporte de carga, San Antonio, Chile | AC55: 1
A56: ChIJj0oIbl3ciZYRvbfTjTSSrr4 | B56: Empresas Carozzi Planta Reñaca | C56: Empresas Carozzi Planta Reñaca | E56: 1 | F56: Otros / Servicios empresariales | G56: Alta | H56: Empresa industrial/logística en zona objetivo con canal de contacto | I56: 75 | J56: +56 32 227 6000 | K56: Fijo | N56: No | O56: Viña del Mar | P56: Valparaíso | R56: Cam. Internacional 2825, Viña del Mar, Valparaíso | S56: Con número | T56: -32.982575 | U56: -71.500646 | V56: Comercio | W56: Comercio | X56: 537 | Y56: 4.5 | Z56: lunes:8 am–4 pm | martes:8 am–4 pm | miércoles:8 am–4 pm | jueves:8 am–4 pm | viernes:8 am–4 pm | sábado:8 am–4 pm | domingo:Cerrado | AA56: https://www.google.com/maps?cid=13740080267569379261 | AB56: Empresa, Viña del Mar, Chile | AC56: 1 | AD56: sin_web_propia
A57: ChIJOy_3Mv85YpYRlEDRDZPxJkE | B57: AGUNSA EXTRAPORTUARIO - AEXSA | C57: AGUNSA EXTRAPORTUARIO - AEXSA | E57: 1 | F57: Portuario / Contenedores | G57: Alta | H57: Empresa industrial/logística en zona objetivo con canal de contacto | I57: 75 | J57: +56 35 245 6800 | K57: Fijo | L57: http://www.aexsa.cl/ | M57: aexsa.cl | N57: Sí | O57: San Antonio | P57: Valparaíso | R57: San Antonio, Valparaíso | S57: Solo comuna | T57: -33.586288 | U57: -71.579295 | V57: Almacén | W57: Almacén | X57: 227 | Y57: 3.9 | Z57: lunes:9 am–9 pm | martes:9 am–9 pm | miércoles:9 am–9 pm | jueves:9 am–9 pm | viernes:9 am–9 pm | sábado:9 am–3 pm | domingo:Cerrado | AA57: https://www.google.com/maps?cid=4694705275474624660 | AB57: Bodegas y almacenaje, San Antonio | AC57: 1 | AD57: direccion_imprecisa
A58: ChIJb6g1Zfg4YpYRNUoyyQOwvLk | B58: Ferretería Antofagasta | C58: Ferretería Antofagasta | E58: 1 | F58: Maquinaria / Industrial | G58: Alta | H58: Empresa industrial/logística en zona objetivo con canal de contacto | I58: 75 | J58: +56 9 9744 6775 | K58: Móvil | L58: https://wa.me/56997446775 | M58: wa.me | N58: No | O58: San Antonio | P58: Valparaíso | Q58: 2662798 | R58: Antofagasta 214, 2662798 San Antonio, Valparaíso | S58: Con número | T58: -33.59618 | U58: -71.610255 | V58: Tienda de herramientas | W58: Tienda de herramientas, Mercado de materiales de construcción, Establecimiento de venta de madera, Proveedor de metales, Proveedor de madera | X58: 60 | Y58: 4.5 | Z58: lunes:9 am–2 pm | martes:9 am–2 pm | miércoles:9 am–2 pm | jueves:9 am–2 pm | viernes:9 am–2 pm | sábado:9:30 am–1:30 pm | domingo:Cerrado | AA58: https://www.google.com/maps?cid=13383765722945178165 | AB58: Maquinaria industrial, San Antonio, Chile | AC58: 1 | AD58: sin_web_propia
A59: ChIJm4tO6kDgiZYR5A_SLU9biVg | B59: Altos del Puerto | C59: Altos del Puerto | E59: 1 | F59: Logística / Almacenaje | G59: Alta | H59: Empresa industrial/logística en zona objetivo con canal de contacto | I59: 75 | J59: +56 9 7748 2466 | K59: Móvil | L59: http://www.altosdelpuerto.cl/ | M59: altosdelpuerto.cl | N59: Sí | O59: Valparaíso | P59: Valparaíso | R59: Camino La Pólvora 106, Valparaíso | S59: Con número | T59: -33.095563 | U59: -71.599969 | V59: Bodega | W59: Bodega | X59: 46 | Y59: 3.8 | AA59: https://www.google.com/maps?cid=6379730742776303588 | AB59: Bodegas, Valparaíso - Chile | AC59: 2 | AD59: sin_horario
A60: ChIJXYWy60bDiZYRE1elK25TwIU | B60: BASF Concón | C60: BASF Concón | E60: 1 | F60: Química / Energía | G60: Alta | H60: Empresa industrial/logística en zona objetivo con canal de contacto | I60: 75 | J60: +56 32 226 7500 | K60: Fijo | L60: http://www.basf.cl/ | M60: basf.cl | N60: Sí | O60: Quintero | P60: Valparaíso | R60: Quintero, Valparaíso | S60: Solo comuna | T60: -32.915821 | U60: -71.496033 | V60: Planta química | W60: Planta química | X60: 7 | Y60: 4.7 | Z60: lunes:8 am–6 pm | martes:8 am–6 pm | miércoles:8 am–6 pm | jueves:8 am–6 pm | viernes:8 am–6 pm | sábado:8 am–6 pm | domingo:Cerrado | AA60: https://www.google.com/maps?cid=9637794935216625427 | AB60: Procesos Químicos, Concón - Chile | AC60: 2 | AD60: direccion_imprecisa
A61: ChIJWU61uN85YpYR12pGP1ryJdU | B61: MAKK SpA | C61: MAKK SpA | E61: 1 | F61: Maquinaria / Industrial | G61: Alta | H61: Empresa industrial/logística en zona objetivo con canal de contacto | I61: 75 | J61: +56 9 4749 7378 | K61: Móvil | L61: http://www.makk.cl/ | M61: makk.cl | N61: Sí | O61: San Antonio | P61: Valparaíso | Q61: 2662936 | R61: Republica 1937, 2662936 Barrancas, San Antonio, Valparaíso | S61: Con número | T61: -33.59915 | U61: -71.60842 | V61: Servicio de alquiler de herramientas | W61: Servicio de alquiler de herramientas | Z61: lunes:8:30 am–1:30 pm | martes:8:30 am–1:30 pm | miércoles:8:30 am–1:30 pm | jueves:8:30 am–1:30 pm | viernes:8:30 am–1:30 pm | sábado:Cerrado | domingo:Cerrado | AA61: https://www.google.com/maps?cid=15358948573639502551 | AB61: Maquinaria (archivo) | AC61: 2 | AD61: sin_resenas
A62: ChIJifX48385YpYRzRgugRuarwo | B62: Inversiones Kanin Ltda | C62: Inversiones Kanin Ltda | E62: 1 | F62: Maquinaria / Industrial | G62: Alta | H62: Empresa industrial/logística en zona objetivo con canal de contacto | I62: 75 | J62: +56 9 7900 5720 | K62: Móvil | L62: https://www.kanin.cl/ | M62: kanin.cl | N62: Sí | O62: San Antonio | P62: Valparaíso | Q62: 2660000 | R62: Divina Providencia 2105, Depto 1, 2660000 San Antonio, Valparaíso | S62: Con número | T62: -33.611124 | U62: -71.61593 | V62: Empresa de movimiento de tierras | W62: Empresa de movimiento de tierras, Empresa de recogida de escombros | Z62: lunes:8 am–6 pm | martes:8 am–6 pm | miércoles:8 am–6 pm | jueves:8 am–6 pm | viernes:8 am–6 pm | sábado:8 am–2 pm | domingo:Cerrado | AA62: https://www.google.com/maps?cid=770003504225720525 | AB62: Maquinaria (archivo) | AC62: 2 | AD62: sin_resenas
A63: ChIJqXTam6TdiZYRpFJgmTXNuNc | B63: Intermarine Services Group | C63: Intermarine Services Group | E63: 1 | F63: Maquinaria / Industrial | G63: Alta | H63: Empresa industrial/logística en zona objetivo con canal de contacto | I63: 75 | J63: +56 9 3263 5175 | K63: Móvil | L63: https://www.intermarineservices.cl/ | M63: intermarineservices.cl | N63: Sí | O63: Viña del Mar | P63: Valparaíso | Q63: 2520000 | R63: 2 Ote. 124, Of. 205, 2520000 Viña del Mar, Valparaíso | S63: Con número | T63: -33.021511 | U63: -71.548534 | V63: Empresa de suministros industriales | W63: Empresa de suministros industriales | Z63: lunes:Abierto las 24 horas | martes:Abierto las 24 horas | miércoles:Abierto las 24 horas | jueves:Abierto las 24 horas | viernes:Abierto las 24 horas | sábado:Abierto las 24 horas | domingo:Abierto las 24 horas | AA63: https://www.google.com/maps?cid=15544399743959454372 | AB63: Manufactura (archivo) | AC63: 1 | AD63: sin_resenas
A64: ChIJz3X5dcjdiZYRaBFIjWu_Yio | B64: A1 Maquinarias | C64: A1 Maquinarias | E64: 1 | F64: Maquinaria / Industrial | G64: Alta | H64: Empresa industrial/logística en zona objetivo con canal de contacto | I64: 75 | J64: +56 9 5283 4355 | K64: Móvil | L64: https://a1maquinarias.cl/ | M64: a1maquinarias.cl | N64: Sí | O64: Viña del Mar | P64: Valparaíso | Q64: 2500000 | R64: 1 Pte 18, Ofi C1, 2500000 Viña del Mar, Valparaíso | S64: Con número | T64: -33.022146 | U64: -71.552638 | V64: Empresa de suministros industriales | W64: Empresa de suministros industriales, Servicio de alquiler de equipos para la construcción, Proveedor de maquinaria de construcción, Concesionario de maquinaria de construcción, Servicio de alquiler de maquinaria para construcción, Taller de maquinaria, Equipo para minería | Z64: lunes:8 am–7 pm | martes:8 am–7 pm | miércoles:8 am–7 pm | jueves:8 am–7 pm | viernes:8 am–7 pm | sábado:9 am–3 pm | domingo:Cerrado | AA64: https://www.google.com/maps?cid=3054213965963333992 | AB64: Maquinaria (archivo) | AC64: 1 | AD64: sin_resenas
A65: ChIJxZqFMMHdiZYRUrvlkQLBz_E | B65: Acemar Chile Ltda | C65: Acemar Chile Ltda | E65: 1 | F65: Maquinaria / Industrial | G65: Alta | H65: Empresa industrial/logística en zona objetivo con canal de contacto | I65: 75 | J65: +56 32 336 6411 | K65: Fijo | L65: http://www.acemarchile.cl/conctactenos/ | M65: acemarchile.cl | N65: Sí | O65: Viña del Mar | P65: Valparaíso | Q65: 2552387 | R65: Raul Toro 144 Achupallas, 2552387 Viña del Mar, Valparaíso | S65: Con número | T65: -33.000318 | U65: -71.514089 | V65: Empresa de suministros industriales | W65: Empresa de suministros industriales | Z65: lunes:9 am–6 pm | martes:9 am–6 pm | miércoles:9 am–6 pm | jueves:9 am–6 pm | viernes:9 am–6 pm | sábado:Cerrado | domingo:Cerrado | AA65: https://www.google.com/maps?cid=17424357700101585746 | AB65: Maquinaria (archivo) | AC65: 1 | AD65: sin_resenas
A66: ChIJjy3J5FPdiZYRBc9bfd1p9mU | B66: Vidangossy Maquinaria | C66: Vidangossy Maquinaria | E66: 1 | F66: Maquinaria / Industrial | G66: Alta | H66: Empresa industrial/logística en zona objetivo con canal de contacto | I66: 75 | J66: +56 9 8731 9307 | K66: Móvil | L66: https://vidangossymaquinaria.com/ | M66: vidangossymaquinaria.com | N66: Sí | O66: Concón | P66: Valparaíso | Q66: 2510000 | R66: Av. Concón Reñaca 4000, Ofi 203, 2510000 Concón, Valparaíso | S66: Con número | T66: -32.93746 | U66: -71.545341 | V66: Proveedor de equipos para fábricas | W66: Proveedor de equipos para fábricas | Z66: lunes:8 am–6 pm | martes:8 am–6 pm | miércoles:8 am–6 pm | jueves:8 am–6 pm | viernes:8 am–6 pm | sábado:8 am–2:30 pm | domingo:Cerrado | AA66: https://www.google.com/maps?cid=7347176242113400581 | AB66: Maquinaria (archivo) | AC66: 1 | AD66: sin_resenas
A67: ChIJlfcyVCnhiZYRMOrr-s2b2H4 | B67: Locargo Transporte y Logística | C67: Locargo Transporte y Logística | E67: 1 | F67: Transporte de carga | G67: Alta | H67: Empresa industrial/logística en zona objetivo con canal de contacto | I67: 75 | J67: +56 9 7698 9476 | K67: Móvil | L67: https://www.locargo.cl/ | M67: locargo.cl | N67: Sí | O67: Valparaíso | P67: Valparaíso | Q67: 2340000 | R67: Esmeralda 973, Ofi 502, 2340000 Valparaíso | S67: Con número | T67: -33.04096 | U67: -71.625364 | V67: Servicio de envíos | W67: Servicio de envíos, Servicio de transporte | Z67: lunes:9 am–5 pm | martes:9 am–5 pm | miércoles:9 am–5 pm | jueves:9 am–5 pm | viernes:9 am–5 pm | sábado:Cerrado | domingo:Cerrado | AA67: https://www.google.com/maps?cid=9140226752728787504 | AB67: Servicios logísticos (archivo) | AC67: 2 | AD67: sin_resenas
A68: ChIJV-1YbsLhiZYR2zSaai1uM90 | B68: Compañía de Servicios Integrales de Transportes y Aduaneros SPA | C68: Compañía de Servicios Integrales de Transportes y Aduaneros SPA | E68: 1 | F68: Transporte de carga | G68: Alta | H68: Empresa industrial/logística en zona objetivo con canal de contacto | I68: 75 | J68: +56 9 5144 2374 | K68: Móvil | L68: http://www.ncsita.com/ | M68: ncsita.com | N68: Sí | O68: Valparaíso | P68: Valparaíso | Q68: 2340000 | R68: Prat 814, Ofi 503, 2340000 Valparaíso | S68: Con número | T68: -33.040344 | U68: -71.627365 | V68: Empresa de transporte por camión | W68: Empresa de transporte por camión | Z68: lunes:9 am–5 pm | martes:9 am–5 pm | miércoles:9 am–5 pm | jueves:9 am–5 pm | viernes:9 am–5 pm | sábado:9 am–1 pm | domingo:Cerrado | AA68: https://www.google.com/maps?cid=15939204647535391963 | AB68: Servicios logísticos (archivo) | AC68: 2 | AD68: sin_resenas
A69: ChIJEV5ikqrfiZYRCpoBgwrOzIg | B69: Transportes Marcelo Sepúlveda | C69: Transportes Marcelo Sepúlveda | E69: 1 | F69: Transporte de carga | G69: Alta | H69: Empresa industrial/logística en zona objetivo con canal de contacto | I69: 70 | J69: +56 9 7621 6002 | K69: Móvil | N69: No | O69: Viña del Mar | P69: Valparaíso | Q69: 2520000 | R69: Av. Valdivia 212, 2520000 Viña del Mar, Valparaíso | S69: Con número | T69: -33.041405 | U69: -71.528312 | V69: Servicio de mudanzas | W69: Servicio de mudanzas | X69: 40 | Y69: 5 | Z69: lunes:Abierto las 24 horas | martes:Abierto las 24 horas | miércoles:Abierto las 24 horas | jueves:Abierto las 24 horas | viernes:Abierto las 24 horas | sábado:Abierto las 24 horas | domingo:Abierto las 24 horas | AA69: https://www.google.com/maps?cid=9857480228950088202 | AB69: Transporte de carga, Viña del Mar, Chile | AC69: 2 | AD69: sin_web_propia
A70: ChIJmyBh1N7eiZYRyymKwdg5rDE | B70: Química Passol S.A. | C70: Química Passol S.A. | E70: 1 | F70: Química / Energía | G70: Alta | H70: Empresa industrial/logística en zona objetivo con canal de contacto | I70: 70 | K70: Sin teléfono | L70: https://www.passol.cl/ | M70: passol.cl | N70: Sí | O70: Viña del Mar | P70: Valparaíso | Q70: 2520651 | R70: C. Limache 4225, 2520651 Viña del Mar, Valparaíso | S70: Con número | T70: -33.050182 | U70: -71.506294 | V70: Pintura | W70: Pintura, Planta química, Fabricante de pinturas | X70: 25 | Y70: 4.1 | Z70: lunes:8 am–6 pm | martes:8 am–6 pm | miércoles:8 am–6 pm | jueves:8 am–6 pm | viernes:8 am–6 pm | sábado:Cerrado | domingo:Cerrado | AA70: https://www.google.com/maps?cid=3579299406975478219 | AB70: Procesos Químicos, Concón - Chile; Procesos Químicos, Quilpué - Chile | AC70: 3 | AD70: sin_telefono
A71: ChIJbUqcgGhHYpYR4oA0XCFrz5U | B71: Transportes Nuevo Mundo | C71: Transportes Nuevo Mundo | E71: 1 | F71: Transporte de carga | G71: Alta | H71: Empresa industrial/logística en zona objetivo con canal de contacto | I71: 70 | K71: Sin teléfono | L71: https://www.transportesnm.cl/ | M71: transportesnm.cl | N71: Sí | O71: San Antonio | P71: Valparaíso | R71: Las Acacias 176, San Antonio, Valparaíso | S71: Con número | T71: -33.562914 | U71: -71.558333 | V71: Oficinas de empresa | W71: Oficinas de empresa | X71: 22 | Y71: 4.7 | Z71: lunes:8 am–10 pm | martes:8 am–10 pm | miércoles:8 am–10 pm | jueves:8 am–10 pm | viernes:8 am–10 pm | sábado:8 am–6 pm | domingo:Cerrado | AA71: https://www.google.com/maps?cid=10794964622855405794 | AB71: Transporte de carga, San Antonio, Chile | AC71: 1 | AD71: sin_telefono
A72: ChIJ92VVPmPeiZYR3eeshGAjn1c | B72: Transportes Artisa | C72: Transportes Artisa | E72: 1 | F72: Transporte de carga | G72: Alta | H72: Empresa industrial/logística en zona objetivo con canal de contacto | I72: 70 | J72: +56 32 218 7550 | K72: Fijo | N72: No | O72: Viña del Mar | P72: Valparaíso | R72: 1 Nte. 2461, Viña del Mar, Valparaíso | S72: Con número | T72: -33.032845 | U72: -71.529174 | V72: Servicio de transporte | W72: Servicio de transporte | X72: 15 | Y72: 4.7 | Z72: lunes:8:30 am–6:30 pm | martes:8:30 am–6:30 pm | miércoles:8:30 am–6:30 pm | jueves:8:30 am–6:30 pm | viernes:8:30 am–6:30 pm | sábado:Cerrado | domingo:Cerrado | AA72: https://www.google.com/maps?cid=6313804100046481373 | AB72: Transporte de carga, Viña del Mar, Chile | AC72: 2 | AD72: sin_web_propia
A73: ChIJPdCNnvPeiZYRfZ4JSCREMc0 | B73: Starken Viña Central Carga | C73: Starken Viña Central Carga | E73: 1 | F73: Transporte de carga | G73: Alta | H73: Empresa industrial/logística en zona objetivo con canal de contacto | I73: 65 | K73: Sin teléfono | L73: https://www.starken.cl/ | M73: starken.cl | N73: Sí | O73: Viña del Mar | P73: Valparaíso | Q73: 2562231 | R73: bodega 13 - C. Limache N°3400, 2562231 Viña del Mar, Valparaíso | S73: Con número | T73: -33.043809 | U73: -71.518378 | V73: Empresa de transporte por camión | W73: Empresa de transporte por camión, Oficina de correos, Servicio de mensajería | X73: 215 | Y73: 2.7 | Z73: lunes:9 am–6:30 pm | martes:9 am–6:30 pm | miércoles:9 am–6:30 pm | jueves:9 am–6:30 pm | viernes:9 am–6:30 pm | sábado:9 am–1 pm | domingo:Cerrado | AA73: https://www.google.com/maps?cid=14785673974252150397 | AB73: Transporte de carga, Viña del Mar, Chile | AC73: 2 | AD73: sin_telefono
A74: ChIJY6NavVM4YpYRWIju5KJpa_s | B74: Sitrans San Antonio Bajo | C74: Sitrans San Antonio Bajo | E74: 1 | F74: Otros / Servicios empresariales | G74: Alta | H74: Empresa industrial/logística en zona objetivo con canal de contacto | I74: 65 | J74: +56 35 236 2100 | K74: Fijo | N74: No | O74: San Antonio | P74: Valparaíso | R74: Bernardo O'Higgins Riquelme 2767, San Antonio, Valparaíso | S74: Con número | T74: -33.60458 | U74: -71.616111 | V74: Oficinas de empresa | W74: Oficinas de empresa | X74: 159 | Y74: 4 | AA74: https://www.google.com/maps?cid=18116690074374408280 | AB74: Empresa, San Antonio, Chile | AC74: 1 | AD74: sin_web_propia, sin_horario
A75: ChIJpbVg4eE4YpYRX7eoEeXZFj8 | B75: Puerto Panul S.A. | C75: Puerto Panul S.A. | E75: 1 | F75: Otros / Servicios empresariales | G75: Alta | H75: Empresa industrial/logística en zona objetivo con canal de contacto | I75: 65 | K75: Sin teléfono | L75: http://www.puertopanul.cl/ | M75: puertopanul.cl | N75: Sí | O75: San Antonio | P75: Valparaíso | R75: Antonio Núñez de Fonseca 440, San Antonio, Valparaíso | S75: Con número | T75: -33.581255 | U75: -71.619611 | V75: Oficinas de empresa | W75: Oficinas de empresa | X75: 75 | Y75: 4.4 | AA75: https://www.google.com/maps?cid=4546060451744102239 | AB75: Empresa, San Antonio, Chile | AC75: 1 | AD75: sin_telefono, sin_horario
A76: ChIJ8daEza05YpYRk_rvwpVriEo | B76: Nodo Logistico | C76: Nodo Logistico | E76: 1 | F76: Logística / Almacenaje | G76: Alta | H76: Empresa industrial/logística en zona objetivo con canal de contacto | I76: 65 | J76: +56 9 6655 2831 | K76: Móvil | N76: No | O76: San Antonio | P76: Valparaíso | R76: La Playa 34, San Antonio, Valparaíso | S76: Con número | T76: -33.607457 | U76: -71.625016 | V76: Servicio de logística | W76: Servicio de logística | X76: 72 | Y76: 3.9 | Z76: lunes:8 am–12 pm | martes:8 am–12 pm | miércoles:8 am–12 pm | jueves:8 am–12 pm | viernes:8 am–12 pm | sábado:8 am–12 pm | domingo:Cerrado | AA76: https://www.google.com/maps?cid=5370660846604122771 | AB76: Logística en San Antonio, Chile; Servicios logísticos, San Antonio, Chile | AC76: 2 | AD76: sin_web_propia
A77: ChIJ99HLpsw5YpYROURRiPBmqH8 | B77: Planta San Antonio | C77: Planta San Antonio | E77: 1 | F77: Otros / Servicios empresariales | G77: Alta | H77: Empresa industrial/logística en zona objetivo con canal de contacto | I77: 65 | K77: Sin teléfono | L77: https://unacem.cl/ | M77: unacem.cl | N77: Sí | O77: San Antonio | P77: Valparaíso | Q77: 2660000 | R77: Ruta G-56, Acceso al puerto 2549, 2660000 San Antonio, Valparaíso | S77: Con número | T77: -33.595652 | U77: -71.589409 | V77: Oficinas de empresa | W77: Oficinas de empresa | X77: 7 | Y77: 5 | Z77: lunes:9 am–7 pm | martes:9 am–7 pm | miércoles:9 am–7 pm | jueves:9 am–7 pm | viernes:9 am–7 pm | sábado:Cerrado | domingo:Cerrado | AA77: https://www.google.com/maps?cid=9198715422169449529 | AB77: Empresa, San Antonio, Chile | AC77: 1 | AD77: sin_telefono
A78: ChIJlQkmhwQ5YpYRgmHcuSt6us4 | B78: COSEDUCAM S.A. | C78: COSEDUCAM S.A. | E78: 1 | F78: Logística / Almacenaje | G78: Alta | H78: Empresa industrial/logística en zona objetivo con canal de contacto | I78: 65 | J78: +56 35 221 2005 | K78: Fijo | N78: No | O78: San Antonio | P78: Valparaíso | Q78: 2660000 | R78: J.L Sanfuentes A 1137, 2660000 San Antonio, Valparaíso | S78: Con número | T78: -33.588741 | U78: -71.613808 | V78: Servicio de gestión de residuos | W78: Servicio de gestión de residuos, Servicio de mensajería | X78: 5 | Y78: 4.8 | Z78: lunes:Abierto las 24 horas | martes:Abierto las 24 horas | miércoles:Abierto las 24 horas | jueves:Abierto las 24 horas | viernes:Abierto las 24 horas | sábado:Abierto las 24 horas | domingo:Abierto las 24 horas | AA78: https://www.google.com/maps?cid=14896353045701747074 | AB78: Servicios logísticos, San Antonio, Chile | AC78: 1 | AD78: sin_web_propia
A79: ChIJV1hlfx_fiZYRKocrpicu9DA | B79: Aerzen Chile S.P.A. | C79: Aerzen Chile S.P.A. | Compresores, Sopladores y Turbosopladores | E79: 1 | F79: Maquinaria / Industrial | G79: Alta | H79: Empresa industrial/logística en zona objetivo con canal de contacto | I79: 65 | K79: Sin teléfono | L79: https://www.aerzen.com/chile | M79: aerzen.com | N79: Sí | O79: Viña del Mar | P79: Valparaíso | Q79: 2562231 | R79: C. Limache 3116, 2562231 Viña del Mar, Valparaíso | S79: Con número | T79: -33.039722 | U79: -71.524436 | V79: Empresa de suministros industriales | W79: Empresa de suministros industriales | X79: 4 | Y79: 4 | Z79: lunes:8:30 am–5:30 pm | martes:8:30 am–5:30 pm | miércoles:8:30 am–5:30 pm | jueves:8:30 am–5:30 pm | viernes:8:30 am–5:30 pm | sábado:Cerrado | domingo:Cerrado | AA79: https://www.google.com/maps?cid=3527495155964413738 | AB79: Maquinaria industrial, Viña del Mar-Chile | AC79: 1 | AD79: sin_telefono, nombre_corregido
A80: ChIJC5D3jvt1YpYRHn3LpOFzMvM | B80: Rentas Valfrio Limitada | C80: Rentas Valfrio Limitada | D80: Delfrio Frigorífico de Valparaiso S.A. | E80: 2 | F80: Frío / Alimentos | G80: Alta | H80: Empresa industrial/logística en zona objetivo con canal de contacto | I80: 65 | J80: +56 32 229 1166 | K80: Fijo | N80: No | O80: Valparaíso | P80: Valparaíso | Q80: 2340000 | R80: Ruta 68 N° 1173 (Ex 1240) Placilla, 2340000 Valparaíso | S80: Con número | T80: -33.118454 | U80: -71.560426 | V80: Instalación de almacenamiento en frío | W80: Instalación de almacenamiento en frío | X80: 1 | Y80: 5 | Z80: lunes:8:30 am–6 pm | martes:8:30 am–6 pm | miércoles:8:30 am–6 pm | jueves:8:30 am–6 pm | viernes:8:30 am–6 pm | sábado:Cerrado | domingo:Cerrado | AA80: https://www.google.com/maps?cid=17524196513021656350 | AB80: Frigoríficos, V Región, Chile | AC80: 1 | AD80: sin_web_propia
A81: ChIJj4m39ujNiZYRtDG8zj3SEtM | B81: Frigorífico Lihuen | C81: Frigorífico Lihuen | E81: 1 | F81: Frío / Alimentos | G81: Alta | H81: Empresa industrial/logística en zona objetivo con canal de contacto | I81: 65 | K81: Sin teléfono | L81: https://holdinglihuen.cl/ | M81: holdinglihuen.cl | N81: Sí | O81: Quillota | P81: Valparaíso | Q81: 2260000 | R81: C. Herboso 64, B, 2260000 Quillota, Valparaíso | S81: Con número | T81: -32.87794 | U81: -71.239018 | V81: Instalación de almacenamiento en frío | W81: Instalación de almacenamiento en frío, Carnicería, Planta de refrigeración | X81: 1 | Y81: 5 | Z81: lunes:8 am–4 pm | martes:8 am–4 pm | miércoles:8 am–4 pm | jueves:8 am–4 pm | viernes:8 am–4 pm | sábado:Cerrado | domingo:Cerrado | AA81: https://www.google.com/maps?cid=15209450054486864308 | AB81: Frigoríficos, V Región, Chile | AC81: 1 | AD81: sin_telefono
A82: ChIJsZaZBKs5YpYR9Sxi3a6NM80 | B82: Frulog | C82: Frulog | E82: 1 | F82: Transporte de carga | G82: Alta | H82: Empresa industrial/logística en zona objetivo con canal de contacto | I82: 65 | K82: Sin teléfono | L82: https://www.frulog.cl/ | M82: frulog.cl | N82: Sí | O82: San Antonio | P82: Valparaíso | Q82: 2660000 | R82: Sanfuentes 2096, 2660000 Valparaíso, San Antonio, Valparaíso | S82: Con número | T82: -33.598801 | U82: -71.614104 | V82: Empresa de transporte por camión | W82: Empresa de transporte por camión | X82: 1 | Y82: 4 | Z82: lunes:9 am–6 pm | martes:9 am–6 pm | miércoles:9 am–6 pm | jueves:9 am–6 pm | viernes:9 am–6 pm | sábado:Cerrado | domingo:Cerrado | AA82: https://www.google.com/maps?cid=14786317783765495029 | AB82: Logística en San Antonio, Chile; Servicios logísticos, San Antonio, Chile; Transporte de carga, San Antonio, Chile | AC82: 3 | AD82: sin_telefono
A83: ChIJiUFHU2vhiZYRWvc28PYYr6s | B83: Transportes GyC Valparaíso | C83: Transportes GyC Valparaíso | E83: 1 | F83: Transporte de carga | G83: Alta | H83: Empresa industrial/logística en zona objetivo con canal de contacto | I83: 65 | J83: +56 9 8213 9767 | K83: Móvil | N83: No | O83: Valparaíso | P83: Valparaíso | Q83: 2340000 | R83: pasaje el peumo - El Criquet, casa 34, 2340000 Valparaíso | S83: Con número | T83: -33.06587 | U83: -71.643531 | V83: Empresa de transporte por camión | W83: Empresa de transporte por camión | X83: 1 | Y83: 5 | Z83: lunes:8:30 am–7:30 pm | martes:8:30 am–7:30 pm | miércoles:8:30 am–7:30 pm | jueves:8:30 am–7:30 pm | viernes:8:30 am–7:30 pm | sábado:8:30 am–7:30 pm | domingo:Cerrado | AA83: https://www.google.com/maps?cid=12371134150281197402 | AB83: Transporte de carga, Valparaiso, Chile | AC83: 1 | AD83: sin_web_propia
A84: ChIJ5YqMzEN1YpYR7h4l2h5j-r4 | B84: Transporte Carreño & Carreño spa | C84: Transporte Carreño & Carreño spa | E84: 1 | F84: Transporte de carga | G84: Alta | H84: Empresa industrial/logística en zona objetivo con canal de contacto | I84: 65 | J84: +56 9 5051 6100 | K84: Móvil | N84: No | O84: Valparaíso | P84: Valparaíso | R84: 2350, Valparaíso | S84: Con número | T84: -33.129962 | U84: -71.551331 | V84: Empresa de transporte por camión | W84: Empresa de transporte por camión | X84: 1 | Y84: 5 | Z84: lunes:Abierto las 24 horas | martes:Abierto las 24 horas | miércoles:Abierto las 24 horas | jueves:Abierto las 24 horas | viernes:Abierto las 24 horas | sábado:Abierto las 24 horas | domingo:Abierto las 24 horas | AA84: https://www.google.com/maps?cid=13761420595544006382 | AB84: Transporte de carga, Valparaiso, Chile | AC84: 1 | AD84: sin_web_propia
A85: ChIJ8VGIq1rfiZYRa-LT7rucytM | B85: Cifuentes Zúñiga Transportes y Servicios Ltda. | C85: Cifuentes Zúñiga Transportes y Servicios Ltda. | E85: 1 | F85: Transporte de carga | G85: Alta | H85: Empresa industrial/logística en zona objetivo con canal de contacto | I85: 65 | J85: +56 9 7995 7860 | K85: Móvil | N85: No | O85: Viña del Mar | P85: Valparaíso | Q85: 2570023 | R85: Jackson 900 Magenta 6 depto 62, 2570023 Valparaíso, Viña del Mar, Valparaíso | S85: Con número | T85: -33.031097 | U85: -71.539122 | V85: Empresa de transporte por camión | W85: Empresa de transporte por camión | X85: 1 | Y85: 5 | Z85: lunes:Abierto las 24 horas | martes:Abierto las 24 horas | miércoles:Abierto las 24 horas | jueves:Abierto las 24 horas | viernes:Abierto las 24 horas | sábado:Abierto las 24 horas | domingo:Abierto las 24 horas | AA85: https://www.google.com/maps?cid=15261182618278027883 | AB85: Transporte de carga, Viña del Mar, Chile | AC85: 2 | AD85: sin_web_propia
A86: ChIJnxpS6XLZiZYRqqr6OyHPPq8 | B86: Transportes Arichile | C86: Transportes Arichile | E86: 1 | F86: Transporte de carga | G86: Alta | H86: Empresa industrial/logística en zona objetivo con canal de contacto | I86: 65 | J86: +56 9 6350 5920 | K86: Móvil | L86: http://transportesarichile.negocio.site/ | M86: negocio.site | N86: No | O86: Viña del Mar | P86: Valparaíso | Q86: 2430000 | R86: 6medio oriente 280 viña del mar Quilpué, 2430000 Valparaíso, Viña del Mar, Valparaíso | S86: Con número | T86: -33.020116 | U86: -71.54259 | V86: Empresa de transporte por camión | W86: Empresa de transporte por camión | X86: 1 | Y86: 5 | Z86: lunes:8 am–6 pm | martes:8 am–6 pm | miércoles:8 am–6 pm | jueves:8 am–6 pm | viernes:8 am–6 pm | sábado:Cerrado | domingo:Cerrado | AA86: https://www.google.com/maps?cid=12627758146840603306 | AB86: Transporte de carga, Viña del Mar, Chile | AC86: 2 | AD86: sin_web_propia
A87: ChIJxUddSq05YpYRYcTsx00HSrc | B87: Sociedad De Servicios Portuarios Y Logistica Margomz Ltda. | C87: Sociedad De Servicios Portuarios Y Logistica Margomz Ltda. | E87: 1 | F87: Portuario / Contenedores | G87: Alta | H87: Empresa industrial/logística en zona objetivo con canal de contacto | I87: 65 | J87: +56 35 228 2862 | K87: Fijo | N87: No | O87: San Antonio | P87: Valparaíso | Q87: 2660916 | R87: La Playa 382, 2660916 San Antonio, Valparaíso | S87: Con número | T87: -33.607944 | U87: -71.620097 | V87: Oficinas de empresa | W87: Oficinas de empresa | X87: 1 | Y87: 5 | Z87: lunes:8:30 am–6 pm | martes:8:30 am–6 pm | miércoles:8:30 am–6 pm | jueves:8:30 am–6 pm | viernes:8:30 am–6 pm | sábado:9 am–12 pm | domingo:Cerrado | AA87: https://www.google.com/maps?cid=13207376887865459809 | AB87: Servicios logísticos, San Antonio, Chile | AC87: 1 | AD87: sin_web_propia
A88: ChIJL_cOP8HgiZYRhClm-WLb-t4 | B88: Frigorifico Fiordosur Sa | C88: Frigorifico Fiordosur Sa | E88: 1 | F88: Frío / Alimentos | G88: Alta | H88: Empresa industrial/logística en zona objetivo con canal de contacto | I88: 65 | J88: +56 32 262 4922 | K88: Fijo | L88: http://www.fiordosur.cl/ | M88: fiordosur.cl | N88: Sí | O88: Valparaíso | P88: Valparaíso | Q88: 2350789 | R88: Filippo Lippi 325, 2350789 Valparaíso | S88: Con número | T88: -33.049134 | U88: -71.600556 | V88: Mayorista de marisco | W88: Mayorista de marisco | AA88: https://www.google.com/maps?cid=16067395838735165828 | AB88: 15-Records-Frigorífic-202610052352.csv | AC88: 1 | AD88: sin_resenas, sin_horario
A89: ChIJpwq6n0jhiZYRWGcPNDqj3yM | B89: Leschaco (Chile) S A Valparaíso Office | C89: Leschaco (Chile) S A Valparaíso Office | E89: 1 | F89: Logística / Almacenaje | G89: Alta | H89: Empresa industrial/logística en zona objetivo con canal de contacto | I89: 65 | J89: +56 2 2731 3000 | K89: Fijo | L89: https://www.leschaco.com/en/start.html# | M89: leschaco.com | N89: Sí | O89: Valparaíso | P89: Valparaíso | Q89: 2361801 | R89: Cochrane 639, Piso 5 Oficina 51, 2361801 Valparaíso | S89: Con número | T89: -33.039023 | U89: -71.628383 | V89: Servicio de logística | W89: Servicio de logística | AA89: https://www.google.com/maps?cid=2584964181510809432 | AB89: Servicios logísticos (archivo) | AC89: 2 | AD89: sin_resenas, sin_horario
A90: ChIJy_QpgOHdiZYRdK8_AKyvnxg | B90: Arca Transportes | C90: Arca Transportes | E90: 1 | F90: Transporte de carga | G90: Alta | H90: Empresa industrial/logística en zona objetivo con canal de contacto | I90: 60 | J90: +56 9 9739 5119 | K90: Móvil | N90: No | O90: Viña del Mar | P90: Valparaíso | Q90: 2520000 | R90: 1 Nte. 461, Of. 703, 2520000 Viña del Mar, Valparaíso | S90: Con número | T90: -33.02177 | U90: -71.55446 | V90: Servicio de lanzadera | W90: Servicio de lanzadera, Servicio de transporte | X90: 43 | Y90: 5 | AA90: https://www.google.com/maps?cid=1774329931480674164 | AB90: Transporte de carga, Viña del Mar, Chile | AC90: 2 | AD90: sin_web_propia, sin_horario
A91: ChIJ515SM3HeiZYREvkg6nTs7Xk | B91: Tecnomak Viña del mar | C91: Tecnomak Viña del mar | E91: 1 | F91: Maquinaria / Industrial | G91: Alta | H91: Empresa industrial/logística en zona objetivo con canal de contacto | I91: 60 | J91: +56 32 254 5700 | K91: Fijo | N91: No | O91: Viña del Mar | P91: Valparaíso | Q91: 2581437 | R91: Cancha 175, 2581437 Viña del Mar, Valparaíso | S91: Con número | T91: -33.028105 | U91: -71.540936 | V91: Tienda de materiales para la construcción | W91: Tienda de materiales para la construcción, Proveedor de maquinaria de construcción, Tienda de herramientas, Tienda de suministros para soldadura | X91: 32 | Y91: 3.7 | Z91: lunes:8:30 am–1:30 pm | martes:8:30 am–1:30 pm | miércoles:8:30 am–1:30 pm | jueves:8:30 am–1:30 pm | viernes:8:30 am–1:30 pm | sábado:Cerrado | domingo:Cerrado | AA91: https://www.google.com/maps?cid=8785938434958096658 | AB91: Maquinaria industrial, Viña del Mar-Chile | AC91: 1 | AD91: sin_web_propia
A92: ChIJ2SGqqQlHYpYR8xsjIE0ayIU | B92: Transportes Pia Ltda. | C92: Transportes Pia Ltda. | E92: 1 | F92: Transporte de carga | G92: Alta | H92: Empresa industrial/logística en zona objetivo con canal de contacto | I92: 60 | J92: +56 9 6617 2505 | K92: Móvil | N92: No | O92: San Antonio | P92: Valparaíso | R92: Unnamed Road, San Antonio, Valparaíso | S92: Camino sin nombre | T92: -33.563284 | U92: -71.566673 | V92: Empresa de transporte por camión | W92: Empresa de transporte por camión | X92: 30 | Y92: 4.3 | Z92: lunes:8:30 am–10 pm | martes:8:30 am–10 pm | miércoles:8:30 am–10 pm | jueves:8:30 am–10 pm | viernes:8:30 am–10 pm | sábado:8:30 am–8 pm | domingo:Cerrado | AA92: https://www.google.com/maps?cid=9639983920940522483 | AB92: Transporte de carga, San Antonio, Chile | AC92: 1 | AD92: sin_web_propia, direccion_imprecisa
A93: ChIJz2_QrEg4YpYR5D9to0vRTyY | B93: Maquinas Cubillos | C93: Maquinas Cubillos | E93: 1 | F93: Maquinaria / Industrial | G93: Alta | H93: Empresa industrial/logística en zona objetivo con canal de contacto | I93: 60 | J93: +56 35 228 2570 | K93: Fijo | N93: No | O93: San Antonio | P93: Valparaíso | Q93: 2660214 | R93: Av. Chile 300-390, 2660214 San Antonio, Valparaíso | S93: Con número | T93: -33.612717 | U93: -71.608782 | V93: Centro comercial | W93: Centro comercial | X93: 27 | Y93: 3.7 | Z93: lunes:9:30 am–2 pm | martes:9:30 am–2 pm | miércoles:9:30 am–2 pm | jueves:9:30 am–2 pm | viernes:9:30 am–2 pm | sábado:11 am–2 pm | domingo:Cerrado | AA93: https://www.google.com/maps?cid=2760655219396001764 | AB93: Maquinaria industrial, San Antonio -Chile; Maquinaria industrial, San Antonio, Chile | AC93: 2 | AD93: sin_web_propia
A94: ChIJTdxlcH45YpYRqXCPf_DrVHg | B94: Consorcio | C94: Consorcio | E94: 1 | F94: Logística / Almacenaje | G94: Alta | H94: Empresa industrial/logística en zona objetivo con canal de contacto | I94: 60 | J94: +56 9 5419 1869 | K94: Móvil | N94: No | O94: San Antonio | P94: Valparaíso | R94: Unnamed Road, San Antonio, Valparaíso | S94: Camino sin nombre | T94: -33.600944 | U94: -71.592645 | V94: Almacén | W94: Almacén | X94: 27 | Y94: 4.2 | Z94: lunes:8 am–10 pm | martes:8 am–10 pm | miércoles:8 am–10 pm | jueves:8 am–10 pm | viernes:8 am–10 pm | sábado:8 am–3 pm | domingo:Cerrado | AA94: https://www.google.com/maps?cid=8670814600759832745 | AB94: Bodegas y almacenaje, San Antonio | AC94: 1 | AD94: sin_web_propia, direccion_imprecisa
A95: ChIJbQcujPn1YpYR9FC9B0IAVx0 | B95: Agrícola Randu | C95: Agrícola Randu | E95: 1 | F95: Vitivinícola / Agrícola | G95: Alta | H95: Empresa industrial/logística en zona objetivo con canal de contacto | I95: 60 | K95: Sin teléfono | L95: http://www.randu.cl/ | M95: randu.cl | N95: Sí | O95: Curacaví | P95: Metropolitana | R95: Unnamed Road, Curacaví, Región Metropolitana | S95: Camino sin nombre | T95: -33.400473 | U95: -71.097607 | V95: Mayorista de productos agrícolas | W95: Mayorista de productos agrícolas | X95: 26 | Y95: 4.3 | Z95: lunes:9 am–5 pm | martes:9 am–5 pm | miércoles:9 am–5 pm | jueves:9 am–5 pm | viernes:9 am–5 pm | sábado:Cerrado | domingo:Cerrado | AA95: https://www.google.com/maps?cid=2114158833671426292 | AB95: Agricola, Curacavi, Chile | AC95: 1 | AD95: sin_telefono, direccion_imprecisa
A96: ChIJp80lM0B1YpYRpDUbl55TMCs | B96: SAMEX Valparaíso | C96: SAMEX Valparaíso | E96: 1 | F96: Transporte de carga | G96: Alta | H96: Empresa industrial/logística en zona objetivo con canal de contacto | I96: 60 | K96: Sin teléfono | L96: https://www.samex.cl/ | M96: samex.cl | N96: Sí | O96: Valparaíso | P96: Valparaíso | Q96: 2340000 | R96: Décima Avenida 2450, 2340000 Valparaíso | S96: Con número | T96: -33.130616 | U96: -71.551216 | V96: Servicio de transporte | W96: Servicio de transporte | X96: 15 | Y96: 2.7 | Z96: lunes:9 am–6 pm | martes:9 am–6 pm | miércoles:9 am–6 pm | jueves:9 am–6 pm | viernes:9 am–5 pm | sábado:Cerrado | domingo:Cerrado | AA96: https://www.google.com/maps?cid=3112079283118093732 | AB96: Servicios logísticos, Valparaiso, Chile; Transporte de carga, Valparaiso, Chile | AC96: 2 | AD96: sin_telefono
A97: ChIJN5uIq9vhiZYRv1Rm-xYqkTI | B97: Logistica Transpiscis Limitada | C97: Logistica Transpiscis Limitada | E97: 1 | F97: Transporte de carga | G97: Alta | H97: Empresa industrial/logística en zona objetivo con canal de contacto | I97: 60 | K97: Sin teléfono | L97: http://web.inverzal.cl/tpweb/ | M97: inverzal.cl | N97: Sí | O97: Valparaíso | P97: Valparaíso | R97: Camino Antiguo A Santiago 390, Valparaíso | S97: Con número | T97: -33.092781 | U97: -71.587376 | V97: Empresa de transporte por camión | W97: Empresa de transporte por camión | X97: 13 | Y97: 4.5 | AA97: https://www.google.com/maps?cid=3643739851714876607 | AB97: Servicios logísticos, Valparaiso - Chile; Servicios logísticos, Valparaiso, Chile; Transporte de carga, Valparaiso, Chile | AC97: 3 | AD97: sin_telefono, sin_horario
A98: ChIJmzxMXuE4YpYRS8zm2l0ded8 | B98: PUERTO SAN ANTONIO | C98: PUERTO SAN ANTONIO | D98: PUERTO SAN ANTONIO | E98: 2 | F98: Logística / Almacenaje | G98: Alta | H98: Empresa industrial/logística en zona objetivo con canal de contacto | I98: 55 | K98: Sin teléfono | L98: http://www.puertosanantonio.com/ | M98: puertosanantonio.com | N98: Sí | O98: San Antonio | P98: Valparaíso | Q98: 2663160 | R98: P.º El Mar, 2663160 San Antonio, Valparaíso | S98: Sin número | T98: -33.581263 | U98: -71.615231 | V98: Servicio de logística | W98: Servicio de logística | X98: 958 | Y98: 4.5 | AA98: https://www.google.com/maps?cid=16102934231581641803 | AB98: Logística en San Antonio, Chile; Servicios logísticos, San Antonio, Chile | AC98: 2 | AD98: sin_telefono, direccion_imprecisa, sin_horario
A99: ChIJ6RqogdBHYpYR0HLSPNkGQ3U | B99: Transportes Alher Logística | C99: Transportes Alher Logística | E99: 1 | F99: Transporte de carga | G99: Alta | H99: Empresa industrial/logística en zona objetivo con canal de contacto | I99: 55 | K99: Sin teléfono | L99: http://logisticaalher.cl/ | M99: logisticaalher.cl | N99: Sí | O99: San Antonio | P99: Valparaíso | R99: San Antonio, Valparaíso | S99: Solo comuna | T99: -33.572313 | U99: -71.565713 | V99: Servicio de transporte | W99: Servicio de transporte | X99: 28 | Y99: 4.6 | Z99: lunes:8:30 am–6:30 pm | martes:8:30 am–6:30 pm | miércoles:8:30 am–6:30 pm | jueves:8:30 am–6:30 pm | viernes:8:30 am–6:30 pm | sábado:Cerrado | domingo:Cerrado | AA99: https://www.google.com/maps?cid=8449604855975277264 | AB99: Logística en San Antonio, Chile; Transporte de carga, San Antonio, Chile | AC99: 2 | AD99: sin_telefono, direccion_imprecisa
A100: ChIJoycOF4LdiZYRohriXV5SPRg | B100: Fletes y mudanzas - Nano transportes | C100: Fletes y mudanzas - Nano transportes | E100: 1 | F100: Transporte de carga | G100: Alta | H100: Empresa industrial/logística en zona objetivo con canal de contacto | I100: 55 | J100: +56 9 9323 4839 | K100: Móvil | N100: No | O100: Viña del Mar | P100: Valparaíso | Q100: 6444444 | R100: Sta. Inés 1665, 6444444 Viña del Mar, Valparaíso | S100: Con número | T100: -33.005436 | U100: -71.539659 | V100: Empresa de transporte por camión | W100: Empresa de transporte por camión | X100: 4 | Y100: 3 | Z100: lunes:8 am–6 pm | martes:8 am–6 pm | miércoles:8 am–6 pm | jueves:8 am–6 pm | viernes:8 am–6 pm | sábado:Cerrado | domingo:Cerrado | AA100: https://www.google.com/maps?cid=1746642795745122978 | AB100: Transporte de carga, Viña del Mar, Chile | AC100: 2 | AD100: sin_web_propia
...

Sheet Prospectos
A1: Empresa | B1: Grupo_empresa | C1: Segmento | D1: Relevancia | E1: Score_completitud | F1: Telefono | G1: Tipo_telefono | H1: Sitio_web | I1: Comuna | J1: Direccion | K1: Categoria_principal | L1: N_resenas | M1: Rating | N1: Google_Maps_URL | O1: Flags_calidad
A2: Viña Casas del Bosque | C2: Vitivinícola / Agrícola | D2: Alta | E2: 100 | F2: +56 2 2480 6941 | G2: Fijo | H2: http://casasdelbosque.cl/ | I2: Casablanca | J2: Ex Fundo Santa Rosa - Hijuela Nº 2, Casablanca, Valparaíso | K2: Bodega | L2: 1688 | M2: 4.6 | N2: https://www.google.com/maps?cid=10300753030481174526
A3: Casa Viñamar | C3: Vitivinícola / Agrícola | D3: Alta | E3: 100 | F3: +56 9 8242 3349 | G3: Móvil | H3: https://vsptwinegroup.com/tours-and-events/es/holidays/vinamar/ | I3: Casablanca | J3: Ruta 68, km 72, Casablanca, Valparaíso | K3: Viñedo | L3: 1636 | M3: 4.7 | N3: https://www.google.com/maps?cid=12329449938592924461
A4: Viña Indómita | C4: Vitivinícola / Agrícola | D4: Alta | E4: 100 | F4: +56 32 215 3902 | G4: Fijo | H4: http://www.indomita.cl/ | I4: Casablanca | J4: Ruta 68, Casablanca, Valparaíso | K4: Viñedo | L4: 1294 | M4: 4.5 | N4: https://www.google.com/maps?cid=4726476439834576790
A5: STI – San Antonio Terminal Internacional | C5: Portuario / Contenedores | D5: Alta | E5: 100 | F5: +56 35 220 1600 | G5: Fijo | H5: http://www.stiport.com/ | I5: San Antonio | J5: Bernardo O'Higgins Riquelme 2263, San Antonio, Valparaíso | K5: Empresa portuaria | L5: 928 | M5: 4 | N5: https://www.google.com/maps?cid=17908076345065983299 | O5: nombre_corregido
A6: Seaport | C6: Portuario / Contenedores | D6: Alta | E6: 100 | F6: +56 35 220 1500 | G6: Fijo | H6: http://www.seaport.cl/ | I6: San Antonio | J6: Ruta G86, Aguas Buenas N° 6729, Cruce a Cartagena, 2660000 San Antonio, Valparaíso | K6: Terminal de contenedores | L6: 775 | M6: 4 | N6: https://www.google.com/maps?cid=722349627185602024
A7: Bodegas RE | C7: Vitivinícola / Agrícola | D7: Alta | E7: 100 | F7: +56 9 9345 9114 | G7: Móvil | H7: http://www.bodegasre.cl/ | I7: Casablanca | J7: F-850 1380, Casablanca, Valparaíso | K7: Bodega | L7: 378 | M7: 4.8 | N7: https://www.google.com/maps?cid=9831653613549114241
A8: Puerto Columbo San Antonio | C8: Otros / Servicios empresariales | D8: Alta | E8: 100 | F8: +56 35 220 3701 | G8: Fijo | H8: http://www.puertocolumbo.com/ | I8: San Antonio | J8: Ruta Nacional 78, Barrio Industrial # 2375, San Antonio, Valparaíso | K8: Oficinas de empresa | L8: 260 | M8: 4.1 | N8: https://www.google.com/maps?cid=2900684782525532505
A9: Terminal y Servicios Logísticos Las Cadenas Ltda. | C9: Logística / Almacenaje | D9: Alta | E9: 100 | F9: +56 9 6122 2911 | G9: Móvil | H9: http://www.tlogisticolascadenas.cl/ | I9: Valparaíso | J9: 2821, Placilla, Cerro El Altar, Valparaíso | K9: Gran superficie | L9: 174 | M9: 4.3 | N9: https://www.google.com/maps?cid=11876321614386547164
A10: Ferretería Industrial METALMAR | C10: Maquinaria / Industrial | D10: Alta | E10: 100 | F10: +56 35 237 5110 | G10: Fijo | H10: http://www.metalmarchile.cl/ | I10: San Antonio | J10: Barros Luco 3058, 2663592 San Antonio, Valparaíso | K10: Ferretería | L10: 147 | M10: 4.6 | N10: https://www.google.com/maps?cid=4344495986652541285
A11: Tranvial | C11: Transporte de carga | D11: Alta | E11: 100 | F11: +56 600 006 0060 | G11: 600 (call center) | H11: https://www.tranvial.com/ | I11: Viña del Mar | J11: Edificio Reitz III - C. Limache 3437, Viña del Mar, Valparaíso | K11: Servicio de transporte | L11: 112 | M11: 4.3 | N11: https://www.google.com/maps?cid=5681984210172315765
A12: Calca | B12: Calca | C12: Otros / Servicios empresariales | D12: Alta | E12: 100 | F12: +56 32 274 1652 | G12: Fijo | H12: http://www.calca.cl/ | I12: Casablanca | J12: Av. Portales 90, 2480505 Casablanca, Valparaíso | K12: Comercio | L12: 56 | M12: 4.6 | N12: https://www.google.com/maps?cid=12175360959117859742
A13: Emergent Cold LatAm | C13: Logística / Almacenaje | D13: Alta | E13: 100 | F13: +56 600 656 0030 | G13: 600 (call center) | H13: https://emergentcoldlatam.com/ | I13: Casablanca | J13: F-852 4621, Lo Vásquez, Casablanca, Valparaíso | K13: Servicio de logística | L13: 55 | M13: 4 | N13: https://www.google.com/maps?cid=8119297471756617067
A14: Empresas Demaria S.A. | B14: Empresas Demaria S.A. | C14: Otros / Servicios empresariales | D14: Alta | E14: 100 | F14: +56 32 226 7000 | G14: Fijo | H14: https://demaria.cl/ | I14: Viña del Mar | J14: C. Limache 3535, 2562126 Viña del Mar, Valparaíso | K14: Oficinas de empresa | L14: 55 | M14: 4.4 | N14: https://www.google.com/maps?cid=3883389849630201333
A15: Egido Empresas | C15: Transporte de carga | D15: Alta | E15: 100 | F15: +56 9 7450 5347 | G15: Móvil | H15: http://www.egido.cl/ | I15: Valparaíso | J15: Camino La Pólvora 4, La Polvora, Valparaíso | K15: Empresa de transporte por camión | L15: 51 | M15: 4.3 | N15: https://www.google.com/maps?cid=12686360603857414265
A16: SERVIEX Ltda | C16: Logística / Almacenaje | D16: Alta | E16: 95 | F16: +56 9 4173 7193 | G16: Móvil | H16: https://serviexltda.cl/ | I16: Valparaíso | J16: Undécima Avenida 1730, Pc 384 Placilla, 2340000 Valparaíso | K16: Servicio de logística | L16: 49 | M16: 5 | N16: https://www.google.com/maps?cid=16285007002273081807
A17: Frigorífico Víctor Mancilla y Cía Ltda. | C17: Frío / Alimentos | D17: Alta | E17: 95 | F17: +56 32 262 7464 | G17: Fijo | H17: http://www.pesqueramancilla.cl/ | I17: Valparaíso | J17: R. Philippi 195, 2391272 Valparaíso | K17: Comercio | L17: 42 | M17: 4.2 | N17: https://www.google.com/maps?cid=3684435156110111844
A18: SL TRANSPORTE LTDA | C18: Transporte de carga | D18: Alta | E18: 95 | F18: +56 9 4008 8368 | G18: Móvil | H18: http://www.sltransporte.cl/ | I18: San Antonio | J18: Los Eucaliptus, Av. Aguas Buenas 597, 2660000 San Antonio, Valparaíso | K18: Empresa de transporte por camión | L18: 41 | M18: 4 | N18: https://www.google.com/maps?cid=4215131197082140141
A19: FRIGORIFICO FRIOMOR S.A | C19: Frío / Alimentos | D19: Alta | E19: 95 | F19: +56 9 9619 6628 | G19: Móvil | H19: http://www.friomor.cl/ | I19: Cartagena | J19: Las Majadas Lote 2 y 3 s/n, Cartagena, San Antonio, Cartagena, Valparaíso | K19: Almacén | L19: 26 | M19: 4.5 | N19: https://www.google.com/maps?cid=12355032772654322559
A20: OSKUPACK | C20: Maquinaria / Industrial | D20: Alta | E20: 95 | F20: +56 9 9822 4595 | G20: Móvil | H20: https://oskupack.cl/ | I20: Viña del Mar | J20: Camino Lajarilla 744, 2520000 Viña del Mar, Valparaíso | K20: Empresa de embalaje | L20: 25 | M20: 4.4 | N20: https://www.google.com/maps?cid=14917846952693574944
A21: INDUSTRIAL COSTA SPA | C21: Maquinaria / Industrial | D21: Alta | E21: 95 | F21: +56 9 8888 4772 | G21: Móvil | H21: http://industrialcostaspa.com/ | I21: Viña del Mar | J21: Camino internacional 5465 Galpón F3, 1, Viña del Mar, Valparaíso | K21: Taller de maquinaria | L21: 23 | M21: 4.1 | N21: https://www.google.com/maps?cid=16120114039017504461
A22: ROLIMAQ - VENTUS | C22: Maquinaria / Industrial | D22: Alta | E22: 95 | F22: +56 9 5908 1452 | G22: Móvil | H22: http://www.rolimaq.cl/ | I22: Viña del Mar | J22: 5 ORIENTE 608 VIÑA DEL MAR, Av. Colón 2877, Valparaíso, Viña del Mar, Valparaíso | K22: Empresa de suministros industriales | L22: 20 | M22: 4.6 | N22: https://www.google.com/maps?cid=11184477459191193844
A23: Delfrio Frigorífico de Valparaiso S.A. | B23: Delfrio Frigorífico de Valparaiso S.A. | C23: Frío / Alimentos | D23: Alta | E23: 95 | F23: +56 32 229 1166 | G23: Fijo | H23: http://www.delfrio.cl/ | I23: Valparaíso | J23: Ruta 68 1240, Placilla, Valparaíso | K23: Servicios de empresa a empresa | L23: 19 | M23: 4.3 | N23: https://www.google.com/maps?cid=11206603421035058062
A24: Distribuidor Autorizado Stihl San Antonio AGROMAR | C24: Maquinaria / Industrial | D24: Alta | E24: 95 | F24: +56 9 8814 2767 | G24: Móvil | H24: https://redstihl.cl/productos/aceite-de-mezcla-premium-stihl-1l/ | I24: San Antonio | J24: Av. Chile 402, 2660750 San Antonio, Valparaíso | K24: Cuarto de herramientas | L24: 15 | M24: 4.1 | N24: https://www.google.com/maps?cid=11467168172239893447
A25: Logistica el Cardal LOGEC, Malvilla | C25: Logística / Almacenaje | D25: Alta | E25: 95 | F25: +56 9 5534 0864 | G25: Móvil | H25: http://www.logec.cl/ | I25: San Antonio | J25: Camino Malvilla 1378, Ruta G974, San Antonio, Valparaíso | K25: Almacén | L25: 15 | M25: 4.5 | N25: https://www.google.com/maps?cid=9429970539089366266
A26: Mibodega | C26: Logística / Almacenaje | D26: Alta | E26: 95 | F26: +56 9 3391 9144 | G26: Móvil | H26: https://mibodega.cl/ | I26: Quilpué | J26: Baquedano 1475, 2430000 Quilpué, Valparaíso | K26: Bodega | L26: 15 | M26: 4.3 | N26: https://www.google.com/maps?cid=8015006014081595754
A27: Empresas Tuxpan | C27: Otros / Servicios empresariales | D27: Alta | E27: 95 | F27: +56 32 268 0906 | G27: Fijo | H27: http://www.tuxpan.com/ | I27: Viña del Mar | J27: 7 Nte. 360, 2520696 Viña del Mar, Valparaíso | K27: Oficinas de empresa | L27: 14 | M27: 5 | N27: https://www.google.com/maps?cid=3906881432640034910
A28: VIRGINIA - Empresas Demaria S.A. | B28: Empresas Demaria S.A. | C28: Maquinaria / Industrial | D28: Alta | E28: 95 | F28: +56 32 226 7000 | G28: Fijo | H28: http://www.virginia.cl/ | I28: Viña del Mar | J28: C. Limache 3535, 2562126 Viña del Mar, Valparaíso | K28: Proveedor de productos de limpieza | L28: 12 | M28: 4.8 | N28: https://www.google.com/maps?cid=10773045159350260194
A29: Bodegas Mauco | C29: Logística / Almacenaje | D29: Alta | E29: 95 | F29: +56 9 9779 1746 | G29: Móvil | H29: http://www.bodegasmauco.cl/ | I29: Quillota | J29: RUTA f 360 KM1 Quillota, 2260000 Valparaíso, Quillota, Valparaíso | K29: Bodega | L29: 11 | M29: 4.5 | N29: https://www.google.com/maps?cid=8561290524054708549 | O29: nombre_corregido
A30: Puerto San Antonio | B30: PUERTO SAN ANTONIO | C30: Portuario / Contenedores | D30: Alta | E30: 90 | F30: +56 35 258 6000 | G30: Fijo | H30: https://puertosanantonio.com/ | I30: San Antonio | J30: Antonio Núñez de Fonseca 1552, 2660000 San Antonio, Valparaíso | K30: Empresa portuaria | L30: 521 | M30: 4.5 | N30: https://www.google.com/maps?cid=12901104601616726355 | O30: sin_horario
A31: D&C San Antonio, patio principal | C31: Portuario / Contenedores | D31: Alta | E31: 90 | F31: +56 32 251 3302 | G31: Fijo | H31: http://www.dycsa.cl/ | I31: San Antonio | J31: Ruta G 94 F Nuevo Acceso al Puerto 3559 Barrio Industrial San Antonio, San Antonio, Valparaíso | K31: Servicio de contenedores | L31: 464 | M31: 3.2 | N31: https://www.google.com/maps?cid=2478614165572187257
A32: Maersk Logistics and Service Chile SpA | B32: Maersk Logistics and Service Chile SpA | C32: Portuario / Contenedores | D32: Alta | E32: 90 | F32: +56 35 220 2700 | G32: Fijo | H32: http://www.maersk.com/ | I32: San Antonio | J32: Avenida Las Factorías 8150, San Antonio, Valparaíso | K32: Terminal de contenedores | L32: 292 | M32: 3.9 | N32: https://www.google.com/maps?cid=13255369959181778585
A33: Kingston Family Vineyards | C33: Vitivinícola / Agrícola | D33: Alta | E33: 90 | F33: +56 32 332 0150 | G33: Fijo | H33: http://www.kingstonvineyards.com/ | I33: Casablanca | J33: Hijuela El Maitén S/N, Casablanca, Valparaíso | K33: Bodega | L33: 216 | M33: 4.8 | N33: https://www.google.com/maps?cid=17955067143115247897 | O33: direccion_imprecisa
A34: TLS Terminal Logistico San Antonio LTDA. | C34: Portuario / Contenedores | D34: Alta | E34: 90 | F34: +56 35 245 0146 | G34: Fijo | H34: http://www.tls.cl/ | I34: Cartagena | J34: Camino antiguo a Santiago SN, Cartagena, Valparaíso | K34: Servicio de contenedores | L34: 158 | M34: 4.1 | N34: https://www.google.com/maps?cid=6926373934490367553 | O34: direccion_imprecisa
A35: Transportes Olivares | B35: Transportes Olivares | C35: Transporte de carga | D35: Alta | E35: 90 | F35: +56 9 9637 6297 | G35: Móvil | H35: http://www.transportesolivares.cl/ | I35: San Antonio | J35: José Miguel Carrera Verdugo 830, of.6, 2660885 San Antonio, Valparaíso | K35: Empresa de transporte por camión | L35: 9 | M35: 4 | N35: https://www.google.com/maps?cid=10231734586617826261
A36: TopMachine | C36: Maquinaria / Industrial | D36: Alta | E36: 90 | F36: +56 9 9222 6713 | G36: Móvil | H36: http://www.topmachine.cl/ | I36: Viña del Mar | J36: 1 - Calle Viana 837 Local 1, Viña del Mar, Valparaíso | K36: Empresa de suministros industriales | L36: 6 | M36: 5 | N36: https://www.google.com/maps?cid=13982729139998668602
A37: Forza Industrial | C37: Maquinaria / Industrial | D37: Alta | E37: 90 | F37: +56 9 6629 5814 | G37: Móvil | H37: https://www.forzaindustrial.cl/ | I37: San Antonio | J37: Av. Chile 55, Loc B, 2660000 Llolleo, San Antonio, Valparaíso | K37: Tienda de herramientas y troqueles | L37: 5 | M37: 5 | N37: https://www.google.com/maps?cid=8985555014261378381 | O37: nombre_corregido
A38: Comercializadora de Carnes Gutiérrez y Gutiérrez | C38: Frío / Alimentos | D38: Alta | E38: 90 | F38: +56 32 221 3124 | G38: Fijo | H38: https://www.carnesag.cl/ | I38: Valparaíso | J38: Juana Ross 155, 2340168 Valparaíso | K38: Proveedor mayorista de alimentos | L38: 5 | M38: 5 | N38: https://www.google.com/maps?cid=15118591021604748916
A39: CER Chile | C39: Otros / Servicios empresariales | D39: Alta | E39: 90 | F39: +56 9 9745 4023 | G39: Móvil | H39: http://www.cer-chile.cl/ | I39: Viña del Mar | J39: C. Limache 3437, Ofi 520, Viña del Mar, Valparaíso | K39: Oficinas de empresa | L39: 5 | M39: 5 | N39: https://www.google.com/maps?cid=17050282414366592689
A40: Transportes Olivares | B40: Transportes Olivares | C40: Transporte de carga | D40: Alta | E40: 90 | F40: +56 9 9637 6297 | G40: Móvil | H40: http://www.transportesolivares.cl/ | I40: San Antonio | J40: Barros Luco 1814, 6, 2662776 Barrancas, San Antonio, Valparaíso | K40: Empresa de transporte por camión | L40: 3 | M40: 5 | N40: https://www.google.com/maps?cid=1921697206804065172
A41: Compañía de Servicios Aduaneros y Transportes SPA | C41: Transporte de carga | D41: Alta | E41: 90 | F41: +56 9 6434 9141 | G41: Móvil | H41: http://www.transporteinternacional.cl/ | I41: Valparaíso | J41: Esmeralda 1074, 2361897 Valparaíso | K41: Empresa de transporte por camión | L41: 2 | M41: 5 | N41: https://www.google.com/maps?cid=2989278510481374814
A42: Imperio Transportes | C42: Transporte de carga | D42: Alta | E42: 90 | F42: +56 9 8157 1998 | G42: Móvil | H42: http://www.imperiotransportes.com/ | I42: Valparaíso | J42: Cerro El Altar 2821, Valparaíso | K42: Empresa de transporte por camión | L42: 2 | M42: 4 | N42: https://www.google.com/maps?cid=6157132699044971350
A43: THM Transporte Humberto Morales | C43: Transporte de carga | D43: Alta | E43: 85 | F43: +56 32 213 1200 | G43: Fijo | H43: http://www.thm.cl/ | I43: Valparaíso | J43: Novena Avenida 2225, 0002222 Valparaíso | K43: Empresa de transporte por camión | L43: 41 | M43: 3.9 | N43: https://www.google.com/maps?cid=2369270700154909362
A44: Bodegas Kochifas | C44: Logística / Almacenaje | D44: Alta | E44: 85 | F44: +56 9 8901 8446 | G44: Móvil | H44: http://www.bodegaskochifas.cl/ | I44: Valparaíso | J44: Fundo los Perales - Cuesta Balmaceda, Cam. La Pólvora, 2340000 Valparaíso | K44: Almacén | L44: 30 | M44: 4.3 | N44: https://www.google.com/maps?cid=16831252184478941563 | O44: direccion_imprecisa
A45: Endopack Chile | C45: Maquinaria / Industrial | D45: Alta | E45: 85 | F45: +56 9 8797 0197 | G45: Móvil | H45: http://www.endopackchile.cl/ | I45: Viña del Mar | J45: Etchevers 185, Loc 67-A, 2520000 Viña del Mar, Valparaíso | K45: Empresa de embalaje | L45: 22 | M45: 3.6 | N45: https://www.google.com/maps?cid=7988653958022959026
A46: Maersk Chile | B46: Maersk Logistics and Service Chile SpA | C46: Otros / Servicios empresariales | D46: Alta | E46: 85 | F46: +56 35 221 1289 | G46: Fijo | H46: https://www.maersk.com/ | I46: San Antonio | J46: Barros Luco 1613, P 12 San Antoni, 2662756 San Antonio, Valparaíso | K46: Servicios de empresa a empresa | L46: 16 | M46: 3.8 | N46: https://www.google.com/maps?cid=11533384835499478704
A47: Reno Chile SA | C47: Química / Energía | D47: Alta | E47: 85 | F47: +56 2 2460 1000 | G47: Fijo | H47: http://www.reno.cl/ | I47: Viña del Mar | J47: C. Limache 3730, Viña del Mar, Valparaíso | K47: Planta química | L47: 13 | M47: 3.6 | N47: https://www.google.com/maps?cid=10258864000908360199
A48: TFL TRANSPORTES | C48: Transporte de carga | D48: Alta | E48: 85 | F48: +56 9 9879 8720 | G48: Móvil | H48: http://www.tfltransportes.cl/ | I48: Valparaíso | J48: NOVENA AVENIDA 2315 PLACILLA, ORIENTE, 3100000 Valparaíso | K48: Empresa de transporte por camión | L48: 12 | M48: 3.6 | N48: https://www.google.com/maps?cid=14037492864940927233
A49: HGT Extraportuarios S.A. | C49: Portuario / Contenedores | D49: Alta | E49: 80 | F49: +56 32 232 4200 | G49: Fijo | H49: http://www.aep.cl/ | I49: San Antonio | J49: Pablo Neruda 289, Barrancas, San Antonio, Valparaíso | K49: Almacén | L49: 336 | M49: 3.8 | N49: https://www.google.com/maps?cid=12680983847669617480 | O49: sin_horario
A50: Transportes TRG | C50: Transporte de carga | D50: Alta | E50: 80 | F50: +56 32 276 8062 | G50: Fijo | H50: http://www.trg.cl/ | I50: Valparaíso | J50: Camino Antiguo S/N Esquina La Pólvora, Valparaíso | K50: Empresa de transporte por camión | L50: 20 | M50: 4.4 | N50: https://www.google.com/maps?cid=2859518826913675064 | O50: direccion_imprecisa
A51: Servicemaq Ltda | C51: Maquinaria / Industrial | D51: Alta | E51: 80 | F51: +56 9 6544 1511 | G51: Móvil | H51: http://www.servicemaq.cl/servicios | I51: Viña del Mar | J51: Cancha 106, 2520000 Viña del Mar, Valparaíso | K51: Proveedor de maquinaria de construcción | L51: 6 | M51: 2 | N51: https://www.google.com/maps?cid=7212479982147849584
A52: Mger Industrial Ltda | C52: Maquinaria / Industrial | D52: Alta | E52: 80 | F52: +56 9 6206 0733 | G52: Móvil | H52: http://www.mger.cl/ | I52: Viña del Mar | J52: Camino lajarilla 744 bodega 3A, Viña del Mar, Valparaíso | K52: Proveedor de maquinaria de construcción | L52: 5 | M52: 3.4 | N52: https://www.google.com/maps?cid=2830459428367980746
A53: Transportes CaboVerde | C53: Transporte de carga | D53: Alta | E53: 80 | F53: +56 9 8297 9433 | G53: Móvil | H53: http://www.transportescaboverde.cl/ | I53: San Antonio | J53: San Pedro 2130, 2660897 San Antonio, Valparaíso | K53: Empresa de transporte por camión | L53: 4 | M53: 3.3 | N53: https://www.google.com/maps?cid=16836470235998956029
A54: Maquintec | C54: Maquinaria / Industrial | D54: Alta | E54: 80 | F54: +56 9 3545 4670 | G54: Móvil | H54: https://maquintec.cl/ | I54: Viña del Mar | J54: Agua Santa 2455, Viña del Mar, Valparaíso | K54: Oficinas de empresa | L54: 3 | M54: 3.7 | N54: https://www.google.com/maps?cid=2901908515080708287
A55: ICA Transportes | C55: Transporte de carga | D55: Alta | E55: 80 | F55: +56 35 228 0179 | G55: Fijo | H55: http://www.icatransportes.cl/ | I55: San Antonio | J55: El Paico 1202, 2661191 San Antonio, Valparaíso | K55: Empresa de transporte por camión | L55: 3 | M55: 3.7 | N55: https://www.google.com/maps?cid=4274804226358126642
A56: Empresas Carozzi Planta Reñaca | C56: Otros / Servicios empresariales | D56: Alta | E56: 75 | F56: +56 32 227 6000 | G56: Fijo | I56: Viña del Mar | J56: Cam. Internacional 2825, Viña del Mar, Valparaíso | K56: Comercio | L56: 537 | M56: 4.5 | N56: https://www.google.com/maps?cid=13740080267569379261 | O56: sin_web_propia
A57: AGUNSA EXTRAPORTUARIO - AEXSA | C57: Portuario / Contenedores | D57: Alta | E57: 75 | F57: +56 35 245 6800 | G57: Fijo | H57: http://www.aexsa.cl/ | I57: San Antonio | J57: San Antonio, Valparaíso | K57: Almacén | L57: 227 | M57: 3.9 | N57: https://www.google.com/maps?cid=4694705275474624660 | O57: direccion_imprecisa
A58: Ferretería Antofagasta | C58: Maquinaria / Industrial | D58: Alta | E58: 75 | F58: +56 9 9744 6775 | G58: Móvil | H58: https://wa.me/56997446775 | I58: San Antonio | J58: Antofagasta 214, 2662798 San Antonio, Valparaíso | K58: Tienda de herramientas | L58: 60 | M58: 4.5 | N58: https://www.google.com/maps?cid=13383765722945178165 | O58: sin_web_propia
A59: Altos del Puerto | C59: Logística / Almacenaje | D59: Alta | E59: 75 | F59: +56 9 7748 2466 | G59: Móvil | H59: http://www.altosdelpuerto.cl/ | I59: Valparaíso | J59: Camino La Pólvora 106, Valparaíso | K59: Bodega | L59: 46 | M59: 3.8 | N59: https://www.google.com/maps?cid=6379730742776303588 | O59: sin_horario
A60: BASF Concón | C60: Química / Energía | D60: Alta | E60: 75 | F60: +56 32 226 7500 | G60: Fijo | H60: http://www.basf.cl/ | I60: Quintero | J60: Quintero, Valparaíso | K60: Planta química | L60: 7 | M60: 4.7 | N60: https://www.google.com/maps?cid=9637794935216625427 | O60: direccion_imprecisa
A61: MAKK SpA | C61: Maquinaria / Industrial | D61: Alta | E61: 75 | F61: +56 9 4749 7378 | G61: Móvil | H61: http://www.makk.cl/ | I61: San Antonio | J61: Republica 1937, 2662936 Barrancas, San Antonio, Valparaíso | K61: Servicio de alquiler de herramientas | N61: https://www.google.com/maps?cid=15358948573639502551 | O61: sin_resenas
A62: Inversiones Kanin Ltda | C62: Maquinaria / Industrial | D62: Alta | E62: 75 | F62: +56 9 7900 5720 | G62: Móvil | H62: https://www.kanin.cl/ | I62: San Antonio | J62: Divina Providencia 2105, Depto 1, 2660000 San Antonio, Valparaíso | K62: Empresa de movimiento de tierras | N62: https://www.google.com/maps?cid=770003504225720525 | O62: sin_resenas
A63: Intermarine Services Group | C63: Maquinaria / Industrial | D63: Alta | E63: 75 | F63: +56 9 3263 5175 | G63: Móvil | H63: https://www.intermarineservices.cl/ | I63: Viña del Mar | J63: 2 Ote. 124, Of. 205, 2520000 Viña del Mar, Valparaíso | K63: Empresa de suministros industriales | N63: https://www.google.com/maps?cid=15544399743959454372 | O63: sin_resenas
A64: A1 Maquinarias | C64: Maquinaria / Industrial | D64: Alta | E64: 75 | F64: +56 9 5283 4355 | G64: Móvil | H64: https://a1maquinarias.cl/ | I64: Viña del Mar | J64: 1 Pte 18, Ofi C1, 2500000 Viña del Mar, Valparaíso | K64: Empresa de suministros industriales | N64: https://www.google.com/maps?cid=3054213965963333992 | O64: sin_resenas
A65: Acemar Chile Ltda | C65: Maquinaria / Industrial | D65: Alta | E65: 75 | F65: +56 32 336 6411 | G65: Fijo | H65: http://www.acemarchile.cl/conctactenos/ | I65: Viña del Mar | J65: Raul Toro 144 Achupallas, 2552387 Viña del Mar, Valparaíso | K65: Empresa de suministros industriales | N65: https://www.google.com/maps?cid=17424357700101585746 | O65: sin_resenas
A66: Vidangossy Maquinaria | C66: Maquinaria / Industrial | D66: Alta | E66: 75 | F66: +56 9 8731 9307 | G66: Móvil | H66: https://vidangossymaquinaria.com/ | I66: Concón | J66: Av. Concón Reñaca 4000, Ofi 203, 2510000 Concón, Valparaíso | K66: Proveedor de equipos para fábricas | N66: https://www.google.com/maps?cid=7347176242113400581 | O66: sin_resenas
A67: Locargo Transporte y Logística | C67: Transporte de carga | D67: Alta | E67: 75 | F67: +56 9 7698 9476 | G67: Móvil | H67: https://www.locargo.cl/ | I67: Valparaíso | J67: Esmeralda 973, Ofi 502, 2340000 Valparaíso | K67: Servicio de envíos | N67: https://www.google.com/maps?cid=9140226752728787504 | O67: sin_resenas
A68: Compañía de Servicios Integrales de Transportes y Aduaneros SPA | C68: Transporte de carga | D68: Alta | E68: 75 | F68: +56 9 5144 2374 | G68: Móvil | H68: http://www.ncsita.com/ | I68: Valparaíso | J68: Prat 814, Ofi 503, 2340000 Valparaíso | K68: Empresa de transporte por camión | N68: https://www.google.com/maps?cid=15939204647535391963 | O68: sin_resenas
A69: Transportes Marcelo Sepúlveda | C69: Transporte de carga | D69: Alta | E69: 70 | F69: +56 9 7621 6002 | G69: Móvil | I69: Viña del Mar | J69: Av. Valdivia 212, 2520000 Viña del Mar, Valparaíso | K69: Servicio de mudanzas | L69: 40 | M69: 5 | N69: https://www.google.com/maps?cid=9857480228950088202 | O69: sin_web_propia
A70: Química Passol S.A. | C70: Química / Energía | D70: Alta | E70: 70 | G70: Sin teléfono | H70: https://www.passol.cl/ | I70: Viña del Mar | J70: C. Limache 4225, 2520651 Viña del Mar, Valparaíso | K70: Pintura | L70: 25 | M70: 4.1 | N70: https://www.google.com/maps?cid=3579299406975478219 | O70: sin_telefono
A71: Transportes Nuevo Mundo | C71: Transporte de carga | D71: Alta | E71: 70 | G71: Sin teléfono | H71: https://www.transportesnm.cl/ | I71: San Antonio | J71: Las Acacias 176, San Antonio, Valparaíso | K71: Oficinas de empresa | L71: 22 | M71: 4.7 | N71: https://www.google.com/maps?cid=10794964622855405794 | O71: sin_telefono
A72: Transportes Artisa | C72: Transporte de carga | D72: Alta | E72: 70 | F72: +56 32 218 7550 | G72: Fijo | I72: Viña del Mar | J72: 1 Nte. 2461, Viña del Mar, Valparaíso | K72: Servicio de transporte | L72: 15 | M72: 4.7 | N72: https://www.google.com/maps?cid=6313804100046481373 | O72: sin_web_propia
A73: Starken Viña Central Carga | C73: Transporte de carga | D73: Alta | E73: 65 | G73: Sin teléfono | H73: https://www.starken.cl/ | I73: Viña del Mar | J73: bodega 13 - C. Limache N°3400, 2562231 Viña del Mar, Valparaíso | K73: Empresa de transporte por camión | L73: 215 | M73: 2.7 | N73: https://www.google.com/maps?cid=14785673974252150397 | O73: sin_telefono
A74: Sitrans San Antonio Bajo | C74: Otros / Servicios empresariales | D74: Alta | E74: 65 | F74: +56 35 236 2100 | G74: Fijo | I74: San Antonio | J74: Bernardo O'Higgins Riquelme 2767, San Antonio, Valparaíso | K74: Oficinas de empresa | L74: 159 | M74: 4 | N74: https://www.google.com/maps?cid=18116690074374408280 | O74: sin_web_propia, sin_horario
A75: Puerto Panul S.A. | C75: Otros / Servicios empresariales | D75: Alta | E75: 65 | G75: Sin teléfono | H75: http://www.puertopanul.cl/ | I75: San Antonio | J75: Antonio Núñez de Fonseca 440, San Antonio, Valparaíso | K75: Oficinas de empresa | L75: 75 | M75: 4.4 | N75: https://www.google.com/maps?cid=4546060451744102239 | O75: sin_telefono, sin_horario
A76: Nodo Logistico | C76: Logística / Almacenaje | D76: Alta | E76: 65 | F76: +56 9 6655 2831 | G76: Móvil | I76: San Antonio | J76: La Playa 34, San Antonio, Valparaíso | K76: Servicio de logística | L76: 72 | M76: 3.9 | N76: https://www.google.com/maps?cid=5370660846604122771 | O76: sin_web_propia
A77: Planta San Antonio | C77: Otros / Servicios empresariales | D77: Alta | E77: 65 | G77: Sin teléfono | H77: https://unacem.cl/ | I77: San Antonio | J77: Ruta G-56, Acceso al puerto 2549, 2660000 San Antonio, Valparaíso | K77: Oficinas de empresa | L77: 7 | M77: 5 | N77: https://www.google.com/maps?cid=9198715422169449529 | O77: sin_telefono
A78: COSEDUCAM S.A. | C78: Logística / Almacenaje | D78: Alta | E78: 65 | F78: +56 35 221 2005 | G78: Fijo | I78: San Antonio | J78: J.L Sanfuentes A 1137, 2660000 San Antonio, Valparaíso | K78: Servicio de gestión de residuos | L78: 5 | M78: 4.8 | N78: https://www.google.com/maps?cid=14896353045701747074 | O78: sin_web_propia
A79: Aerzen Chile S.P.A. | C79: Maquinaria / Industrial | D79: Alta | E79: 65 | G79: Sin teléfono | H79: https://www.aerzen.com/chile | I79: Viña del Mar | J79: C. Limache 3116, 2562231 Viña del Mar, Valparaíso | K79: Empresa de suministros industriales | L79: 4 | M79: 4 | N79: https://www.google.com/maps?cid=3527495155964413738 | O79: sin_telefono, nombre_corregido
A80: Rentas Valfrio Limitada | B80: Delfrio Frigorífico de Valparaiso S.A. | C80: Frío / Alimentos | D80: Alta | E80: 65 | F80: +56 32 229 1166 | G80: Fijo | I80: Valparaíso | J80: Ruta 68 N° 1173 (Ex 1240) Placilla, 2340000 Valparaíso | K80: Instalación de almacenamiento en frío | L80: 1 | M80: 5 | N80: https://www.google.com/maps?cid=17524196513021656350 | O80: sin_web_propia
A81: Frigorífico Lihuen | C81: Frío / Alimentos | D81: Alta | E81: 65 | G81: Sin teléfono | H81: https://holdinglihuen.cl/ | I81: Quillota | J81: C. Herboso 64, B, 2260000 Quillota, Valparaíso | K81: Instalación de almacenamiento en frío | L81: 1 | M81: 5 | N81: https://www.google.com/maps?cid=15209450054486864308 | O81: sin_telefono
A82: Frulog | C82: Transporte de carga | D82: Alta | E82: 65 | G82: Sin teléfono | H82: https://www.frulog.cl/ | I82: San Antonio | J82: Sanfuentes 2096, 2660000 Valparaíso, San Antonio, Valparaíso | K82: Empresa de transporte por camión | L82: 1 | M82: 4 | N82: https://www.google.com/maps?cid=14786317783765495029 | O82: sin_telefono
A83: Transportes GyC Valparaíso | C83: Transporte de carga | D83: Alta | E83: 65 | F83: +56 9 8213 9767 | G83: Móvil | I83: Valparaíso | J83: pasaje el peumo - El Criquet, casa 34, 2340000 Valparaíso | K83: Empresa de transporte por camión | L83: 1 | M83: 5 | N83: https://www.google.com/maps?cid=12371134150281197402 | O83: sin_web_propia
A84: Transporte Carreño & Carreño spa | C84: Transporte de carga | D84: Alta | E84: 65 | F84: +56 9 5051 6100 | G84: Móvil | I84: Valparaíso | J84: 2350, Valparaíso | K84: Empresa de transporte por camión | L84: 1 | M84: 5 | N84: https://www.google.com/maps?cid=13761420595544006382 | O84: sin_web_propia
A85: Cifuentes Zúñiga Transportes y Servicios Ltda. | C85: Transporte de carga | D85: Alta | E85: 65 | F85: +56 9 7995 7860 | G85: Móvil | I85: Viña del Mar | J85: Jackson 900 Magenta 6 depto 62, 2570023 Valparaíso, Viña del Mar, Valparaíso | K85: Empresa de transporte por camión | L85: 1 | M85: 5 | N85: https://www.google.com/maps?cid=15261182618278027883 | O85: sin_web_propia
A86: Transportes Arichile | C86: Transporte de carga | D86: Alta | E86: 65 | F86: +56 9 6350 5920 | G86: Móvil | H86: http://transportesarichile.negocio.site/ | I86: Viña del Mar | J86: 6medio oriente 280 viña del mar Quilpué, 2430000 Valparaíso, Viña del Mar, Valparaíso | K86: Empresa de transporte por camión | L86: 1 | M86: 5 | N86: https://www.google.com/maps?cid=12627758146840603306 | O86: sin_web_propia
A87: Sociedad De Servicios Portuarios Y Logistica Margomz Ltda. | C87: Portuario / Contenedores | D87: Alta | E87: 65 | F87: +56 35 228 2862 | G87: Fijo | I87: San Antonio | J87: La Playa 382, 2660916 San Antonio, Valparaíso | K87: Oficinas de empresa | L87: 1 | M87: 5 | N87: https://www.google.com/maps?cid=13207376887865459809 | O87: sin_web_propia
A88: Frigorifico Fiordosur Sa | C88: Frío / Alimentos | D88: Alta | E88: 65 | F88: +56 32 262 4922 | G88: Fijo | H88: http://www.fiordosur.cl/ | I88: Valparaíso | J88: Filippo Lippi 325, 2350789 Valparaíso | K88: Mayorista de marisco | N88: https://www.google.com/maps?cid=16067395838735165828 | O88: sin_resenas, sin_horario
A89: Leschaco (Chile) S A Valparaíso Office | C89: Logística / Almacenaje | D89: Alta | E89: 65 | F89: +56 2 2731 3000 | G89: Fijo | H89: https://www.leschaco.com/en/start.html# | I89: Valparaíso | J89: Cochrane 639, Piso 5 Oficina 51, 2361801 Valparaíso | K89: Servicio de logística | N89: https://www.google.com/maps?cid=2584964181510809432 | O89: sin_resenas, sin_horario
A90: Arca Transportes | C90: Transporte de carga | D90: Alta | E90: 60 | F90: +56 9 9739 5119 | G90: Móvil | I90: Viña del Mar | J90: 1 Nte. 461, Of. 703, 2520000 Viña del Mar, Valparaíso | K90: Servicio de lanzadera | L90: 43 | M90: 5 | N90: https://www.google.com/maps?cid=1774329931480674164 | O90: sin_web_propia, sin_horario
A91: Tecnomak Viña del mar | C91: Maquinaria / Industrial | D91: Alta | E91: 60 | F91: +56 32 254 5700 | G91: Fijo | I91: Viña del Mar | J91: Cancha 175, 2581437 Viña del Mar, Valparaíso | K91: Tienda de materiales para la construcción | L91: 32 | M91: 3.7 | N91: https://www.google.com/maps?cid=8785938434958096658 | O91: sin_web_propia
A92: Transportes Pia Ltda. | C92: Transporte de carga | D92: Alta | E92: 60 | F92: +56 9 6617 2505 | G92: Móvil | I92: San Antonio | J92: Unnamed Road, San Antonio, Valparaíso | K92: Empresa de transporte por camión | L92: 30 | M92: 4.3 | N92: https://www.google.com/maps?cid=9639983920940522483 | O92: sin_web_propia, direccion_imprecisa
A93: Maquinas Cubillos | C93: Maquinaria / Industrial | D93: Alta | E93: 60 | F93: +56 35 228 2570 | G93: Fijo | I93: San Antonio | J93: Av. Chile 300-390, 2660214 San Antonio, Valparaíso | K93: Centro comercial | L93: 27 | M93: 3.7 | N93: https://www.google.com/maps?cid=2760655219396001764 | O93: sin_web_propia
A94: Consorcio | C94: Logística / Almacenaje | D94: Alta | E94: 60 | F94: +56 9 5419 1869 | G94: Móvil | I94: San Antonio | J94: Unnamed Road, San Antonio, Valparaíso | K94: Almacén | L94: 27 | M94: 4.2 | N94: https://www.google.com/maps?cid=8670814600759832745 | O94: sin_web_propia, direccion_imprecisa
A95: Agrícola Randu | C95: Vitivinícola / Agrícola | D95: Alta | E95: 60 | G95: Sin teléfono | H95: http://www.randu.cl/ | I95: Curacaví | J95: Unnamed Road, Curacaví, Región Metropolitana | K95: Mayorista de productos agrícolas | L95: 26 | M95: 4.3 | N95: https://www.google.com/maps?cid=2114158833671426292 | O95: sin_telefono, direccion_imprecisa
A96: SAMEX Valparaíso | C96: Transporte de carga | D96: Alta | E96: 60 | G96: Sin teléfono | H96: https://www.samex.cl/ | I96: Valparaíso | J96: Décima Avenida 2450, 2340000 Valparaíso | K96: Servicio de transporte | L96: 15 | M96: 2.7 | N96: https://www.google.com/maps?cid=3112079283118093732 | O96: sin_telefono
A97: Logistica Transpiscis Limitada | C97: Transporte de carga | D97: Alta | E97: 60 | G97: Sin teléfono | H97: http://web.inverzal.cl/tpweb/ | I97: Valparaíso | J97: Camino Antiguo A Santiago 390, Valparaíso | K97: Empresa de transporte por camión | L97: 13 | M97: 4.5 | N97: https://www.google.com/maps?cid=3643739851714876607 | O97: sin_telefono, sin_horario
A98: PUERTO SAN ANTONIO | B98: PUERTO SAN ANTONIO | C98: Logística / Almacenaje | D98: Alta | E98: 55 | G98: Sin teléfono | H98: http://www.puertosanantonio.com/ | I98: San Antonio | J98: P.º El Mar, 2663160 San Antonio, Valparaíso | K98: Servicio de logística | L98: 958 | M98: 4.5 | N98: https://www.google.com/maps?cid=16102934231581641803 | O98: sin_telefono, direccion_imprecisa, sin_horario
A99: Transportes Alher Logística | C99: Transporte de carga | D99: Alta | E99: 55 | G99: Sin teléfono | H99: http://logisticaalher.cl/ | I99: San Antonio | J99: San Antonio, Valparaíso | K99: Servicio de transporte | L99: 28 | M99: 4.6 | N99: https://www.google.com/maps?cid=8449604855975277264 | O99: sin_telefono, direccion_imprecisa
A100: Fletes y mudanzas - Nano transportes | C100: Transporte de carga | D100: Alta | E100: 55 | F100: +56 9 9323 4839 | G100: Móvil | I100: Viña del Mar | J100: Sta. Inés 1665, 6444444 Viña del Mar, Valparaíso | K100: Empresa de transporte por camión | L100: 4 | M100: 3 | N100: https://www.google.com/maps?cid=1746642795745122978 | O100: sin_web_propia
...

Sheet Revisar_descartados
A1: Empresa | B1: Nombre_original | C1: Relevancia | D1: Motivo_relevancia | E1: Categorias | F1: Direccion | G1: Telefono | H1: Google_Maps_URL
A2: Vivero Las Higueras | B2: Vivero Las Higueras | C2: Baja | D2: Negocio minorista / no industrial (Centro de jardinería) | E2: Centro de jardinería, Jardín, Vivero | F2: Ambrosio O'Higgins 2159, 9630000 Curacavi, Curacaví, Región Metropolitana | G2: +56 9 4592 5759 | H2: https://www.google.com/maps?cid=12293987451101561929
A3: Equipos Gastronomicos Rorland | B3: Equipos Gastronomicos Rorland | C3: Baja | D3: Comercio minorista de equipos gastronómicos | E3: Comercio | F3: Independencia 2377, 2363026 Valparaíso | G3: +56 32 225 3651 | H3: https://www.google.com/maps?cid=1219856587436675942
A4: Corralosorno Quilpué | B4: Corralosorno Quilpué | C4: Baja | D4: Negocio minorista / no industrial (Carnicería) | E4: Carnicería | F4: Av. Industrial 1750, 2420468 Quilpué, Valparaíso | G4: +56 9 3414 8336 | H4: https://www.google.com/maps?cid=17096525727655765651
A5: Escuela Industrial San Antonio | B5: Escuela Industrial San Antonio | C5: Baja | D5: Negocio minorista / no industrial (Escuela secundaria de formación profesional) | E5: Escuela secundaria de formación profesional | F5: Centenario 278, 2661311 San Antonio, Valparaíso | G5: +56 35 229 1641 | H5: https://www.google.com/maps?cid=4177057867605349442
A6: Centro de Negocios Viña | B6: Centro de Negocios Viña | C6: Baja | D6: Negocio minorista / no industrial (Alquiler de oficinas virtuales) | E6: Alquiler de oficinas virtuales | F6: 1 Nte. 461, Ofi N°703, 2520307 Viña del Mar, Valparaíso | G6: +56 32 320 5459 | H6: https://www.google.com/maps?cid=6431957245828810260
A7: Centro de Negocios Sercotec Viña del Mar | B7: Centro de Negocios Sercotec Viña del Mar | C7: Baja | D7: Negocio minorista / no industrial (Consultora de administración empresarial) | E7: Consultora de administración empresarial | F7: 10 Nte 1059, 2531034 Viña del Mar, Valparaíso | G7: +56 9 8536 1466 | H7: https://www.google.com/maps?cid=3631155152832843340
A8: Frigorificio de Osorno .S.A Sala de ventas Quilpué | B8: Frigorificio de Osorno .S.A Sala de ventas Quilpué | C8: Baja | D8: Negocio minorista / no industrial (Carnicería) | E8: Carnicería, Establecimiento de servicios, Supermercado | G8: +56 9 3414 8336 | H8: https://www.google.com/maps?cid=11703444163609919525
A9: Casablanca chile Vinamar | B9: Casablanca chile Vinamar | C9: Baja | D9: Negocio minorista / no industrial (Restaurante) | E9: Restaurante | F9: Santiago - Valparaíso, Casablanca, Valparaíso | G9: +56 32 275 4300 | H9: https://www.google.com/maps?cid=943218181419965127
A10: La Industrial Outlet | B10: La Industrial Outlet | C10: Baja | D10: Ferretería minorista | E10: Ferretería | F10: San Antonio 1280, Loc 18, 2530970 Viña del Mar, Valparaíso | G10: +56 9 8900 4831 | H10: https://www.google.com/maps?cid=1712249352124228757
A11: Bodega El Granero | B11: Bodega El Granero | C11: Baja | D11: Negocio minorista / no industrial (Tienda de alimentos para animales) | E11: Tienda de alimentos para animales | F11: Chacabuco 2726, Chacabuco 2780, 2340000 Valparaíso | G11: +56 32 222 9968 | H11: https://www.google.com/maps?cid=17202916291960963566
A12: BODEGA URRIOLA | B12: BODEGA URRIOLA | C12: Baja | D12: Negocio minorista / no industrial (Tienda de bebidas alcohólicas) | E12: Tienda de bebidas alcohólicas, Delicatessen, Tienda de vinos | F12: Urriola 393, 2370654 Valparaíso | G12: +56 9 3698 0027 | H12: https://www.google.com/maps?cid=900648830059042680
A13: Bodega Chacabuco | B13: Bodega Chacabuco | C13: Baja | D13: Negocio minorista / no industrial (Tienda de alimentación) | E13: Tienda de alimentación | F13: Chacabuco 2748, 2340103 Valparaíso | G13: +56 32 211 6704 | H13: https://www.google.com/maps?cid=7102832595028841173
A14: Carniceria Nacional | B14: Carniceria Nacional | C14: Baja | D14: Negocio minorista / no industrial (Carnicería) | E14: Carnicería | F14: Sta. Luisa 980, Casablanca, Valparaíso | G14: +56 9 4526 4464 | H14: https://www.google.com/maps?cid=14628573641233465999
A15: Agricom | B15: Agricom | C15: Baja | D15: Negocio minorista / no industrial (Frutería) | E15: Frutería | F15: Curacavi, Curacaví, Región Metropolitana | G15: +56 9 9133 3721 | H15: https://www.google.com/maps?cid=13116013631737311498
A16: Carnicería Carnes Casablanca | B16: Carnicería Carnes Casablanca | C16: Baja | D16: Negocio minorista / no industrial (Carnicería) | E16: Carnicería | F16: Av. Portales 771, 2480427 Casablanca, Valparaíso | G16: +56 9 9689 5670 | H16: https://www.google.com/maps?cid=7002970082433172947
A17: Bodega el Campo | B17: Bodega el Campo | C17: Baja | D17: Comercio minorista | E17: Bodega | F17: Chacabuco 2780, 2340103 Valparaíso | G17: +56 32 222 9968 | H17: https://www.google.com/maps?cid=17924098167821079798
A18: Foco Alimentos Spa | B18: Foco Alimentos Spa | C18: Baja | D18: Negocio minorista / no industrial (Carnicería) | E18: Carnicería | F18: El Boldo 366, Loc 2 y 3, 2710000 Algarrobo, Valparaíso | G18: +56 9 9904 0482 | H18: https://www.google.com/maps?cid=9977597838848029023
A19: Terminal de Buses De Viña Del Mar | B19: Terminal de Buses De Viña Del Mar | C19: Baja | D19: Negocio minorista / no industrial (Empresa de autobuses) | E19: Empresa de autobuses | F19: Av. Valparaíso 1055, 2520479 Viña del Mar, Valparaíso | H19: https://www.google.com/maps?cid=6437795891577142128
A20: Centro De Abastecimiento De La Armada | B20: Centro De Abastecimiento De La Armada | C20: Baja | D20: Institución militar, no prospecto comercial | E20: Bodega | F20: Antonio Varas 348, Valparaíso | H20: https://www.google.com/maps?cid=1687301309762889876
A21: Frigorífico Casa Blanca S.A. | B21: Frigorífico Casa Blanca S.A. | C21: Descartar | D21: Empresa en Uruguay (homónimo de Casablanca, Chile) | E21: Fabricante de alimentos | F21: 60000 Casablanca, Departamento de Paysandú, Uruguay | G21: +59847242627 | H21: https://www.google.com/maps?cid=18401867757408298922
A22: Bodega Simón Bolívar | B22: Bodega Simón Bolívar | C22: Descartar | D22: Edificio histórico (ficha Wikipedia), no es empresa | E22: Almacén | F22: Av. Federico Errázuriz, Valparaíso | H22: https://www.google.com/maps?cid=4781915382013770219
A23: San Antonio Port - Chile | B23: San Antonio Port - Chile | C23: Descartar | D23: Duplicado de Puerto San Antonio sin datos | E23: Empresa portuaria | F23: San Antonio, Valparaíso | H23: https://www.google.com/maps?cid=10739526799880319739
A24: Transporte de carga por carretera | B24: Transporte de carga por carretera | C24: Descartar | D24: Ficha genérica sin empresa identificable | E24: Servicio de transporte | F24: Avenida 23 de Noviembre, San Antonio, Valparaíso | H24: https://www.google.com/maps?cid=12160355797537377473
A25: portería ENAP | B25: portería ENAP | C25: Descartar | D25: Portería de ENAP Aconcagua (duplicado) | E25: Distribuidor de productos químicos industriales | F25: Av. Principal 300-398, Concón, Valparaíso | H25: https://www.google.com/maps?cid=17017377497588589331
A26: Las Bodegas | B26: Las Bodegas | C26: Descartar | D26: Ficha genérica sin datos | F26: San Antonio, Valparaíso | H26: https://www.google.com/maps?cid=11293194763914809494

Sheet Diccionario
A1: Campo | B1: Descripción
A2: Place_Id | B2: ID único de Google Maps; clave de deduplicación
A3: Empresa | B3: Nombre limpio (sin relleno SEO)
A4: Nombre_original | B4: Nombre tal cual en Google Maps
A5: Grupo_empresa | B5: Empresa matriz cuando varias fichas comparten dominio web o teléfono
A6: N_sedes_grupo | B6: Nº de fichas del mismo grupo
A7: Segmento | B7: Rubro asignado por reglas sobre categorías de Google, nombre y búsqueda de origen
A8: Relevancia | B8: Alta: industrial/logística en zona objetivo con contacto · Media: falta contacto o fuera de zona · Baja: minorista/no industrial · Descartar: no es empresa, duplicado o fuera de Chile
A9: Motivo_relevancia | B9: Regla que asignó la relevancia
A10: Score_completitud | B10: 0–100: teléfono 25 · web propia 25 · dirección con número 15 (aprox. 5) · reseñas ≥50:15, ≥10:10, ≥1:5 · rating ≥4: 10 · horario 10
A11: Telefono | B11: Formato internacional +56
A12: Tipo_telefono | B12: Móvil / Fijo / 600 / Extranjero / Sin teléfono
... A19: Columnas eliminadas | B19: Email y Social Medias (bloqueados por plan gratuito), Claimed (siempre false), Price (1 valor), Phones, Review URL, Featured Image, Cid

Sheet Log_limpieza
A1: Paso | B1: Filas afectadas | C1: Detalle
A2: Carga | B2: 344 | C2: 24 CSV (se ignoran 22 archivos basura __MACOSX/._*)
A3: Eliminar pie de página del scraper | B3: 48 | C3: Filas "Map Lead Scraper exports only 15 records..." / "This data was exported from..."
A4: Deduplicar por Place Id | B4: 101 | C4: 296 filas → 195 empresas únicas (las búsquedas de origen se conservan agregadas)
A5: Eliminar columnas sin información | B5: 195 | C5: Email y Social Medias = "visible after upgrade" en 100%; Claimed = false en 100%; Price con 1 solo valor
A6: Eliminar columnas redundantes | B6: 195 | C6: Phones (≈Phone), Review URL (derivable del Place Id), Featured Image (URL temporal), Cid (incluido en Google Maps URL)
A7: Normalizar nombre | B7: 6 | C7: Recorte de nombres con relleno SEO ("X I HERRAMIENTAS I ...", "X | Arriendo ..."); "." → STI (según dominio stiport.com). Original en Nombre_original
A8: Normalizar teléfono a formato internacional | B8: 144 | C8: Se toma la versión +56 de "Phones"; se clasifica móvil/fijo/600
A9: Marcar sitios no propios | B9: 7 | C9: Instagram, WhatsApp, g.page, Wikipedia, negocio.site, ueniweb no cuentan como web corporativa
A10: Parsear dirección | B10: 195 | C10: Extracción de comuna, región, código postal y nivel de precisión (Plus Code, camino sin nombre, solo comuna)
A11: Agrupar sedes de una misma empresa | B11: 16 | C11: 8 grupos detectados por dominio web o teléfono compartido (no se borran: son sedes distintas)
