Workbook

Sheet Contactos
A1: ID | B1: Nombre | C1: Cargo | D1: Empresa | E1: País | F1: Email | G1: LinkedIn | H1: Origen | I1: Estado | J1: Prioridad | K1: Próxima acción | L1: Notas | M1: Segmento SafetyMind | N1: Stand(s) | O1: N° stands | P1: Web | Q1: Teléfono(s) | R1: Dirección | S1: En Directorio SSO
A2: 1 | D2: ACTIVOS MINEROS S.A.C. | E2: Perú | H2: ExpoMina 2026 | I2: Prospecto | J2: Alta | K2: Mapear Gerente SSOMA/HSE y unidades mineras; proponer piloto | L2: ExpoMina 2026. Varios stands (mayor inversión). Sin contacto publicado. | M2: Minera (cliente final) | N2: E-285, E-287 | O2: 2 | P2: amsac.pe | S2: No
A3: 2 | D3: ANGLO AMERICAN QUELLAVECO S.A. | E3: Perú | H3: ExpoMina 2026 | I3: Prospecto | J3: Alta | K3: Mapear Gerente SSOMA/HSE y unidades mineras; proponer piloto | L3: ExpoMina 2026. Sin contacto publicado. | M3: Minera (cliente final) | N3: A-078 | O3: 1 | P3: https://peru.angloamerican.com/ | S3: No
A4: 3 | D4: SOCIEDAD MINERA CERRO VERDE S.A.A. | E4: Perú | H4: ExpoMina 2026 | I4: Prospecto | J4: Alta | K4: Mapear Gerente SSOMA/HSE y unidades mineras; proponer piloto | L4: ExpoMina 2026. Sin contacto publicado. | M4: Minera (cliente final) | N4: A-175 | O4: 1 | P4: www.cerroverde.pe | S4: No
A5: 4 | D5: EQUANS SERVICES PERÚ S.A. | E5: Perú | F5: contacto.espe@equans.com | H5: ExpoMina 2026 | I5: Prospecto | J5: Alta | K5: Identificar Gerente SSOMA/HSE en LinkedIn y proponer demo | L5: ExpoMina 2026. Varios stands (mayor inversión). También en CRM Directorio SSO 2026 (ID 52). | M5: Cliente potencial – contratista / operación de alto riesgo | N5: A-297, A-298, A-301, A-302 | O5: 4 | P5: www.equans.pe | R5: Av. Paseo de la República 3617 San Isidro - Lima | S5: Sí
A6: 5 | D6: NEUMA PERÚ CONTRATISTAS GENERALES S.A.C. | E6: Perú | F6: ventas@neumaperu.com.pe | H6: ExpoMina 2026 | I6: Prospecto | J6: Alta | K6: Identificar Gerente SSOMA/HSE en LinkedIn y proponer demo | L6: ExpoMina 2026. Varios stands (mayor inversión). También en CRM Directorio SSO 2026 (ID 105). | M6: Cliente potencial – contratista / operación de alto riesgo | N6: F-084, F-085, F-086 | O6: 3 | P6: www.neumaperu.com.pe | Q6: 6180300 / 971523609 | R6: Av. Nicolás Ayllón 2142 - Ate Vitarte Lima | S6: Sí
A7: 6 | D7: AOM SUMINISTROS INDUSTRIALES S.A.C | E7: Perú | F7: info@aom.pe | H7: ExpoMina 2026 | I7: Prospecto | J7: Alta | K7: Identificar Gerente SSOMA/HSE en LinkedIn y proponer demo | L7: ExpoMina 2026. Varios stands (mayor inversión). También en CRM Directorio SSO 2026 (ID 10). | M7: Cliente potencial – contratista / operación de alto riesgo | N7: A-161, A-410 | O7: 2 | P7: www.aom.com.pe | R7: Jr. Cruz del Sur 140 Of.1503, Santiago de Surco - Lima | S7: Sí
A8: 7 | D8: CONSORCIO MINERIA SUBTERRANEA S.A.C. COMISUB S.A.C. | E8: Perú | H8: ExpoMina 2026 | I8: Prospecto | J8: Alta | K8: Identificar Gerente SSOMA/HSE en LinkedIn y proponer demo | L8: ExpoMina 2026. Varios stands (mayor inversión). Sin contacto publicado. | M8: Cliente potencial – contratista / operación de alto riesgo | N8: A-075, A-076 | O8: 2 | P8: https://comisub.com/ | S8: No
A9: 8 | D9: MAQUINAS Y MONTAJES S.A | E9: Perú (por validar) | H9: ExpoMina 2026 | I9: Prospecto | J9: Alta | K9: Identificar Gerente SSOMA/HSE en LinkedIn y proponer demo | L9: ExpoMina 2026. Varios stands (mayor inversión). País inferido; validar. Sin contacto publicado. | M9: Cliente potencial – contratista / operación de alto riesgo | N9: A-079, A-080 | O9: 2 | P9: www.maquinasymontajes.com | S9: No
A10: 9 | D10: TUMI CONTRATISTAS MINEROS S.A.C | E10: Perú | F10: sales.ventas@tumirb.com | H10: ExpoMina 2026 | I10: Prospecto | J10: Alta | K10: Identificar Gerente SSOMA/HSE en LinkedIn y proponer demo | L10: ExpoMina 2026. Varios stands (mayor inversión). También en CRM Directorio SSO 2026 (ID 163). | M10: Cliente potencial – contratista / operación de alto riesgo | N10: E-205A, E-205B | O10: 2 | P10: https://tumirb.com | Q10: 982483947 | R10: Unidad Inmobiliaria Nº1 con frente Av. Paul Poblet s/n, Lurín - Lima | S10: Sí
A11: 10 | D11: AHORRO DE ENERGÍA Y MANTENIMIENTO INDUSTRIAL | E11: Perú | F11: ademinsa@ademinsa.com | H11: ExpoMina 2026 | I11: Prospecto | J11: Alta | K11: Identificar Gerente SSOMA/HSE en LinkedIn y proponer demo | L11: ExpoMina 2026. También en CRM Directorio SSO 2026 (ID 2). | M11: Cliente potencial – contratista / operación de alto riesgo | N11: E-359 | O11: 1 | P11: https://ademinsa.com/ | Q11: 2750082 | R11: Cl. Cerro Azul 479 Of. 101A Urb. San Ignacio de Loyola Santiago de Surco - Lima | S11: Sí
A12: 11 | D12: ARMOTEC CONTRATISTAS GENERALES S.A.C. - ARMOTEC S.A.C. | E12: Perú | H12: ExpoMina 2026 | I12: Prospecto | J12: Alta | K12: Identificar Gerente SSOMA/HSE en LinkedIn y proponer demo | L12: ExpoMina 2026. Sin contacto publicado. | M12: Cliente potencial – contratista / operación de alto riesgo | N12: B-211 | O12: 1 | P12: http://armotec.pe | S12: No
A13: 12 | D13: COMERCIAL DRILLING SERVICES S.A.C.- CODRISE S.A.C. | E13: Perú | H13: ExpoMina 2026 | I13: Prospecto | J13: Alta | K13: Identificar Gerente SSOMA/HSE en LinkedIn y proponer demo | L13: ExpoMina 2026. Sin contacto publicado. | M13: Cliente potencial – contratista / operación de alto riesgo | N13: B-094 | O13: 1 | P13: https://codrise.com/ | S13: No
A14: 13 | D14: CONSORCIO MINING CONSTRUCCION & SOLUTION S.A.C. - CONSORCIO MICONSOL S.A.C. | E14: Perú | H14: ExpoMina 2026 | I14: Prospecto | J14: Alta | K14: Identificar Gerente SSOMA/HSE en LinkedIn y proponer demo | L14: ExpoMina 2026. Sin contacto publicado. | M14: Cliente potencial – contratista / operación de alto riesgo | N14: E-001 | O14: 1 | P14: https://essotech.pe/ | S14: No
A15: 14 | D15: CONSTRUCCIONES ELECTROMECANICAS DELCROSA S.A. O DELCROSA S.A. | E15: Perú | H15: ExpoMina 2026 | I15: Prospecto | J15: Alta | K15: Identificar Gerente SSOMA/HSE en LinkedIn y proponer demo | L15: ExpoMina 2026. Sin contacto publicado. | M15: Cliente potencial – contratista / operación de alto riesgo | N15: E-173 | O15: 1 | P15: https://www.delcrosa.com.pe/es | S15: No
A16: 15 | D16: CONSTRUCTORA GALAXIA S.A.C. | E16: Perú | H16: ExpoMina 2026 | I16: Prospecto | J16: Alta | K16: Identificar Gerente SSOMA/HSE en LinkedIn y proponer demo | L16: ExpoMina 2026. Sin contacto publicado. | M16: Cliente potencial – contratista / operación de alto riesgo | N16: A-390 | O16: 1 | S16: No
A17: 16 | D17: CONSULTORES EN INGENIERIA GEOTECNICA ESTRUCTURAL Y CONSTRUCCION S.A.C. - COINGEC S.A.C. | E17: Perú | H17: ExpoMina 2026 | I17: Prospecto | J17: Alta | K17: Identificar Gerente SSOMA/HSE en LinkedIn y proponer demo | L17: ExpoMina 2026. Sin contacto publicado. | M17: Cliente potencial – contratista / operación de alto riesgo | N17: A-199 | O17: 1 | P17: https://coingec.com/ | S17: No
A18: 17 | D18: EMPRESA DE SERVICIOS CONSTRUCCION CONSULTORIA | E18: Por validar | H18: ExpoMina 2026 | I18: Prospecto | J18: Alta | K18: Identificar Gerente SSOMA/HSE en LinkedIn y proponer demo | L18: ExpoMina 2026. País inferido; validar. Sin contacto publicado. | M18: Cliente potencial – contratista / operación de alto riesgo | N18: E-334 | O18: 1 | S18: No
A19: 18 | D19: FABRICACIONES ANDINAS S.A.C. | E19: Perú | H19: ExpoMina 2026 | I19: Prospecto | J19: Alta | K19: Identificar Gerente SSOMA/HSE en LinkedIn y proponer demo | L19: ExpoMina 2026. Sin contacto publicado. | M19: Cliente potencial – contratista / operación de alto riesgo | N19: A-261 | O19: 1 | P19: en construccion | S19: No
A20: 19 | D20: FAMESA EXPLOSIVOS S.A.C. | E20: Perú | F20: ventas@famesa.com.pe | H20: ExpoMina 2026 | I20: Prospecto | J20: Alta | K20: Identificar Gerente SSOMA/HSE en LinkedIn y proponer demo | L20: ExpoMina 2026. También en CRM Directorio SSO 2026 (ID 60). | M20: Cliente potencial – contratista / operación de alto riesgo | N20: E-016 | O20: 1 | P20: www.famesaexplosivos.com | Q20: 6139800 | R20: Panamericana Norte km 28 Puente Piedra - Lima | S20: Sí
A21: 20 | D21: GINSUMIL CORPORATION S.A.C. | E21: Perú | F21: ventas@ginsumilcorp.com | H21: ExpoMina 2026 | I21: Prospecto | J21: Alta | K21: Identificar Gerente SSOMA/HSE en LinkedIn y proponer demo | L21: ExpoMina 2026. También en CRM Directorio SSO 2026 (ID 70). | M21: Cliente potencial – contratista / operación de alto riesgo | N21: B-263 | O21: 1 | P21: https://ginsumilcorp.com/ | Q21: 993022915 | R21: Av. Mariano Pastor Sevilla Mz.D Lt.40 Sector 5 San Juan de Miraflores - Lima | S21: Sí
A22: 21 | D22: GS METAL DRILLING S.A.C. | E22: Perú | H22: ExpoMina 2026 | I22: Prospecto | J22: Alta | K22: Identificar Gerente SSOMA/HSE en LinkedIn y proponer demo | L22: ExpoMina 2026. Sin contacto publicado. | M22: Cliente potencial – contratista / operación de alto riesgo | N22: B-091 | O22: 1 | P22: www.gsdrilling.pe | S22: No
A23: 22 | D23: INGENIERÍA Y CONSTRUCCIÓN SIGDO KOPPERS EQUIPOS Y SERVICIOS S.A.C. - ICSK EQUIPOS Y SERVICIOS S.A.C. | E23: Perú | H23: ExpoMina 2026 | I23: Prospecto | J23: Alta | K23: Identificar Gerente SSOMA/HSE en LinkedIn y proponer demo | L23: ExpoMina 2026. Sin contacto publicado. | M23: Cliente potencial – contratista / operación de alto riesgo | N23: B-267 | O23: 1 | P23: www.skdeysu.com | S23: No
A24: 23 | D24: JMF INGENIERIA & CONSTRUCCION SAC | E24: Perú | H24: ExpoMina 2026 | I24: Prospecto | J24: Alta | K24: Identificar Gerente SSOMA/HSE en LinkedIn y proponer demo | L24: ExpoMina 2026. Sin contacto publicado. | M24: Cliente potencial – contratista / operación de alto riesgo | N24: E-275 | O24: 1 | P24: https://www.jmf.com.pe/ | S24: No
A25: 24 | D25: MINERA DRILLING S.R.L. | E25: Perú | H25: ExpoMina 2026 | I25: Prospecto | J25: Alta | K25: Identificar Gerente SSOMA/HSE en LinkedIn y proponer demo | L25: ExpoMina 2026. Sin contacto publicado. | M25: Cliente potencial – contratista / operación de alto riesgo | N25: A-192 | O25: 1 | P25: www.mineradrilling.com | S25: No
A26: 25 | D26: MINTECH MINING TECHNOLOGY E.I.R.L. | E26: Perú | F26: info@mintech.com.pe | H26: ExpoMina 2026 | I26: Prospecto | J26: Alta | K26: Identificar Gerente SSOMA/HSE en LinkedIn y proponer demo | L26: ExpoMina 2026. También en CRM Directorio SSO 2026 (ID 99). | M26: Cliente potencial – contratista / operación de alto riesgo | N26: E-226 | O26: 1 | P26: www.mintech.com.pe | Q26: 2766979 / 6228124 | R26: Av. Los Pinos Mz.W Lt.2 Asociación Chillón Puente Piedra - Lima | S26: Sí
A27: 26 | D27: NEXTECH CONSTRUCCION MODULAR S.A.C. | E27: Perú | H27: ExpoMina 2026 | I27: Prospecto | J27: Alta | K27: Identificar Gerente SSOMA/HSE en LinkedIn y proponer demo | L27: ExpoMina 2026. Sin contacto publicado. | M27: Cliente potencial – contratista / operación de alto riesgo | N27: E-183 | O27: 1 | P27: https://nextechmodular.com/ | S27: No
A28: 27 | D28: OVERPRIME MANUFACTURING S.A.C. | E28: Perú | H28: ExpoMina 2026 | I28: Prospecto | J28: Alta | K28: Identificar Gerente SSOMA/HSE en LinkedIn y proponer demo | L28: ExpoMina 2026. También en CRM Directorio SSO 2026 (ID 111). | M28: Cliente potencial – contratista / operación de alto riesgo | N28: E-013 | O28: 1 | P28: https://overprimegroup.com/ | Q28: 5187100 / 994660177 | R28: Av. Alameda Sur 216 Urb. Villa Marina Chorrillos - Lima | S28: Sí
A29: 28 | D29: PENTATECH CONSTRUCCION S.A.C. | E29: Perú | H29: ExpoMina 2026 | I29: Prospecto | J29: Alta | K29: Identificar Gerente SSOMA/HSE en LinkedIn y proponer demo | L29: ExpoMina 2026. Sin contacto publicado. | M29: Cliente potencial – contratista / operación de alto riesgo | N29: B-242A | O29: 1 | P29: www.pentatechsac.com | S29: No
A30: 29 | D30: PEVOEX CONTRATISTAS S.A.C. | E30: Perú | F30: presupuestos@pevoex.com.pe | H30: ExpoMina 2026 | I30: Prospecto | J30: Alta | K30: Identificar Gerente SSOMA/HSE en LinkedIn y proponer demo | L30: ExpoMina 2026. También en CRM Directorio SSO 2026 (ID 113). | M30: Cliente potencial – contratista / operación de alto riesgo | N30: B-023 | O30: 1 | P30: pevoex.com | Q30: 6832277 / 989262241 | R30: Av. Circunvalación del Club Golf Los Incas 154 Of. 404 Santiago de Surco - Lima | S30: Sí
A31: 30 | D31: PROYECTOS EJECUCION Y MONTAJES INDST.SA | E31: Perú | H31: ExpoMina 2026 | I31: Prospecto | J31: Alta | K31: Identificar Gerente SSOMA/HSE en LinkedIn y proponer demo | L31: ExpoMina 2026. Sin contacto publicado. | M31: Cliente potencial – contratista / operación de alto riesgo | N31: E-368 | O31: 1 | P31: www.proemisa.pe | S31: No
A32: 31 | D32: RCP INGENIEROS CONSULTORES Y CONTRATISTAS DE SERVICIOS ESPECIALIZADOS E.I.R.L. | E32: Perú | H32: ExpoMina 2026 | I32: Prospecto | J32: Alta | K32: Identificar Gerente SSOMA/HSE en LinkedIn y proponer demo | L32: ExpoMina 2026. Sin contacto publicado. | M32: Cliente potencial – contratista / operación de alto riesgo | N32: E-148D | O32: 1 | P32: www.geodrone.com.pe | S32: No
A33: 32 | D33: REPRESENTACIONES PERUVIAN TRADING S.A. | E33: Perú | F33: ventas@rptsa.com.pe | H33: ExpoMina 2026 | I33: Prospecto | J33: Alta | K33: Identificar Gerente SSOMA/HSE en LinkedIn y proponer demo | L33: ExpoMina 2026. También en CRM Directorio SSO 2026 (ID 123). | M33: Cliente potencial – contratista / operación de alto riesgo | N33: A-350 | O33: 1 | P33: https://rptsa.com.pe/ | Q33: 4428559 | R33: Pje. Los Jilgueros 108 Urb. Limatambo Surquillo - Lima | S33: Sí
A34: 33 | D34: ROBOCON SERVICIOS S.A.C. | E34: Perú | H34: ExpoMina 2026 | I34: Prospecto | J34: Alta | K34: Identificar Gerente SSOMA/HSE en LinkedIn y proponer demo | L34: ExpoMina 2026. Sin contacto publicado. | M34: Cliente potencial – contratista / operación de alto riesgo | N34: A-010 | O34: 1 | P34: https://robocon.pe/ | S34: No
A35: 34 | D35: ROEDA S.A | E35: Perú | F35: roeda@roeda.com.pe | H35: ExpoMina 2026 | I35: Prospecto | J35: Alta | K35: Identificar Gerente SSOMA/HSE en LinkedIn y proponer demo | L35: ExpoMina 2026. También en CRM Directorio SSO 2026 (ID 127). | M35: Cliente potencial – contratista / operación de alto riesgo | N35: A-259 | O35: 1 | P35: www.roeda.com.pe | Q35: 3151400 / 997567133 | R35: Jr. Tarma 272- Cercado de Lima - Lima | S35: Sí
A36: 35 | D36: RYDER DRILLING TOOLS S.A.C.- RYDER DRILLING TOOLS S.A.C. | E36: Perú | H36: ExpoMina 2026 | I36: Prospecto | J36: Alta | K36: Identificar Gerente SSOMA/HSE en LinkedIn y proponer demo | L36: ExpoMina 2026. Sin contacto publicado. | M36: Cliente potencial – contratista / operación de alto riesgo | N36: A-402 | O36: 1 | P36: https://ryderdrilling.com/ | S36: No
A37: 36 | D37: SAFE & CARE S.A.C. | E37: Perú | F37: ventas@safeycare.com | H37: ExpoMina 2026 | I37: Prospecto | J37: Alta | K37: Identificar Gerente SSOMA/HSE en LinkedIn y proponer demo | L37: ExpoMina 2026. También en CRM Directorio SSO 2026 (ID 130). | M37: Cliente potencial – contratista / operación de alto riesgo | N37: A-107 | O37: 1 | P37: https://safeycare.com/ | Q37: (+51) 959267990 / (+51) 989147895 | R37: Cl. Los Talladores 275 - Ate - Lima | S37: Sí
A38: 37 | D38: SISTEMAS DE PERFORACION Y GEOTECNIA S.A.C | E38: Perú | H38: ExpoMina 2026 | I38: Prospecto | J38: Alta | K38: Identificar Gerente SSOMA/HSE en LinkedIn y proponer demo | L38: ExpoMina 2026. Sin contacto publicado. | M38: Cliente potencial – contratista / operación de alto riesgo | N38: B-169 | O38: 1 | P38: https://incotep.com/ | S38: No
A39: 38 | D39: SOLUCIONES QUIMICAS PARA LA MINERIA Y LA CONSTRUCCION S.A.C.- SOQUIMIC S.A.C. | E39: Perú | H39: ExpoMina 2026 | I39: Prospecto | J39: Alta | K39: Identificar Gerente SSOMA/HSE en LinkedIn y proponer demo | L39: ExpoMina 2026. Sin contacto publicado. | M39: Cliente potencial – contratista / operación de alto riesgo | N39: E-002 | O39: 1 | P39: www.chryso.com | S39: No
A40: 39 | D40: TRANSPORTES LINEA S.A. | E40: Perú | H40: ExpoMina 2026 | I40: Prospecto | J40: Alta | K40: Identificar Gerente SSOMA/HSE en LinkedIn y proponer demo | L40: ExpoMina 2026. Sin contacto publicado. | M40: Cliente potencial – contratista / operación de alto riesgo | N40: E-291 | O40: 1 | P40: www.linea.pe | S40: No
A41: 40 | D41: ULMA ENCOFRADOS PERÚ S.A. | E41: Perú | F41: ventas@ulmaconstruction.com.pe | H41: ExpoMina 2026 | I41: Prospecto | J41: Alta | K41: Identificar Gerente SSOMA/HSE en LinkedIn y proponer demo | L41: ExpoMina 2026. También en CRM Directorio SSO 2026 (ID 164). | M41: Cliente potencial – contratista / operación de alto riesgo | N41: E-322A | O41: 1 | P41: https://www.ulmaconstruction.com.pe/es-pe | Q41: 6136700 | R41: Av. Argentina 2882 - Cercado de Lima Lima | S41: Sí
A42: 41 | D42: CAD SOLUTIONS SA | E42: Perú | H42: ExpoMina 2026 | I42: Prospecto | J42: Alta | K42: Mapear oferta: evaluar integración o competencia | L42: ExpoMina 2026. Varios stands (mayor inversión). Sin contacto publicado. | M42: Partner tecnológico / competidor | N42: B-155A, B-155B | O42: 2 | P42: www.cadsolutions.pe | S42: No
A43: 42 | D43: ENTEL PERÚ S.A. | E43: Perú | H43: ExpoMina 2026 | I43: Prospecto | J43: Alta | K43: Mapear oferta: evaluar integración o competencia | L43: ExpoMina 2026. Varios stands (mayor inversión). Sin contacto publicado. | M43: Partner tecnológico / competidor | N43: A-262, A-263 | O43: 2 | S43: No
A44: 43 | D44: MAPTEK COMPUTACION CHILE LIMITADA SUCURSAL PERU | E44: Perú | H44: ExpoMina 2026 | I44: Prospecto | J44: Alta | K44: Mapear oferta: evaluar integración o competencia | L44: ExpoMina 2026. Varios stands (mayor inversión). Sin contacto publicado. | M44: Partner tecnológico / competidor | N44: A-096, A-100 | O44: 2 | P44: https://www.maptek.com/cl/ | S44: No
A45: 44 | D45: SOUTHERN TECHNOLOGY GROUP PERÚ S.A.C. - STG PERÚ S.A.C. | E45: Perú | H45: ExpoMina 2026 | I45: Prospecto | J45: Alta | K45: Mapear oferta: evaluar integración o competencia | L45: ExpoMina 2026. Varios stands (mayor inversión). Sin contacto publicado. | M45: Partner tecnológico / competidor | N45: E-390, E-391 | O45: 2 | P45: https://www.stglatam.com/ | S45: No
A46: 45 | D46: YOKOGAWA AMERICA DO SUL LTDA SUCURSAL PERU | E46: Perú | H46: ExpoMina 2026 | I46: Prospecto | J46: Alta | K46: Mapear oferta: evaluar integración o competencia | L46: ExpoMina 2026. Varios stands (mayor inversión). Sin contacto publicado. | M46: Partner tecnológico / competidor | N46: A-196, A-197 | O46: 2 | P46: https://www.yokogawa.com/sa-es/ | S46: No
A47: 46 | D47: AGIA TECHNOLOGY S.A.C. | E47: Perú | H47: ExpoMina 2026 | I47: Prospecto | J47: Alta | K47: Mapear oferta: evaluar integración o competencia | L47: ExpoMina 2026. Sin contacto publicado. | M47: Partner tecnológico / competidor | N47: A-286A | O47: 1 | P47: atsecurity.ai | S47: No
A48: 47 | D48: FLO-2D SOFTWARE, INC. | E48: Estados Unidos (por validar) | H48: ExpoMina 2026 | I48: Prospecto | J48: Alta | K48: Mapear oferta: evaluar integración o competencia | L48: ExpoMina 2026. País inferido; validar. Sin contacto publicado. | M48: Partner tecnológico / competidor | N48: A-366 | O48: 1 | P48: www.flo-2d.com | S48: No
A49: 48 | D49: GC. TELECOM S.A.C. | E49: Perú | H49: ExpoMina 2026 | I49: Prospecto | J49: Alta | K49: Mapear oferta: evaluar integración o competencia | L49: ExpoMina 2026. Sin contacto publicado. | M49: Partner tecnológico / competidor | N49: E-010 | O49: 1 | P49: https://telecomstore.pe | S49: No
A50: 49 | D50: GEO SYSTEMS S.A.C. | E50: Perú | H50: ExpoMina 2026 | I50: Prospecto | J50: Alta | K50: Mapear oferta: evaluar integración o competencia | L50: ExpoMina 2026. Sin contacto publicado. | M50: Partner tecnológico / competidor | N50: A-092 | O50: 1 | P50: www.geosystemsperu.com | S50: No
A51: 50 | D51: HANWHA VISION MEXICO | E51: México | H51: ExpoMina 2026 | I51: Prospecto | J51: Alta | K51: Mapear oferta: evaluar integración o competencia | L51: ExpoMina 2026. Sin contacto publicado. | M51: Partner tecnológico / competidor | N51: A-401 | O51: 1 | P51: www.hanwhavision.com | S51: No
A52: 51 | D52: HEXAGON MINING PERÚ S.A.C. | E52: Perú | F52: jorge.loayza@hexagon.com | H52: ExpoMina 2026 | I52: Prospecto | J52: Alta | K52: Mapear oferta: evaluar integración o competencia | L52: ExpoMina 2026. También en CRM Directorio SSO 2026 (ID 334). | M52: Partner tecnológico / competidor | N52: B-241 | O52: 1 | P52: https://hexagon.com/company/divisions/mining | Q52: 6264422 | R52: Av. La Encalada 1388 Piso 5 Of. 501 Santiago de Surco - Lima | S52: Sí
A53: 52 | D53: HIALEAH RADIO S.A.C. | E53: Perú | H53: ExpoMina 2026 | I53: Prospecto | J53: Alta | K53: Mapear oferta: evaluar integración o competencia | L53: ExpoMina 2026. Sin contacto publicado. | M53: Partner tecnológico / competidor | N53: E-329A | O53: 1 | P53: www.hialeahsac.com | S53: No
A54: 53 | D54: ID AUTOMATION S.A.C. | E54: Perú | H54: ExpoMina 2026 | I54: Prospecto | J54: Alta | K54: Mapear oferta: evaluar integración o competencia | L54: ExpoMina 2026. Sin contacto publicado. | M54: Partner tecnológico / competidor | N54: E-348B | O54: 1 | P54: www.idautomat.com | S54: No
A55: 54 | D55: INGENIERIA DE CYCLONES, BOMBAS Y AUTOMATIZACION SAC - ICBA INGENIERIA DE CYCLONES SAC | E55: Perú | H55: ExpoMina 2026 | I55: Prospecto | J55: Alta | K55: Mapear oferta: evaluar integración o competencia | L55: ExpoMina 2026. Sin contacto publicado. | M55: Partner tecnológico / competidor | N55: A-315 | O55: 1 | P55: https://icba.com.pe/ | S55: No
A56: 55 | D56: INTEGRATEL PERÚ S.A.A | E56: Perú | H56: ExpoMina 2026 | I56: Prospecto | J56: Alta | K56: Mapear oferta: evaluar integración o competencia | L56: ExpoMina 2026. Sin contacto publicado. | M56: Partner tecnológico / competidor | N56: A-171 | O56: 1 | S56: No
A57: 56 | D57: MATYC AUTOMATION S.A.C. | E57: Perú | H57: ExpoMina 2026 | I57: Prospecto | J57: Alta | K57: Mapear oferta: evaluar integración o competencia | L57: ExpoMina 2026. Sin contacto publicado. | M57: Partner tecnológico / competidor | N57: A-306 | O57: 1 | P57: www.matycperu.com | S57: No
A58: 57 | D58: PALACIOS AUTOMATIC S.A.C. | E58: Perú | H58: ExpoMina 2026 | I58: Prospecto | J58: Alta | K58: Mapear oferta: evaluar integración o competencia | L58: ExpoMina 2026. Sin contacto publicado. | M58: Partner tecnológico / competidor | N58: A-108 | O58: 1 | P58: https://palaciosautomatic.com/ | S58: No
A59: 58 | D59: PROCESS AUTOMATION S.A.C. | E59: Perú | H59: ExpoMina 2026 | I59: Prospecto | J59: Alta | K59: Mapear oferta: evaluar integración o competencia | L59: ExpoMina 2026. Sin contacto publicado. | M59: Partner tecnológico / competidor | N59: A-090 | O59: 1 | P59: www.pasac.pe | S59: No
A60: 59 | D60: ROBOTIA SPA | E60: Chile | H60: ExpoMina 2026 | I60: Prospecto | J60: Alta | K60: Mapear oferta: evaluar integración o competencia | L60: ExpoMina 2026. Sin contacto publicado. | M60: Partner tecnológico / competidor | N60: A-337 | O60: 1 | P60: www.robotia.cl | S60: No
A61: 60 | D61: RTS AUTOMATION S.A.C. | E61: Perú | H61: ExpoMina 2026 | I61: Prospecto | J61: Alta | K61: Mapear oferta: evaluar integración o competencia | L61: ExpoMina 2026. Sin contacto publicado. | M61: Partner tecnológico / competidor | N61: B-177 | O61: 1 | P61: rts-auto.com | S61: No
A62: 61 | D62: TE.SA.M. PERÚ S.A. | E62: Perú | F62: acliente@tesam.com | H62: ExpoMina 2026 | I62: Prospecto | J62: Alta | K62: Mapear oferta: evaluar integración o competencia | L62: ExpoMina 2026. También en CRM Directorio SSO 2026 (ID 178). | M62: Partner tecnológico / competidor | N62: E-278A | O62: 1 | P62: www.tesam.com | Q62: 7054100 / 981230093 | R62: Av. Circunvalación del Club Golf Los Incas 134 Torre 1 of. 302B Santiago de Surco - Lima | S62: Sí
A63: 62 | D63: TRANSWORLD POWER AND TELECOM S.A.C.- TRANSWORLD POWER AND TELECOM S.A.C. | E63: Perú | H63: ExpoMina 2026 | I63: Prospecto | J63: Alta | K63: Mapear oferta: evaluar integración o competencia | L63: ExpoMina 2026. Sin contacto publicado. | M63: Partner tecnológico / competidor | N63: B-110 | O63: 1 | P63: transworld.pe | S63: No
A64: 63 | B64: Jhon Santillán | D64: VISION ONE INTERNATIONAL S.R.L. | E64: Perú | F64: ventas@visionone.pe | H64: ExpoMina 2026 | I64: Prospecto | J64: Alta | K64: Mapear oferta: evaluar integración o competencia | L64: ExpoMina 2026. También en CRM Directorio SSO 2026 (ID 273). | M64: Partner tecnológico / competidor | N64: B-221 | O64: 1 | P64: www.visionone.pe | Q64: (01) 7509910 / (+51) 954305931 / (+51) 991266014 | R64: Cl. Monte Grande 188 - Santiago de Surco - Lima | S64: Sí
A65: 64 | D65: WISETRACK PERÚ SAC | E65: Perú | F65: info.peru@wisetrackcorp.com | H65: ExpoMina 2026 | I65: Prospecto | J65: Alta | K65: Mapear oferta: evaluar integración o competencia | L65: ExpoMina 2026. También en CRM Directorio SSO 2026 (ID 183). | M65: Partner tecnológico / competidor | N65: A-003 | O65: 1 | P65: https://wisetrackcorp.com/ | Q65: (01) 6282611 | R65: Cl. El Boulevard 180 Of. 603 Urb. Hogares de Monterrico Chico Santiago de Surco - Lima | S65: Sí
A66: 65 | D66: ZOLUXIONES IT SERVICES S.A.C. | E66: Perú | H66: ExpoMina 2026 | I66: Prospecto | J66: Alta | K66: Mapear oferta: evaluar integración o competencia | L66: ExpoMina 2026. Sin contacto publicado. | M66: Partner tecnológico / competidor | N66: A-060 | O66: 1 | P66: zoxrobotics.com | S66: No
A67: 66 | D67: GEOINGENIEROS CONSULTORES S.A.C. | E67: Perú | H67: ExpoMina 2026 | I67: Prospecto | J67: Alta | K67: Explorar alianza comercial / reventa a sus clientes | L67: ExpoMina 2026. Varios stands (mayor inversión). Sin contacto publicado. | M67: Canal / aliado – consultoría SST | N67: A-028, A-373 | O67: 2 | P67: www.geoingenieros.com.pe | S67: No
A68: 67 | D68: LOGISTICA ASESORES CONSULTORES S.A.C. | E68: Perú | H68: ExpoMina 2026 | I68: Prospecto | J68: Alta | K68: Explorar alianza comercial / reventa a sus clientes | L68: ExpoMina 2026. Varios stands (mayor inversión). Sin contacto publicado. | M68: Canal / aliado – consultoría SST | N68: B-035, B-036 | O68: 2 | P68: https://lacsac.pe/ | S68: No
A69: 68 | D69: CASTEM (CAPACITACION Y SERVICIO TECNICO MINERO) E.I.R.L. | E69: Perú | H69: ExpoMina 2026 | I69: Prospecto | J69: Alta | K69: Explorar alianza comercial / reventa a sus clientes | L69: ExpoMina 2026. Sin contacto publicado. | M69: Canal / aliado – consultoría SST | N69: B-061A | O69: 1 | P69: https://castem.com.pe/ | S69: No
A70: 69 | D70: CENTRO TECNOLOGICO MINERO | E70: Perú | F70: informes@cetemin.edu.pe | H70: ExpoMina 2026 | I70: Prospecto | J70: Alta | K70: Explorar alianza comercial / reventa a sus clientes | L70: ExpoMina 2026. También en CRM Directorio SSO 2026 (ID 192). | M70: Canal / aliado – consultoría SST | N70: A-363 | O70: 1 | P70: https://www.cetemin.edu.pe/ | Q70: 7026055 | R70: Cl. Camino Real s/n km 29 Carretera Central, Lt.E4 Sección San José Chosica - Lima | S70: Sí
A71: 70 | D71: ENGINEERING SERVICES & CONSULTING S.A.C. | E71: Perú | H71: ExpoMina 2026 | I71: Prospecto | J71: Alta | K71: Explorar alianza comercial / reventa a sus clientes | L71: ExpoMina 2026. Sin contacto publicado. | M71: Canal / aliado – consultoría SST | N71: A-025 | O71: 1 | P71: https://sincro.pe/ | S71: No
A72: 71 | D72: FAROS ASESORES LIMITADA | E72: Chile | H72: ExpoMina 2026 | I72: Prospecto | J72: Alta | K72: Explorar alianza comercial / reventa a sus clientes | L72: ExpoMina 2026. Sin contacto publicado. | M72: Canal / aliado – consultoría SST | N72: B-272F | O72: 1 | P72: https://faros.cl/ | S72: No
A73: 72 | D73: GRUPO ALFA CONSULTORES S.A.C | E73: Perú | H73: ExpoMina 2026 | I73: Prospecto | J73: Alta | K73: Explorar alianza comercial / reventa a sus clientes | L73: ExpoMina 2026. Sin contacto publicado. | M73: Canal / aliado – consultoría SST | N73: E-367 | O73: 1 | P73: https://grupo-alfa.pe/ | S73: No
A74: 73 | D74: IDOM CONSULTING, ENGINEERING, ARCHITECTURE, S.A. | E74: Perú (por validar) | H74: ExpoMina 2026 | I74: Prospecto | J74: Alta | K74: Explorar alianza comercial / reventa a sus clientes | L74: ExpoMina 2026. País inferido; validar. Sin contacto publicado. | M74: Canal / aliado – consultoría SST | N74: A-258 | O74: 1 | P74: https://www.idom.com/ | S74: No
A75: 74 | D75: INERCO CONSULTORIA PERÚ S.A.C. | E75: Perú | F75: infoperu@inerco.com | H75: ExpoMina 2026 | I75: Prospecto | J75: Alta | K75: Explorar alianza comercial / reventa a sus clientes | L75: ExpoMina 2026. También en CRM Directorio SSO 2026 (ID 220). | M75: Canal / aliado – consultoría SST | N75: A-045 | O75: 1 | P75: https://peru.inerco.com | Q75: 4801354 | R75: Cl. Las Orquídeas 585 Piso 13 San Isidro - Lima | S75: Sí
A76: 75 | D76: INSTITUTO DE INGENIEROS DE MINAS DEL PERU | E76: Perú | H76: ExpoMina 2026 | I76: Prospecto | J76: Alta | K76: Explorar alianza comercial / reventa a sus clientes | L76: ExpoMina 2026. Sin contacto publicado. | M76: Canal / aliado – consultoría SST | N76: A-293 | O76: 1 | P76: https://iimp.org.pe/ | S76: No
A77: 76 | D77: MEGA SOLUCIONES S.A.C. | E77: Perú | F77: ventas@megasolucionessac.com | H77: ExpoMina 2026 | I77: Prospecto | J77: Alta | K77: Explorar alianza comercial / reventa a sus clientes | L77: ExpoMina 2026. También en CRM Directorio SSO 2026 (ID 235). | M77: Canal / aliado – consultoría SST | N77: A-037 | O77: 1 | P77: www.megasolucionessac.com | Q77: 7199174 / 941467946 | R77: Cl. 6 Mz.I Lt.9B Urb. Las Praderas Lurín - Lima | S77: Sí
A78: 77 | D78: MV TELEMEDICINA Y CONSULTORIA MEDICA E.I.R.L. | E78: Perú | H78: ExpoMina 2026 | I78: Prospecto | J78: Alta | K78: Explorar alianza comercial / reventa a sus clientes | L78: ExpoMina 2026. Sin contacto publicado. | M78: Canal / aliado – consultoría SST | N78: B-280 | O78: 1 | P78: www.medvidasalud.com | S78: No
A79: 78 | D79: TAYM INVERSIONES & ASESORIA INTEGRAL S.A.C. | E79: Perú | H79: ExpoMina 2026 | I79: Prospecto | J79: Alta | K79: Explorar alianza comercial / reventa a sus clientes | L79: ExpoMina 2026. Sin contacto publicado. | M79: Canal / aliado – consultoría SST | N79: E-384 | O79: 1 | P79: https://www.mercadolibre.com.pe/tienda/milwaukee | S79: No
A80: 79 | D80: UNIVERSIDAD CONTINENTAL S.A.C. | E80: Perú | H80: ExpoMina 2026 | I80: Prospecto | J80: Alta | K80: Explorar alianza comercial / reventa a sus clientes | L80: ExpoMina 2026. Sin contacto publicado. | M80: Canal / aliado – consultoría SST | N80: A-165 | O80: 1 | P80: https://posgrado.ucontinental.edu.pe/ | S80: No
A81: 80 | D81: UNIVERSIDAD NACIONAL DE INGENIERIA UNI | E81: Perú | H81: ExpoMina 2026 | I81: Prospecto | J81: Alta | K81: Explorar alianza comercial / reventa a sus clientes | L81: ExpoMina 2026. Sin contacto publicado. | M81: Canal / aliado – consultoría SST | N81: E-348E | O81: 1 | P81: https://hub.uni.edu.pe/ | S81: No
A82: 81 | B82: Armando Amaro | C82: Jefe de Ventas | D82: ANDES SEGURIDAD S.A.C. | E82: Perú | F82: ventas@andesseguridad.com | H82: ExpoMina 2026 | I82: Prospecto | J82: Alta | K82: Evaluar como canal de distribución hacia minería/industria | L82: ExpoMina 2026. Varios stands (mayor inversión). También en CRM Directorio SSO 2026 (ID 275). | M82: Canal / distribuidor EPP | N82: A-030, A-031, A-177, A-177A | O82: 4 | P82: www.andes-safety.com | Q82: (01) 7152525 / (+51) 987581941 / (+51) 948501615 / (+054) 283327 / (+51) 947254611 | R82: Cl. Dean Saavedra 170 Urb. Maranga, San Miguel - Lima | Arequipa: Mz.B Lt.12 Urb. Puerta Verde, José Luis Bustamante y Rivero | S82: Sí
A83: 82 | B83: Alan Núñez | C83: Gerente comercial | D83: SEGURINDUSTRIA SA | E83: Perú | F83: contacto@segusa.com.pe | H83: ExpoMina 2026 | I83: Prospecto | J83: Alta | K83: Evaluar como canal de distribución hacia minería/industria | L83: ExpoMina 2026. También en CRM Directorio SSO 2026 (ID 272). | M83: Canal / distribuidor EPP | N83: A-179A | O83: 1 | P83: https://segurindustria.pe/ | Q83: 4500778 / 958690332 / (+51) 995668230 / (+044) 230362 / (+044) 207500 / (+51) 973848449 | R83: Jr. Paita 191 Urb. Parque Industrial - San Juan de Miraflores - Lima | Trujillo: Av. Nicolás de Piérola 980 Urb. Primavera | S83: Sí
A84: 83 | B84: Rocío Paredes Guillén | D84: CENERIS E.I.R.L. | E84: Perú | F84: info@ceneris.com | H84: ExpoMina 2026 | I84: Prospecto | J84: Alta | K84: Evaluar co-venta o integración de soluciones | L84: ExpoMina 2026. También en CRM Directorio SSO 2026 (ID 268). | M84: Aliado complementario – seguridad | N84: A-382 | O84: 1 | P84: https://ceneris.com/ | Q84: (01) 4800065 / (+51) 995716810 / (+51) 992098057 | R84: Lima: Av. Tomás Marsano 1368 Urb. La Aurora, Miraflores | Arequipa: Av. Lima 147 Urb. Vallecito - Cercado | S84: Sí
A85: 84 | D85: FERREYROS SOCIEDAD ANÓNIMA | E85: Perú | H85: ExpoMina 2026 | I85: Prospecto | J85: Media | K85: Explorar integración con flota/equipos (visión + telemetría) | L85: ExpoMina 2026. Varios stands (mayor inversión). Sin contacto publicado. | M85: Partner OEM – equipos mineros | N85: E-348G, E-348H, B-243 | O85: 3 | P85: www.ferreyros.com.pe | S85: No
A86: 85 | D86: VOLVO PERÚ S A | E86: Perú | F86: alovolvo@volvo.com | H86: ExpoMina 2026 | I86: Prospecto | J86: Media | K86: Explorar integración con flota/equipos (visión + telemetría) | L86: ExpoMina 2026. Varios stands (mayor inversión). También en CRM Directorio SSO 2026 (ID 674). | M86: Partner OEM – equipos mineros | N86: PASADIZO, C-016, C-017 | O86: 3 | P86: volvogroupperu.pe | Q86: 3171100 / 918911611 | R86: Carretera Panamericana Sur km 23.88 Lurín - Lima | S86: Sí
A87: 86 | D87: BOART LONGYEAR SAC | E87: Perú | F87: info@boartlongyear.com | H87: ExpoMina 2026 | I87: Prospecto | J87: Media | K87: Explorar integración con flota/equipos (visión + telemetría) | L87: ExpoMina 2026. Varios stands (mayor inversión). También en CRM Directorio SSO 2026 (ID 16). | M87: Partner OEM – equipos mineros | N87: A-022, A-024 | O87: 2 | P87: www.boartlongyear.com | Q87: 2034200 | R87: Av. El Derby 055 Torre 1 Of. 601 Centro de Negocios Cronos - Santiago de Surco Lima | S87: Sí
A88: 87 | D88: BRIDGESTONE MINING SOLUTIONS PERÚ S.A.C. | E88: Perú | H88: ExpoMina 2026 | I88: Prospecto | J88: Media | K88: Explorar integración con flota/equipos (visión + telemetría) | L88: ExpoMina 2026. Varios stands (mayor inversión). Sin contacto publicado. | M88: Partner OEM – equipos mineros | N88: E-306, E-307 | O88: 2 | P88: https://www.otr.bridgestone.com.pe/ | S88: No
A89: 88 | D89: DSI UNDERGROUND PERÚ S.A.C | E89: Perú | H89: ExpoMina 2026 | I89: Prospecto | J89: Media | K89: Explorar integración con flota/equipos (visión + telemetría) | L89: ExpoMina 2026. Varios stands (mayor inversión). Sin contacto publicado. | M89: Partner OEM – equipos mineros | N89: E-110, E-115 | O89: 2 | P89: rocktechnology.sandvik/groundsupport | S89: No
A90: 89 | D90: XCMG PERÚ S.A.C. | E90: Perú | H90: ExpoMina 2026 | I90: Prospecto | J90: Media | K90: Explorar integración con flota/equipos (visión + telemetría) | L90: ExpoMina 2026. Varios stands (mayor inversión). Sin contacto publicado. | M90: Partner OEM – equipos mineros | N90: A-408, A-409 | O90: 2 | P90: www.xcmg.pe | S90: No
A91: 90 | D91: ZOOMLION HEAVY INDUSTRY PERÚ S.A.C. | E91: Perú | H91: ExpoMina 2026 | I91: Prospecto | J91: Media | K91: Explorar integración con flota/equipos (visión + telemetría) | L91: ExpoMina 2026. Varios stands (mayor inversión). Sin contacto publicado. | M91: Partner OEM – equipos mineros | N91: D-001, D-002 | O91: 2 | S91: No
A92: 91 | D92: KOMATSU-MITSUI MAQUINARIAS PERÚ S.A. | E92: Perú | F92: contacto.komatsu@kmmp.com.pe | H92: ExpoMina 2026 | I92: Prospecto | J92: Media | K92: Explorar integración con flota/equipos (visión + telemetría) | L92: ExpoMina 2026. También en CRM Directorio SSO 2026 (ID 612). | M92: Partner OEM – equipos mineros | N92: D-003 | O92: 1 | P92: https://kmmp.com.pe/ | Q92: 6158400 / 982504661 | R92: Av. Argentina 4453 - Callao | S92: Sí
A93: 92 | D93: MARCO PERUANA S A | E93: Perú | H93: ExpoMina 2026 | I93: Prospecto | J93: Media | K93: Explorar integración con flota/equipos (visión + telemetría) | L93: ExpoMina 2026. Sin contacto publicado. | M93: Partner OEM – equipos mineros | N93: C-004 | O93: 1 | S93: No
A94: 93 | D94: METSO PERÚ S.A. | E94: Perú | H94: ExpoMina 2026 | I94: Prospecto | J94: Media | K94: Explorar integración con flota/equipos (visión + telemetría) | L94: ExpoMina 2026. Sin contacto publicado. | M94: Partner OEM – equipos mineros | N94: A-124 | O94: 1 | P94: https://www.metso.com/pe/ | S94: No
A95: 94 | D95: NORMET PERÚ S.R.L. | E95: Perú | H95: ExpoMina 2026 | I95: Prospecto | J95: Media | K95: Explorar integración con flota/equipos (visión + telemetría) | L95: ExpoMina 2026. Sin contacto publicado. | M95: Partner OEM – equipos mineros | N95: B-054 | O95: 1 | P95: www.normet.com | S95: No
A96: 95 | D96: SIEMAG TECBERG GMBH | E96: Alemania | H96: ExpoMina 2026 | I96: Prospecto | J96: Media | K96: Explorar integración con flota/equipos (visión + telemetría) | L96: ExpoMina 2026. Sin contacto publicado. | M96: Partner OEM – equipos mineros | N96: E-110A | O96: 1 | P96: www.siemag-tecberg.com | S96: No
A97: 96 | D97: TRECK SEGURIDAD INDUSTRIAL S.A.C. | E97: Perú | F97: ventas@treck.pe | H97: ExpoMina 2026 | I97: Prospecto | J97: Media | K97: Evaluar como canal de distribución hacia minería/industria | L97: ExpoMina 2026. Varios stands (mayor inversión). También en CRM Directorio SSO 2026 (ID 670). | M97: Canal / distribuidor EPP | N97: E-268B, E-268C, E-268D, E-268G, E-268H, E-268I | O97: 6 | P97: https://trecksafety.com/ | Q97: 980920323 | R97: Av. Manuel Olguín 211 Int. 903 Santiago de Surco - Lima | S97: Sí
A98: 97 | D98: EMPRESA METAL MECANICA S A EMEMSA | E98: Perú (por validar) | H98: ExpoMina 2026 | I98: Prospecto | J98: Media | K98: Evaluar como canal de distribución hacia minería/industria | L98: ExpoMina 2026. Varios stands (mayor inversión). País inferido; validar. Sin contacto publicado. | M98: Canal / distribuidor EPP | N98: A-144, A-145 | O98: 2 | P98: https://ememsa.com/ | S98: No
A99: 98 | D99: EXIGE INDUSTRIAL S.A.C. | E99: Perú | F99: ventas@exigeindustrial.com | H99: ExpoMina 2026 | I99: Prospecto | J99: Media | K99: Evaluar como canal de distribución hacia minería/industria | L99: ExpoMina 2026. Varios stands (mayor inversión). También en CRM Directorio SSO 2026 (ID 410). | M99: Canal / distribuidor EPP | N99: A-126, A-127 | O99: 2 | P99: https://exigeindustrial.com/ | Q99: 993766468 | R99: Cl. Los Talladores 275 Urb. Los Artesanos Ate - Lima | S99: Sí
A100: 99 | D100: INDUSTRIAS MANRIQUE S.A.C. | E100: Perú | F100: ventas@grupomanrique.com | H100: ExpoMina 2026 | I100: Prospecto | J100: Media | K100: Evaluar como canal de distribución hacia minería/industria | L100: ExpoMina 2026. Varios stands (mayor inversión). También en CRM Directorio SSO 2026 (ID 421). | M100: Canal / distribuidor EPP | N100: B-244, B-245 | O100: 2 | P100: im.com.pe | Q100: 6344747 / 982052829 | R100: Cl. Los Tornos 259 Urb. El Naranjal San Martín de Porres - Lima | S100: Sí
...

Sheet Oportunidades
A1: ID oportunidad | B1: ID contacto | C1: Empresa | D1: Necesidad | E1: Solución propuesta | F1: Etapa | G1: Valor estimado | H1: Probabilidad | I1: Próxima acción | J1: Fecha

Sheet Resumen
A1: Evento/Fuente | B1: País | C1: Cantidad
A2: ExpoMina 2026 | B2: Perú | C2: =COUNTIFS(Contactos!$H:$H,$A2,Contactos!$E:$E,$B2) -> 593
A3: ExpoMina 2026 | B3: China | C3: =COUNTIFS(Contactos!$H:$H,$A3,Contactos!$E:$E,$B3) -> 258
A4: ExpoMina 2026 | B4: Por validar | C4: =COUNTIFS(Contactos!$H:$H,$A4,Contactos!$E:$E,$B4) -> 55
A5: ExpoMina 2026 | B5: Perú (por validar) | C5: =COUNTIFS(Contactos!$H:$H,$A5,Contactos!$E:$E,$B5) -> 33
A6: ExpoMina 2026 | B6: Estados Unidos (por validar) | C6: =COUNTIFS(Contactos!$H:$H,$A6,Contactos!$E:$E,$B6) -> 11
A7: ExpoMina 2026 | B7: Chile | C7: =COUNTIFS(Contactos!$H:$H,$A7,Contactos!$E:$E,$B7) -> 8
A8: ExpoMina 2026 | B8: Chile (por validar) | C8: =COUNTIFS(Contactos!$H:$H,$A8,Contactos!$E:$E,$B8) -> 5
A9: ExpoMina 2026 | B9: México | C9: =COUNTIFS(Contactos!$H:$H,$A9,Contactos!$E:$E,$B9) -> 3
A10: ExpoMina 2026 | B10: Alemania | C10: =COUNTIFS(Contactos!$H:$H,$A10,Contactos!$E:$E,$B10) -> 2
A11: ExpoMina 2026 | B11: Argentina | C11: =COUNTIFS(Contactos!$H:$H,$A11,Contactos!$E:$E,$B11) -> 2
A12: ExpoMina 2026 | B12: India | C12: =COUNTIFS(Contactos!$H:$H,$A12,Contactos!$E:$E,$B12) -> 2
A13: ExpoMina 2026 | B13: Colombia | C13: =COUNTIFS(Contactos!$H:$H,$A13,Contactos!$E:$E,$B13) -> 2
... A17: ExpoMina 2026 | B17: Sudáfrica | C17: =COUNTIFS(Contactos!$H:$H,$A17,Contactos!$E:$E,$B17) -> 1
A18: Total | C18: =SUM(C2:C17) -> 979
A20: Segmento SafetyMind | B20: Alta | C20: Media | D20: Baja | E20: Total
A21: Minera (cliente final) | B21: =COUNTIFS(Contactos!$M:$M,$A21,Contactos!$J:$J,B$20) -> 3 | C21: =COUNTIFS(Contactos!$M:$M,$A21,Contactos!$J:$J,C$20) -> 0 | D21: =COUNTIFS(Contactos!$M:$M,$A21,Contactos!$J:$J,D$20) -> 0 | E21: =SUM(B21:D21) -> 3
A22: Cliente potencial – contratista / operación de alto riesgo | B22: =COUNTIFS(Contactos!$M:$M,$A22,Contactos!$J:$J,B$20) -> 37 | C22: =COUNTIFS(Contactos!$M:$M,$A22,Contactos!$J:$J,C$20) -> 0 | D22: =COUNTIFS(Contactos!$M:$M,$A22,Contactos!$J:$J,D$20) -> 0 | E22: =SUM(B22:D22) -> 37
A23: Partner tecnológico / competidor | B23: =COUNTIFS(Contactos!$M:$M,$A23,Contactos!$J:$J,B$20) -> 25 | C23: =COUNTIFS(Contactos!$M:$M,$A23,Contactos!$J:$J,C$20) -> 0 | D23: =COUNTIFS(Contactos!$M:$M,$A23,Contactos!$J:$J,D$20) -> 0 | E23: =SUM(B23:D23) -> 25
A24: Canal / aliado – consultoría SST | B24: =COUNTIFS(Contactos!$M:$M,$A24,Contactos!$J:$J,B$20) -> 15 | C24: =COUNTIFS(Contactos!$M:$M,$A24,Contactos!$J:$J,C$20) -> 0 | D24: =COUNTIFS(Contactos!$M:$M,$A24,Contactos!$J:$J,D$20) -> 0 | E24: =SUM(B24:D24) -> 15
A25: Partner OEM – equipos mineros | B25: =COUNTIFS(Contactos!$M:$M,$A25,Contactos!$J:$J,B$20) -> 0 | C25: =COUNTIFS(Contactos!$M:$M,$A25,Contactos!$J:$J,C$20) -> 12 | D25: =COUNTIFS(Contactos!$M:$M,$A25,Contactos!$J:$J,D$20) -> 0 | E25: =SUM(B25:D25) -> 12
A26: Canal / distribuidor EPP | B26: =COUNTIFS(Contactos!$M:$M,$A26,Contactos!$J:$J,B$20) -> 2 | C26: =COUNTIFS(Contactos!$M:$M,$A26,Contactos!$J:$J,C$20) -> 20 | D26: =COUNTIFS(Contactos!$M:$M,$A26,Contactos!$J:$J,D$20) -> 0 | E26: =SUM(B26:D26) -> 22
A27: Aliado complementario – seguridad | B27: =COUNTIFS(Contactos!$M:$M,$A27,Contactos!$J:$J,B$20) -> 1 | C27: =COUNTIFS(Contactos!$M:$M,$A27,Contactos!$J:$J,C$20) -> 11 | D27: =COUNTIFS(Contactos!$M:$M,$A27,Contactos!$J:$J,D$20) -> 0 | E27: =SUM(B27:D27) -> 12
A28: Aliado complementario – salud | B28: =COUNTIFS(Contactos!$M:$M,$A28,Contactos!$J:$J,B$20) -> 0 | C28: =COUNTIFS(Contactos!$M:$M,$A28,Contactos!$J:$J,C$20) -> 1 | D28: =COUNTIFS(Contactos!$M:$M,$A28,Contactos!$J:$J,D$20) -> 0 | E28: =SUM(B28:D28) -> 1
A29: Institución / gremio / pabellón país | B29: =COUNTIFS(Contactos!$M:$M,$A29,Contactos!$J:$J,B$20) -> 0 | C29: =COUNTIFS(Contactos!$M:$M,$A29,Contactos!$J:$J,C$20) -> 7 | D29: =COUNTIFS(Contactos!$M:$M,$A29,Contactos!$J:$J,D$20) -> 0 | E29: =SUM(B29:D29) -> 7
A30: Proveedor industrial (equipos/insumos) | B30: =COUNTIFS(Contactos!$M:$M,$A30,Contactos!$J:$J,B$20) -> 0 | C30: =COUNTIFS(Contactos!$M:$M,$A30,Contactos!$J:$J,C$20) -> 0 | D30: =COUNTIFS(Contactos!$M:$M,$A30,Contactos!$J:$J,D$20) -> 845 | E30: =SUM(B30:D30) -> 845
A31: Total | B31: =SUM(B21:B30) -> 83 | C31: =SUM(C21:C30) -> 51 | D31: =SUM(D21:D30) -> 845 | E31: =SUM(E21:E30) -> 979
A33: Estado (pipeline) | B33: Cantidad
A34: Prospecto | B34: =COUNTIF(Contactos!$I:$I,A34) -> 979
A35: Contactado | B35: =COUNTIF(Contactos!$I:$I,A35) -> 0
A36: Reunión | B36: =COUNTIF(Contactos!$I:$I,A36) -> 0
A37: Propuesta | B37: =COUNTIF(Contactos!$I:$I,A37) -> 0
A38: Cliente | B38: =COUNTIF(Contactos!$I:$I,A38) -> 0
A39: No interesado | B39: =COUNTIF(Contactos!$I:$I,A39) -> 0
A41: Indicadores | B41: Cantidad
A42: Registros originales (stands) | B42: 1209
A43: Empresas únicas | B43: =COUNTA(Contactos!$D$2:$D$3000) -> 979
A44: Con web | B44: =COUNTIF(Contactos!$P$2:$P$3000,"?*") -> 952
A45: También en Directorio SSO | B45: =COUNTIF(Contactos!$S:$S,"Sí") -> 74
A46: Con email (vía Directorio) | B46: =COUNTIF(Contactos!$F$2:$F$3000,"?*") -> 69
A47: Con 2+ stands | B47: =COUNTIF(Contactos!$O$2:$O$3000,">1") -> 176

Sheet Eventos
A1: Evento | B1: País | C1: Valor para SafetyMind
A2: Directorio SSO 2026 – Cero Accidentes (22.ª ed.) | B2: Perú | C2: Mapa de ~670 proveedores SST en Perú (ver CRM_Directorio_SSO_2026).
A3: ExpoMina Perú 2026 | B3: Perú | C3: Feria minera: mineras, contratistas, OEM de equipos, tecnología y proveedores; base para agendar reuniones en stand y prospección post-evento.
