Workbook

Sheet Contactos
A1: ID | B1: Nombre | C1: Cargo | D1: Empresa | E1: País | F1: Email | G1: LinkedIn | H1: Origen | I1: Estado | J1: Prioridad | K1: Próxima acción | L1: Notas | M1: Segmento SafetyMind | N1: Stand(s) | O1: Ubicación | P1: Agrupación | Q1: Razón social | R1: Descripción | S1: Web | T1: Cruce otros CRM
A2: 1 | D2: ALDEBARAN RESOURCES INC. | E2: Argentina | F2: fatima.olavarria@aldebaranresources.com | H2: Expo San Juan Minera 2026 | I2: Prospecto | J2: Alta | K2: Identificar Gerente de Seguridad/SSO de la operación o proyecto; proponer piloto (rajo, planta, flota) | L2: Expo San Juan Minera 2026. | M2: Cliente final – minera / energía (operación o proyecto) | N2: B204 | O2: Pabellón 1 | Q2: MINERA PEREGRINE ARGENTINA S.A.U. | R2: Proyecto de cobre en etapa de exploración avanzada, ubicado en Calingasta, San Juan, Argentina. Se trata de uno de los depósitos de cobre más grandes a nivel mundial. Actualmente, el proyecto avanza hacia la etapa de prefactibilidad, consolidando información clave para su desarrollo futuro. | T2: No
A3: 2 | D3: CALERAS SAN JUAN | E3: Argentina | H3: Expo San Juan Minera 2026 | I3: Prospecto | J3: Alta | K3: Identificar Gerente de Seguridad/SSO de la operación o proyecto; proponer piloto (rajo, planta, flota) | L3: Expo San Juan Minera 2026. Sin email publicado. | M3: Cliente final – minera / energía (operación o proyecto) | N3: E529 | E550 | E551 | O3: Pabellón 2 | Q3: CALERAS SAN JUAN SA | R3: Caleras San Juan S.A. es una empresa minera fundada en el año 1952. Con más de 70 años de experiencia en la fabricación de cales y productos derivados, somos la primer empresa calera de capitales 100% argentinos en obtener la certificación trinorma. | T3: No
A4: 3 | D4: CALIDRA | E4: Argentina | F4: info@calidra.com.ar | H4: Expo San Juan Minera 2026 | I4: Prospecto | J4: Alta | K4: Identificar Gerente de Seguridad/SSO de la operación o proyecto; proponer piloto (rajo, planta, flota) | L4: Expo San Juan Minera 2026. | M4: Cliente final – minera / energía (operación o proyecto) | N4: E547 | E548 | E549 | O4: Pabellón 2 | Q4: CEFAS S.A | R4: Calidra cuenta con más de 115 años de historia y experiencia en la industria de la cal, acompañando el desarrollo productivo de la región y siendo parte activa de las cadenas de valor de múltiples industrias. A lo largo de su trayectoria, ha consolidado un profundo conocimiento técnico, una cultura de trabajo sólida y un compromiso permanente con la calidad, la seguridad y la mejora continua. En este contexto, Calidra Cono Sur reúne las operaciones de Calidra en Argentina y Chile, integrando equipos, capacidades productivas y logísticas para brindar soluciones industriales de alto valor agregado a sectores estratégicos como minería, construcción, siderurgia, estabilización de suelos, agricultura, química, pinturas y recubrimientos. La compañía opera con yacimientos de alta pureza, reservas de largo plazo y tecnología de clase mundial, incluyendo hornos Maerz de alta eficiencia. La propuesta de valor de Calidra Cono Sur se basa en la seguridad de suministro, la pureza desde el origen, una alta capacidad productiva y logística, y un fuerte enfoque en la asistencia técnica, la capacitación y el trabajo conjunto con sus clientes. Sus procesos están certificados bajo normas ISO 9001, ISO 14001 e ISO 45001, garantizando estándares internacionales de calidad, ambiente y seguridad. Con una visión de desarrollo sostenible, Calidra asume el compromiso de reducir a cero las emisiones del grupo hacia 2050, impulsando iniciativas ambientales, sociales y de seguridad que generan un impacto positivo y duradero en las comunidades donde está presente. Porque en Calidra, la cal está siempre ahí. | S4: https://www.calidra.com.ar/ | T4: No
A5: 4 | D5: CASPOSO ARGENTINA LTD. - SUCURSAL ARGENTINA | E5: Argentina | F5: info@australgold.com | H5: Expo San Juan Minera 2026 | I5: Prospecto | J5: Alta | K5: Identificar Gerente de Seguridad/SSO de la operación o proyecto; proponer piloto (rajo, planta, flota) | L5: Expo San Juan Minera 2026. | M5: Cliente final – minera / energía (operación o proyecto) | N5: D443 | O5: Pabellón 2 | R5: Mina Casposo producción de oro y plata | S5: https://australgold.com/ | T5: No
A6: 5 | D6: ECO MINERA | E6: Argentina | H6: Expo San Juan Minera 2026 | I6: Prospecto | J6: Alta | K6: Identificar Gerente de Seguridad/SSO de la operación o proyecto; proponer piloto (rajo, planta, flota) | L6: Expo San Juan Minera 2026. Sin email publicado. | M6: Cliente final – minera / energía (operación o proyecto) | N6: A166 | A167 | O6: Pabellón 1 | Q6: ECO MINERA S.A | T6: No
A7: 6 | D7: EPSE | E7: Argentina | F7: info@epse.com.ar | H7: Expo San Juan Minera 2026 | I7: Prospecto | J7: Alta | K7: Identificar Gerente de Seguridad/SSO de la operación o proyecto; proponer piloto (rajo, planta, flota) | L7: Expo San Juan Minera 2026. | M7: Cliente final – minera / energía (operación o proyecto) | N7: Isla: 2E | O7: Exterior | Q7: ENERGIA PROVINCIAL SOCIEDAD DEL ESTADO | R7: EPSE no es solamente un generador, sino el brazo ejecutor del Gobierno de San Juan en materia energética. • EPSE cuenta con amplia experiencia en el rubro de parques solares fotovoltaicos conectados a la red, habiendo licitado, construido e inspeccionado distintas obras en el marco de las energía renovables, específicamente solares, en la provincia de San Juan y también fuera de ella. • Es de destacar también que EPSE opera y mantiene las distintas centrales hidroeléctricas, estaciones transformadoras de alta/media tensión y de parques de generación fotovoltaicas que son de su propiedad. • En términos de MDL, EPSE logró certificar la primera central hidroeléctrica de Sudamérica (Los Caracoles) en el año 2010, y vendió los bonos generados en el mercado obligatorio, además de participar en otros proyectos de descarbonización. MISION : • Gestionar, de forma eficaz y eficiente, los recursos energéticos de nuestra región, logrando la satisfacción de nuestros clientes, accionistas, socios y personal, generando valores económicos, sociales y ambientales mediante la integración público privada para la generación de energía, montaje de plantas y provisión de servicios al sector energético. • Desarrollar de forma continua todo nuestro personal • Innovar tecnológicamente • Identificar a largo plazo tanto las necesidades energéticas de la región como así también las oportunidades tecnológicas de generación, planificando el desarrollo y evolución de las fuentes energéticas para cubrir en tiempo y forma las necesidades. • Trabajar de manera segura y ambientalmente sostenible. VISION Ser reconocidos como la empresa referente, a nivel nacional, en generación eléctrica y desarrollo de proyectos pioneros e innovadores, sustentado en la eficiencia de sus acciones y en el profesionalismo de su personal en favor de sus clientes, la comunidad y el ambiente. | S7: https://www.epse.com.ar/ | T7: No
A8: 7 | D8: GLENCORE EL PACHÓN | E8: Argentina | F8: comunicaciones.elpachon@glencore.com.ar | H8: Expo San Juan Minera 2026 | I8: Prospecto | J8: Alta | K8: Identificar Gerente de Seguridad/SSO de la operación o proyecto; proponer piloto (rajo, planta, flota) | L8: Expo San Juan Minera 2026. | M8: Cliente final – minera / energía (operación o proyecto) | N8: B205 | B206 | B215 | O8: Pabellón 1 | Q8: GLENCORE PACHON S.A. | R8: Proyecto El Pachón El Pachón es un yacimiento de cobre y molibdeno emplazado en el departamento Calingasta, provincia de San Juan, Argentina. Se encuentra situado a 3.600 metros sobre el nivel del mar, a 5 kilómetros del límite internacional con Chile. 100% del yacimiento pertenece a la compañía Glencore. Actualmente se encuentra en etapa de exploración avanzada. La producción media prevista sería aproximadamente 360.000t anuales de cobre en concentrado para los 10 primeros años. Acerca de Glencore Glencore es una de las mayores empresas de recursos naturales diversificados del mundo y uno de los principales productores y comercializadores de más de 60 materias primas. A través de una red de activos, clientes y proveedores que se extiende por todo el mundo, producimos, procesamos, reciclamos, obtenemos, comercializamos y distribuimos los productos que hacen posible la vida cotidiana. Con más de 140.000 empleados y contratistas, y una sólida presencia en más de 30 países, incluidas regiones consolidadas y emergentes en materia de recursos naturales, nuestras actividades industriales y de comercialización cuentan con el respaldo de una red global de oficinas. Los clientes de Glencore son consumidores industriales, como los de los sectores automotriz, siderúrgico, de generación de energía, de fabricación de baterías y petrolero. También proporcionamos financiación, logística y otros servicios a productores y consumidores de materias primas. | S8: https://www.elpachon.com.ar/ | T8: No
A9: 8 | D9: GOLDEN MINING | E9: Argentina | H9: Expo San Juan Minera 2026 | I9: Prospecto | J9: Alta | K9: Identificar Gerente de Seguridad/SSO de la operación o proyecto; proponer piloto (rajo, planta, flota) | L9: Expo San Juan Minera 2026. Sin email publicado. | M9: Cliente final – minera / energía (operación o proyecto) | N9: D435 | D436 | O9: Pabellón 2 | Q9: GOLDEN MINING S.A. | R9: Golden Mining es una compañía minera enfocada en el desarrollo y producción de oro en Sudamérica. Su principal activo es la mina Hualilán, ubicado en San Juan, Argentina. La empresa se distingue por su estrategia de toll milling, que permite acelerar la generación de ingresos reduciendo inversión inicial y riesgos, junto con un enfoque en eficiencia operativa y desarrollo progresivo del proyecto. Golden Mining is a mining company focused on the development and production of gold in South America. Its flagship asset is the Hualilán Mine, located in San Juan, Argentina. The company stands out for its toll milling strategy, enabling early cash flow generation with lower upfront capital and reduced risk, combined with a focus on operational efficiency and phased project development. | T9: No
A10: 9 | D10: MCEWEN COPPER PROYECTO LOS AZULES | E10: Argentina | H10: Expo San Juan Minera 2026 | I10: Prospecto | J10: Alta | K10: Identificar Gerente de Seguridad/SSO de la operación o proyecto; proponer piloto (rajo, planta, flota) | L10: Expo San Juan Minera 2026. Sin email publicado. | M10: Cliente final – minera / energía (operación o proyecto) | N10: Isla: 16 | O10: Exterior | Q10: ANDES CORPORACION MINERA S.A. | T10: No
A11: 10 | D11: MOGOTES METALS INC. | E11: Argentina | F11: info@mogotesmetals.com | H11: Expo San Juan Minera 2026 | I11: Prospecto | J11: Alta | K11: Identificar Gerente de Seguridad/SSO de la operación o proyecto; proponer piloto (rajo, planta, flota) | L11: Expo San Juan Minera 2026. | M11: Cliente final – minera / energía (operación o proyecto) | N11: B214 | O11: Pabellón 1 | Q11: MOGOTES METALS INC | R11: Mogotes Metals es una empresa minera en fase de exploración y desarrollo dedicada a la adquisición y exploración de propiedades minerales en todo el mundo. Actualmente, el objetivo de la compañía es identificar un recurso mineral en el Proyecto Filo Sur. El objetivo general de la compañía es identificar, evaluar, adquirir y explorar propiedades minerales adicionales con el fin de descubrir más recursos minerales. | S11: https://www.mogotesmetals.com/ | T11: No
A12: 11 | D12: NEW PEAK | E12: Argentina | F12: agrahame@newpeak.com.au | H12: Expo San Juan Minera 2026 | I12: Prospecto | J12: Alta | K12: Identificar Gerente de Seguridad/SSO de la operación o proyecto; proponer piloto (rajo, planta, flota) | L12: Expo San Juan Minera 2026. | M12: Cliente final – minera / energía (operación o proyecto) | N12: D434 | O12: Pabellón 2 | R12: NEwPeak inició un nuevo programa de perforación en su proyecto aurífero Las Opeñas, 100 % de su propiedad, situado en el Departamento de Iglesia, provincia de San Juan, Argentina. La Compañía tambien esta a la espera de los resultados de los análisis de su primer programa de perforación en su proyecto Tansey, en busca de las prolongaciones de una histórica mina de oro subterránea en el distrito de Tansey, en Queensland, Australia. | S12: https://www.neupeak.com.au/ | T12: No
A13: 12 | D13: PAN AMERICAN ENERGY - AXION PUEBLA | E13: Argentina | H13: Expo San Juan Minera 2026 | I13: Prospecto | J13: Alta | K13: Identificar Gerente de Seguridad/SSO de la operación o proyecto; proponer piloto (rajo, planta, flota) | L13: Expo San Juan Minera 2026. Sin email publicado. | M13: Cliente final – minera / energía (operación o proyecto) | N13: F642 | F643 | O13: Pabellón 2 | Q13: PUEBLA EQUIPO | R13: AXION Energy Minería -Pan American Energy- trabaja de manera articulada con AXION Puebla en la provincia de San Juan para abastecer y acompañar el desarrollo del sector minero. En conjunto, brindan soluciones integrales de energía, asegurando el suministro de combustibles y lubricantes en zonas operativas clave, muchas veces de difícil acceso. Además, aportan logística especializada, asistencia técnica y soporte constante para garantizar la continuidad y eficiencia de las operaciones mineras. Este trabajo conjunto permite potenciar la actividad productiva en San Juan, acompañando a las empresas del sector con estándares de calidad, seguridad y compromiso, alineados con las necesidades específicas de la industria minera. | T13: No
A14: 13 | D14: SABLE RESOURCES LTD | E14: Canadá | H14: Expo San Juan Minera 2026 | I14: Prospecto | J14: Alta | K14: Identificar Gerente de Seguridad/SSO de la operación o proyecto; proponer piloto (rajo, planta, flota) | L14: Expo San Juan Minera 2026. Sin email publicado. | M14: Cliente final – minera / energía (operación o proyecto) | N14: B213 | O14: Pabellón 1 | R14: Sable Resources Ltd. is a Canada-based junior exploration company focused on the discovery and development of copper, gold, and related mineral projects across the Americas. In Argentina, the company has a strong presence in San Juan Province, where it has been actively exploring for more than 7 years. Its portfolio includes key projects such as Don Julio, El Fierro, Zorro, and Cerro Negro, among others, located within highly prospective Andean mineral belts. Sable applies a modern exploration approach based on solid geological models, integrated geophysical and geochemical data, and an active project generation strategy. The company aims to advance its portfolio through strategic partnerships while maintaining high technical, environmental, and community engagement standards. | T14: No
A15: 14 | D15: VELADERO | E15: Argentina | H15: Expo San Juan Minera 2026 | I15: Prospecto | J15: Alta | K15: Identificar Gerente de Seguridad/SSO de la operación o proyecto; proponer piloto (rajo, planta, flota) | L15: Expo San Juan Minera 2026. Sin email publicado. | M15: Cliente final – minera / energía (operación o proyecto) | N15: D441 | D442 | O15: Pabellón 2 | Q15: MINERA ARGENTINA GOLD | R15: Veladero es una mina de oro y plata situada en la provincia de San Juan - Argentina, a una altitud de entre 4.000 y 4.850 metros sobre el nivel del mar, somos una empresa conjunta de Barrick y Shandong Gold. Nuestra misión es ser una mina de oro de clase mundial, con un ambiente de trabajo libre de peligros y trabajadores plenos y comprometidos, que cree valor a largo plazo para nuestros socios y comunidades. | S15: https://www.veladero.com/ | T15: No
A16: 15 | D16: VICUÑA | E16: Argentina | H16: Expo San Juan Minera 2026 | I16: Prospecto | J16: Alta | K16: Identificar Gerente de Seguridad/SSO de la operación o proyecto; proponer piloto (rajo, planta, flota) | L16: Expo San Juan Minera 2026. Sin email publicado. | M16: Cliente final – minera / energía (operación o proyecto) | N16: B201 | B202 | B203 | B210 | B211 | O16: Pabellón 1 | Q16: VICUÑA CORP | T16: No
A17: 16 | D17: YPF | E17: Argentina | H17: Expo San Juan Minera 2026 | I17: Prospecto | J17: Alta | K17: Identificar Gerente de Seguridad/SSO de la operación o proyecto; proponer piloto (rajo, planta, flota) | L17: Expo San Juan Minera 2026. Sin email publicado. | M17: Cliente final – minera / energía (operación o proyecto) | N17: B244 | B245 | B246 | B252 | B253 | B254 | O17: Pabellón 1 | Q17: YPF S.A. | R17: Somos el mayor productor de Oil & Gas de la Argentina, con sólidos resultados y capacidad para llevar adelante los proyectos que convertirán al país en un exportador de energía a nivel mundial. Nuestro objetivo es convertirnos en una empresa no convencional de clase mundial y que Argentina pueda exportar USD 30.000 millones en petróleo y gas para el 2031. Hoy, estamos al frente de los proyectos industriales más ambiciosos del país. Lideramos el Vaca Muerta Oil Sur (VMOS), que potenciará la producción de crudo, y el Argentina LNG, un proyecto de escala global que permitirá exportar gas al mundo. Buscamos constantemente innovación y nuevas tecnologías. Con nuestros Real Time Intelligence Centers, tomamos decisiones más eficientes basadas en datos en tiempo real, aumentando la rentabilidad. Trabajamos por los combustibles del futuro y de calidad internacional. | S17: https://ypf.com/ | T17: No
A18: 17 | D18: ACONCAGUA SERVICIOS MINEROS SRL | E18: Argentina | F18: asanchez@aconcagua-trans.com.ar | H18: Expo San Juan Minera 2026 | I18: Prospecto | J18: Alta | K18: Identificar Jefe de Prevención/SSO; proponer piloto en frente de trabajo (perforación, transporte, campamento) | L18: Expo San Juan Minera 2026. | M18: Cliente final – contratista minero (operación, perforación, transporte, campamento) | N18: Isla: 32A | Isla: 32B | Isla: 38A | Isla: 38B | O18: Exterior | R18: Especialistas en Transporte Minero desde 2002, Impulsando el desarrollo de Recursos Humanos y Proveedores Locales. | S18: https://www.aconcagua-trans.com.ar/ | T18: No
A19: 18 | D19: ADL | E19: Argentina | F19: alejandroacosta@exploservice.com.ar | H19: Expo San Juan Minera 2026 | I19: Prospecto | J19: Alta | K19: Identificar Jefe de Prevención/SSO; proponer piloto en frente de trabajo (perforación, transporte, campamento) | L19: Expo San Juan Minera 2026. | M19: Cliente final – contratista minero (operación, perforación, transporte, campamento) | N19: A111 | A112 | A113 | A114 | A115 | A116 | A121 | A122 | A123 | A124 | A125 | A126 | Isla: 2A | Isla: 2B | Isla: 8A | Isla: 8B | Isla: 14A | Isla: 14B | O19: Pabellón 1 | P19: CASEMI | Q19: ADL S.R.L. | R19: ADL SRL es una empresa especializada en servicios de perforación y voladura orientados a la industria minera y a proyectos de ingeniería civil, abarcando tanto etapas de exploración como de producción. Asimismo, desarrolla excavaciones para obras de construcción, adaptándose a las necesidades específicas de cada proyecto. Con más de 25 años de trayectoria en el sector, ADL SRL se destaca por su amplia experiencia y por contar con un equipo de profesionales altamente capacitados, comprometidos con la excelencia operativa y la mejora continua de sus procesos. La empresa trabaja bajo estrictos estándares de calidad, seguridad y cuidado del medio ambiente, garantizando soluciones eficientes, confiables y sostenibles que contribuyen al cumplimiento de los objetivos de sus clientes. | T19: No
A20: 19 | D20: ANDEMIRA S.A. | E20: Argentina | F20: obertero@andemira.com.ar | H20: Expo San Juan Minera 2026 | I20: Prospecto | J20: Alta | K20: Identificar Jefe de Prevención/SSO; proponer piloto en frente de trabajo (perforación, transporte, campamento) | L20: Expo San Juan Minera 2026. | M20: Cliente final – contratista minero (operación, perforación, transporte, campamento) | N20: C328 | C347 | O20: Pabellón 1 | R20: ANDEMIRA es una empresa de servicios a la minería que nace con 20 años de historia. Nuestros pilares son: OPERACIONES DE CONFIANZA, COMPROMISO AMBIENTAL y TALENTO AL SERVISIO. Nos especializamos en operaciones mineras subterráneas y superficie, construcción de diques de colas (y sus alteos de cota), pad de lixiviación, apertura y mantenimiento de caminos, construcción de plataformas de perforación y obras civiles en yacimientos mineros. | S20: https://andemira.com.ar/ | T20: No
A21: 20 | D21: ANDESITA SAS | E21: Argentina | F21: eugeniaacosta@exploservice.com.ar | H21: Expo San Juan Minera 2026 | I21: Prospecto | J21: Alta | K21: Identificar Jefe de Prevención/SSO; proponer piloto en frente de trabajo (perforación, transporte, campamento) | L21: Expo San Juan Minera 2026. | M21: Cliente final – contratista minero (operación, perforación, transporte, campamento) | N21: A111 | A112 | A113 | A114 | A115 | A116 | A121 | A122 | A123 | A124 | A125 | A126 | Isla: 2A | Isla: 2B | Isla: 8A | Isla: 8B | Isla: 14A | Isla: 14B | O21: Pabellón 1 | P21: CASEMI | Q21: ANDESITA S. A. S. | R21: Andesita SAS es una empresa dedicada a la ejecución de obras civiles, con experiencia en proyectos vinculados al sector minero y energético. Cuenta con trayectoria en el desarrollo de infraestructura para parques solares, realizando trabajos de movimiento de suelo, preparación de terreno y colocación de estructuras. La empresa se destaca por su compromiso con la calidad, la seguridad operativa y el cumplimiento de plazos, adaptándose a las necesidades de cada proyecto. Andesita SAS contribuye al desarrollo de soluciones eficientes y al crecimiento de la infraestructura energética sostenible. | S21: https://www.rocktec.com.ar/ | T21: No
A22: 21 | D22: ARAMARK | E22: Argentina | F22: comercial@aramark.com.ar | H22: Expo San Juan Minera 2026 | I22: Prospecto | J22: Alta | K22: Identificar Jefe de Prevención/SSO; proponer piloto en frente de trabajo (perforación, transporte, campamento) | L22: Expo San Juan Minera 2026. | M22: Cliente final – contratista minero (operación, perforación, transporte, campamento) | N22: D433 | O22: Pabellón 2 | Q22: CENTRAL DE RESTAURANTES SRL | R22: Aramark es una Empresa de Servicios de Alimentación en Campamentos Mineros e Industrias, Servicios de Hotelería y Gestión Integral de Instalaciones. | S22: https://www.aramark.ar/ | T22: No
A23: 22 | D23: ARCE GEOFÍSICOS ARGENTINA | E23: Argentina | F23: garce@geofisicos.com.pe | H23: Expo San Juan Minera 2026 | I23: Prospecto | J23: Alta | K23: Identificar Jefe de Prevención/SSO; proponer piloto en frente de trabajo (perforación, transporte, campamento) | L23: Expo San Juan Minera 2026. También en: Directorio SSO (ID 533). | M23: Cliente final – contratista minero (operación, perforación, transporte, campamento) | N23: B243 | O23: Pabellón 1 | R23: ARCE GEOFÍSICOS ARGENTINA: ESTUDIOS Y CONSULTORÍA GEOFÍSICA Desde 1960, Arce Geofísicos ha liderado el sector de la geofísica en América Latina, ofreciendo soluciones innovadoras y de alta calidad. Contamos con una sólida experiencia en toda América Latina, trabajando en estrecha colaboración con empresas líderes del sector minero, petrolero, agrícola, de energías renovables y de construcción. Nuestra red de operaciones se extiende a países como Perú, México, Bolivia, Colombia, Chile, Argentina, Ecuador, Guyana, Nicaragua, Guatemala, Panamá, Honduras, El Salvador, y República Dominicana, donde hemos contribuido con tecnología de punta y un equipo altamente capacitado. Productos/servicios de la empresa: I. Estudios de Prospección Minera: Magnetometría (precesión de protones, overhauser omnidireccional, vapor de potasio y vapor de cesio), Radiometría, Microgravimetría, Resistividad Eléctrica y Polarización Inducida (1D, 2D, 2D a 3D), así como Resistividad Eléctrica y Polarización Inducida de Señal Completa y Configuración Distribuida (AG-DAS), Métodos Electromagnéticos de Dominio de Tiempo (TDEM) con diversos sensores (fluxgate, bobina de baja frecuencia), Magnetometría en UAV, Análisis de Muestras, Magnetotelúrico (MT) y Audio-magnetotelúrico (AMT). II. Aplicaciones para Geotecnia: Microgravimetría, Tomografía Sísmica de Onda P, Análisis Multicanal de Onda de Superficie con fuente activa (MASW) o con fuente pasiva (MAM), Resistividad Eléctrica (1D, 2D, 3D), y Métodos Electromagnéticos de Dominio de Tiempo (TDEM) con diversos sensores (fluxgate, bobina de baja frecuencia). III. Estudios de Prospección por Agua Subterránea: Para estas aplicaciones utilizamos los métodos de Resistividad Eléctrica (1D, 2D, 3D), y Métodos Electromagnéticos de Dominio de Tiempo (TDEM) con distintos tamaños de loops para alcanzar distintas profundidades. | S23: https://www.geofisicos.com/ | T23: Directorio SSO (ID 533)
A24: 23 | D24: ATA | E24: Argentina | F24: mariela.pringles@atalimentaria.com | H24: Expo San Juan Minera 2026 | I24: Prospecto | J24: Alta | K24: Identificar Jefe de Prevención/SSO; proponer piloto en frente de trabajo (perforación, transporte, campamento) | L24: Expo San Juan Minera 2026. | M24: Cliente final – contratista minero (operación, perforación, transporte, campamento) | N24: Isla: 57 | Isla: 77 | O24: Exterior | Q24: ALTA TECNOLOGÍA ALIMENTARIA | R24: Somos una empresa argentina radicada en San Juan, especializada en alimentación institucional, hotelería y servicios en sitios remotos. Nuestro equipo combina experiencia, innovación y compromiso humano para garantizar bienestar y eficiencia en cada operación de manera sostenible. | S24: https://atalimentaria.com/web/ | T24: No
A25: 24 | D25: B & W | E25: Argentina | H25: Expo San Juan Minera 2026 | I25: Prospecto | J25: Alta | K25: Identificar Jefe de Prevención/SSO; proponer piloto en frente de trabajo (perforación, transporte, campamento) | L25: Expo San Juan Minera 2026. Sin email publicado. | M25: Cliente final – contratista minero (operación, perforación, transporte, campamento) | N25: A117 | A118 | O25: Pabellón 1 | Q25: B & W HIDROGEOLOGIA Y MEDIOAMBIENTE S.R.L. | R25: BW es una empresa especializada en soluciones hidrogeológicas y ambientales para la industria minera, con foco en el desarrollo sostenible y la gestión eficiente de los recursos hídricos. Brindamos servicios integrales que abarcan desde la caracterización hidrogeológica, monitoreo y muestreo de aguas superficiales y subterráneas, hasta modelación numérica, diseño de sistemas de desaguado de mina y soporte técnico para operaciones en entornos complejos, incluyendo alta montaña. Nuestro enfoque combina conocimiento técnico sólido, experiencia en terreno y tecnologías avanzadas, lo que nos permite acompañar a nuestros clientes en todas las etapas del proyecto, desde la exploración hasta la operación y cierre. En BW trabajamos para asegurar decisiones basadas en datos confiables, minimizando riesgos y promoviendo un desarrollo responsable de los recursos. | T25: No
A26: 25 | D26: BECHER LOGISTICA | E26: Argentina | F26: analaura@becherlogistica.com.ar | H26: Expo San Juan Minera 2026 | I26: Prospecto | J26: Alta | K26: Identificar Jefe de Prevención/SSO; proponer piloto en frente de trabajo (perforación, transporte, campamento) | L26: Expo San Juan Minera 2026. | M26: Cliente final – contratista minero (operación, perforación, transporte, campamento) | N26: A159 | A160 | O26: Pabellón 1 | Q26: VIA SRL | R26: Becher Logística es una empresa sanjuanina especializada en soluciones logísticas integrales y mineras , con sólida trayectoria en transporte de cargas generales, distribución, cargas peligrosas, proyectos especiales y operaciones para la industria y el sector minero. Brindamos servicios adaptados a cada cliente, priorizando la seguridad vial, la eficiencia operativa, el cumplimiento normativo y altos estándares de servicio en cada etapa. Trabajamos bajo principios de mejora continua y normas de gestión de calidad, con experiencia en entornos de alta exigencia acompañando proyectos en minería, comercio e industria. Nuestro compromiso es impulsar el crecimiento de nuestros clientes y comunidades a través de un servicio confiable y humano, brindando seguridad y soluciones que respondan a necesidades reales. | S26: https://www.becherlogistica.com.ar/ | T26: No
A27: 26 | D27: C&M SA - CONSTRUCCION Y MINERIA SA | E27: Argentina | F27: contacto@cymweb.com.ar | H27: Expo San Juan Minera 2026 | I27: Prospecto | J27: Alta | K27: Identificar Jefe de Prevención/SSO; proponer piloto en frente de trabajo (perforación, transporte, campamento) | L27: Expo San Juan Minera 2026. | M27: Cliente final – contratista minero (operación, perforación, transporte, campamento) | N27: B218 | B219 | O27: Pabellón 1 | Q27: CONSTRUCCION Y MINERIA S.A. | R27: Desde 1998, Construcción & Minería SA se dedica a ofrecer servicios integrales de alta calidad para los sectores minero, petrolero y civil. Nuestro enfoque combina experiencia, tecnología de vanguardia y un compromiso constante con la satisfacción de nuestros clientes. Trabajamos como socios estratégicos para superar los desafíos técnicos y operativos de cada proyecto. Brindamos atención personalizada, asesoramiento y excelente calidad de insumos y servicios. Calidad garantizada: Implementamos los más altos estándares internacionales de calidad en cada uno de nuestros procesos Equipo experimentado: Contamos con un experimentado personal dedicados a garantizar los mejores resultados. Altos estándares en tecnología: Productos de primera línea de todas las aristas del mundo, Canadá, USA, Europa, Australia y Oriente. Orientación al cliente: Trabajamos como verdaderos socios estratégicos, avanzando juntos con perseverancia, humildad y disciplina. | S27: http://cymweb.com.ar/ | T27: No
A28: 27 | D28: CASTEM | E28: Perú | F28: elozada@castem.com.pe | H28: Expo San Juan Minera 2026 | I28: Prospecto | J28: Alta | K28: Identificar Jefe de Prevención/SSO; proponer piloto en frente de trabajo (perforación, transporte, campamento) | L28: Expo San Juan Minera 2026. También en: Directorio SSO (ID 20); ExpoMina (ID 68). | M28: Cliente final – contratista minero (operación, perforación, transporte, campamento) | N28: A161 | O28: Pabellón 1 | R28: Somos una empresa 100 % peruana con 25 años de experiencia en minería y construcción. Brindamos soluciones integrales e innovadoras para la estabilización, fortificación y sostenimiento de roca y suelo, desarrollando productos de alta calidad adaptados a cada cliente. Contamos con un amplio portafolio y un equipo de ingenieros que visita operaciones mineras para ofrecer soporte técnico directo, en coordinación con el área comercial. Ofrecemos cartuchos de resina y cemento, cargadores de ANFO, pernos de anclaje y de fricción “Split Set”, y bombas de inyección, entre otros. Brindamos acompañamiento permanente, soporte comercial y asistencia técnica especializada, garantizando soluciones eficientes y confiables en cada proyecto. | S28: https://castem.com.pe/ | T28: Directorio SSO (ID 20); ExpoMina (ID 68)
A29: 28 | D29: CATERWEST | E29: Argentina | F29: info@caterwest.com | H29: Expo San Juan Minera 2026 | I29: Prospecto | J29: Alta | K29: Identificar Jefe de Prevención/SSO; proponer piloto en frente de trabajo (perforación, transporte, campamento) | L29: Expo San Juan Minera 2026. | M29: Cliente final – contratista minero (operación, perforación, transporte, campamento) | N29: Isla: 13 | O29: Exterior | Q29: CATERWEST S.A | R29: Somos líderes en la provisión de soluciones integrales para la vida en sitios remotos, con una sólida especialización en los sectores minero, energético e industrial. A través de nuestra gestión en alimentación, hotelería, logística y mantenimiento, nos posicionamos como el aliado estratégico que garantiza la continuidad operativa de nuestros clientes. Con ADN sanjuanino y estándares internacionales, operamos bajo un firme compromiso de gestión ambiental y desarrollo genuino de las comunidades locales, transformando servicios en valor compartido. | S29: https://caterwest.com/ | T29: No
A30: 29 | D30: CINTER | E30: Argentina | F30: santiago.ochoa@cinter.com.ar | H30: Expo San Juan Minera 2026 | I30: Prospecto | J30: Alta | K30: Identificar Jefe de Prevención/SSO; proponer piloto en frente de trabajo (perforación, transporte, campamento) | L30: Expo San Juan Minera 2026. | M30: Cliente final – contratista minero (operación, perforación, transporte, campamento) | N30: B207 | B208 | B216 | B217 | O30: Pabellón 1 | Q30: CINTER S.R.L. | R30: CINTER es una empresa argentina de Ingeniería y Construcciones, con más de 50 años de experiencia en el mercado de Obras Industriales, lo que la han posicionado como líder en la fabricación de Estructuras Metálicas y ejecución de obras “Llave en Mano” para diversos sectores de la industria y con una destacada participación en el sector minero. Se ha consolidado como el mayor fabricante de estructuras metálicas del país, habiendo participado en la construcción de la mayoría de los grandes proyectos mineros del país. Es de destacar, que contamos con la planta de procesamiento de acero más grande y moderna del país con una capacidad de producción superior a 1.500Tn/mes, bajo los más altos estándares de calidad que demanda el sector y como consecuencia del ambicioso programa de inversión que viene ejecutando la empresa en los últimos 10 años. Ejemplo de esto último, lo constituye una línea robotizada de ensamblado de estructura, de origen austríaco, única en Sudamérica y que representa la tecnología más evolucionada que existe en el mercado de las estructuras de acero que incrementa, no solo la capacidad productiva de la empresa, sino también los niveles la calidad. | S30: https://www.cinter.com.ar/ | T30: No
A31: 30 | D31: COCYAR S.A. | E31: Argentina | F31: juancarloscaffaratti@cocyar.com | H31: Expo San Juan Minera 2026 | I31: Prospecto | J31: Alta | K31: Identificar Jefe de Prevención/SSO; proponer piloto en frente de trabajo (perforación, transporte, campamento) | L31: Expo San Juan Minera 2026. | M31: Cliente final – contratista minero (operación, perforación, transporte, campamento) | N31: F636 | F637 | F638 | F645 | F648 | F655 | F656 | F657 | F658 | F659 | F660 | F661 | F662 | F663 | F664 | F665 | F666 | F667 | O31: Pabellón 2 | P31: CFI - CONSEJO FEDERAL DE INVERSIONES | R31: COCYAR SA Somos una empresa constructora con más de 30 años de trayectoria en el gerenciamiento y ejecución de obras civiles, de arquitectura y electromecánicas, especializándose en proyectos bajo la modalidad "llave en mano", contando con certificaciones de calidad. Actualmente estamos realizando propuestas personalizadas y adaptadas a las necesidades específicas de nuestros clientes. Debido a su perfil y nuestra experiencia en distintas áreas de desarrollos, como infraestructura, obras civiles, arquitectura e industrial de todo tipo. Fabricamos nuestras propias estructuras metálicas, ejecutamos Obras eléctricas en BT, MT y AT, movimientos de suelos, bases y naves industriales, plantas de tratamientos, acueductos, infraestructura urbana, por lo que nos gustaría presentarles formalmente nuestros servicios y explorar posibles proyectos a futuro. Contamos con la capacidad de formar parte de un proyecto desde la ingeniería, la construcción y la puesta en marcha. En algunos casos, operamos y mantenemos nuestras obras. No dude en llamarnos, ofrecemos soluciones reales a sus necesidades. Cordiales saludos. Juan | S31: https://www.cocyar.com/ | T31: No
A32: 31 | D32: CONOSUR DRILLING S.A. | E32: Argentina | H32: Expo San Juan Minera 2026 | I32: Prospecto | J32: Alta | K32: Identificar Jefe de Prevención/SSO; proponer piloto en frente de trabajo (perforación, transporte, campamento) | L32: Expo San Juan Minera 2026. Sin email publicado. | M32: Cliente final – contratista minero (operación, perforación, transporte, campamento) | N32: C344 | O32: Pabellón 1 | Q32: CONOSUR DRILLING SA | R32: ConoSur Drilling S.A. es una empresa argentina especializada en servicios de perforación para la industria minera, con más de 25 años de experiencia acumulada en el sector. La compañía brinda soluciones integrales en perforación diamantina, rotary, aire reverso y estudios de suelo, incorporando tecnología de vanguardia y equipos adaptados a los desafíos operativos de cada proyecto. Con presencia en distintas regiones del país y un equipo conformado por profesionales altamente calificados, ConoSur Drilling se posiciona como un socio estratégico para campañas de exploración minera, desarrollo de recursos y perforaciones de producción. Su modelo de gestión está basado en la mejora continua, la eficiencia operativa y un fuerte compromiso con la seguridad, la salud, el medio ambiente y las comunidades donde opera, promoviendo un desarrollo sostenible de la industria minera argentina | T32: No
A33: 32 | D33: CRUZ DEL SUR | E33: Argentina | F33: marketing@cruzdelsur.com | H33: Expo San Juan Minera 2026 | I33: Prospecto | J33: Alta | K33: Identificar Jefe de Prevención/SSO; proponer piloto en frente de trabajo (perforación, transporte, campamento) | L33: Expo San Juan Minera 2026. | M33: Cliente final – contratista minero (operación, perforación, transporte, campamento) | N33: B255 | O33: Pabellón 1 | Q33: VICTOR MASSON CRUZ DEL SUR S A | R33: Cruz del Sur es una compañía argentina de transporte y logística integral con 70 años de trayectoria, una red federal de sucursales y cobertura en todo el país. Acompaña a empresas de distintos sectores con soluciones adaptadas a las necesidades de cada operación y cuenta con una amplia experiencia en industrias de alta exigencia, como la minería. Para este sector, desarrolla servicios de abastecimiento, transporte de cargas generales y peligrosas y operaciones especiales, combinando conocimiento regional, trazabilidad, capacidad operativa 24/7 y altos estándares de seguridad, con certificaciones específicas como el Código Internacional para el Manejo del Cianuro (ICMI). | S33: https://www.cruzdelsur.com/ | T33: No
A34: 33 | D34: CUYO MINERO | E34: Argentina | H34: Expo San Juan Minera 2026 | I34: Prospecto | J34: Alta | K34: Identificar Jefe de Prevención/SSO; proponer piloto en frente de trabajo (perforación, transporte, campamento) | L34: Expo San Juan Minera 2026. Sin email publicado. | M34: Cliente final – contratista minero (operación, perforación, transporte, campamento) | N34: C326 | O34: Pabellón 1 | T34: No
A35: 34 | D35: DELTA MINING | E35: Argentina | F35: info@deltamining.com.ar | H35: Expo San Juan Minera 2026 | I35: Prospecto | J35: Alta | K35: Identificar Jefe de Prevención/SSO; proponer piloto en frente de trabajo (perforación, transporte, campamento) | L35: Expo San Juan Minera 2026. | M35: Cliente final – contratista minero (operación, perforación, transporte, campamento) | N35: A131 | O35: Pabellón 1 | Q35: DELTA MINING S.A. | R35: QUE HACEMOS: Brindar servicios de alquiler de equipos viales para movimientos de suelo con operador, ofreciendo soluciones flexibles y adaptables, que satisfagan las necesidades de nuestros clientes. Contribuyendo a la apertura de caminos en zonas foráneas, a través de un desarrollo sustentable y bajo un estricto cuidado del medio ambiente, preservando la salud, la seguridad y el bienestar de nuestros empleados. NUESTROS SERVICIOS: SERVICIOS VIALES Ofrecemos servicios de apertura de caminos en alta cordillera, movimiento de suelo, nivelación y de limpieza de terrenos. Para ello, contamos con equipos exclusivos de altísima calidad y personal capacitado para brindar la mejor atención a nuestros clientes. Asimismo, realizamos trabajos de planchadas para perforación, excavaciones y trincheras. ALQUILER DE EQUIPOS VIALES Ofrecemos en alquiler equipos viales de alta calidad con y sin chofer. SERVICIO DE HIDROGRÚA Ofrecemos un servicio integral de carga, movimientos, transporte y descarga de materiales; facilitando la logística y reduciendo costos y tiempos para su empresa. ALQUILER DE CAMIÓN HIDROGRÚA Ofrecemos en alquiler camiones Hidrogrúa con y sin chofer. ALQUILER DE CAMIÓN CISTERNA Ofrecemos en alquiler camión cisterna con y sin chofer, con permisos para el transporte de mercancía peligrosa vigentes. ALQUILER DE CAMIONETAS Alquiler de camionetas 4x4 equipadas para cordillera, con y sin chofer. EXPERIENCIA: Nuestro equipo de profesionales participó en proyectos relevantes (como Filo del sol, Josemaria, Filo sur, el Fierro), adquiriendo experiencia desde la Prospección hasta la etapa de Explotación. Contamos con altos estándares de protección y compromiso hacia el cuidado del medio ambiente, trabajando en armonía con las comunidades. Desarrollamos un trabajo acorde a las mejores prácticas profesionales, guardando un alto valor a la confidencialidad con nuestros clientes. Creemos en la cooperación y el trabajo conjunto para desarrollar sinergias. QUE NOS DIFERENCIA: Promovemos los valores de confiabilidad, puntualidad, honestidad y el respeto hacia el cliente, siendo estos los que rigen nuestro accionar diario y los que nos motivan a evolucionar para brindar un servicio que supere las expectativas de nuestros clientes Nuestra trayectoria avala la calidad y responsabilidad de nuestro personal, así como también la solución a las necesidades particulares de cada empresa, adaptando el servicio de acuerdo a las necesidades del trabajo requerido | S35: https://deltamining.com.ar/ | T35: No
A36: 35 | D36: DRILLAR SAN JUAN | E36: Argentina | F36: info@drillar.ar | H36: Expo San Juan Minera 2026 | I36: Prospecto | J36: Alta | K36: Identificar Jefe de Prevención/SSO; proponer piloto en frente de trabajo (perforación, transporte, campamento) | L36: Expo San Juan Minera 2026. | M36: Cliente final – contratista minero (operación, perforación, transporte, campamento) | N36: A102 | A103 | O36: Pabellón 1 | Q36: DRILLAR SAN JUAN S.A.S | R36: DrillAr es una compañía argentina de perforación liderada por un equipo de profesionales con vasta experiencia en el rubro de la perforación minera y petróleo. Este personal se ha desempeñado en cargos ejecutivos y operativos en varias empresas multinacionales de perforación contribuyendo al éxito de cada una de ellas donde se desempeñó. La experiencia del equipo permite a la empresa, conocer una gran cantidad de proyectos de exploración y mineros a nivel nacional, además de conocer todas las técnicas de perforación y de servicios asociados. | S36: https://drillar.ar/ | T36: No
A37: 36 | D37: ECOVIAL | E37: Argentina | F37: ecovialsrl@gmail.com | H37: Expo San Juan Minera 2026 | I37: Prospecto | J37: Alta | K37: Identificar Jefe de Prevención/SSO; proponer piloto en frente de trabajo (perforación, transporte, campamento) | L37: Expo San Juan Minera 2026. | M37: Cliente final – contratista minero (operación, perforación, transporte, campamento) | N37: Isla: 36 | O37: Exterior | R37: ECO VIAL SRL es una empresa especializada en movimientos de suelo y servicios con maquinaria vial, orientada a brindar soluciones eficientes para proyectos de obra civil, minería y desarrollo de infraestructura. Contamos con experiencia en trabajos de terraplenes, nivelación de terrenos, excavaciones, apertura de caminos, limpieza de predios y desagües, adaptándonos a las necesidades específicas de cada cliente y proyecto. Disponemos de un moderno parque de maquinaria vial en alquiler, operada por personal capacitado, garantizando productividad, seguridad y cumplimiento de plazos. | T37: No
A38: 37 | D38: ENAEX | E38: Argentina | F38: roberta.politano@enaex.com | H38: Expo San Juan Minera 2026 | I38: Prospecto | J38: Alta | K38: Identificar Jefe de Prevención/SSO; proponer piloto en frente de trabajo (perforación, transporte, campamento) | L38: Expo San Juan Minera 2026. También en: Exponor (ID 38). | M38: Cliente final – contratista minero (operación, perforación, transporte, campamento) | N38: A132 | A133 | A144 | A145 | Isla: 7 | O38: Pabellón 1 | Q38: ENAEX ARGENTINA SRL | R38: Empresa líder en prestación de servicios integrales de fragmentación de rocas para la minería a cielo abierto (OP) y subterránea (UG), construcción y exploración sísmica. Se especializa en fabricación, comercialización y distribución de explosivos, emulsiones y sistema de iniciación remotos a distancia con tecnología de última generación | T38: Exponor (ID 38)
A39: 38 | D39: ESPECO | E39: Argentina | F39: david@especo.com.ar | H39: Expo San Juan Minera 2026 | I39: Prospecto | J39: Alta | K39: Identificar Jefe de Prevención/SSO; proponer piloto en frente de trabajo (perforación, transporte, campamento) | L39: Expo San Juan Minera 2026. | M39: Cliente final – contratista minero (operación, perforación, transporte, campamento) | N39: A111 | A112 | A113 | A114 | A115 | A116 | A121 | A122 | A123 | A124 | A125 | A126 | Isla: 2A | Isla: 2B | Isla: 8A | Isla: 8B | Isla: 14A | Isla: 14B | O39: Pabellón 1 | P39: CASEMI | Q39: ESPECO S.R.L. | R39: En ESPECO SRL brindamos soluciones integrales en alquiler de vehículos 4x4, orientadas a empresas que operan en entornos exigentes y de difícil acceso. Nos especializamos en acompañar industrias como la minería, energía, petróleo y obras de infraestructura, garantizando movilidad segura, eficiente y confiable en todo tipo de terrenos. Nuestra flota está compuesta por unidades modernas, equipadas y mantenidas bajo estrictos estándares de calidad y seguridad, adaptadas a las condiciones más desafiantes. Cada vehículo es sometido a controles preventivos periódicos, asegurando un rendimiento óptimo y minimizando riesgos operativos. En ESPECO entendemos que la seguridad es un valor clave. Por ello, incorporamos protocolos rigurosos en cada servicio, alineados con las normativas vigentes y las exigencias de nuestros clientes. Nuestro compromiso es brindar no solo vehículos, sino soluciones que acompañen la continuidad operativa de cada proyecto. Nos destacamos por la flexibilidad, la respuesta rápida y la atención personalizada, adaptándonos a las necesidades específicas de cada cliente. Acompañamos cada operación con un enfoque profesional, confiable y orientado a resultados. | S39: https://www.especo.com.ar/ | T39: No
A40: 39 | D40: FG LOGISTICA | E40: Argentina | H40: Expo San Juan Minera 2026 | I40: Prospecto | J40: Alta | K40: Identificar Jefe de Prevención/SSO; proponer piloto en frente de trabajo (perforación, transporte, campamento) | L40: Expo San Juan Minera 2026. Sin email publicado. También en: Exponor (ID 42). | M40: Cliente final – contratista minero (operación, perforación, transporte, campamento) | N40: F610 | O40: Pabellón 2 | R40: Logística FG es una unidad de negocios del Grupo FG, que ofrece soluciones logísticas integrales, incluyendo manejo de contenedores, manipulación de carga, almacenamiento de importación y exportación, y servicios de transporte de carga | T40: Exponor (ID 42)
A41: 40 | D41: GEOAR S.R.L | E41: Argentina | H41: Expo San Juan Minera 2026 | I41: Prospecto | J41: Alta | K41: Identificar Jefe de Prevención/SSO; proponer piloto en frente de trabajo (perforación, transporte, campamento) | L41: Expo San Juan Minera 2026. Sin email publicado. | M41: Cliente final – contratista minero (operación, perforación, transporte, campamento) | N41: A162 | O41: Pabellón 1 | R41: Una empresa argentina ​conformada por Geociencistas que desde hace​ más de 25 años ​se perfeccionan y ​realiza​n​ Servicios Geofísicos tanto a nivel nacional como internacional.​​​ Nos dedicamos al estudio del subsuelo, contando para esto con profesionales altamente capacitados y equipamiento de última generación. Nuestra experiencia sumada a la incorporación de nuevas tecnologías nos permite abarcar todos los métodos geofísicos aplicables para exploración, evaluación y caracterización del subsuelo para la industria minera, petrolera, geotecnia, geodinámica, hidrogeológica, arqueología, obras civiles, auscultación del subsuelo y medio ambiente. Nuestro desafío es satisfacer al cliente dando solución a cualquier problemática. GEOAR se caracteriza por la confiabilidad, calidad y compromiso desde el inicio hasta el final de cada uno de nuestros trabajos. An Argentinian company made of Geoscientists that have been performing Geophysics services on a national and international level and have been perfecting their craft for over 25 years. We devote ourselves to the study of the subsurface, with our highly trained professionals and latest generation equipment. Our experience, added to the incorporation of the latest technologies available lets us encompass every geophysical method available for exploration, evaluation and characterization of the subsurface for industries or research, such as the mining industry, fuel industry, geotechnics, geodynamics, archaeology, civil works, subsoil auscultation and environmental works. Our goal is to grant satisfaction to any client by giving them the solution to any of their problems. GEOAR is characterized by the trust, quality and compromise of the work we do from beginning to end. | T41: No
A42: 41 | D42: GEOTUB | E42: Argentina | F42: info@geotub.com.ar | H42: Expo San Juan Minera 2026 | I42: Prospecto | J42: Alta | K42: Identificar Jefe de Prevención/SSO; proponer piloto en frente de trabajo (perforación, transporte, campamento) | L42: Expo San Juan Minera 2026. | M42: Cliente final – contratista minero (operación, perforación, transporte, campamento) | N42: E501 | O42: Pabellón 2 | Q42: GEOTUB S.A. | R42: Más de 20 años llevando agua donde necesites. Soluciones integrales de entubación de pozos; no solo ofrecemos soluciones de entubación, nos comprometemos de principio a fin, brindando asesoría y asistencia para el máximo rendimiento de cada pozo. Filtros para pozos de agua con la mayor capacidad filtrante y tecnología autolimpiante. Disponibles en Acero Galvanizado para protección anticorrosiva y resistencia mecánica, o en Acero Inoxidable 304L/316L para máxima resistencia a la corrosión en condiciones extremas. Su diseño de ranura continua optimiza el caudal y asegura la máxima durabilidad y eficiencia de la instalación. | S42: https://geotub.com.ar/ | T42: No
A43: 42 | D43: GRUAS BILLIA | E43: Argentina | F43: fbillia@industriasbillia.com.ar | H43: Expo San Juan Minera 2026 | I43: Prospecto | J43: Alta | K43: Identificar Jefe de Prevención/SSO; proponer piloto en frente de trabajo (perforación, transporte, campamento) | L43: Expo San Juan Minera 2026. | M43: Cliente final – contratista minero (operación, perforación, transporte, campamento) | O43: Exterior | Q43: INDUSTRIAS BILLIA | R43: **En el año 1980 Jorge Federico Billia forma la empresa Industrias Billia la cual se especializó en tareas principalmente metalúrgicas y de tornería. Con el tiempo se agregaron los rubros de reparaciones hidráulica y mecánicas. Todos estos frentes de trabajos en su mayoría relacionados con la industria de San Juan. Con el pasar de los años la empresa inició un nuevo rubro e incursionó en la compra de autoelevadores para alquiler como así también el servicio de descargas varias con operadores incluidos. Años más tarde continuó con la adquisición de grúas para realizar servicios de izajes a empresas de San Juan y la región de Cuyo.** +44 Años en el Rubro **En el año 2004 se crea la empresa Natalio SA, la cual pertenece al grupo Billia. El presidente de esta firma es Jorge Federico Billia. En esta empresa se realizan exclusivamente tareas relacionadas con la actividad minera en nuestras tres divisiones, servicio de izajes con grúas, servicio de izajes con hidrogrúas y transporte de cargas pesadas. Con los inicios del proyecto Veladero en el año 2004, la empresa Natalio SA comienza la construcción y expansión de todo el campamento de la mina, siendo solicitado nuestro servicio hasta la actualidad. Del año 2010 a 2013 trabajamos con más de 30 equipos activos en la mina Pascua – Lama en San Juan. Contamos con personal especializado para realizar nuestro propio mantenimiento, tornería liviana y pesada, sala de hidráulica, sector de electrónica y electricidad, mecánicos especializados en automotor y maquinaria pesada, división metalúrgica y pintura. En todos los proyectos colocamos nuestros talleres móviles con insumos suficientes para realizar un constante servicio preventivo y evitar cualquier tipo de pérdida de tiempo. En la actualidad tenemos un grupo humano de 110 personas entre las diferentes áreas de ambas empresas y una flota de más de 100 vehículos entre grúas, hidrogrúas, camiones, semirremolques, carretones y camionetas. Contamos con un departamento de Higiene y Seguridad propio en San Juan y con equipos activos de supervisión e higiene y seguridad en cada proyecto. Este nuevo rubro incluye capacitaciones permanentes al personar (operadores y riggers) ya que es mano de obra calificada por ser por en su mayoría tareas de alto riesgo. En el año 2024, luego de una serie de auditorías y mejoras en la empresa, logramos certificar normas ISO 9001, 14001 y 45001, que refieren a calidad, medio ambiente y seguridad y salud respectivamente.** | T43: No
A44: 43 | D44: GRUAS MARTIN | E44: Argentina | H44: Expo San Juan Minera 2026 | I44: Prospecto | J44: Alta | K44: Identificar Jefe de Prevención/SSO; proponer piloto en frente de trabajo (perforación, transporte, campamento) | L44: Expo San Juan Minera 2026. Sin email publicado. | M44: Cliente final – contratista minero (operación, perforación, transporte, campamento) | N44: E536 | E537 | E538 | E542 | E543 | E544 | E545 | E546 | E552 | E553 | E554 | E555 | E556 | O44: Pabellón 2 | P44: CLÚSTER DE PETRÓLEO GAS Y MINERÍA DE CORDOBA | Q44: GRUAS MARTIN SA | T44: No
A45: 44 | D45: GRÚAS SAN BLAS | E45: Argentina | H45: Expo San Juan Minera 2026 | I45: Prospecto | J45: Alta | K45: Identificar Jefe de Prevención/SSO; proponer piloto en frente de trabajo (perforación, transporte, campamento) | L45: Expo San Juan Minera 2026. Sin email publicado. | M45: Cliente final – contratista minero (operación, perforación, transporte, campamento) | N45: F620 | F621 | O45: Pabellón 2 | Q45: GRÚAS SAN BLAS SA | R45: Grúas San Blas es una empresa especializada en la venta, alquiler y servicio postventa de maquinaria destinada a diversos sectores industriales, entre ellos construcción, vialidad, minería, petróleo y gas, industria y puertos. Representa marcas líderes a nivel mundial como SANY, Bobcat y Manitou , ofreciendo equipos de alta calidad, tecnología de vanguardia y respaldo técnico especializado. Con más de 45 años de trayectoria en el mercado, cuenta con una amplia red de sucursales en 16 provincias argentinas, lo que le permite brindar cobertura nacional, atención personalizada y soporte inmediato a sus clientes. | T45: No
A46: 45 | D46: GRUPO SIT SERVICIOS INTEGRALES TOPOGRÁFICOS | E46: Argentina | F46: contacto@gruposit.com.ar | H46: Expo San Juan Minera 2026 | I46: Prospecto | J46: Alta | K46: Identificar Jefe de Prevención/SSO; proponer piloto en frente de trabajo (perforación, transporte, campamento) | L46: Expo San Juan Minera 2026. | M46: Cliente final – contratista minero (operación, perforación, transporte, campamento) | N46: E515 | O46: Pabellón 2 | Q46: GRUPO SIT SRL | R46: Grupo SIT SRL | Servicios Integrales Topográficos Somos una empresa especializada en brindar soluciones topográficas para proyectos de ingeniería, con más de 19 años de experiencia en obras de gran escala en minería, energía, siderurgia, infraestructura, industria automotriz y consultoría. Operamos en todo el territorio argentino, con presencia en Rosario, Salta y San Juan, aportando precisión, control y trazabilidad en cada etapa del proyecto. Nuestra propuesta se basa en el profesionalismo, la innovación tecnológica y el trabajo en equipo, respaldados por una estructura sólida, tecnología de última generación y un equipo de más de 80 profesionales. Contamos con certificación Trinorma ISO 9001, 14001 y 45001, que garantiza calidad, gestión ambiental y seguridad en nuestras operaciones, y fuimos reconocidos como Great Place to Work, reflejando nuestro compromiso con un buen entorno laboral. | S46: https://gruposit.com.ar/ | T46: No
A47: 46 | D47: GSI | E47: Argentina | F47: servicios@gsi-srl.com.ar | H47: Expo San Juan Minera 2026 | I47: Prospecto | J47: Alta | K47: Identificar Jefe de Prevención/SSO; proponer piloto en frente de trabajo (perforación, transporte, campamento) | L47: Expo San Juan Minera 2026. | M47: Cliente final – contratista minero (operación, perforación, transporte, campamento) | N47: A111 | A112 | A113 | A114 | A115 | A116 | A121 | A122 | A123 | A124 | A125 | A126 | Isla: 2A | Isla: 2B | Isla: 8A | Isla: 8B | Isla: 14A | Isla: 14B | O47: Pabellón 1 | P47: CASEMI | Q47: GSI S. R. L. | R47: GSI SRL es el socio estratégico 360° que simplifica la gestión de la Gran Minería ofreciendo un único punto de contacto para centralizar soluciones de CAPEX y OPEX. Contamos con taller de mantenimiento para flotas livianas y pesadas, y equipamos vehículos para minería sumando la telemetría y tecnología de USS. Proveemos rental de unidades 4x4 en alianza con Valdivia Automotores, garantizando operatividad continua con nuestra asistencia 24/7 en campo. Ejecutamos obras de ingeniería y construcción civil y eléctrica de gran envergadura integrando el know-how y la capacidad del Grupo NH. Lideramos la ingeniería de mantenimiento y gestión de activos para elevar la confiabilidad industrial de la mina junto a los expertos de JPS Argentina. Nos diferencia nuestro dominio logístico en alta montaña y la capacidad de radicar tecnología global transformándola en ejecución y desarrollo 100% sanjuanino. | S47: https://www.gsi-srl.com.ar/ | T47: No
A48: 47 | D48: HG PERFORACIONES | E48: Argentina | H48: Expo San Juan Minera 2026 | I48: Prospecto | J48: Alta | K48: Identificar Jefe de Prevención/SSO; proponer piloto en frente de trabajo (perforación, transporte, campamento) | L48: Expo San Juan Minera 2026. Sin email publicado. | M48: Cliente final – contratista minero (operación, perforación, transporte, campamento) | N48: A111 | A112 | A113 | A114 | A115 | A116 | A121 | A122 | A123 | A124 | A125 | A126 | Isla: 2A | Isla: 2B | Isla: 8A | Isla: 8B | Isla: 14A | Isla: 14B | O48: Pabellón 1 | P48: CASEMI | Q48: HG PERFORACIONES SRL | T48: No
A49: 48 | D49: INGEAP | E49: Argentina | F49: ventas@ingeap.com | H49: Expo San Juan Minera 2026 | I49: Prospecto | J49: Alta | K49: Identificar Jefe de Prevención/SSO; proponer piloto en frente de trabajo (perforación, transporte, campamento) | L49: Expo San Juan Minera 2026. | M49: Cliente final – contratista minero (operación, perforación, transporte, campamento) | N49: A165 | O49: Pabellón 1 | R49: INGEAP S.A.S. | INGENIERÍA DE PRECISIÓN Y TOPOGRAFÍA PARA MINERÍA, OIL & GAS Y GRANDES OBRAS Somos una empresa de ingeniería especializada en transformar datos de terreno en decisiones operativas precisas. Nuestros ingenieros y topógrafos de campo optimizan la ejecución de grande proyectos mediante tecnología de vanguardia —como Fotogrametría con Drones, GPS y Estaciones Totales— garantizando certeza geométrica para eliminar riesgos y sobrecostos en entornos complejos. Nuestras Soluciones Especializadas: Control de Movimiento de Suelos: Cálculo preciso de volúmenes mediante modelos digitales de terreno (DTM) y trazado de locaciones (pads) para asegurar que la infraestructura se asiente en terrenos nivelados y seguros. Ingeniería y Gestión de Activos: Desarrollo de ingeniería de detalle, metodologías BIM y soluciones GIS para la gestión de activos, redes e interferencias, incluyendo relevamientos de alta precisión que sirven como base confiable para diversos estudios de ingeniería. Monitoreo y Topografía de Obra: Control geométrico de obras civiles y montajes estructurales bajo estándares rigurosos, garantizando que la ejecución en campo coincida exactamente con el diseño de ingeniería. Oficina Técnica y Documentación As-Built: Certificación de obra y relevamientos detallados para el seguimiento técnico y cierre de proyectos, actuando como un brazo de ingeniería de respuesta inmediata en sitio. Acompañamos a nuestros clientes priorizando la eficiencia operativa y la agilidad de despliegue, asegurando que sus proyectos avancen sin cuellos de botella. Respaldamos nuestra gestión con certificaciones ISO 9001 e ISO 45001, garantizando altos estándares de calidad y seguridad ocupacional en sitio. INGEAP S.A.S. | PRECISION ENGINEERING AND SURVEYING FOR MINING, OIL & GAS, AND LARGE-SCALE INFRASTRUCTURE We are an engineering company specialized in transforming terrain data into precise operational decisions. Our field engineers and surveyors optimize the execution of megaprojects using cutting-edge technology—such as Drone Photogrammetry, High-End GPS, and Total Stations—guaranteeing geometric certainty to eliminate risks and cost overruns in complex environments. Our Specialized Solutions: Earthworks Control: Precise volume calculation through Digital Terrain Models (DTM) and pad layout tracing to ensure infrastructure is built on level and safe ground. Engineering and Asset Management: Detail engineering development, BIM methodologies, and GIS solutions for utility and interference management, including high-precision surveys that serve as a reliable baseline for various engineering studies. Construction Monitoring and Surveying: Geometric control of civil works and structural assemblies under rigorous standards, guaranteeing that field execution perfectly matches the engineering design. Technical Office and As-Built Documentation: Work certification and detailed surveys for technical monitoring and project closure, acting as an immediate-response engineering arm on-site. We support our clients by prioritizing operational efficiency and deployment agility, ensuring their projects move forward without bottlenecks. We back our operations with ISO 9001 and ISO 45001 certifications, and have been audited and validated with excellence scores by the country's leading operators, ensuring the highest standards of quality and occupational safety on site. | S49: https://ingeap.com/ | T49: No
A50: 49 | D50: INTERENERGY | E50: Argentina | F50: juanmontes.elo@gmail.com | H50: Expo San Juan Minera 2026 | I50: Prospecto | J50: Alta | K50: Identificar Jefe de Prevención/SSO; proponer piloto en frente de trabajo (perforación, transporte, campamento) | L50: Expo San Juan Minera 2026. | M50: Cliente final – contratista minero (operación, perforación, transporte, campamento) | N50: Isla: 26C-INF | O50: Exterior | R50: IntiEnergy es una empresa sanjuanina de servicios para mineria junior y exploración. Operamos con un equipo ágil, dimensionado al proyecto, con foco en reducir el impacto en cada campaña: energia solar móvil que disminuye el uso de diésel y gestión circular de residuos con trazabilidad documentada. Cubrimos desde la apertura de caminos y plataformas DDH/RC hasta el cierre del ciclo, en escala 15 a 30 personas. Liderada por Mercedes Soria, con el respaldo de la trayectoria del grupo Nielsen. | T50: No
A51: 50 | D51: JRI ARGENTINA | E51: Argentina | F51: info@grupocicon.com | H51: Expo San Juan Minera 2026 | I51: Prospecto | J51: Alta | K51: Identificar Jefe de Prevención/SSO; proponer piloto en frente de trabajo (perforación, transporte, campamento) | L51: Expo San Juan Minera 2026. También en: ExpoMina (ID 495). | M51: Cliente final – contratista minero (operación, perforación, transporte, campamento) | N51: D407 | O51: Pabellón 2 | R51: JRI Ingeniería Argentina es una empresa de ingeniería multidisciplinaria con base en San Juan, especializada en proyectos del sector minero. Contamos con un equipo humano altamente calificado, expertos en Minería, Plantas, Pipelines y Relaves. Ofrecemos servicios que abarcan toda la cadena de valor: desde estudios de perfil y prefactibilidad hasta ingeniería de detalle, asistencia a la construcción y puesta en marcha. Con 15 años de trayectoria en el mercado local e internacional, la empresa cuenta con un equipo de ingeniería multidisciplinario capaz de dar respuesta integral a proyectos de minería subterránea y a cielo abierto, incorporando tecnologías de diseño digitalizado BIM/PIM y metodologías avanzadas de gestión de trabajo AWP. Sus proyectos se han desarrollado en Argentina, Bolivia, Brasil, Perú, Ecuador, República Dominicana y otros países, consolidando una presencia internacional sostenida. JRI Argentina forma parte del Grupo JRI, referente de la ingeniería minera en Latinoamérica, y se posiciona como la propuesta local para proyectos que demanden rigor técnico, capital humano calificado y soluciones de ingeniería adaptadas a las particularidades de la minería argentina. | T51: ExpoMina (ID 495)
A52: 51 | D52: JSC SOLUCIONES INTEGRALES | E52: Argentina | F52: contacto@jscmining.com | H52: Expo San Juan Minera 2026 | I52: Prospecto | J52: Alta | K52: Identificar Jefe de Prevención/SSO; proponer piloto en frente de trabajo (perforación, transporte, campamento) | L52: Expo San Juan Minera 2026. | M52: Cliente final – contratista minero (operación, perforación, transporte, campamento) | N52: D411 | D426 | O52: Pabellón 2 | Q52: JSC MINNING S.A.S. | R52: JSC Soluciones Integrales ofrece servicios de alimentación, facility management y gestión de campamentos para proyectos mineros. Su misión es ofrecer una solución completa que permita a los operadores mineros concentrarse en su actividad y dejar en manos expertas los servicios de soporte. Brinda en forma integral los siguientes servicios: alimentación, limpieza, hotelería, lavandería, mantenimiento, administración de campamentos, gestión de proyectos, instalación de módulos. La gestión de calidad es uno de los pilares fundamentales de JSC Soluciones Integrales, con un equipo de calidad y seguridad de más de 50 profesionales y certificaciones ISO 9001, ISO 14001, ISO 45001 y HACCP. JSC cuenta con amplia experiencia en el trabajo conjunto con las comunidades locales, integrándolas en los proyectos mediante la incorporación de sus trabajadores, el desarrollo de proveedores, la realización de compras locales y talleres de capacitación. | S52: https://jscmining.com/ | T52: No
A53: 52 | D53: L & G LOGISTICA Y GASTRONOMIA | E53: Argentina | H53: Expo San Juan Minera 2026 | I53: Prospecto | J53: Alta | K53: Identificar Jefe de Prevención/SSO; proponer piloto en frente de trabajo (perforación, transporte, campamento) | L53: Expo San Juan Minera 2026. Sin email publicado. | M53: Cliente final – contratista minero (operación, perforación, transporte, campamento) | N53: Isla: 17 | O53: Exterior | Q53: L&G LOGISTICA Y GASTRONOMIA | T53: No
A54: 53 | D54: MAJOR DRILLING | E54: Argentina | F54: argentina@majordrilling.com | H54: Expo San Juan Minera 2026 | I54: Prospecto | J54: Alta | K54: Identificar Jefe de Prevención/SSO; proponer piloto en frente de trabajo (perforación, transporte, campamento) | L54: Expo San Juan Minera 2026. | M54: Cliente final – contratista minero (operación, perforación, transporte, campamento) | N54: D449 | D450 | O54: Pabellón 2 | Q54: MAJOR PERFORACIONES S.A. | R54: Major Drilling Group International Inc. es una de las mayores empresas de servicios de perforación del mundo, principalmente al servicio de la industria minera. Mantenemos operaciones de campo y oficinas en Canadá, Estados Unidos, México, Sudamérica, África y Australasia. Nuestros equipos globales especializados ofrecen un conjunto completo de servicios de perforación para proyectos tanto de superficie como subterráneos. | S54: https://www.majordrilling.com/ | T54: No
A55: 54 | D55: MAPAL SIGMA - MINING CONSTRUCTIONS | E55: Argentina | F55: tecnica@mapalsigma.com | H55: Expo San Juan Minera 2026 | I55: Prospecto | J55: Alta | K55: Identificar Jefe de Prevención/SSO; proponer piloto en frente de trabajo (perforación, transporte, campamento) | L55: Expo San Juan Minera 2026. | M55: Cliente final – contratista minero (operación, perforación, transporte, campamento) | N55: Isla: 1 | O55: Exterior | Q55: CONSORCIO MAPAL SIGMA | R55: MAPAL SIGMA, somos el resultado de la visión de dos empresas sanjuaninas de más de 60 años de experiencia en obras públicas y privadas. A través de nuestro consorcio impulsamos y potenciamos el desarrollo de servicios y obras en la minería, de exploración, civiles, viales, de arte e infraestructura, tanto en San Juan como en otras provincias del país. Contribuyendo al desarrollo y progreso sustentable del proyecto, la comunidad y la sociedad donde nos desenvolvemos. | S55: https://www.mapal.com.ar/mapalsigma | T55: No
A56: 55 | D56: MILICIC S.A. | E56: Argentina | F56: milicic@milicic.com.ar | H56: Expo San Juan Minera 2026 | I56: Prospecto | J56: Alta | K56: Identificar Jefe de Prevención/SSO; proponer piloto en frente de trabajo (perforación, transporte, campamento) | L56: Expo San Juan Minera 2026. | M56: Cliente final – contratista minero (operación, perforación, transporte, campamento) | N56: E541 | E557 | O56: Pabellón 2 | Q56: MILICIC S.A | R56: Somos una empresa argentina de construcciones y servicios con más 52 años de experiencia en grandes obras que han acompañado el desarrollo de los principales sectores productivos. Con más de 2000 colaboradores y más de 800 proyectos ejecutados, brindamos soluciones para los desafíos más complejos en minería, Oil & Gas, energía e infraestructura. Construimos confianza con nuestros clientes, socios y equipos en cada proyecto que desarrollamos. Buscamos soluciones con capacidad técnica y flexibilidad. Nos guía la orientación al cliente, el foco en resultados y la responsabilidad con el entorno. Con sede en Rosario, oficinas comerciales en la ciudad de Buenos Aires, una sede en el corazón de Vaca Muerta, en Añelo, la sede de Milicic Minería en San Juan, una sede en Lima, Perú y presencia en Uruguay y Paraguay, nos integramos al sector de empresas de servicios de alto valor agregado en Argentina y la región. | S56: https://www.milicic.com.ar/ | T56: No
A57: 56 | D57: MINEXO | E57: Argentina | F57: info@minexo.com.ar | H57: Expo San Juan Minera 2026 | I57: Prospecto | J57: Alta | K57: Identificar Jefe de Prevención/SSO; proponer piloto en frente de trabajo (perforación, transporte, campamento) | L57: Expo San Juan Minera 2026. | M57: Cliente final – contratista minero (operación, perforación, transporte, campamento) | N57: A138 | A139 | O57: Pabellón 1 | Q57: MINEXO SERVICIOS MINEROS SRL | R57: Minexo Servicios Mineros SRL esta comprometida desde hace 10 años a brindar soluciones de valor para la minería moderna. Nuestras areas de negocio incluyen: Herramental de corte de alta calidad para equipos mineros, Insumos y componentes para equipos de trituración, Repuestos y partes para perforadoras hidráulicas y equipos móviles de minería. La VISIÓN de MINEXO es crear relaciones duraderas con nuestros clientes para que nos consideren una pieza clave en la cadena de valor de sus empresas. La MISIÓN de MINEXO es brindar a los clientes la tranquilidad y confianza de que sus equipos estarán operativos, con el suministro adecuado de repuestos y componentes en el plazo necesario, con la calidad requerida y al precio justo. VALORES: COMPROMISO, GARANTÍA, CONFIABILIDAD. | S57: https://minexo.com.ar/ | T57: No
A58: 57 | D58: NAV CAMPAMENTOS | E58: Argentina | F58: info@navmodulos.com | H58: Expo San Juan Minera 2026 | I58: Prospecto | J58: Alta | K58: Identificar Jefe de Prevención/SSO; proponer piloto en frente de trabajo (perforación, transporte, campamento) | L58: Expo San Juan Minera 2026. | M58: Cliente final – contratista minero (operación, perforación, transporte, campamento) | N58: Isla: 80 | O58: Exterior | Q58: CAMPAMENTOS S.R.L. | R58: Campamentos S.R.L. es una empresa mendocina con más de 30 años de trayectoria dedicada al desarrollo de soluciones habitacionales y modulares para distintos sectores. A partir de nuestra experiencia en diseño, ingeniería y fabricación, desarrollamos NAV, nuestra línea de paneles y módulos habitacionales pensada para crear espacios funcionales, eficientes y adaptables a las necesidades de cada proyecto. Nuestras soluciones están diseñadas para responder a contextos exigentes, incluyendo entornos remotos o zonas inhóspitas, donde la rapidez de implementación, la durabilidad y la eficiencia son clave. Acompañamos a nuestros clientes en todas las etapas del proceso, desde el desarrollo de la idea hasta la implementación y el servicio postventa, brindando soluciones confiables, flexibles y de alta calidad. Productos y Servicios: Soluciones habitacionales modulares: diseño, fabricación e implementación de paneles y módulos NAV para la creación de espacios funcionales, eficientes y adaptables a cada proyecto. | S58: https://www.navmodulos.com/ | T58: No
A59: 58 | D59: NIELSEN EXPEDICIONES | E59: Argentina | F59: pablo.nielsen@nielsenexpediciones.com.ar | H59: Expo San Juan Minera 2026 | I59: Prospecto | J59: Alta | K59: Identificar Jefe de Prevención/SSO; proponer piloto en frente de trabajo (perforación, transporte, campamento) | L59: Expo San Juan Minera 2026. | M59: Cliente final – contratista minero (operación, perforación, transporte, campamento) | N59: Isla: 26C-INF | O59: Exterior | Q59: NIELSEN LOGISTICA Y EXPEDICIONE SA | Group Industry Suppliers | R59: Nielsen es un equipo de personas. Tres generaciones de operación en la misma cordillera construyeron un equipo que conoce el territorio, entiende los tiempos de la minería y responde desde zona — no desde una oficina en capital. Cuenta con, operadores, choferes y técnicos con experiencia probada en alta montaña. Personal aclimatado y capacitado para trabajar desde los 3.200 hasta los 5.500 msnm. Bases en Pocito e Iglesia, La Brea. Campamento propio, somos locales. Taller propio — Metalúrgica y Mecánica Personal especializado para fabricación, reparación y mantenimiento. Capacidad de respuesta sin esperar proveedor externo. Garantizamos la operación mediante una logística especializada integral para sitios remotos desde la exploración hasta la explotación. Pablo Nielsen CEO · Tercera Generación "La Minería tiene un rol protagónico para el cambio de la matriz energética mundial." | S59: https://nielsenexpediciones.com.ar/ | T59: No
A60: 59 | D60: OAPCE MULTITRANS Y CARGO TRANSFER CUYANA | E60: Argentina | F60: nicolas.fossati@oapce.com.ar | H60: Expo San Juan Minera 2026 | I60: Prospecto | J60: Alta | K60: Identificar Jefe de Prevención/SSO; proponer piloto en frente de trabajo (perforación, transporte, campamento) | L60: Expo San Juan Minera 2026. | M60: Cliente final – contratista minero (operación, perforación, transporte, campamento) | N60: A130 | A147 | O60: Pabellón 1 | Q60: OAPCE TRANSPORTES INTERNACIONALES S A | R60: Grupo OAPCE - Multitrans Sobre la empresa Con 40 años de trayectoria ininterrumpida en el mercado, Grupo OAPCE-Multitrans se posiciona como el socio estratégico líder en soluciones logísticas integrales y comercio exterior para industrias de alta complejidad. Nuestra especialización en Minería, Energía y Oil & Gas nos permite gestionar proyectos críticos con la precisión y seguridad que el sector demanda. Operamos bajo estándares internacionales de calidad (Certificación ISO 9001:2015) y contamos con una infraestructura propia que incluye terminales portuarias (PVC Terminals) y unidades de transferencia de carga diseñadas para optimizar la cadena de suministros en toda la región. Nuestros Servicios Logística de Proyectos (Project Cargo): Ingeniería logística para el movimiento de cargas sobredimensionadas y pesadas hacia yacimientos y plantas industriales. Comercio Exterior: Gestión aduanera integral, asesoramiento normativo y coordinación multimodal (Marítimo, Aéreo y Terrestre). Infraestructura Energética y Minera: Soluciones de almacenaje y logística de última milla en zonas de difícil acceso y alta montaña. Compliance: Procesos auditables y políticas de ética alineadas con los estándares de las principales compañías multinacionales. | S60: https://oapce.com.ar/ | T60: No
A61: 60 | D61: ORICA | E61: Argentina | F61: camila.bazan@orica.com | H61: Expo San Juan Minera 2026 | I61: Prospecto | J61: Alta | K61: Identificar Jefe de Prevención/SSO; proponer piloto en frente de trabajo (perforación, transporte, campamento) | L61: Expo San Juan Minera 2026. También en: Exponor (ID 58). | M61: Cliente final – contratista minero (operación, perforación, transporte, campamento) | N61: B235 | B236 | O61: Pabellón 1 | Q61: ORICA ARGENTINA SAIC | R61: Orica (ASX: ORI) es uno de los principales proveedores globales de soluciones para la minería y la infraestructura. Desde la producción y el suministro de explosivos, sistemas de detonación, productos químicos para la minería y monitoreo geotécnico, hasta nuestras soluciones digitales de vanguardia y una amplia gama de servicios, movilizamos de manera sostenible los recursos de la Tierra. Con 150 años de trayectoria, nuestro equipo global de más de 14.000 colaboradores apoya actualmente a clientes en operaciones de minería de superficie y subterránea, canteras, construcción y petróleo y gas. La sostenibilidad es una parte esencial de nuestras operaciones. Hemos establecido el objetivo de alcanzar emisiones netas cero para 2050 y estamos comprometidos a contribuir a los objetivos del Acuerdo de París. Obtenga más información en: www.orica.com | S61: https://orica.com/ | T61: Exponor (ID 58)
A62: 61 | D62: PARAMASSI ANDINA SRL | E62: Argentina | F62: gdg@paramassi.com.ar | H62: Expo San Juan Minera 2026 | I62: Prospecto | J62: Alta | K62: Identificar Jefe de Prevención/SSO; proponer piloto en frente de trabajo (perforación, transporte, campamento) | L62: Expo San Juan Minera 2026. | M62: Cliente final – contratista minero (operación, perforación, transporte, campamento) | N62: B222 | O62: Pabellón 1 | R62: Empresa Sanjuanina. Diseño, provisión e instalación de sistemas de protección en taludes de infraestructura de montaña, anti desprendimientos de rocas, anti avalanchas y control de erosión. Fragmentación de rocas, estudios geotécnicos y jardines verticales. | S62: https://www.paramassi.com.ar/ | T62: No
A63: 62 | D63: PUERTOTRANS | E63: Argentina | H63: Expo San Juan Minera 2026 | I63: Prospecto | J63: Alta | K63: Identificar Jefe de Prevención/SSO; proponer piloto en frente de trabajo (perforación, transporte, campamento) | L63: Expo San Juan Minera 2026. Sin email publicado. | M63: Cliente final – contratista minero (operación, perforación, transporte, campamento) | N63: A111 | A112 | A113 | A114 | A115 | A116 | A121 | A122 | A123 | A124 | A125 | A126 | Isla: 2A | Isla: 2B | Isla: 8A | Isla: 8B | Isla: 14A | Isla: 14B | O63: Pabellón 1 | P63: CASEMI | T63: No
A64: 63 | D64: SERVICIOS MINEROS DE AMERICA | E64: Argentina | H64: Expo San Juan Minera 2026 | I64: Prospecto | J64: Alta | K64: Identificar Jefe de Prevención/SSO; proponer piloto en frente de trabajo (perforación, transporte, campamento) | L64: Expo San Juan Minera 2026. Sin email publicado. | M64: Cliente final – contratista minero (operación, perforación, transporte, campamento) | N64: A111 | A112 | A113 | A114 | A115 | A116 | A121 | A122 | A123 | A124 | A125 | A126 | Isla: 2A | Isla: 2B | Isla: 8A | Isla: 8B | Isla: 14A | Isla: 14B | O64: Pabellón 1 | P64: CASEMI | Q64: SERVICIOS MINEROS DE AMERICA S.A.S. | T64: No
A65: 64 | D65: SOTUR | E65: Argentina | F65: mkarensosa@live.com.ar | H65: Expo San Juan Minera 2026 | I65: Prospecto | J65: Alta | K65: Identificar Jefe de Prevención/SSO; proponer piloto en frente de trabajo (perforación, transporte, campamento) | L65: Expo San Juan Minera 2026. | M65: Cliente final – contratista minero (operación, perforación, transporte, campamento) | N65: Isla: 8C | Isla: 14C | O65: Exterior | R65: Empresa con más de 20 años de experiencia en transporte de pasajeros, especializada en servicios para minería e industrias de alta exigencia. Brinda soluciones de traslado de personal a empresas públicas y privadas, destacándose por su seguridad, calidad y cumplimiento. Nacida en Jáchal, San Juan, como empresa familiar, ha crecido consolidándose en base a la excelencia operativa y el compromiso con sus clientes. | S65: https://sotur.com/ | T65: No
A66: 65 | D66: SYOTEC | E66: Argentina | F66: gabrilezarate@syotec.com.ar | H66: Expo San Juan Minera 2026 | I66: Prospecto | J66: Alta | K66: Identificar Jefe de Prevención/SSO; proponer piloto en frente de trabajo (perforación, transporte, campamento) | L66: Expo San Juan Minera 2026. | M66: Cliente final – contratista minero (operación, perforación, transporte, campamento) | N66: Isla: 18 | O66: Exterior | R66: En SYOTEC S.A.S. desarrollamos y ejecutamos soluciones para minería e industria, combinando trabajo en campo con automatización y optimización de procesos. Nos enfocamos en mejorar la productividad, asegurar la continuidad operativa y adaptar cada servicio a las condiciones reales de operación, con un fuerte respaldo técnico y compromiso con la seguridad. | S66: https://syotec.com.ar/ | T66: No
A67: 66 | D67: TAGING | E67: Argentina | H67: Expo San Juan Minera 2026 | I67: Prospecto | J67: Alta | K67: Identificar Jefe de Prevención/SSO; proponer piloto en frente de trabajo (perforación, transporte, campamento) | L67: Expo San Juan Minera 2026. Sin email publicado. | M67: Cliente final – contratista minero (operación, perforación, transporte, campamento) | N67: C301 | O67: Pabellón 1 | R67: Desde hace más de una década participa activamente en el desarrollo de proyectos mineros estratégicos en Argentina, con experiencia comprobada en litio, cobre, oro y plata, aportando ingeniería aplicada en contextos de alta complejidad técnica, geográfica y operativa. A través de su unidad TAGING CUYO, con base en la provincia de San Juan, la compañía acompaña el desarrollo de proyectos en la región, integrando conocimiento local, experiencia en ingeniería y estándares internacionales, y fomentando el empleo y el desarrollo regional. Brinda servicios integrales que incluyen: ● Ingeniería Conceptual, Básica y de Detalle. ● Ingeniería de Procesos y Optimización, con herramientas propias de simulación. ● Estudios técnicos y económicos (PEA, PFS, FS). ● Estudios de seguridad (HAZID, HAZOP, CHAZOP). ● Ingeniería de Valor y análisis de constructibilidad. ● Gerenciamiento de proyectos, planificación, supervisión, compras y contratos. ● Precomisionado, comisionado y puesta en marcha, con sistemas propios de gestión. Uno de los principales diferenciales es el enfoque en decisiones tempranas, entendiendo que gran parte de los riesgos, costos y plazos de un proyecto se definen antes de la etapa de construcción. Desde esta perspectiva, la ingeniería se convierte en una herramienta clave para reducir la incertidumbre y mejorar la viabilidad de los proyectos. TAGING cuenta con certificación internacional Trinorma: ISO 9001 (Gestión de Calidad), ISO 14001 (Gestión Ambiental) y ISO 45001 (Seguridad y Salud en el Trabajo). Lo que la posiciona como una empresa local con estándares globales. En línea con su enfoque tecnológico, TAGING dispone de soluciones propias como TAG-SYS, orientado a la gestión integral de proyectos, precomisionado y comisionado, y TAG-SIM, una plataforma de simulación de procesos que facilita la anticipación de escenarios, la optimización de diseños y la toma de decisiones basadas en datos. Con foco en eficiencia, sostenibilidad y excelencia técnica, TAGING CUYO se consolida como un socio estratégico para los desafíos actuales y futuros de la minería en San Juan y la región. | T67: No
A68: 67 | D68: TECMACO | E68: Argentina | F68: info@tecmaco.com.ar | H68: Expo San Juan Minera 2026 | I68: Prospecto | J68: Alta | K68: Identificar Jefe de Prevención/SSO; proponer piloto en frente de trabajo (perforación, transporte, campamento) | L68: Expo San Juan Minera 2026. | M68: Cliente final – contratista minero (operación, perforación, transporte, campamento) | N68: Isla: 34 | Isla: 40 | O68: Exterior | Q68: TECMACO INTEGRAL S.A. | R68: En Tecmaco, contamos con la flota más numerosa, amplia y tecnológica de Argentina, equipada para satisfacer cualquier necesidad de izaje. Nuestro departamento de ingeniería ofrece soluciones personalizadas para garantizar la seguridad y eficiencia en cada proyecto. Además, nuestros operadores están altamente capacitados, asegurando maniobras precisas y seguras en todo momento. | S68: https://www.tecmaco.com.ar/ | T68: No
A69: 68 | D69: TERRA LOGISTICA | E69: Argentina | H69: Expo San Juan Minera 2026 | I69: Prospecto | J69: Alta | K69: Identificar Jefe de Prevención/SSO; proponer piloto en frente de trabajo (perforación, transporte, campamento) | L69: Expo San Juan Minera 2026. Sin email publicado. | M69: Cliente final – contratista minero (operación, perforación, transporte, campamento) | N69: A111 | A112 | A113 | A114 | A115 | A116 | A121 | A122 | A123 | A124 | A125 | A126 | Isla: 2A | Isla: 2B | Isla: 8A | Isla: 8B | Isla: 14A | Isla: 14B | O69: Pabellón 1 | P69: CASEMI | Q69: TERRA LOGISTICA S.A. | T69: No
A70: 69 | D70: TRANSPORTE VESPRINI | E70: Argentina | H70: Expo San Juan Minera 2026 | I70: Prospecto | J70: Alta | K70: Identificar Jefe de Prevención/SSO; proponer piloto en frente de trabajo (perforación, transporte, campamento) | L70: Expo San Juan Minera 2026. Sin email publicado. | M70: Cliente final – contratista minero (operación, perforación, transporte, campamento) | N70: Isla: 69 | O70: Exterior | Q70: TRANSPORTE VESPRINI S.A. | R70: Transporte Vesprini, consolidada hace más de 50 años. Cuenta con 21 sucursales atendiendo a lo ancho y a lo largo de todo el país, brindando un servicio rápido, eficiente, confiable y seguro. Expertos en logística integral, nos encontramos habilitados para poder transportar todo tipo de carga, especialistas en soluciones logísticas. | T70: No
A71: 70 | D71: TRANSPORTES PAP | E71: Argentina | F71: liladelcid@transpap.com.ar | H71: Expo San Juan Minera 2026 | I71: Prospecto | J71: Alta | K71: Identificar Jefe de Prevención/SSO; proponer piloto en frente de trabajo (perforación, transporte, campamento) | L71: Expo San Juan Minera 2026. | M71: Cliente final – contratista minero (operación, perforación, transporte, campamento) | N71: Isla: 9 | Isla: 15 | O71: Exterior | R71: Creada en el año 1994, PAP, surge como una propuesta para el transporte de pasajeros, ofreciendo una modalidad que ninguna otra empresa ofrecía hasta el momento, transporte a medida de nuestros clientes. El éxito en éste segmento es el disparador para que comience un fuerte proceso de crecimiento, ampliando así la gama de servicios prestados y de especialización en la actividad de transporte y logística para la Industria y el Turismo. La capacidad operativa de nuestra compañía, conformada por personal altamente calificado, las más modernas unidades y tecnología de vanguardia, ha permitido a PAP tener participación en grandes obras, en los principales proyectos mineros del país, en viajes especiales y de turismo tanto en Argentina como en países limítrofes, procurando un servicio que supere las expectativas de nuestros clientes. Con la satisfacción del cliente, cuidado por el medio ambiente y la seguridad como pilares fundamentales para nuestro crecimiento, PAP ha logrado consolidarse como líder en el servicio de transporte y logística. | S71: https://transpap.com.ar/ | T71: No
A72: 71 | D72: WINDLAND | E72: Argentina | F72: jpmaricich@windland.com.ar | H72: Expo San Juan Minera 2026 | I72: Prospecto | J72: Alta | K72: Identificar Jefe de Prevención/SSO; proponer piloto en frente de trabajo (perforación, transporte, campamento) | L72: Expo San Juan Minera 2026. | M72: Cliente final – contratista minero (operación, perforación, transporte, campamento) | N72: Isla: 56 | O72: Exterior | Q72: WINDLAND S.A | R72: Windland S.A. es una empresa argentina con más de 30 años de trayectoria, especializada en servicios de alquiler de flota y mantenimiento integral, orientados principalmente a los sectores de petróleo, gas, minería y construcción. Fundada en 1994, la compañía ha evolucionado desde un esquema de rental de vehículos livianos hacia un modelo de servicios integrales, incorporando soluciones a medida para clientes corporativos, incluyendo alquiler con operario y gestión completa de flotas. A lo largo de su crecimiento, Windland ha desarrollado una sólida presencia territorial con bases operativas en Comodoro Rivadavia, Neuquén, San Juan, Catamarca y Salta, todas equipadas con talleres propios y capacidad de servicio en campo. La empresa cuenta actualmente con una flota de más de 650 unidades, compuesta mayormente por vehículos livianos, complementados con camiones y equipos viales, lo que le permite atender proyectos de diversa escala y complejidad. Su experiencia incluye la participación en proyectos de alta exigencia en el sector minero y energético, destacándose contratos de largo plazo con compañías líderes de la industria. El diferencial de Windland radica en su enfoque de servicio “tailor made”, adaptando sus soluciones a las necesidades específicas de cada cliente, combinado con una fuerte capacidad operativa, conocimiento del mercado y una estructura ágil. Actualmente, la compañía continúa su expansión mediante el fortalecimiento de su red de talleres, el desarrollo de alianzas estratégicas y la incorporación constante de unidades, atendiendo así la demanda de servicios de rental en el mercado. | S72: https://www.windland.com.ar/ | T72: No
A73: 72 | D73: ZLATO/DUMANDZIC | E73: Argentina | H73: Expo San Juan Minera 2026 | I73: Prospecto | J73: Alta | K73: Identificar Jefe de Prevención/SSO; proponer piloto en frente de trabajo (perforación, transporte, campamento) | L73: Expo San Juan Minera 2026. Sin email publicado. | M73: Cliente final – contratista minero (operación, perforación, transporte, campamento) | N73: A136 | A141 | O73: Pabellón 1 | R73: Nos especializamos en dar servicios a las empresas mineras con movimiento masivos de suelos, construcción de Valles de Lixiviación, Diques de Relave y Pozas para la producción de Litio, obras civiles, rental de equipos viales de grande, mediana y pequeña envergadura, construcción y mantenimiento de caminos. Vasta experiencia en trabajos de alta montaña, logística y manejo de maquinaria pesada. | T73: No
A74: 73 | D74: ALS SOLUCIONES TECNOLOGICAS | E74: Argentina | F74: alejandro@alsingenieria.com | H74: Expo San Juan Minera 2026 | I74: Prospecto | J74: Alta | K74: Mapear oferta: evaluar integración (telemetría, comunicaciones, IA) o competencia | L74: Expo San Juan Minera 2026. | M74: Partner tecnológico / competidor | N74: C306 | C307 | C315 | C316 | C317 | O74: Pabellón 1 | P74: AHK - CÁMARA DE INDUSTRIA Y COMERCIO ARGENTINO-ALEMANA | R74: ALS Soluciones Tecnológicas SRL impulsa la transformación hacia la Industria 4.0 mediante soluciones de automatización y control de procesos, integrando data analytics, edge computing e inteligencia artificial para habilitar la toma de decisiones en tiempo real. Con más de 20 años de experiencia en diversas industrias y como Solution Partner de Siemens en Automation and Drives, diseñamos e implementamos tecnologías de vanguardia que optimizan la producción, reducen costos y elevan la eficiencia y confiabilidad operativa de nuestros clientes. | S74: https://www.alsingenieria.com/ | T74: No
A75: 74 | D75: DATAWISE | E75: Argentina | F75: info@datawise.com.ar | H75: Expo San Juan Minera 2026 | I75: Prospecto | J75: Alta | K75: Mapear oferta: evaluar integración (telemetría, comunicaciones, IA) o competencia | L75: Expo San Juan Minera 2026. | M75: Partner tecnológico / competidor | N75: D414 | O75: Pabellón 2 | R75: Datawise S.A. es una compañía argentina especializada en soluciones tecnológicas integrales, orientadas a la transformación digital de organizaciones públicas y privadas. Con una sólida trayectoria en el mercado, ofrece servicios de infraestructura IT, nube, ciberseguridad, networking y soluciones de valor agregado. A través de alianzas estratégicas con fabricantes líderes como HPE, HP Inc., Aruba, Cisco y otros, Datawise diseña, implementa y gestiona arquitecturas tecnológicas de alto rendimiento, adaptadas a las necesidades de cada cliente. Su enfoque combina expertise técnico, visión consultiva y acompañamiento continuo, permitiendo optimizar costos, mejorar la eficiencia operativa y potenciar la innovación en entornos críticos de negocio. | S75: https://www.datawise.com.ar/ | T75: No
A76: 75 | D76: DEKA LYSEIS | E76: Argentina | H76: Expo San Juan Minera 2026 | I76: Prospecto | J76: Alta | K76: Mapear oferta: evaluar integración (telemetría, comunicaciones, IA) o competencia | L76: Expo San Juan Minera 2026. Sin email publicado. | M76: Partner tecnológico / competidor | N76: E536 | E537 | E538 | E542 | E543 | E544 | E545 | E546 | E552 | E553 | E554 | E555 | E556 | O76: Pabellón 2 | P76: CLÚSTER DE PETRÓLEO GAS Y MINERÍA DE CORDOBA | Q76: DEKA LYSEIS S. A. | R76: Deka Lýseis, Resellers de soluciones y softwares Lideramos el proceso de Transformación Digital para mejorar la Gestión de Proyectos poniendo el foco en la Metodología BIM. Implementamos soluciones basadas en productos AUTODESK Estamos comprometidos a brindar un servicio excepcional, apoyo técnico especializado y una experiencia de alta calidad, para construir relaciones duraderas y fomentar el crecimiento mutuo. Somos Resellers GOLD de Autodesk Brindamos soluciones para las industrias de manufacturas, infraestructuras, construcción, medios y entretenimiento y datos transmitidos vía inalámbrica, de Autodesk. Líder en software de diseño 3D, ingeniería y entretenimiento. Somos ATC ATC (Authorized Training Center) Centro de Capacitación Autorizado (ATC, por sus siglas en inglés) por Autodesk. DekaLýseis esta autorizada por Autodesk para proporcionar formación oficial y de alta calidad en sus productos de software. Nuestra misión: Ofrecer soluciones innovadoras, personalizadas y transformadoras, para satisfacer las exigencias de nuestros socios, ayudándoles a mejorar su eficiencia, productividad y competitividad en el mercado. Nos comprometemos a brindar un servicio excepcional, apoyo técnico especializado y una experiencia de alta calidad, para construir relaciones duraderas y fomentar el crecimiento mutuo. Aseguramos poder transformar los desafíos de nuestros clientes en oportunidades mediante soluciones de vanguardia, entregando valor y resultados medibles que superen sus expectativas. Construimos el Puente hacia la Excelencia en AECO Somos una compañía global líder con más de 3 años de experiencia, destacándonos en la innovación de activos digitales mediante la aplicación de metodología BIM. Nuestro equipo: Lideramos la Industria AECO con Amplia Trayectoria DekaLýseis cuenta con un equipo de expertos altamente capacitados en diferentes disciplinas. Nuestros equipo incluye asesores, especialistas en VDC/BIM, y expertos en gemelos digitales y VR, todos con certificaciones diversas en sus respectivos campos y capacitaciones en gestión de proyectos. Nuestros valores: Impulsamos el Éxito con Cimientos Sólidos | T76: No
A77: 76 | D77: DISEGNO | E77: Argentina | F77: MARKETING@DISEGNOSOFT.COM.AR | H77: Expo San Juan Minera 2026 | I77: Prospecto | J77: Alta | K77: Mapear oferta: evaluar integración (telemetría, comunicaciones, IA) o competencia | L77: Expo San Juan Minera 2026. | M77: Partner tecnológico / competidor | N77: E517 | O77: Pabellón 2 | Q77: DISEGNO SOFT S.R.L. | R77: Somos una empresa dedicada a proveer una solución completa e innovadora de alta tecnología a nuestros clientes, abarcando todos los procesos empresariales, desde el diseño (CAD CAE), fabricación (CAM), gestión de información asociada a proyectos (PDM) y gestión integrada de procesos productivos (ERP). Así cumpliendo con el ciclo 360° desde la idea a la realidad (PLM). | S77: https://disegnosoft.com.ar/ | T77: No
A78: 77 | D78: GAMT | E78: Argentina | F78: comercial@gamtgroup.com | H78: Expo San Juan Minera 2026 | I78: Prospecto | J78: Alta | K78: Mapear oferta: evaluar integración (telemetría, comunicaciones, IA) o competencia | L78: Expo San Juan Minera 2026. | M78: Partner tecnológico / competidor | N78: D408 | O78: Pabellón 2 | Q78: GAMT TEST & MEASUREMENT SRL | R78: GAMT es una empresa referente en ingeniería de precisión, especializada en soluciones de test, medición, monitoreo y automatización industrial. Integramos servicios de ingeniería avanzada y tecnologías de monitoreo continuo para optimizar la confiabilidad y eficiencia de activos industriales. Hemos desarrollado proyectos con empresas líderes del sector minero, energético e industrial, acompañando a nuestros clientes desde el diagnóstico técnico hasta la implementación de soluciones especializadas. | S78: https://gamtgroup.com/ | T78: No
A79: 78 | D79: GEOSISTEMAS | E79: Argentina | H79: Expo San Juan Minera 2026 | I79: Prospecto | J79: Alta | K79: Mapear oferta: evaluar integración (telemetría, comunicaciones, IA) o competencia | L79: Expo San Juan Minera 2026. Sin email publicado. | M79: Partner tecnológico / competidor | N79: A146 | O79: Pabellón 1 | Q79: GEOSISTEMAS S.R.L | R79: Somos una empresa Argentina proveedora de soluciones de geoposicionamiento, tecnología geoespacial y sistemas GNSS para ingeniería, construcción y agricultura de precisión, certificada bajo las normas ISO-9001 y TUV. Trabajamos apasionadamente en innovar, para mejorar la productividad, la eficiencia y la seguridad de nuestros clientes. | T79: No
A80: 79 | D80: GEOTAB | E80: Argentina | H80: Expo San Juan Minera 2026 | I80: Prospecto | J80: Alta | K80: Mapear oferta: evaluar integración (telemetría, comunicaciones, IA) o competencia | L80: Expo San Juan Minera 2026. Sin email publicado. También en: Exponor (ID 114). | M80: Partner tecnológico / competidor | N80: Isla: 50 | O80: Exterior | S80: https://www.geotab.com/ | T80: Exponor (ID 114)
A81: 80 | D81: GHM SATELITAL SRL | E81: Argentina | F81: gerencia@ghmsatelital.ar | H81: Expo San Juan Minera 2026 | I81: Prospecto | J81: Alta | K81: Mapear oferta: evaluar integración (telemetría, comunicaciones, IA) o competencia | L81: Expo San Juan Minera 2026. | M81: Partner tecnológico / competidor | N81: Isla: 14E | O81: Exterior | R81: Ofrecemos conectividad, monitoreo, energía, meteorología y soluciones tecnológicas para minería, energía e industria. Priorizamos no solo la eficiencia operativa, sino también el bienestar de las comunidades y los trabajadores. | S81: https://ghmsatelital.com/ | T81: No
A82: 81 | D82: GREENWORKING | E82: Argentina | F82: info@greenworking.com.ar | H82: Expo San Juan Minera 2026 | I82: Prospecto | J82: Alta | K82: Mapear oferta: evaluar integración (telemetría, comunicaciones, IA) o competencia | L82: Expo San Juan Minera 2026. | M82: Partner tecnológico / competidor | N82: F644 | F649 | O82: Pabellón 2 | R82: Infraestructura de redes de Cobre y Fibra Óptica. Diseño y armado de Data Centers y Salas técnicas. Sistemas de Seguridad Electrónica (CCTV, CCAA) Electricidad y Energía de respaldo. Diseño y armado de Suelos Elevados (piso técnico). Climatización. | S82: https://greenworking.com.ar/ | T82: No
A83: 82 | D83: I-POINT S. A. S. | E83: Argentina | F83: victor.cornejo@puntoi.ar | H83: Expo San Juan Minera 2026 | I83: Prospecto | J83: Alta | K83: Mapear oferta: evaluar integración (telemetría, comunicaciones, IA) o competencia | L83: Expo San Juan Minera 2026. | M83: Partner tecnológico / competidor | N83: A111 | A112 | A113 | A114 | A115 | A116 | A121 | A122 | A123 | A124 | A125 | A126 | Isla: 2A | Isla: 2B | Isla: 8A | Isla: 8B | Isla: 14A | Isla: 14B | O83: Pabellón 1 | P83: CASEMI | R83: En Punto I, contamos con más de 10 años de experiencia brindando soluciones tecnológicas innovadoras que conectan personas y empresas, superando cualquier barrera geográfica. Somos integradores de soluciones de comunicaciones, especializados en: Infraestructura de Red Sistema inteligente de seguridad (Videovigilancia- Control de Accesos) Internet Satelital Seguimiento de Flota LTE y Satelital. (control de somnolencia, métricas de manejo, etc). | S83: https://puntoi.ar/ | T83: No
A84: 83 | D84: INTERSAT SA | E84: Argentina | H84: Expo San Juan Minera 2026 | I84: Prospecto | J84: Alta | K84: Mapear oferta: evaluar integración (telemetría, comunicaciones, IA) o competencia | L84: Expo San Juan Minera 2026. Sin email publicado. | M84: Partner tecnológico / competidor | N84: Isla: 27-INF | O84: Exterior | R84: Intersat SA es una empresa argentina de comunicaciones y tecnología, especializada en conectividad de alta disponibilidad e integración de soluciones tecnológicas críticas. Con base en la provincia de San Juan, desarrollamos infraestructura digital diseñada para entornos productivos, industriales y gubernamentales, incluso en ubicaciones remotas o de alta complejidad. Nos enfocamos en soluciones reales, escalables y confiables, combinando infraestructura propia, tecnología líder mundial y un profundo conocimiento del territorio. | T84: No
A85: 84 | D85: ISTRA | E85: Argentina | F85: contacto@istraservicios.com | H85: Expo San Juan Minera 2026 | I85: Prospecto | J85: Alta | K85: Mapear oferta: evaluar integración (telemetría, comunicaciones, IA) o competencia | L85: Expo San Juan Minera 2026. | M85: Partner tecnológico / competidor | N85: A111 | A112 | A113 | A114 | A115 | A116 | A121 | A122 | A123 | A124 | A125 | A126 | Isla: 2A | Isla: 2B | Isla: 8A | Isla: 8B | Isla: 14A | Isla: 14B | O85: Pabellón 1 | P85: CASEMI | Q85: JUAN FRANCISCO RUEDIN | R85: Somo una empresa sanjuanina especializadas en: -TELECOMUNICACIONES -OBRAS ELECTRICAS E INGENIERIA DEL TRANSITO -AUTOMATIZACION Y CONTROL Nuestros servicios son escabeles a las necesidades del cliente. | S85: https://istra.com.ar/ | T85: No
A86: 85 | D86: MAKERS SAS | E86: Argentina | F86: matias.junco@mmakers.ar | H86: Expo San Juan Minera 2026 | I86: Prospecto | J86: Alta | K86: Mapear oferta: evaluar integración (telemetría, comunicaciones, IA) o competencia | L86: Expo San Juan Minera 2026. Software e IA a medida para minería (posible competidor/aliado). | M86: Partner tecnológico / competidor | N86: A111 | A112 | A113 | A114 | A115 | A116 | A121 | A122 | A123 | A124 | A125 | A126 | Isla: 2A | Isla: 2B | Isla: 8A | Isla: 8B | Isla: 14A | Isla: 14B | O86: Pabellón 1 | P86: CASEMI | Q86: SOFTWARE MAKERS S. A. S. | R86: Desarrollamos software a medida e inteligencia artificial para empresas mineras e industriales que están perdiendo tiempo y dinero por procesos manuales, falta de control y sistemas que no se adaptan a su operación. Implementamos soluciones modulares que en 60 a 90 días ponen en producción un primer sistema funcional que resuelve un problema crítico, sin frenar la operación. Nos especializamos en: - Digitalización de operaciones (Órdenes de trabajo, mantenimiento, logística) - Integraciones con ERP existentes (Tango, SAP, etc.) - Inteligencia Artificial aplicada a datos operativos - Sistemas de higiene y seguridad con análisis predictivo +10 años de experiencia, +50.000 horas de desarrollo y más de 30 clientes activos en industria, minería y transporte. Nuestro foco no es vender software. Es eliminar pérdidas operativas reales. | S86: https://mmakers.ar/ | T86: No
A87: 86 | D87: MARIO ZINI & CIA S.R.L | E87: Argentina | F87: info@mariozini.com | H87: Expo San Juan Minera 2026 | I87: Prospecto | J87: Alta | K87: Mapear oferta: evaluar integración (telemetría, comunicaciones, IA) o competencia | L87: Expo San Juan Minera 2026. | M87: Partner tecnológico / competidor | N87: A156 | A157 | A158 | O87: Pabellón 1 | R87: Comunicaciones Críticas para Minería Mario Zini es una empresa especializada en el diseño, implementación y mantenimiento de sistemas de comunicaciones críticas, con fuerte foco en el sector minero. Acompañamos a nuestros clientes en entornos desafiantes, brindando soluciones confiables que garantizan conectividad, seguridad y continuidad operativa. ⛰️ Experiencia en Entornos Extremos Con amplia trayectoria en alta montaña y zonas remotas, desarrollamos proyectos integrales que incluyen: • Ingeniería y diseño de redes • Provisión de equipamiento • Instalación de sistemas • Soporte técnico en campo 📡 Soluciones Integrales Ofrecemos soluciones completamente integradas adaptadas a la operación minera, asegurando: • Comunicaciones de alta disponibilidad, eficiencia y operatividad. • Cobertura confiable en zonas remotas • Infraestructura robusta y escalable 🏆 Alianza Estratégica Como Socio de Negocios Platinum de Motorola Solutions, brindamos: • Acceso a tecnología de vanguardia • Estándares internacionales y mejores prácticas • Acompañamiento estratégico a largo plazo 🚀 Nuestro Compromiso Conectamos lo que la minería no puede detener. Comunicaciones confiables para operaciones más seguras y eficientes en los entornos más exigentes. | S87: https://mariozini.com/ | T87: No
A88: 87 | D88: MC MONITOREO & CONTROL DE PERFORACION | E88: Argentina | F88: info@mcim.com.ar | H88: Expo San Juan Minera 2026 | I88: Prospecto | J88: Alta | K88: Mapear oferta: evaluar integración (telemetría, comunicaciones, IA) o competencia | L88: Expo San Juan Minera 2026. | M88: Partner tecnológico / competidor | N88: A127 | O88: Pabellón 1 | Q88: MC INSTALACIONES MANTENIMIENTO | R88: Instalación de sistemas de instrumentación electrónica, con transmisión y visualización de datos en tiempo real; para equipos y maquinas que requieran monitoreo, control y supervisión sobre su funcionamiento y operación. | T88: No
A89: 88 | D89: MINETECH | E89: Argentina | F89: info@minetech.com.ar | H89: Expo San Juan Minera 2026 | I89: Prospecto | J89: Alta | K89: Mapear oferta: evaluar integración (telemetría, comunicaciones, IA) o competencia | L89: Expo San Juan Minera 2026. Socio de Motorola Solutions y MSA en minería (comunicaciones y seguridad). | M89: Partner tecnológico / competidor | N89: E505 | E506 | O89: Pabellón 2 | Q89: MINETECH S.R.L. | R89: MineTech es una empresa líder con amplia trayectoria en el sector minero, especializada en la integración de soluciones tecnológicas y de seguridad. Nos destacamos por proveer sistemas de comunicación críticos, infraestructura de radioenlaces, refugios para minería subterránea, medición de variables ambientales, entre otros. Trabajamos junto a socios estratégicos como Motorola Solutions y MSA para garantizar la máxima calidad en cada proyecto. Con presencia en los principales proyectos mineros del país, transformamos la experiencia técnica en resultados confiables para nuestros clientes. | S89: https://www.minetech.com.ar/ | T89: No
A90: 89 | D90: ORIGAMI SOFTWARE | E90: Argentina | F90: info@origami-soft.com | H90: Expo San Juan Minera 2026 | I90: Prospecto | J90: Alta | K90: Mapear oferta: evaluar integración (telemetría, comunicaciones, IA) o competencia | L90: Expo San Juan Minera 2026. | M90: Partner tecnológico / competidor | N90: F615 | O90: Pabellón 2 | R90: En Origami Software somos una empresa tecnológica con base en Mendoza. Nos especializamos en brindar soluciones a procesos empresariales basadas en tecnología, destacando implementaciones de ERP Odoo (Partner Gold, único del oeste argentino). Con más de 15 años de experiencia y 500+ proyectos ejecutados, entendemos los desafíos de la transformación digital en industrias complejas. Nuestros servicios incluyen: Implementaciones Odoo ERP Desarrollo de software a medida (webs y webapps) Integración de sistemas Automatización e IA aplicada (agentes inteligentes, integración de APIs) Consultoría de procesos Lo que nos diferencia es nuestro enfoque orientado al negocio. No somos solo desarrolladores: contamos con especialistas en industria, consultores de procesos y profesionales que entienden el contexto empresarial de nuestros clientes. Analizamos profundamente tus necesidades, procesos y objetivos para crear soluciones tecnológicas que realmente generan impacto en tu organización. Nos guían valores como la ética, el respeto, la empatía y el compromiso con tu negocio. Somos certificados como Great Place to Work, demostrando nuestro compromiso con la excelencia organizacional. | S90: https://www.origami-soft.com/ | T90: No
A91: 90 | D91: SITRACK | E91: Argentina | F91: claudio.galindez@sitrack.com | H91: Expo San Juan Minera 2026 | I91: Prospecto | J91: Alta | K91: Mapear oferta: evaluar integración (telemetría, comunicaciones, IA) o competencia | L91: Expo San Juan Minera 2026. También en: Exponor (ID 151). | M91: Partner tecnológico / competidor | N91: Isla: 6DER | O91: Exterior | R91: Fundada en 1999, somos una empresa de alta tecnología dedicada a la provisión de servicios de información a medida. Colaboramos estrechamente con nuestros clientes en el desarrollo de herramientas adaptadas a su operatoria y necesidades, aportando soluciones integrales de servicio a los sectores Logístico, Naviero, Petrolero, Residuo, Maquinaria, Dadores de Carga y Diagnóstico, entre otros. Nuestra empresa posee oficinas y operación 24/7 en Argentina, Brasil, Chile, Uruguay y México, siendo la única empresa que abarca totalmente el corredor Bioceánico, y que además desarrollamos una de las más amplias redes de instalación y servicios de Sudamérica. En la actualidad, más de 250 profesionales altamente capacitados desarrollan y operan los diferentes sistemas que prestan servicio a más de 100.000 móviles distribuidos en las principales empresas de América Latina. | S91: https://www.sitrack.com/ | T91: Exponor (ID 151)
A92: 91 | D92: SLIMSTOCK (ALAMO) | E92: Países Bajos | F92: info@alamoconsultores.com | H92: Expo San Juan Minera 2026 | I92: Prospecto | J92: Alta | K92: Mapear oferta: evaluar integración (telemetría, comunicaciones, IA) o competencia | L92: Expo San Juan Minera 2026. También en: Exponor (ID 1182). | M92: Partner tecnológico / competidor | N92: D409 | D410 | D427 | O92: Pabellón 2 | P92: NETHERLANDS / PAISES BAJOS | Q92: SLIMSTOCK B.V. | R92: Para competir necesitas una cadena de suministro eficiente Alcanzar la excelencia operativa debería ser sencillo. Por eso desarrollamos nuestra plataforma Slim4, galardonada en múltiples ocasiones, para que la planificación integral de la cadena de suministro sea fácil para todos. Impulsada por inteligencia artificial, Slim4 ofrece una solución integrada que unifica planificación, ejecución y datos en una única plataforma inteligente. De confianza para mayoristas, minoristas y fabricantes, el motor de Slim4 respalda a tus equipos y procesos para ayudarte a tomar decisiones mejores, más rápidas y más inteligentes en toda tu cadena de suministro. | S92: https://alamoconsultores.com/slimstock/ | T92: Exponor (ID 1182)
A93: 92 | D93: TCTECH SRL | E93: Argentina | F93: comercial@nexarnetworks.com.ar | H93: Expo San Juan Minera 2026 | I93: Prospecto | J93: Alta | K93: Mapear oferta: evaluar integración (telemetría, comunicaciones, IA) o competencia | L93: Expo San Juan Minera 2026. | M93: Partner tecnológico / competidor | N93: E536 | E537 | E538 | E542 | E543 | E544 | E545 | E546 | E552 | E553 | E554 | E555 | E556 | O93: Pabellón 2 | P93: CLÚSTER DE PETRÓLEO GAS Y MINERÍA DE CORDOBA | R93: En Nexar Networks desarrollamos soluciones de conectividad crítica para la industria minera mediante redes celulares privadas 4G y 5G (Private LTE / Private 5G), diseñadas para operar en entornos remotos, exigentes y de alta disponibilidad. La minería moderna necesita comunicaciones seguras, estables y de baja latencia para soportar operaciones estratégicas donde las redes públicas no llegan y donde el Wi-Fi industrial presenta limitaciones de cobertura, movilidad y escalabilidad. Nuestras soluciones permiten: - cobertura amplia y confiable en mina, planta y operaciones remotas - conectividad segura para personal, maquinaria y sensores - baja latencia para aplicaciones críticas - control total de la red y soberanía de los datos - integración con plataformas industriales y sistemas existentes Habilitamos casos de uso como: - teleoperación de maquinaria pesada - monitoreo SCADA en tiempo real - vehículos autónomos y AGVs - videovigilancia y seguridad operacional - IoT industrial y sensorización masiva - comunicaciones de misión crítica (MCPTT / Push-to-Talk) Brindamos una solución integral end-to-end: - ingeniería y diseño de cobertura RF - despliegue de infraestructura RAN y Core EPC / 5GC - integración con satélite, fibra y backhaul de campo - operación, soporte y mantenimiento continuo Transformamos la conectividad en una ventaja competitiva, mejorando productividad, seguridad y eficiencia operativa para la minería del futuro. | S93: https://www.nexarnetworks.com.ar/ | T93: No
A94: 93 | D94: TCV DESARROLLO DE SOLUCIONES | E94: Argentina | F94: info@tcvsoluciones.com | H94: Expo San Juan Minera 2026 | I94: Prospecto | J94: Alta | K94: Mapear oferta: evaluar integración (telemetría, comunicaciones, IA) o competencia | L94: Expo San Juan Minera 2026. Competidor directo: videovigilancia con IA contra fatiga, somnolencia y distracción en flotas. | M94: Partner tecnológico / competidor | N94: A111 | A112 | A113 | A114 | A115 | A116 | A121 | A122 | A123 | A124 | A125 | A126 | Isla: 2A | Isla: 2B | Isla: 8A | Isla: 8B | Isla: 14A | Isla: 14B | O94: Pabellón 1 | P94: CASEMI | Q94: TCV DESARROLLO DE SOLUCIONES S. R. L. | R94: En TCV trabajamos en soluciones tecnologicas enfocadas en fortalecer las operaciones vehiculares. Desarrollamos e implementamos sistemas de videovigilancia con inteligencia artificial, orientadas a optimizar procesos y mejorar la toma de decisiónes frente a una problematica tan grande como los accidentes debido a fatiga, somnolencia y distracciones. Con una fuerte orientación a resultados y adaptación a entornos exigentes, TCV se posiciona como un socio estratégico para empresas que priorizan la seguridad operativa, la reducción de riesgos y la optimización de sus operaciones. | S94: https://www.tcvsoluciones.com.ar/ | T94: No
A95: 94 | D95: TECHNOLOGY BUREAU - NOKIA | E95: Argentina | H95: Expo San Juan Minera 2026 | I95: Prospecto | J95: Alta | K95: Mapear oferta: evaluar integración (telemetría, comunicaciones, IA) o competencia | L95: Expo San Juan Minera 2026. Sin email publicado. | M95: Partner tecnológico / competidor | N95: Isla: 21SUP | O95: Exterior | R95: Technology Bureau es una empresa Latinoamericana dedicada a brindar soluciones integrales de Telecomunicación IT. Con más de 30 años de experiencia, se posiciona como un socio tecnológico que acompaña a empresas, operadores y gobiernos en sus procesos de transformación digital. Su propuesta se basa en ofrecer soluciones “end to end”, combinando tecnología, ingeniería y servicios: desde el diseño e implementación hasta el soporte de proyectos tecnológicos complejos. | T95: No
A96: 95 | D96: TESACOM | E96: Argentina | F96: info@tesacom.net | H96: Expo San Juan Minera 2026 | I96: Prospecto | J96: Alta | K96: Mapear oferta: evaluar integración (telemetría, comunicaciones, IA) o competencia | L96: Expo San Juan Minera 2026. También en: Directorio SSO (ID 181). | M96: Partner tecnológico / competidor | N96: D400 | D401 | D402 | D403 | D417 | D418 | D419 | D420 | D438 | D439 | D459 | D460 | D461 | E500 | E509 | E525 | E526 | E527 | E528 | O96: Pabellón 2 | P96: GAPP | Q96: TESAM ARGENTINA S.A. | R96: Telecomunicaciones Satelitales e IoT para Operaciones Industriales Somos una empresa con +25 años de trayectoria en telecomunicaciones satelitales para operaciones industriales en Latinoamérica. Nos mueve el desafío de impulsar el desarrollo productivo en nuestra región. Comercializamos e integramos productos y servicios de proveedores como Iridium, Viasat-Inmarsat, Pulsar Internacional, Starlink, KVH, Orbcomm, Globalstar, Skywave. Desarrollamos plataformas y hardware para el monitoreo de activos creando una propuesta de valor integral para los principales sectores productivos. Contamos con oficinas comerciales en Argentina, Chile, Perú y Paraguay. | S96: https://www.tesacom.net/ | T96: Directorio SSO (ID 181)
A97: 96 | D97: TRIM STUDIOS SRL - SYTEX | E97: Argentina | F97: info@sytex.io | H97: Expo San Juan Minera 2026 | I97: Prospecto | J97: Alta | K97: Mapear oferta: evaluar integración (telemetría, comunicaciones, IA) o competencia | L97: Expo San Juan Minera 2026. | M97: Partner tecnológico / competidor | N97: E536 | E537 | E538 | E542 | E543 | E544 | E545 | E546 | E552 | E553 | E554 | E555 | E556 | O97: Pabellón 2 | P97: CLÚSTER DE PETRÓLEO GAS Y MINERÍA DE CORDOBA | Q97: TRIM STUDIOS SRL | R97: En Sytex digitalizamos y damos control en tiempo real a la operación en campo. Centralizamos tareas, avances y evidencia (fotos, datos, checklists) en una sola plataforma, validada con IA para asegurar calidad y trazabilidad desde el origen. Eliminamos planillas y reportes tardíos, dando visibilidad y control a operaciones con múltiples frentes y contratistas. Más de 15.000 técnicos en LATAM ya usan Sytex para ejecutar mejor y decidir con información confiable. | S97: https://es.sytex.io/ | T97: No
A98: 97 | D98: AMERICAN ADVISOR | E98: Argentina | H98: Expo San Juan Minera 2026 | I98: Prospecto | J98: Alta | K98: Explorar alianza comercial / canal de implementación y formación en seguridad | L98: Expo San Juan Minera 2026. Sin email publicado. | M98: Canal / aliado – consultoría, capacitación y certificación | N98: A111 | A112 | A113 | A114 | A115 | A116 | A121 | A122 | A123 | A124 | A125 | A126 | Isla: 2A | Isla: 2B | Isla: 8A | Isla: 8B | Isla: 14A | Isla: 14B | O98: Pabellón 1 | P98: CASEMI | Q98: AMERICAN ADVISOR -ESTANDAR CO S.R.L.- | R98: AMERICAN ADVISOR es una empresa con un enfoque integral, creada bajo el concepto de Centro Modelo, orientada a acompañar a organizaciones, instituciones e industrias en el desarrollo eficiente y seguro de su recurso humano, promoviendo el bienestar de los colaboradores, la prevención de riesgos y el cuidado del medioambiente. Nuestro equipo interdisciplinario brinda soluciones estratégicas y a medida, con presencia clave en actividades mineras, industriales y productivas de la región. Nos especializamos en servicios como: Medicina Laboral (Asesoramiento y Exámenes Médicos), Medicina en Sitios Remotos (Asistencia, Emergencia y Urgencia), Capacitaciones y Certificaciones de Operarios y Conductores Profesionales, Inspección y Certificación de Equipos de Izaje, Viales y Subterráneos, Servicios y Asesoramiento en Higiene y Seguridad Laboral; integrando infraestructura propia, equipamiento de vanguardia y personal capacitado para garantizar calidad, eficiencia y resultados confiables. En American Advisor trabajamos bajo estándares nacionales e internacionales, con una gestión profesional basada en mejora continua. Por eso, somos orgullosamente una organización CERTIFICADA TRINORMA, cumpliendo con los requisitos de ISO 9001:2015 (Gestión de la Calidad), ISO 14001:2015 (Gestión Ambiental) e ISO 45001:2018 (Seguridad y Salud en el Trabajo). Estas certificaciones reflejan nuestro compromiso con procesos sólidos, sustentabilidad, prevención y excelencia operativa en cada prestación. Además, contamos con la ACREDITACION DEL OAA como Organismo de Inspección, respaldando técnica y legalmente inspecciones y certificaciones de equipos bajo normas reconocidas. Este diferencial convierte a AMERICAN ADVISOR en la ÚNICA empresa de la provincia de San Juan certificada y acreditada bajo estos estándares, consolidándonos como un aliado estratégico para compañías que buscan cumplimiento normativo, confiabilidad y prestigio en sus operaciones! | T98: No
A99: 98 | D99: ARCADIS | E99: Países Bajos | F99: info.cl@arcadis.com | H99: Expo San Juan Minera 2026 | I99: Prospecto | J99: Alta | K99: Explorar alianza comercial / canal de implementación y formación en seguridad | L99: Expo San Juan Minera 2026. También en: Directorio SSO (ID 187); Exponor (ID 179). | M99: Canal / aliado – consultoría, capacitación y certificación | N99: D409 | D410 | D427 | O99: Pabellón 2 | P99: NETHERLANDS / PAISES BAJOS | Q99: ARCADIS CHILE S.P.A. | R99: Con operaciones en mas de 30 países y con más de 136 años de experiencia global y más de 45 años en Chile, Arcadis es la empresa líder mundial en la entrega de soluciones sostenibles, aplicadas al diseño, ingeniería y consultoría para activos naturales y construidos. Somos alrededor de 34.000 profesionales, diseñadores, ingenieros, planificadores de proyectos y especialistas minera, agua, infraestructura y energía, unidos por nuestra pasión de mejorar la calidad de vida. Como parte de nuestro compromiso con acelerar un futuro positivo para el planeta, trabajamos junto a nuestros clientes para tomar decisiones de proyectos sostenibles, combinando innovación digital y humana, y desarrollando capacidades orientadas al futuro mejor. | S99: https://www.arcadis.com/ | T99: Directorio SSO (ID 187); Exponor (ID 179)
A100: 99 | D100: CONSULTORA OLGUÍN | E100: Argentina | F100: luisomarolguin@gmail.com | H100: Expo San Juan Minera 2026 | I100: Prospecto | J100: Alta | K100: Explorar alianza comercial / canal de implementación y formación en seguridad | L100: Expo San Juan Minera 2026. | M100: Canal / aliado – consultoría, capacitación y certificación | N100: F631 | O100: Pabellón 2 | R100: Somos una consultora multidisciplinaria con sede en San Juan, nacida con el propósito de ofrecer un respaldo integral a las empresas y emprendedores de la región, en Consultora Olguin Del Castillo combinamos experiencia técnica en sectores clave como la minería y la construcción con una visión experta en el área contable y financiera. Entendemos que el éxito de un proyecto de inversión no depende de un solo factor, sino de una gestión coordinada. Por eso, nuestro equipo de profesionales trabaja de manera transversal para brindar soluciones que van desde el asesoramiento legal y contable hasta la dirección de proyectos complejos. Nos apasiona ver crecer a las empresas locales y ser el motor que facilita su expansión en un mercado exigente. | S100: https://odcconsultora.com/ | T100: No
...

Sheet Oportunidades
A1: ID oportunidad | B1: ID contacto | C1: Empresa | D1: Necesidad | E1: Solución propuesta | F1: Etapa | G1: Valor estimado | H1: Probabilidad | I1: Próxima acción | J1: Fecha

Sheet Resumen
A1: Evento/Fuente | B1: País | C1: Cantidad
A2: Expo San Juan Minera 2026 | B2: Argentina | C2: =COUNTIFS(Contactos!$H:$H,$A2,Contactos!$E:$E,$B2) -> 386
A3: Expo San Juan Minera 2026 | B3: Perú | C3: =COUNTIFS(Contactos!$H:$H,$A3,Contactos!$E:$E,$B3) -> 11
A4: Expo San Juan Minera 2026 | B4: Alemania | C4: =COUNTIFS(Contactos!$H:$H,$A4,Contactos!$E:$E,$B4) -> 9
A5: Expo San Juan Minera 2026 | B5: Canadá | C5: =COUNTIFS(Contactos!$H:$H,$A5,Contactos!$E:$E,$B5) -> 5
A6: Expo San Juan Minera 2026 | B6: Países Bajos | C6: =COUNTIFS(Contactos!$H:$H,$A6,Contactos!$E:$E,$B6) -> 5
A7: Expo San Juan Minera 2026 | B7: Chile | C7: =COUNTIFS(Contactos!$H:$H,$A7,Contactos!$E:$E,$B7) -> 5
A8: Expo San Juan Minera 2026 | B8: China | C8: =COUNTIFS(Contactos!$H:$H,$A8,Contactos!$E:$E,$B8) -> 3
A9: Expo San Juan Minera 2026 | B9: Finlandia | C9: =COUNTIFS(Contactos!$H:$H,$A9,Contactos!$E:$E,$B9) -> 1
A10: Expo San Juan Minera 2026 | B10: Estados Unidos | C10: =COUNTIFS(Contactos!$H:$H,$A10,Contactos!$E:$E,$B10) -> 1
A11: Total | C11: =SUM(C2:C10) -> 426
A13: Segmento SafetyMind | B13: Alta | C13: Media | D13: Baja | E13: Total
A14: Cliente final – minera / energía (operación o proyecto) | B14: =COUNTIFS(Contactos!$M:$M,$A14,Contactos!$J:$J,B$13) -> 16 | C14: =COUNTIFS(Contactos!$M:$M,$A14,Contactos!$J:$J,C$13) -> 0 | D14: =COUNTIFS(Contactos!$M:$M,$A14,Contactos!$J:$J,D$13) -> 0 | E14: =SUM(B14:D14) -> 16
A15: Cliente final – contratista minero (operación, perforación, transporte, campamento) | B15: =COUNTIFS(Contactos!$M:$M,$A15,Contactos!$J:$J,B$13) -> 56 | C15: =COUNTIFS(Contactos!$M:$M,$A15,Contactos!$J:$J,C$13) -> 0 | D15: =COUNTIFS(Contactos!$M:$M,$A15,Contactos!$J:$J,D$13) -> 0 | E15: =SUM(B15:D15) -> 56
A16: Partner tecnológico / competidor | B16: =COUNTIFS(Contactos!$M:$M,$A16,Contactos!$J:$J,B$13) -> 24 | C16: =COUNTIFS(Contactos!$M:$M,$A16,Contactos!$J:$J,C$13) -> 0 | D16: =COUNTIFS(Contactos!$M:$M,$A16,Contactos!$J:$J,D$13) -> 0 | E16: =SUM(B16:D16) -> 24
A17: Canal / aliado – consultoría, capacitación y certificación | B17: =COUNTIFS(Contactos!$M:$M,$A17,Contactos!$J:$J,B$13) -> 12 | C17: =COUNTIFS(Contactos!$M:$M,$A17,Contactos!$J:$J,C$13) -> 0 | D17: =COUNTIFS(Contactos!$M:$M,$A17,Contactos!$J:$J,D$13) -> 0 | E17: =SUM(B17:D17) -> 12
A18: Partner OEM – maquinaria y equipos mineros | B18: =COUNTIFS(Contactos!$M:$M,$A18,Contactos!$J:$J,B$13) -> 0 | C18: =COUNTIFS(Contactos!$M:$M,$A18,Contactos!$J:$J,C$13) -> 39 | D18: =COUNTIFS(Contactos!$M:$M,$A18,Contactos!$J:$J,D$13) -> 0 | E18: =SUM(B18:D18) -> 39
A19: Canal / distribuidor EPP | B19: =COUNTIFS(Contactos!$M:$M,$A19,Contactos!$J:$J,B$13) -> 0 | C19: =COUNTIFS(Contactos!$M:$M,$A19,Contactos!$J:$J,C$13) -> 7 | D19: =COUNTIFS(Contactos!$M:$M,$A19,Contactos!$J:$J,D$13) -> 0 | E19: =SUM(B19:D19) -> 7
A20: Aliado complementario – seguridad y emergencias | B20: =COUNTIFS(Contactos!$M:$M,$A20,Contactos!$J:$J,B$13) -> 0 | C20: =COUNTIFS(Contactos!$M:$M,$A20,Contactos!$J:$J,C$13) -> 8 | D20: =COUNTIFS(Contactos!$M:$M,$A20,Contactos!$J:$J,D$13) -> 0 | E20: =SUM(B20:D20) -> 8
A21: Aliado complementario – salud | B21: =COUNTIFS(Contactos!$M:$M,$A21,Contactos!$J:$J,B$13) -> 0 | C21: =COUNTIFS(Contactos!$M:$M,$A21,Contactos!$J:$J,C$13) -> 3 | D21: =COUNTIFS(Contactos!$M:$M,$A21,Contactos!$J:$J,D$13) -> 0 | E21: =SUM(B21:D21) -> 3
A22: Institución / cámara / medio / gobierno | B22: =COUNTIFS(Contactos!$M:$M,$A22,Contactos!$J:$J,B$13) -> 0 | C22: =COUNTIFS(Contactos!$M:$M,$A22,Contactos!$J:$J,C$13) -> 38 | D22: =COUNTIFS(Contactos!$M:$M,$A22,Contactos!$J:$J,D$13) -> 0 | E22: =SUM(B22:D22) -> 38
A23: Proveedor industrial / servicios | B23: =COUNTIFS(Contactos!$M:$M,$A23,Contactos!$J:$J,B$13) -> 0 | C23: =COUNTIFS(Contactos!$M:$M,$A23,Contactos!$J:$J,C$13) -> 0 | D23: =COUNTIFS(Contactos!$M:$M,$A23,Contactos!$J:$J,D$13) -> 202 | E23: =SUM(B23:D23) -> 202
A24: Fuera de foco (turismo y servicios locales) | B24: =COUNTIFS(Contactos!$M:$M,$A24,Contactos!$J:$J,B$13) -> 0 | C24: =COUNTIFS(Contactos!$M:$M,$A24,Contactos!$J:$J,C$13) -> 0 | D24: =COUNTIFS(Contactos!$M:$M,$A24,Contactos!$J:$J,D$13) -> 21 | E24: =SUM(B24:D24) -> 21
A25: Total | B25: =SUM(B14:B24) -> 108 | C25: =SUM(C14:C24) -> 95 | D25: =SUM(D14:D24) -> 223 | E25: =SUM(E14:E24) -> 426
A27: Estado (pipeline) | B27: Cantidad
A28: Prospecto | B28: =COUNTIF(Contactos!$I:$I,A28) -> 426
A29: Contactado | B29: =COUNTIF(Contactos!$I:$I,A29) -> 0
A30: Reunión | B30: =COUNTIF(Contactos!$I:$I,A30) -> 0
A31: Propuesta | B31: =COUNTIF(Contactos!$I:$I,A31) -> 0
A32: Cliente | B32: =COUNTIF(Contactos!$I:$I,A32) -> 0
A33: No interesado | B33: =COUNTIF(Contactos!$I:$I,A33) -> 0
A35: Indicadores | B35: Cantidad
A36: Registros originales | B36: 426
A37: Empresas / instituciones únicas | B37: =COUNTA(Contactos!$D$2:$D$3000) -> 426
A38: Con sede en Argentina | B38: =COUNTIF(Contactos!$E$2:$E$3000,"Argentina") -> 386
A39: Con email | B39: =COUNTIF(Contactos!$F$2:$F$3000,"?*") -> 289
A40: Con web | B40: =COUNTIF(Contactos!$S$2:$S$3000,"?*") -> 285
A41: En otros CRM | B41: =COUNTIF(Contactos!$T$2:$T$3000,"*(ID*") -> 52

Sheet Eventos
A1: Evento | B1: País | C1: Valor para SafetyMind
A2: Directorio SSO 2026 – Cero Accidentes (22.ª ed.) | B2: Perú | C2: Mapa de ~670 proveedores SST en Perú (ver CRM_Directorio_SSO_2026).
A3: ExpoMina Perú 2026 | B3: Perú | C3: Feria minera (ver CRM_ExpoMina_2026).
A4: Exponor 2026 (Antofagasta) | B4: Chile | C4: Feria minera del norte de Chile (ver CRM_Exponor_2026).
A5: AquaSur 2026 (Puerto Montt) | B5: Chile | C5: Feria acuícola (ver CRM_AquaSur_2026).
A6: FIDAE 2026 (Santiago) | B6: Chile | C6: Feria aeroespacial y de defensa (ver CRM_FIDAE_2026).
A7: Expo San Juan Minera 2026 | B7: Argentina | C7: Feria minera de San Juan (cobre y oro): operaciones y proyectos (Veladero, Vicuña, Los Azules, El Pachón, Casposo), contratistas de perforación, voladura, transporte y campamentos, y cámaras (Cámara Minera, CASEMI, AOMA). Puerta de entrada a Argentina.
