Workbook

Sheet Contactos
A1: ID | B1: Nombre | C1: Cargo | D1: Empresa | E1: País | F1: Email | G1: LinkedIn | H1: Origen | I1: Estado | J1: Prioridad | K1: Próxima acción | L1: Notas | M1: Rubro(s) | N1: Segmento SafetyMind | O1: Teléfono(s) | P1: Web | Q1: Dirección | R1: Ciudad/Región | S1: Anunciante
A2: 1 | D2: Administración de Empresas S.A.C. | E2: Perú | F2: dpalacios@aesa.com.pe | H2: Directorio SSO 2026 | I2: Prospecto | J2: Alta | K2: Identificar Gerente SSOMA/HSE en LinkedIn y proponer demo | L2: Directorio SSO 2026, pág. PDF 37. Sin contacto nominal; no inventar decisor. | M2: Empresas contratistas y conexas | N2: Cliente potencial – operación de alto riesgo | O2: 7062230 | P2: www.aesa.com.pe | Q2: Cl. Las Begonias 441 Of. 1401 Urb. Jardín - San Isidro - Lima | R2: Lima | S2: No
A3: 2 | D3: Ahorro de Energía y Mantenimiento Industrial S.A.C. | E3: Perú | F3: ademinsa@ademinsa.com | H3: Directorio SSO 2026 | I3: Prospecto | J3: Alta | K3: Identificar Gerente SSOMA/HSE en LinkedIn y proponer demo | L3: Directorio SSO 2026, pág. PDF 18. Sin contacto nominal; no inventar decisor. Otros emails: atencionalcliente@ademinsa.com. | M3: Mantenimiento industrial | N3: Cliente potencial – operación de alto riesgo | O3: 2750082 | P3: www.ademinsa.com | Q3: Cl. Cerro Azul 479 Of. 101A Urb. San Ignacio de Loyola Santiago de Surco - Lima | R3: Lima | S3: No
A4: 3 | D4: AiD Ingenieros S.A.C. | E4: Perú | F4: aidingenieros@aidingenieros.com.pe | H4: Directorio SSO 2026 | I4: Prospecto | J4: Alta | K4: Identificar Gerente SSOMA/HSE en LinkedIn y proponer demo | L4: Directorio SSO 2026, pág. PDF 18, 37. Sin contacto nominal; no inventar decisor. | M4: Mantenimiento industrial; Empresas contratistas y conexas | N4: Cliente potencial – operación de alto riesgo | O4: (054) 446162 | P4: www.aidingenieros.com.pe | Q4: Mz. C Lt. 5B Urb. Magisterial II Etapa Yanahuara - Arequipa | R4: Arequipa | S4: No
A5: 4 | D5: AK Drilling International S.A. | E5: Perú | F5: global@akdint.com | H5: Directorio SSO 2026 | I5: Prospecto | J5: Alta | K5: Identificar Gerente SSOMA/HSE en LinkedIn y proponer demo | L5: Directorio SSO 2026, pág. PDF 20, 37. Sin contacto nominal; no inventar decisor. | M5: Perforación geológica; Empresas contratistas y conexas | N5: Cliente potencial – operación de alto riesgo | O5: 2513380 | P5: www.akdrillinginternational.com | Q5: Cl. Perseo Mz. J Lt. 12 Urb. La Campiña Chorrillos - Lima | R5: Lima | S5: No
A6: 5 | D6: Alicomser Contratistas S.A.C. | E6: Perú | F6: alicomser@alicomser.com | H6: Directorio SSO 2026 | I6: Prospecto | J6: Alta | K6: Identificar Gerente SSOMA/HSE en LinkedIn y proponer demo | L6: Directorio SSO 2026, pág. PDF 32, 35, 37. Sin contacto nominal; no inventar decisor. | M6: Sostenimiento de rocas y suelos; Ventilación industrial y subterránea; Empresas contratistas y conexas | N6: Cliente potencial – operación de alto riesgo | O6: 5310928 / 914946043 | P6: www.alicomser.com | Q6: Av. Universitaria Mz. H Lt. 7 P. 2 Asoc. Daniel Alcides Carrión II Los Olivos - Lima | R6: Lima | S6: No
A7: 6 | D7: Almacenera Pacífico S.A.C. | E7: Perú | F7: ventas@alpa.com.pe | H7: Directorio SSO 2026 | I7: Prospecto | J7: Alta | K7: Identificar Gerente SSOMA/HSE en LinkedIn y proponer demo | L7: Directorio SSO 2026, pág. PDF 34. Sin contacto nominal; no inventar decisor. | M7: Transporte de combustibles y materiales peligrosos | N7: Cliente potencial – operación de alto riesgo | O7: 6181620 / 983283750 | P7: www.alpa.com.pe | Q7: Carretera Antigua Panamericana Sur km 29.5 - Lurín - Lima | R7: Lima | S7: No
A8: 7 | D8: Almasa S.R.L. | E8: Perú | F8: almasa@almasa.com.pe | H8: Directorio SSO 2026 | I8: Prospecto | J8: Alta | K8: Identificar Gerente SSOMA/HSE en LinkedIn y proponer demo | L8: Directorio SSO 2026, pág. PDF 37. Sin contacto nominal; no inventar decisor. | M8: Empresas contratistas y conexas | N8: Cliente potencial – operación de alto riesgo | O8: 3720204 | P8: www.almasa.com.pe | Q8: Jr. Monterosa 270 Of. 602 Urb. Chacarilla del Estanque Santiago de Surco - Lima | R8: Lima | S8: No
A9: 8 | D9: American Sur Internacional S.A.C. | E9: Perú | F9: info@americasurinternacional.com | H9: Directorio SSO 2026 | I9: Prospecto | J9: Alta | K9: Identificar Gerente SSOMA/HSE en LinkedIn y proponer demo | L9: Directorio SSO 2026, pág. PDF 20. Sin contacto nominal; no inventar decisor. | M9: Perforación geológica | N9: Cliente potencial – operación de alto riesgo | O9: 2190700 | P9: www.americasurinternacional.com | Q9: Av. Alameda Sur 568 Urb. Villa Marina Chorrillos - Lima | R9: Lima | S9: No
A10: 9 | D10: Anddes Asociados S.A.C. | E10: Perú | F10: info@anddes.com | H10: Directorio SSO 2026 | I10: Prospecto | J10: Alta | K10: Identificar Gerente SSOMA/HSE en LinkedIn y proponer demo | L10: Directorio SSO 2026, pág. PDF 20, 37. Sin contacto nominal; no inventar decisor. | M10: Medioambiente: productos y servicios; Empresas contratistas y conexas | N10: Cliente potencial – operación de alto riesgo | O10: 3174900 | P10: www.anddes.com | Q10: Av. Javier Prado Este Cdra.48, Edificio Capital Golf Of. 1301 - Santiago de Surco Lima | R10: Lima | S10: No
A11: 10 | D11: AOM Suministros Industriales S.A.C. | E11: Perú | F11: info@aom.pe | H11: Directorio SSO 2026 | I11: Prospecto | J11: Alta | K11: Identificar Gerente SSOMA/HSE en LinkedIn y proponer demo | L11: Directorio SSO 2026, pág. PDF 7, 14, 19, 20. Sin contacto nominal; no inventar decisor. | M11: Campamentos e instalaciones; Equipos de protección personal; Máquinas, herramientas y repuestos; Perforación geológica | N11: Cliente potencial – operación de alto riesgo | P11: www.aom.pe | Q11: Jr. Cruz del Sur 140 Of.1503, Santiago de Surco - Lima | R11: Lima | S11: No
A12: 11 | D12: APM Terminals Inland Services S.A. | E12: Perú | F12: apmtcservicios@apmterminals.com | H12: Directorio SSO 2026 | I12: Prospecto | J12: Alta | K12: Identificar Gerente SSOMA/HSE en LinkedIn y proponer demo | L12: Directorio SSO 2026, pág. PDF 34. Sin contacto nominal; no inventar decisor. | M12: Transporte de combustibles y materiales peligrosos | N12: Cliente potencial – operación de alto riesgo | O12: 2008800 | P12: www.apmterminals.com | Q12: Av. Néstor Gambetta km 4.5 - Callao | R12: Callao | S12: No
A13: 12 | D13: Arkel Perú S.A.C. | E13: Perú | F13: info@arkel.pe | H13: Directorio SSO 2026 | I13: Prospecto | J13: Alta | K13: Identificar Gerente SSOMA/HSE en LinkedIn y proponer demo | L13: Directorio SSO 2026, pág. PDF 32. Sin contacto nominal; no inventar decisor. | M13: Sostenimiento de rocas y suelos | N13: Cliente potencial – operación de alto riesgo | O13: 901284293 | P13: www.arkel.pe | Q13: Jr. Ricardo Palma 174 Primera Zona Collique - Comas Lima | R13: Lima | S13: No
A14: 13 | D14: Beagle Shipping S.A. | E14: Perú | F14: servicioalcliente@beagle.com.pe | H14: Directorio SSO 2026 | I14: Prospecto | J14: Alta | K14: Identificar Gerente SSOMA/HSE en LinkedIn y proponer demo | L14: Directorio SSO 2026, pág. PDF 34. Sin contacto nominal; no inventar decisor. | M14: Transporte de combustibles y materiales peligrosos | N14: Cliente potencial – operación de alto riesgo | O14: 6168585 | P14: www.beagle.com.pe | Q14: Jr. Comandante Jiménez 120 Of. B Magdalena del Mar - Lima | R14: Lima | S14: No
A15: 14 | D15: Beton Terra Ingenieros S.A.C. | E15: Perú | F15: contacto@betonterra.com | H15: Directorio SSO 2026 | I15: Prospecto | J15: Alta | K15: Identificar Gerente SSOMA/HSE en LinkedIn y proponer demo | L15: Directorio SSO 2026, pág. PDF 20. Sin contacto nominal; no inventar decisor. | M15: Perforación geológica | N15: Cliente potencial – operación de alto riesgo | O15: 991888076 | P15: www.betonterra.pe | Q15: Jr. Pablo Picasso Mz. B1 Lt. 13 Of. 201, Los Álamos de Monterrico Etapa 3 - Santiago de Surco - Lima | R15: Lima | S15: No
A16: 15 | D16: BISA | E16: Perú | F16: comercial@bisa.com.pe | H16: Directorio SSO 2026 | I16: Prospecto | J16: Alta | K16: Identificar Gerente SSOMA/HSE en LinkedIn y proponer demo | L16: Directorio SSO 2026, pág. PDF 37. Sin contacto nominal; no inventar decisor. | M16: Empresas contratistas y conexas | N16: Cliente potencial – operación de alto riesgo | O16: 6266200 | P16: www.bisa.com.pe | Q16: Av. Andrés Reyes 338 Of. Piso 5 - San Isidro - Lima | R16: Lima | S16: No
A17: 16 | D17: Boart Longyear S.A.C. | E17: Perú | F17: info@boartlongyear.com | H17: Directorio SSO 2026 | I17: Prospecto | J17: Alta | K17: Identificar Gerente SSOMA/HSE en LinkedIn y proponer demo | L17: Directorio SSO 2026, pág. PDF 19, 20, 37. Sin contacto nominal; no inventar decisor. | M17: Máquinas, herramientas y repuestos; Perforación geológica; Empresas contratistas y conexas | N17: Cliente potencial – operación de alto riesgo | O17: 2034200 | P17: www.boartlongyear.com | Q17: Av. El Derby 055 Torre 1 Of. 601 Centro de Negocios Cronos - Santiago de Surco Lima | R17: Lima | S17: No
A18: 17 | D18: Bouby S.A.C. | E18: Perú | F18: boubysac@boubysac.com | H18: Directorio SSO 2026 | I18: Prospecto | J18: Alta | K18: Identificar Gerente SSOMA/HSE en LinkedIn y proponer demo | L18: Directorio SSO 2026, pág. PDF 37. Sin contacto nominal; no inventar decisor. | M18: Empresas contratistas y conexas | N18: Cliente potencial – operación de alto riesgo | O18: 3482991 | P18: www.boubysac.com | Q18: Av. La Mar 267, Santa Anita - Lima | R18: Lima | S18: No
A19: 18 | D19: C&V International SRL | E19: Perú | F19: ventas@cvinternational.com.pe | H19: Directorio SSO 2026 | I19: Prospecto | J19: Alta | K19: Identificar Gerente SSOMA/HSE en LinkedIn y proponer demo | L19: Directorio SSO 2026, pág. PDF 37. Sin contacto nominal; no inventar decisor. | M19: Empresas contratistas y conexas | N19: Cliente potencial – operación de alto riesgo | O19: 5156714 | P19: www.cvinternational.com.pe | Q19: Cl. Emiliano Tenorio Gadea 260 Urb. San Amadeo de Garagay San Martin de Porres - Lima | R19: Lima | S19: No
A20: 19 | D20: Canchanya Ingenieros S.R.L. | E20: Perú | F20: hcanchanya@cis.com.pe | H20: Directorio SSO 2026 | I20: Prospecto | J20: Alta | K20: Identificar Gerente SSOMA/HSE en LinkedIn y proponer demo | L20: Directorio SSO 2026, pág. PDF 20, 32, 36, 37. Sin contacto nominal; no inventar decisor. | M20: Perforación geológica; Sostenimiento de rocas y suelos; Voladura, explosivos y polvorines; Empresas contratistas y conexas | N20: Cliente potencial – operación de alto riesgo | O20: 7172709 | P20: www.cis.com.pe | Q20: Av. Separadora Industrial 1910 Urb. Residencial Monterrico - La Molina Lima | R20: Lima | S20: No
A21: 20 | B21: Gisella Ojeda | D21: Castem E.I.R.L. | E21: Perú | F21: gojeda@castem.com.pe | H21: Directorio SSO 2026 | I21: Prospecto | J21: Alta | K21: Identificar Gerente SSOMA/HSE en LinkedIn y proponer demo | L21: Directorio SSO 2026, pág. PDF 32, 37. Anunciante (inversión activa en SST). Contacto publicado; validar vigencia. | M21: Sostenimiento de rocas y suelos; Empresas contratistas y conexas | N21: Cliente potencial – operación de alto riesgo | O21: (01) 5274146 / 946084469 | P21: www.castem.com.pe | Q21: Cl. San Francisco Mz.G Lt. 88 Urb. Leoncio Prado, Puente Piedra - Lima | R21: Lima | S21: Sí
A22: 21 | D22: CEMPROTEC S.A.C. | E22: Perú | F22: comercial@cemprotec.com.pe | H22: Directorio SSO 2026 | I22: Prospecto | J22: Alta | K22: Identificar Gerente SSOMA/HSE en LinkedIn y proponer demo | L22: Directorio SSO 2026, pág. PDF 37. Sin contacto nominal; no inventar decisor. | M22: Empresas contratistas y conexas | N22: Cliente potencial – operación de alto riesgo | O22: 989156472 | P22: www.cemprotec.com.pe | Q22: Av. Las Praderas de Lurín Mz.A Lt.9 Grupo D Panamericana Sur km 37.22 Lurín - Lima | R22: Lima | S22: No
A23: 22 | D23: CERV / Certus S.A.C. | E23: Perú | F23: comercial@cerv.com.pe | H23: Directorio SSO 2026 | I23: Prospecto | J23: Alta | K23: Identificar Gerente SSOMA/HSE en LinkedIn y proponer demo | L23: Directorio SSO 2026, pág. PDF 9, 18. Sin contacto nominal; no inventar decisor. | M23: Capacitación, consultoría y auditoría; Mantenimiento industrial | N23: Cliente potencial – operación de alto riesgo | O23: 980508948 | P23: www.cerv.com.pe | Q23: Cl. Melgar 620 Of. 201 Cerro Colorado - Arequipa | R23: Arequipa | S23: No
A24: 23 | D24: Cesel Ingenieros | E24: Perú | F24: cesel@cesel.com.pe | H24: Directorio SSO 2026 | I24: Prospecto | J24: Alta | K24: Identificar Gerente SSOMA/HSE en LinkedIn y proponer demo | L24: Directorio SSO 2026, pág. PDF 37. Sin contacto nominal; no inventar decisor. | M24: Empresas contratistas y conexas | N24: Cliente potencial – operación de alto riesgo | O24: 7055000 | P24: www.cesel.com.pe | Q24: Av. José Gálvez Barrenechea 646 Urb. Córpac - San Isidro - Lima | R24: Lima | S24: No
A25: 24 | D25: Cime Ingenieros S.R.L. | E25: Perú | F25: info@cimeingenieros.com | H25: Directorio SSO 2026 | I25: Prospecto | J25: Alta | K25: Identificar Gerente SSOMA/HSE en LinkedIn y proponer demo | L25: Directorio SSO 2026, pág. PDF 18, 37. Sin contacto nominal; no inventar decisor. | M25: Mantenimiento industrial; Empresas contratistas y conexas | N25: Cliente potencial – operación de alto riesgo | O25: 5623571 / 4521115 | P25: www.cimeingenieros.com | Q25: Cl. Gamma 180 Urb. Parque Internacional de Industria y Comercio Callao | R25: Callao | S25: No
A26: 25 | D26: Cimec Ingenieros S.A. | E26: Perú | F26: info@cimec.com | H26: Directorio SSO 2026 | I26: Prospecto | J26: Alta | K26: Identificar Gerente SSOMA/HSE en LinkedIn y proponer demo | L26: Directorio SSO 2026, pág. PDF 37. Sin contacto nominal; no inventar decisor. Otros emails: noticimec@cimec.com. | M26: Empresas contratistas y conexas | N26: Cliente potencial – operación de alto riesgo | O26: 7193630 / 995746542 | P26: www.cimec.com | Q26: Cl. Ismael Bielich Flores 753 Urb. Benavides - Santiago de Surco - Lima | R26: Lima | S26: No
A27: 26 | D27: CN Minería y Construcción S.A.C. | E27: Perú | F27: cnsac@cnsac.com.pe | H27: Directorio SSO 2026 | I27: Prospecto | J27: Alta | K27: Identificar Gerente SSOMA/HSE en LinkedIn y proponer demo | L27: Directorio SSO 2026, pág. PDF 37. Sin contacto nominal; no inventar decisor. | M27: Empresas contratistas y conexas | N27: Cliente potencial – operación de alto riesgo | O27: 6128989 | P27: www.cnsac.com.pe | Q27: Av. Mariscal Nieto 119 Urb. El Pino Industrial - San Luis - Lima | R27: Lima | S27: No
A28: 27 | D28: Coansa del Perú Ingenieros S.A.C. | E28: Perú | F28: asistente.gerencia@coansadelperu.com | H28: Directorio SSO 2026 | I28: Prospecto | J28: Alta | K28: Identificar Gerente SSOMA/HSE en LinkedIn y proponer demo | L28: Directorio SSO 2026, pág. PDF 37. Sin contacto nominal; no inventar decisor. | M28: Empresas contratistas y conexas | N28: Cliente potencial – operación de alto riesgo | O28: (076) 348759 | P28: www.coansadelperu.com | Q28: Av. Javier Prado Este 560 Of. 2302 San Isidro - Lima | R28: Lima | S28: No
A29: 28 | D29: Comercial del Acero S.A. | E29: Perú | F29: ventas@comasa.com.pe | H29: Directorio SSO 2026 | I29: Prospecto | J29: Alta | K29: Identificar Gerente SSOMA/HSE en LinkedIn y proponer demo | L29: Directorio SSO 2026, pág. PDF 32. Sin contacto nominal; no inventar decisor. | M29: Sostenimiento de rocas y suelos | N29: Cliente potencial – operación de alto riesgo | O29: 6193000 | P29: www.comasa.com.pe | Q29: Av. Argentina 2051 - Cercado de Lima Lima | R29: Lima | S29: No
A30: 29 | D30: Concremax S.A. | E30: Perú | H30: Directorio SSO 2026 | I30: Prospecto | J30: Alta | K30: Identificar Gerente SSOMA/HSE en LinkedIn y proponer demo | L30: Directorio SSO 2026, pág. PDF 37. Sin contacto nominal; no inventar decisor. | M30: Empresas contratistas y conexas | N30: Cliente potencial – operación de alto riesgo | O30: 2172700 / 905454100 | P30: www.concremax.com.pe | Q30: Cooperativa Las Vertientes Mz. F Lt. 3A Villa El Salvador - Lima | R30: Lima | S30: No
A31: 30 | D31: Confipetrol Andina S.A. | E31: Perú | H31: Directorio SSO 2026 | I31: Prospecto | J31: Alta | K31: Identificar Gerente SSOMA/HSE en LinkedIn y proponer demo | L31: Directorio SSO 2026, pág. PDF 37. Sin contacto nominal; no inventar decisor. | M31: Empresas contratistas y conexas | N31: Cliente potencial – operación de alto riesgo | O31: 7106100 | P31: www.confipetrol.com | Q31: Av. Santo Toribio 173 Edf. Real 8 Of.1002 - San Isidro - Lima | R31: Lima | S31: No
A32: 31 | D32: CONGEMIN JH S.A.C. | E32: Perú | F32: contacto@congemin.com | H32: Directorio SSO 2026 | I32: Prospecto | J32: Alta | K32: Identificar Gerente SSOMA/HSE en LinkedIn y proponer demo | L32: Directorio SSO 2026, pág. PDF 20, 32, 36, 37. Sin contacto nominal; no inventar decisor. | M32: Perforación geológica; Sostenimiento de rocas y suelos; Voladura, explosivos y polvorines; Empresas contratistas y conexas | N32: Cliente potencial – operación de alto riesgo | O32: 3496849 | P32: www.congemin.com | Q32: Cl. Las Acacias Mz.I Lt.5A Urb. La Capitana, Huachipa - Lurigancho Lima | R32: Lima | S32: No
A33: 32 | D33: Consorcio Metalúrgico S.A. | E33: Perú | F33: ventas@comesa.com.pe | H33: Directorio SSO 2026 | I33: Prospecto | J33: Alta | K33: Identificar Gerente SSOMA/HSE en LinkedIn y proponer demo | L33: Directorio SSO 2026, pág. PDF 37. Sin contacto nominal; no inventar decisor. | M33: Empresas contratistas y conexas | N33: Cliente potencial – operación de alto riesgo | O33: 4648000 | P33: www.comesa.com.pe | Q33: Av. Maquinarias 3150 - Cercado de Lima - Lima | R33: Lima | S33: No
A34: 33 | D34: Contrans S.A.C. | E34: Perú | F34: ventas@contrans.com.pe | H34: Directorio SSO 2026 | I34: Prospecto | J34: Alta | K34: Identificar Gerente SSOMA/HSE en LinkedIn y proponer demo | L34: Directorio SSO 2026, pág. PDF 34. Sin contacto nominal; no inventar decisor. | M34: Transporte de combustibles y materiales peligrosos | N34: Cliente potencial – operación de alto riesgo | O34: 6123500 | P34: www.contrans.com.pe | Q34: Av. A Nº204 ex Fundo Oquendo Alt. km 8.5 de Av. Néstor Gambetta Callao | R34: Callao | S34: No
A35: 34 | D35: Contrata Minera Cristóbal S.A.C. | E35: Perú | F35: contacto.cristobal@cmcristobal.com | H35: Directorio SSO 2026 | I35: Prospecto | J35: Alta | K35: Identificar Gerente SSOMA/HSE en LinkedIn y proponer demo | L35: Directorio SSO 2026, pág. PDF 37. Sin contacto nominal; no inventar decisor. Otros emails: info.cristobal@cmcristobal.com. | M35: Empresas contratistas y conexas | N35: Cliente potencial – operación de alto riesgo | O35: 2608282 | P35: www.cmcristobal.com | Q35: Jr. Sevilla 283 - Santiago de Surco Lima | R35: Lima | S35: No
A36: 35 | D36: Contratos Mineros e Inversiones S.A.C. | E36: Perú | F36: info@contmin.pe | H36: Directorio SSO 2026 | I36: Prospecto | J36: Alta | K36: Identificar Gerente SSOMA/HSE en LinkedIn y proponer demo | L36: Directorio SSO 2026, pág. PDF 37. Sin contacto nominal; no inventar decisor. | M36: Empresas contratistas y conexas | N36: Cliente potencial – operación de alto riesgo | O36: 7356273 | P36: www.contmin.pe | Q36: Av. Coronel Andrés Reyes 437 Of. 601 San Isidro - Lima | R36: Lima | S36: No
A37: 36 | D37: Coopsol Minería y Petróleo S.A. | E37: Perú | F37: informes@coopsol.com | H37: Directorio SSO 2026 | I37: Prospecto | J37: Alta | K37: Identificar Gerente SSOMA/HSE en LinkedIn y proponer demo | L37: Directorio SSO 2026, pág. PDF 37. Sin contacto nominal; no inventar decisor. | M37: Empresas contratistas y conexas | N37: Cliente potencial – operación de alto riesgo | O37: 4223344 / 4409882 / 6178800 | P37: www.coopsolmineria.com | Q37: Cl. Federico Villareal 555 Urb. Chacarilla de Santa Cruz - San Isidro - Lima | R37: Lima | S37: No
A38: 37 | D38: Corimayo Servicios Mineros S.A.C. | E38: Perú | H38: Directorio SSO 2026 | I38: Prospecto | J38: Alta | K38: Identificar Gerente SSOMA/HSE en LinkedIn y proponer demo | L38: Directorio SSO 2026, pág. PDF 20, 36. Sin contacto nominal; no inventar decisor. | M38: Perforación geológica; Voladura, explosivos y polvorines | N38: Cliente potencial – operación de alto riesgo | O38: 2717153 | Q38: Cl. Albert Einstein 334 Urb. La Calera de la Merced - Surquillo - Lima | R38: Lima | S38: No
A39: 38 | D39: Corporación Aceros Arequipa S.A. | E39: Perú | H39: Directorio SSO 2026 | I39: Prospecto | J39: Alta | K39: Identificar Gerente SSOMA/HSE en LinkedIn y proponer demo | L39: Directorio SSO 2026, pág. PDF 32. Sin contacto nominal; no inventar decisor. | M39: Sostenimiento de rocas y suelos | N39: Cliente potencial – operación de alto riesgo | O39: 5171800 | P39: www.acerosarequipa.com | Q39: Carretera Panamericana Sur km 229 - Pisco - Ica | R39: Ica | S39: No
A40: 39 | D40: Corporación ADHARA | E40: Perú | F40: ventas@adhara.pe | H40: Directorio SSO 2026 | I40: Prospecto | J40: Alta | K40: Identificar Gerente SSOMA/HSE en LinkedIn y proponer demo | L40: Directorio SSO 2026, pág. PDF 33. Sin contacto nominal; no inventar decisor. | M40: Sostenimiento de rocas y suelos | N40: Cliente potencial – operación de alto riesgo | O40: (+51) 900704108 | P40: www.adhara.pe | Q40: Mza. N Lt. 25 Urb. Santo Domingo II Etapa, Carabayllo - Lima | R40: Lima | S40: No
A41: 40 | D41: Corporación Oroya S.R.L. | E41: Perú | F41: gerenciag@corpor.com.pe | H41: Directorio SSO 2026 | I41: Prospecto | J41: Alta | K41: Identificar Gerente SSOMA/HSE en LinkedIn y proponer demo | L41: Directorio SSO 2026, pág. PDF 18, 37. Sin contacto nominal; no inventar decisor. | M41: Mantenimiento industrial; Empresas contratistas y conexas | N41: Cliente potencial – operación de alto riesgo | O41: 964108474 | P41: www.corpor.com.pe | Q41: Av. Cajamarquilla Mz. A Lt. 24 A.V. Señor de Muruhuay - Lurigancho - Lima | R41: Lima | S41: No
A42: 41 | D42: Cosapi Minería S.A.C. | E42: Perú | F42: comunicaciones@cosapi.com.pe | H42: Directorio SSO 2026 | I42: Prospecto | J42: Alta | K42: Identificar Gerente SSOMA/HSE en LinkedIn y proponer demo | L42: Directorio SSO 2026, pág. PDF 37. Sin contacto nominal; no inventar decisor. | M42: Empresas contratistas y conexas | N42: Cliente potencial – operación de alto riesgo | O42: 2113500 | P42: www.cosapi.com.pe | Q42: Av. República de Colombia 791 San Isidro - Lima | R42: Lima | S42: No
A43: 42 | D43: DCR Minería y Construcción S.A.C. | E43: Perú | H43: Directorio SSO 2026 | I43: Prospecto | J43: Alta | K43: Identificar Gerente SSOMA/HSE en LinkedIn y proponer demo | L43: Directorio SSO 2026, pág. PDF 34, 37. Sin contacto nominal; no inventar decisor. | M43: Transporte de combustibles y materiales peligrosos; Empresas contratistas y conexas | N43: Cliente potencial – operación de alto riesgo | O43: 6513232 | P43: dcrmineriayconstruccion.com; www.dcrmineriayconstruccion.com | Q43: Lima: Av. Nicolás Arriola 791 Santa Catalina - La Victoria Arequipa: Variante de Uchumayo km 2.5 Cerro Colorado - Lima | R43: Lima | S43: No
A44: 43 | D44: Dinet S.A. | E44: Perú | F44: contactodinet@dinet.com.pe | H44: Directorio SSO 2026 | I44: Prospecto | J44: Alta | K44: Identificar Gerente SSOMA/HSE en LinkedIn y proponer demo | L44: Directorio SSO 2026, pág. PDF 34. Sin contacto nominal; no inventar decisor. Otros emails: atencion.ecommerce@dinet.com.pe. | M44: Transporte de combustibles y materiales peligrosos | N44: Cliente potencial – operación de alto riesgo | O44: 5170100 | P44: www.dinet.com.pe | Q44: Jr. Domenico Morelli 110 Of. 601 C.C. La Rambla Torre 1 San Borja - Lima | R44: Lima | S44: No
A45: 44 | D45: Díaz Acarreos Generales S.A.C. | E45: Perú | F45: informes@dag.com.pe | H45: Directorio SSO 2026 | I45: Prospecto | J45: Alta | K45: Identificar Gerente SSOMA/HSE en LinkedIn y proponer demo | L45: Directorio SSO 2026, pág. PDF 34. Sin contacto nominal; no inventar decisor. | M45: Transporte de combustibles y materiales peligrosos | N45: Cliente potencial – operación de alto riesgo | O45: 044491121 / 942633146 / 942629279 | P45: www.dag.com.pe | Q45: Av. Evitamiento s/n Fundo La Encalada Trujillo - La Libertad | R45: La Libertad | S45: No
A46: 45 | D46: E & E Bolt Service and Solutions E.I.R.L. | E46: Perú | F46: gestioncomercial@eeboltservice.com | H46: Directorio SSO 2026 | I46: Prospecto | J46: Alta | K46: Identificar Gerente SSOMA/HSE en LinkedIn y proponer demo | L46: Directorio SSO 2026, pág. PDF 33. Sin contacto nominal; no inventar decisor. | M46: Sostenimiento de rocas y suelos | N46: Cliente potencial – operación de alto riesgo | O46: 973598628 / 968618227 / 977138963 | P46: www.eeboltservice.com | Q46: Jr. Ángela Podestá 447 Urb. Colmenares Pueblo Libre - Lima | R46: Lima | S46: No
A47: 46 | D47: Edewit S.R.L. | E47: Perú | F47: edgarv@edewit.com | H47: Directorio SSO 2026 | I47: Prospecto | J47: Alta | K47: Identificar Gerente SSOMA/HSE en LinkedIn y proponer demo | L47: Directorio SSO 2026, pág. PDF 34. Sin contacto nominal; no inventar decisor. | M47: Transporte de combustibles y materiales peligrosos | N47: Cliente potencial – operación de alto riesgo | O47: 996285856 | P47: www.edewit.com | Q47: Cl. Río Caplina 158 Urb Santa Isolina Comas - Lima | R47: Lima | S47: No
A48: 47 | D48: EMER S.A.C. | E48: Perú | F48: ventas@emerperu.com | H48: Directorio SSO 2026 | I48: Prospecto | J48: Alta | K48: Identificar Gerente SSOMA/HSE en LinkedIn y proponer demo | L48: Directorio SSO 2026, pág. PDF 33. Sin contacto nominal; no inventar decisor. | M48: Sostenimiento de rocas y suelos | N48: Cliente potencial – operación de alto riesgo | O48: 989282734 | P48: www.emerperu.com | Q48: Jr. Cajamarquilla 1372, Urb. Zárate San Juan de Lurigancho - Lima | R48: Lima | S48: No
A49: 48 | D49: Emergenza Ingeniería y Servicios E.I.R.L. | E49: Perú | F49: contacto@emergenzaingenieria.com | H49: Directorio SSO 2026 | I49: Prospecto | J49: Alta | K49: Identificar Gerente SSOMA/HSE en LinkedIn y proponer demo | L49: Directorio SSO 2026, pág. PDF 18, 21, 24. Sin contacto nominal; no inventar decisor. | M49: Mantenimiento industrial; Protección contra incendios; Reflectivos y señalización | N49: Cliente potencial – operación de alto riesgo | O49: 998928325 | Q49: Cl. 35 Mz.B6 Lt.14Urb. La Planicie VI Etapa, Ventiseis de Octubre - Piura | R49: Piura | S49: No
A50: 49 | D50: Eminec S.A.C. | E50: Perú | F50: contacto@eminecsac.com | H50: Directorio SSO 2026 | I50: Prospecto | J50: Alta | K50: Identificar Gerente SSOMA/HSE en LinkedIn y proponer demo | L50: Directorio SSO 2026, pág. PDF 21, 33, 37. Sin contacto nominal; no inventar decisor. | M50: Perforación geológica; Sostenimiento de rocas y suelos; Empresas contratistas y conexas | N50: Cliente potencial – operación de alto riesgo | O50: 2414986 | P50: www.eminecsac.com | Q50: Jr. Los Pinos 114 Of. 906 - Miraflores Lima | R50: Lima | S50: No
A51: 50 | D51: Empresa de Transportes N&V S.A.C. | E51: Perú | F51: gerenciaoperaciones@nvsac.com.pe | H51: Directorio SSO 2026 | I51: Prospecto | J51: Alta | K51: Identificar Gerente SSOMA/HSE en LinkedIn y proponer demo | L51: Directorio SSO 2026, pág. PDF 34. Sin contacto nominal; no inventar decisor. | M51: Transporte de combustibles y materiales peligrosos | N51: Cliente potencial – operación de alto riesgo | O51: 992367652 | Q51: Carretera Industrial km 560 Sector Primavera- Trujillo - La Libertad | R51: La Libertad | S51: No
A52: 51 | D52: Epiroc | E52: Perú | F52: contacto.andina@epiroc.com | H52: Directorio SSO 2026 | I52: Prospecto | J52: Alta | K52: Identificar Gerente SSOMA/HSE en LinkedIn y proponer demo | L52: Directorio SSO 2026, pág. PDF 33. Sin contacto nominal; no inventar decisor. | M52: Sostenimiento de rocas y suelos | N52: Cliente potencial – operación de alto riesgo | O52: 4116100 | P52: www.epiroc.com | Q52: Cl. Francisco Graña Urb. Santa Catalina, La Victoria - Lima | R52: Lima | S52: No
A53: 52 | D53: Equans Services Perú S.A. | E53: Perú | F53: contacto.espe@equans.com | H53: Directorio SSO 2026 | I53: Prospecto | J53: Alta | K53: Identificar Gerente SSOMA/HSE en LinkedIn y proponer demo | L53: Directorio SSO 2026, pág. PDF 18. Sin contacto nominal; no inventar decisor. | M53: Mantenimiento industrial | N53: Cliente potencial – operación de alto riesgo | P53: www.equans.pe | Q53: Av. Paseo de la República 3617 San Isidro - Lima | R53: Lima | S53: No
A54: 53 | D54: Esso Technologies S.A.C. | E54: Perú | F54: ventas@essotechnologies.com | H54: Directorio SSO 2026 | I54: Prospecto | J54: Alta | K54: Identificar Gerente SSOMA/HSE en LinkedIn y proponer demo | L54: Directorio SSO 2026, pág. PDF 18, 19, 21, 35. Sin contacto nominal; no inventar decisor. | M54: Iluminación industrial; Máquinas, herramientas y repuestos; Perforación geológica; Ventilación industrial y subterránea | N54: Cliente potencial – operación de alto riesgo | O54: 2501013 / 998763199 | P54: www.essotechnologies.com | Q54: Av. Separadora Industrial 980 Urb. Olimpo - Ate - Lima | R54: Lima | S54: No
A55: 54 | D55: ETRAMIM S.R.L. | E55: Perú | H55: Directorio SSO 2026 | I55: Prospecto | J55: Alta | K55: Identificar Gerente SSOMA/HSE en LinkedIn y proponer demo | L55: Directorio SSO 2026, pág. PDF 37. Sin contacto nominal; no inventar decisor. | M55: Empresas contratistas y conexas | N55: Cliente potencial – operación de alto riesgo | O55: (054) 384537 / 958331651 | P55: www.etramim.com | Q55: Urb. Señorial Mz.H Lt.5, Cayma Arequipa | R55: Arequipa | S55: No
A56: 55 | D56: Explo Drilling Perú S.C.R.L. | E56: Perú | F56: explo@explodrillingperu.pe | H56: Directorio SSO 2026 | I56: Prospecto | J56: Alta | K56: Identificar Gerente SSOMA/HSE en LinkedIn y proponer demo | L56: Directorio SSO 2026, pág. PDF 37. Sin contacto nominal; no inventar decisor. | M56: Empresas contratistas y conexas | N56: Cliente potencial – operación de alto riesgo | O56: (054) 464101 / 958545971 | P56: www.explodrillingperu.pe | Q56: Urb. Industrial Cayro Mz. C Lt. 3 Paucarpata - Arequipa | R56: Arequipa | S56: No
A57: 56 | D57: Explomin del Perú S.A. | E57: Perú | F57: contacto@explomin.com | H57: Directorio SSO 2026 | I57: Prospecto | J57: Alta | K57: Identificar Gerente SSOMA/HSE en LinkedIn y proponer demo | L57: Directorio SSO 2026, pág. PDF 21, 37. Sin contacto nominal; no inventar decisor. | M57: Perforación geológica; Empresas contratistas y conexas | N57: Cliente potencial – operación de alto riesgo | O57: 2957070 | P57: www.explomin.com | Q57: Mz.A Lt.2 A.V. Villa El Milagro (km 22.5 Panamericana Sur-Conchán) Villa El Salvador - Lima | R57: Lima | S57: No
A58: 57 | D58: Exploraciones Mineras EA & T S.A.C. | E58: Perú | F58: informes@exminsac.com | H58: Directorio SSO 2026 | I58: Prospecto | J58: Alta | K58: Identificar Gerente SSOMA/HSE en LinkedIn y proponer demo | L58: Directorio SSO 2026, pág. PDF 37. Sin contacto nominal; no inventar decisor. | M58: Empresas contratistas y conexas | N58: Cliente potencial – operación de alto riesgo | O58: 985652654 | P58: www.exminsac.com | Q58: Cl. Nueva York 302 Urb. San Nicolás Trujillo- La Libertad | R58: La Libertad | S58: No
A59: 58 | D59: Explosupport S.A.C. | E59: Perú | F59: contacto@explosupport.com | H59: Directorio SSO 2026 | I59: Prospecto | J59: Alta | K59: Identificar Gerente SSOMA/HSE en LinkedIn y proponer demo | L59: Directorio SSO 2026, pág. PDF 37. Sin contacto nominal; no inventar decisor. | M59: Empresas contratistas y conexas | N59: Cliente potencial – operación de alto riesgo | O59: 4761410 | P59: www.explosupport.com | Q59: Av. Javier Prado Este 1238, Urb. Córpac San Isidro - Lima | R59: Lima | S59: No
A60: 59 | D60: EXSA S.A. | E60: Perú | H60: Directorio SSO 2026 | I60: Prospecto | J60: Alta | K60: Identificar Gerente SSOMA/HSE en LinkedIn y proponer demo | L60: Directorio SSO 2026, pág. PDF 36. Sin contacto nominal; no inventar decisor. | M60: Voladura, explosivos y polvorines | N60: Cliente potencial – operación de alto riesgo | O60: 2176000 | P60: www.orica.com | Q60: Av. Dionisio Derteano 144 Piso 19 San Isidro - Lima | R60: Lima | S60: No
A61: 60 | D61: Famesa Explosivos S.A.C. | E61: Perú | F61: ventas@famesa.com.pe | H61: Directorio SSO 2026 | I61: Prospecto | J61: Alta | K61: Identificar Gerente SSOMA/HSE en LinkedIn y proponer demo | L61: Directorio SSO 2026, pág. PDF 36, 37. Sin contacto nominal; no inventar decisor. | M61: Voladura, explosivos y polvorines; Empresas contratistas y conexas | N61: Cliente potencial – operación de alto riesgo | O61: 6139800 | P61: www.famesa.com.pe | Q61: Panamericana Norte km 28 Puente Piedra - Lima | R61: Lima | S61: No
A62: 61 | D62: Fixa S.A. | E62: Perú | H62: Directorio SSO 2026 | I62: Prospecto | J62: Alta | K62: Identificar Gerente SSOMA/HSE en LinkedIn y proponer demo | L62: Directorio SSO 2026, pág. PDF 33. Sin contacto nominal; no inventar decisor. | M62: Sostenimiento de rocas y suelos | N62: Cliente potencial – operación de alto riesgo | O62: 4517854 / 4511688 / 4514548 | Q62: Cl. Omega 261, Parque Industrial y Comercio - Callao | R62: Callao | S62: No
A63: 62 | D63: FLSMIDTH S.A.C. | E63: Perú | F63: info@flsidth.com | H63: Directorio SSO 2026 | I63: Prospecto | J63: Alta | K63: Identificar Gerente SSOMA/HSE en LinkedIn y proponer demo | L63: Directorio SSO 2026, pág. PDF 12, 18, 37. Sin contacto nominal; no inventar decisor. | M63: Electricidad industrial; Mantenimiento industrial; Empresas contratistas y conexas | N63: Cliente potencial – operación de alto riesgo | O63: 7080500 | P63: www.flsmidth.com | Q63: Av. Juan de Arona 755 (Piso 9, Of. 9 116), San Isidro - Lima | R63: Lima | S63: No
A64: 63 | D64: GC Ground S.A.C. | E64: Perú | F64: infogcground@gcground.com | H64: Directorio SSO 2026 | I64: Prospecto | J64: Alta | K64: Identificar Gerente SSOMA/HSE en LinkedIn y proponer demo | L64: Directorio SSO 2026, pág. PDF 37. Sin contacto nominal; no inventar decisor. | M64: Empresas contratistas y conexas | N64: Cliente potencial – operación de alto riesgo | O64: 2566056 / 996284660 | P64: www.gcground.com | Q64: Cl. Monterosa 240 Of. 903 Urb. Chacarilla del Estanque Santiago de Surco - Lima | R64: Lima | S64: No
A65: 64 | D65: Geodrill S.A.C. | E65: Perú | F65: info@geodrill.com.pe | H65: Directorio SSO 2026 | I65: Prospecto | J65: Alta | K65: Identificar Gerente SSOMA/HSE en LinkedIn y proponer demo | L65: Directorio SSO 2026, pág. PDF 21, 37. Sin contacto nominal; no inventar decisor. | M65: Perforación geológica; Empresas contratistas y conexas | N65: Cliente potencial – operación de alto riesgo | O65: (054) 568111 | P65: www.geo-drill.com | Q65: Juan Barcleay 261, Parque Industrial Arequipa | R65: Arequipa | S65: No
A66: 65 | D66: Geodrilling E.I.R.L. | E66: Perú | F66: geo@geodrillingperu.pe | H66: Directorio SSO 2026 | I66: Prospecto | J66: Alta | K66: Identificar Gerente SSOMA/HSE en LinkedIn y proponer demo | L66: Directorio SSO 2026, pág. PDF 21, 37. Sin contacto nominal; no inventar decisor. | M66: Perforación geológica; Empresas contratistas y conexas | N66: Cliente potencial – operación de alto riesgo | O66: 7291995 / 985691930 | P66: www.geodrillingperu.pe | Q66: Cl. Garcilaso de la Vega 346 Urb. San Joaquín - Bellavista - Callao | R66: Callao | S66: No
A67: 66 | D67: Geofundaciones del Perú S.A.C. | E67: Perú | F67: comercial@geofundaciones.pe | H67: Directorio SSO 2026 | I67: Prospecto | J67: Alta | K67: Identificar Gerente SSOMA/HSE en LinkedIn y proponer demo | L67: Directorio SSO 2026, pág. PDF 37. Sin contacto nominal; no inventar decisor. | M67: Empresas contratistas y conexas | N67: Cliente potencial – operación de alto riesgo | O67: 4697376 / 946381153 | P67: www.geofundaciones.pe | Q67: Av. Los Faisanes 170 Of. D Urb. La Campiña, Chorrillos - Lima | R67: Lima | S67: No
A68: 67 | D68: Geomecánica Latina S.A. | E68: Perú | F68: info@geomecanicalatina.com | H68: Directorio SSO 2026 | I68: Prospecto | J68: Alta | K68: Identificar Gerente SSOMA/HSE en LinkedIn y proponer demo | L68: Directorio SSO 2026, pág. PDF 33. Sin contacto nominal; no inventar decisor. | M68: Sostenimiento de rocas y suelos | N68: Cliente potencial – operación de alto riesgo | O68: 4351969 / 963870698 | P68: www.geomecanicalatina.com | Q68: Av. Marginal 467 Urb. Salamanca Ate - Lima | R68: Lima | S68: No
A69: 68 | D69: Geotec S.A. | E69: Perú | F69: geotec@geotec.com.pe | H69: Directorio SSO 2026 | I69: Prospecto | J69: Alta | K69: Identificar Gerente SSOMA/HSE en LinkedIn y proponer demo | L69: Directorio SSO 2026, pág. PDF 21, 37. Sin contacto nominal; no inventar decisor. | M69: Perforación geológica; Empresas contratistas y conexas | N69: Cliente potencial – operación de alto riesgo | O69: 989138078 | P69: www.geotec.com.pe | Q69: Av. Industrial 228 Urb. Aurora Ate - Lima | R69: Lima | S69: No
A70: 69 | D70: Geotecnia Peruana S.R.L. | E70: Perú | F70: peruana@geotecnia.net | H70: Directorio SSO 2026 | I70: Prospecto | J70: Alta | K70: Identificar Gerente SSOMA/HSE en LinkedIn y proponer demo | L70: Directorio SSO 2026, pág. PDF 21, 36, 37. Sin contacto nominal; no inventar decisor. | M70: Perforación geológica; Voladura, explosivos y polvorines; Empresas contratistas y conexas | N70: Cliente potencial – operación de alto riesgo | O70: 4366040 / 998735963 | P70: www.geotecniaperuana.com | Q70: Cl. Camino Real Mz.N Lt.2 Urb. San Francisco - Ate Vitarte - Lima | R70: Lima | S70: No
A71: 70 | D71: Ginsumil Corporation | E71: Perú | F71: ventas@ginsumilcorp.com | H71: Directorio SSO 2026 | I71: Prospecto | J71: Alta | K71: Identificar Gerente SSOMA/HSE en LinkedIn y proponer demo | L71: Directorio SSO 2026, pág. PDF 21. Sin contacto nominal; no inventar decisor. | M71: Perforación geológica | N71: Cliente potencial – operación de alto riesgo | O71: 993022915 | P71: www.ginsumilcorp.com | Q71: Av. Mariano Pastor Sevilla Mz.D Lt.40 Sector 5 San Juan de Miraflores - Lima | R71: Lima | S71: No
A72: 71 | D72: Grupo Coopsol | E72: Perú | F72: informes@coopsol.com | H72: Directorio SSO 2026 | I72: Prospecto | J72: Alta | K72: Identificar Gerente SSOMA/HSE en LinkedIn y proponer demo | L72: Directorio SSO 2026, pág. PDF 17, 18. Sin contacto nominal; no inventar decisor. | M72: Higiene industrial, saneamiento y limpieza; Mantenimiento industrial | N72: Cliente potencial – operación de alto riesgo | O72: 4223344 | P72: www.grupocoopsol.com | Q72: Cl. Federico Villarreal 555 - San Isidro Lima | R72: Lima | S72: No
A73: 72 | D73: Grupo Vivargo S.A.C. | E73: Perú | F73: centralperu@vivargo.com | H73: Directorio SSO 2026 | I73: Prospecto | J73: Alta | K73: Identificar Gerente SSOMA/HSE en LinkedIn y proponer demo | L73: Directorio SSO 2026, pág. PDF 34, 35. Sin contacto nominal; no inventar decisor. | M73: Transporte de combustibles y materiales peligrosos; Vehículos: ventas, alquiler, repuestos y reparaciones | N73: Cliente potencial – operación de alto riesgo | O73: 7158000 / 959376659 | P73: www.vivargo.com | Q73: Av. Premio Real Mz. S1 Lt. 4 Urb. Los Huertos de Villa - Chorrillos - Lima | R73: Lima | S73: No
A74: 73 | D74: GSH Genie | E74: Perú | F74: ingenieria@gsh.pe | H74: Directorio SSO 2026 | I74: Prospecto | J74: Alta | K74: Identificar Gerente SSOMA/HSE en LinkedIn y proponer demo | L74: Directorio SSO 2026, pág. PDF 33. Sin contacto nominal; no inventar decisor. | M74: Sostenimiento de rocas y suelos | N74: Cliente potencial – operación de alto riesgo | O74: 966798391 | P74: www.gsh.pe | Q74: Jr. Johan Strauss 732 San Borja - Lima | R74: Lima | S74: No
... A79: 78 | D79: IESA S.A. | E79: Perú | F79: comercial@iesa.com.pe | H79: Directorio SSO 2026 | I79: Prospecto | J79: Alta | K79: Identificar Gerente SSOMA/HSE en LinkedIn y proponer demo | L79: Directorio SSO 2026, pág. PDF 37. Sin contacto nominal; no inventar decisor. | M79: Empresas contratistas y conexas | N79: Cliente potencial – operación de alto riesgo | O79: 6142121 | P79: www.iesa.com.pe | Q79: Av. Los Insurgentes 1075 La Perla - Callao | R79: Callao | S79: No
A80: 79 | D80: IMECON | E80: Perú | H80: Directorio SSO 2026 | I80: Prospecto | J80: Alta | K80: Identificar Gerente SSOMA/HSE en LinkedIn y proponer demo | L80: Directorio SSO 2026, pág. PDF 37. Sin contacto nominal; no inventar decisor. | M80: Empresas contratistas y conexas | N80: Cliente potencial – operación de alto riesgo | O80: 7433222 | P80: www.imecon.com.pe | Q80: Autopista Panamericana Sur km 46 Punta Negra - Lima | R80: Lima | S80: No
A81: 80 | D81: INCIMMET S.A. | E81: Perú | F81: comercial_peru@incimmet.com | H81: Directorio SSO 2026 | I81: Prospecto | J81: Alta | K81: Identificar Gerente SSOMA/HSE en LinkedIn y proponer demo | L81: Directorio SSO 2026, pág. PDF 37. Sin contacto nominal; no inventar decisor. | M81: Empresas contratistas y conexas | N81: Cliente potencial – operación de alto riesgo | O81: 963701111 | P81: www.incimmet.com | Q81: Av. Manuel Olguín 211, Piso 14 Of.1401 Santiago de Surco - Lima | R81: Lima | S81: No
A82: 81 | D82: Ingeomin S.A.C. | E82: Perú | H82: Directorio SSO 2026 | I82: Prospecto | J82: Alta | K82: Identificar Gerente SSOMA/HSE en LinkedIn y proponer demo | L82: Directorio SSO 2026, pág. PDF 21. Sin contacto nominal; no inventar decisor. | M82: Perforación geológica | N82: Cliente potencial – operación de alto riesgo | O82: 3513888 | Q82: Av. Prol. Javier Prado 9269 Urb. Los Portales de Javier Prado Ate - Lima | R82: Lima | S82: No
A83: 82 | D83: Innova BS S.A.C. | E83: Perú | F83: info@innovabs.com | H83: Directorio SSO 2026 | I83: Prospecto | J83: Alta | K83: Identificar Gerente SSOMA/HSE en LinkedIn y proponer demo | L83: Directorio SSO 2026, pág. PDF 19. Sin contacto nominal; no inventar decisor. | M83: Mantenimiento industrial | N83: Cliente potencial – operación de alto riesgo | O83: 935841522 | P83: www.innovabs.com | Q83: Cl. Grimaldo del Solar 162 Of. 307 Miraflores - Lima | R83: Lima | S83: No
A84: 83 | D84: Jaidor S.A.C. | E84: Perú | F84: transportesjaidor@hotmail.com | H84: Directorio SSO 2026 | I84: Prospecto | J84: Alta | K84: Identificar Gerente SSOMA/HSE en LinkedIn y proponer demo | L84: Directorio SSO 2026, pág. PDF 34. Sin contacto nominal; no inventar decisor. | M84: Transporte de combustibles y materiales peligrosos | N84: Cliente potencial – operación de alto riesgo | O84: 941751202 | Q84: Jr. Trujillo Sur 932 Chosica Lurigancho - Lima | R84: Lima | S84: No
A85: 84 | D85: JC Portal Drilling Supplies S.A.C. | E85: Perú | F85: ycaicedo@jcpds.pe | H85: Directorio SSO 2026 | I85: Prospecto | J85: Alta | K85: Identificar Gerente SSOMA/HSE en LinkedIn y proponer demo | L85: Directorio SSO 2026, pág. PDF 21. Sin contacto nominal; no inventar decisor. | M85: Perforación geológica | N85: Cliente potencial – operación de alto riesgo | O85: 992565590 | P85: www.jcportalds.com | Q85: Cl. Camino B Lt.17A Centro Logístico Servinegocios Almacén 01 Nº17A Urb. Villa Baja, Chorrillos - Lima | R85: Lima | S85: No
A86: 85 | D86: JRC Ingeniería y Construcción S.A.C. | E86: Perú | F86: info@jrcing.com.pe | H86: Directorio SSO 2026 | I86: Prospecto | J86: Alta | K86: Identificar Gerente SSOMA/HSE en LinkedIn y proponer demo | L86: Directorio SSO 2026, pág. PDF 37. Sin contacto nominal; no inventar decisor. | M86: Empresas contratistas y conexas | N86: Cliente potencial – operación de alto riesgo | O86: 6301500 | P86: www.jrc.com.pe | Q86: Av. Jorge Basadre 233 Int.601 Centro Empresarial, San Isidro - Lima | R86: Lima | S86: No
A87: 86 | D87: Layher Perú S.A.C. | E87: Perú | F87: comercial@layher.pe | H87: Directorio SSO 2026 | I87: Prospecto | J87: Alta | K87: Identificar Gerente SSOMA/HSE en LinkedIn y proponer demo | L87: Directorio SSO 2026, pág. PDF 6, 7, 37. Sin contacto nominal; no inventar decisor. | M87: Andamios y trabajos en altura; Campamentos e instalaciones; Empresas contratistas y conexas | N87: Cliente potencial – operación de alto riesgo | O87: (01) 4303268 / (+51) 986672239 | P87: www.layher.pe | Q87: Av. Portillo Grande Mz.22 Lt.1 Urb. Macrópolis Etapa 1, Lurín - Lima | R87: Lima | S87: No
A88: 87 | D88: MAC Transport S.A.C. | E88: Perú | F88: contactos@mactransport.com.pe | H88: Directorio SSO 2026 | I88: Prospecto | J88: Alta | K88: Identificar Gerente SSOMA/HSE en LinkedIn y proponer demo | L88: Directorio SSO 2026, pág. PDF 34. Sin contacto nominal; no inventar decisor. | M88: Transporte de combustibles y materiales peligrosos | N88: Cliente potencial – operación de alto riesgo | O88: 6238782 | P88: www.mactransport.com.pe | Q88: Cl. Monterosa 240 Of. 401 Urb. Chacarilla Santiago de Surco - Lima | R88: Lima | S88: No
A89: 88 | D89: Maccaferri del Perú S.A.C. | E89: Perú | F89: info.pe@maccaferri.com | H89: Directorio SSO 2026 | I89: Prospecto | J89: Alta | K89: Identificar Gerente SSOMA/HSE en LinkedIn y proponer demo | L89: Directorio SSO 2026, pág. PDF 33. Sin contacto nominal; no inventar decisor. | M89: Sostenimiento de rocas y suelos | N89: Cliente potencial – operación de alto riesgo | O89: 2011060 | P89: www.maccaferri.com.pe | Q89: Carretera Nueva Panamericana Sur Km 33 - Lurín - Lima | R89: Lima | S89: No
A90: 89 | D90: Mainserv Ingenieros S.A.C. | E90: Perú | H90: Directorio SSO 2026 | I90: Prospecto | J90: Alta | K90: Identificar Gerente SSOMA/HSE en LinkedIn y proponer demo | L90: Directorio SSO 2026, pág. PDF 37. Sin contacto nominal; no inventar decisor. | M90: Empresas contratistas y conexas | N90: Cliente potencial – operación de alto riesgo | O90: 4899266 | P90: www.mainservingenieros.com | Q90: Av. Aviación 2695 Of.302 - San Borja Lima | R90: Lima | S90: No
A91: 90 | D91: Manuchar Perú S.A.C. | E91: Perú | F91: info@manuchar.com.pe | H91: Directorio SSO 2026 | I91: Prospecto | J91: Alta | K91: Identificar Gerente SSOMA/HSE en LinkedIn y proponer demo | L91: Directorio SSO 2026, pág. PDF 5, 34. Sin contacto nominal; no inventar decisor. | M91: Agua, análisis, tecnología y productos; Transporte de combustibles y materiales peligrosos | N91: Cliente potencial – operación de alto riesgo | O91: 6185600 | P91: www.manuchar.com | Q91: Cl. 2 Nro.147 (Av. Néstor Gambetta ex Fundo Oquendo) Callao | R91: Callao | S91: No
A92: 91 | D92: Mas Errazuriz del Perú S.A.C. | E92: Perú | F92: consultas@maserrazuriz.com.pe | H92: Directorio SSO 2026 | I92: Prospecto | J92: Alta | K92: Identificar Gerente SSOMA/HSE en LinkedIn y proponer demo | L92: Directorio SSO 2026, pág. PDF 33, 37. Sin contacto nominal; no inventar decisor. | M92: Sostenimiento de rocas y suelos; Empresas contratistas y conexas | N92: Cliente potencial – operación de alto riesgo | O92: 2022300 | P92: www.maserrazuriz.cl | Q92: Av. Alfredo Benavides 768 Int.1201 Urb. Leuro - Miraflores - Lima | R92: Lima | S92: No
A93: 92 | D93: Master Drilling Perú S.A.C. | E93: Perú | F93: info@masterdrilling.com | H93: Directorio SSO 2026 | I93: Prospecto | J93: Alta | K93: Identificar Gerente SSOMA/HSE en LinkedIn y proponer demo | L93: Directorio SSO 2026, pág. PDF 21, 37. Sin contacto nominal; no inventar decisor. | M93: Perforación geológica; Empresas contratistas y conexas | N93: Cliente potencial – operación de alto riesgo | O93: 3367474 | P93: www.masterdrilling.com | Q93: Urb. La Concordia Mz.B Lt.13 (Sublote 13A-13B) km 17 Antigua Panamericana Sur, Villa El Salvador - Lima | R93: Lima | S93: No
A94: 93 | D94: MCA Perforaciones S.A.C. | E94: Perú | F94: contacto@mca.la | H94: Directorio SSO 2026 | I94: Prospecto | J94: Alta | K94: Identificar Gerente SSOMA/HSE en LinkedIn y proponer demo | L94: Directorio SSO 2026, pág. PDF 21. Sin contacto nominal; no inventar decisor. | M94: Perforación geológica | N94: Cliente potencial – operación de alto riesgo | O94: 989102880 | P94: www.mcaperforaciones.com | Q94: Cl. Francia 173 Urb. Los Portales de Javier Prado, Ate Vitarte - Lima | R94: Lima | S94: No
A95: 94 | D95: MDH Perforaciones | E95: Perú | F95: oper@mdh.com.pe | H95: Directorio SSO 2026 | I95: Prospecto | J95: Alta | K95: Identificar Gerente SSOMA/HSE en LinkedIn y proponer demo | L95: Directorio SSO 2026, pág. PDF 37. Sin contacto nominal; no inventar decisor. | M95: Empresas contratistas y conexas | N95: Cliente potencial – operación de alto riesgo | O95: 7007250 / 958799938 / 986979436 | P95: www.mdh.com.pe | Q95: Av. Malecón Checa 3677 - San Juan de Lurigancho - Lima | R95: Lima | S95: No
A96: 95 | D96: MDH-PD S.A.C. | E96: Perú | F96: oper@mdh.com.pe | H96: Directorio SSO 2026 | I96: Prospecto | J96: Alta | K96: Identificar Gerente SSOMA/HSE en LinkedIn y proponer demo | L96: Directorio SSO 2026, pág. PDF 21, 33. Sin contacto nominal; no inventar decisor. | M96: Perforación geológica; Sostenimiento de rocas y suelos | N96: Cliente potencial – operación de alto riesgo | O96: 7007250 / 958799938 | P96: www.mdh.com.pe | Q96: Av. Malecón Checa 3677 San Juan de Lurigancho - Lima | R96: Lima | S96: No
A97: 96 | D97: Metcom M&S E.I.R.L. | E97: Perú | F97: info@metcomperu.com | H97: Directorio SSO 2026 | I97: Prospecto | J97: Alta | K97: Identificar Gerente SSOMA/HSE en LinkedIn y proponer demo | L97: Directorio SSO 2026, pág. PDF 19, 32, 37. Sin contacto nominal; no inventar decisor. | M97: Mantenimiento industrial; Soldadura industrial; Empresas contratistas y conexas | N97: Cliente potencial – operación de alto riesgo | O97: (054) 250389 | P97: www.metcomperu.com | Q97: Urb. Alborada K-8 A.V. Apima II Cerro Colorado - Arequipa | R97: Arequipa | S97: No
A98: 97 | D98: MICSAC | E98: Perú | F98: informes@micsac.com | H98: Directorio SSO 2026 | I98: Prospecto | J98: Alta | K98: Identificar Gerente SSOMA/HSE en LinkedIn y proponer demo | L98: Directorio SSO 2026, pág. PDF 19. Sin contacto nominal; no inventar decisor. | M98: Mantenimiento industrial | N98: Cliente potencial – operación de alto riesgo | P98: www.micsac.com | Q98: Jr. Tambo Real 390, Chorrillos - Lima | R98: Lima | S98: No
A99: 98 | D99: Minera Tauro S.A.C. | E99: Perú | F99: info@minerataurosac.com | H99: Directorio SSO 2026 | I99: Prospecto | J99: Alta | K99: Identificar Gerente SSOMA/HSE en LinkedIn y proponer demo | L99: Directorio SSO 2026, pág. PDF 37. Sin contacto nominal; no inventar decisor. | M99: Empresas contratistas y conexas | N99: Cliente potencial – operación de alto riesgo | O99: 2252974 / 4760212 | P99: www.minerataurosac.com | Q99: Av. Aviación 2490 - 301 - San Borja Lima | R99: Lima | S99: No
A100: 99 | D100: Mintech Mining Technology E.I.R.L. | E100: Perú | F100: info@mintech.com.pe | H100: Directorio SSO 2026 | I100: Prospecto | J100: Alta | K100: Identificar Gerente SSOMA/HSE en LinkedIn y proponer demo | L100: Directorio SSO 2026, pág. PDF 33. Sin contacto nominal; no inventar decisor. | M100: Sostenimiento de rocas y suelos | N100: Cliente potencial – operación de alto riesgo | O100: 2766979 / 6228124 | P100: www.mintech.com.pe | Q100: Av. Los Pinos Mz.W Lt.2 Asociación Chillón Puente Piedra - Lima | R100: Lima | S100: No
A101: 100 | D101: Miro Vidal y Compañia S.A.C. | E101: Perú | F101: mvc@mvc.com.pe | H101: Directorio SSO 2026 | I101: Prospecto | J101: Alta | K101: Identificar Gerente SSOMA/HSE en LinkedIn y proponer demo | L101: Directorio SSO 2026, pág. PDF 37. Sin contacto nominal; no inventar decisor. | M101: Empresas contratistas y conexas | N101: Cliente potencial – operación de alto riesgo | O101: 4366677 | P101: www.mvc.com.pe | Q101: Cl. Talladores 317 Urb. Los Artesanos Ate Vitarte - Lima | R101: Lima | S101: No
A102: 101 | D102: Mota-Engil Perú S.A. | E102: Perú | H102: Directorio SSO 2026 | I102: Prospecto | J102: Alta | K102: Identificar Gerente SSOMA/HSE en LinkedIn y proponer demo | L102: Directorio SSO 2026, pág. PDF 37. Sin contacto nominal; no inventar decisor. | M102: Empresas contratistas y conexas | N102: Cliente potencial – operación de alto riesgo | O102: 4143665 | P102: www.mota-engil.pe | Q102: Av. Javier Prado Este 444 Edificio Torre Prado P. 22-23 - San Isidro - Lima | R102: Lima | S102: No
A103: 102 | D103: Multiservicios LIFER & EB S.A.C. | E103: Perú | F103: lifer.eb.sac@gmail.com | H103: Directorio SSO 2026 | I103: Prospecto | J103: Alta | K103: Identificar Gerente SSOMA/HSE en LinkedIn y proponer demo | L103: Directorio SSO 2026, pág. PDF 34. Sin contacto nominal; no inventar decisor. | M103: Transporte de combustibles y materiales peligrosos | N103: Cliente potencial – operación de alto riesgo | O103: 966390619 | Q103: Mz. K Lt. 6 Urb. Las Capullanas Trujillo - La Libertad | R103: La Libertad | S103: No
A104: 103 | D104: Multiservicios Papillon S.A.C. | E104: Perú | H104: Directorio SSO 2026 | I104: Prospecto | J104: Alta | K104: Identificar Gerente SSOMA/HSE en LinkedIn y proponer demo | L104: Directorio SSO 2026, pág. PDF 34. Sin contacto nominal; no inventar decisor. | M104: Transporte de combustibles y materiales peligrosos | N104: Cliente potencial – operación de alto riesgo | Q104: Jr. Washington 1308 Of. 802 Cercado de Lima - Lima | R104: Lima | S104: No
...

Sheet Oportunidades
A1: ID oportunidad | B1: ID contacto | C1: Empresa | D1: Necesidad | E1: Solución propuesta | F1: Etapa | G1: Valor estimado | H1: Probabilidad | I1: Próxima acción | J1: Fecha

Sheet Resumen
A1: Evento/Fuente | B1: País | C1: Cantidad
A2: Directorio SSO 2026 | B2: Perú | C2: =COUNTIFS(Contactos!$H:$H,$A2,Contactos!$E:$E,$B2) -> 667
A3: Directorio SSO 2026 | B3: Colombia | C3: =COUNTIFS(Contactos!$H:$H,$A3,Contactos!$E:$E,$B3) -> 1
A4: Directorio SSO 2026 | B4: Brasil | C4: =COUNTIFS(Contactos!$H:$H,$A4,Contactos!$E:$E,$B4) -> 1
A5: Directorio SSO 2026 | B5: Argentina | C5: =COUNTIFS(Contactos!$H:$H,$A5,Contactos!$E:$E,$B5) -> 1
A6: Directorio SSO 2026 | B6: Canadá | C6: =COUNTIFS(Contactos!$H:$H,$A6,Contactos!$E:$E,$B6) -> 1
A7: Directorio SSO 2026 | B7: Estados Unidos | C7: =COUNTIFS(Contactos!$H:$H,$A7,Contactos!$E:$E,$B7) -> 1
A8: Directorio SSO 2026 | B8: Australia | C8: =COUNTIFS(Contactos!$H:$H,$A8,Contactos!$E:$E,$B8) -> 1
A9: Directorio SSO 2026 | B9: China | C9: =COUNTIFS(Contactos!$H:$H,$A9,Contactos!$E:$E,$B9) -> 1
A10: Total | C10: =SUM(C2:C9) -> 674
A12: Segmento SafetyMind | B12: Alta | C12: Media | D12: Baja | E12: Total
A13: Cliente potencial – operación de alto riesgo | B13: =COUNTIFS(Contactos!$N:$N,$A13,Contactos!$J:$J,B$12) -> 168 | C13: =COUNTIFS(Contactos!$N:$N,$A13,Contactos!$J:$J,C$12) -> 0 | D13: =COUNTIFS(Contactos!$N:$N,$A13,Contactos!$J:$J,D$12) -> 0 | E13: =SUM(B13:D13) -> 168
A14: Partner tecnológico / competidor | B14: =COUNTIFS(Contactos!$N:$N,$A14,Contactos!$J:$J,B$12) -> 16 | C14: =COUNTIFS(Contactos!$N:$N,$A14,Contactos!$J:$J,C$12) -> 0 | D14: =COUNTIFS(Contactos!$N:$N,$A14,Contactos!$J:$J,D$12) -> 0 | E14: =SUM(B14:D14) -> 16
A15: Canal / aliado – consultoría SST | B15: =COUNTIFS(Contactos!$N:$N,$A15,Contactos!$J:$J,B$12) -> 82 | C15: =COUNTIFS(Contactos!$N:$N,$A15,Contactos!$J:$J,C$12) -> 0 | D15: =COUNTIFS(Contactos!$N:$N,$A15,Contactos!$J:$J,D$12) -> 0 | E15: =SUM(B15:D15) -> 82
A16: Aliado complementario – seguridad | B16: =COUNTIFS(Contactos!$N:$N,$A16,Contactos!$J:$J,B$12) -> 8 | C16: =COUNTIFS(Contactos!$N:$N,$A16,Contactos!$J:$J,C$12) -> 105 | D16: =COUNTIFS(Contactos!$N:$N,$A16,Contactos!$J:$J,D$12) -> 0 | E16: =SUM(B16:D16) -> 113
A17: Canal / distribuidor EPP | B17: =COUNTIFS(Contactos!$N:$N,$A17,Contactos!$J:$J,B$12) -> 6 | C17: =COUNTIFS(Contactos!$N:$N,$A17,Contactos!$J:$J,C$12) -> 78 | D17: =COUNTIFS(Contactos!$N:$N,$A17,Contactos!$J:$J,D$12) -> 0 | E17: =SUM(B17:D17) -> 84
A18: Aliado complementario – salud | B18: =COUNTIFS(Contactos!$N:$N,$A18,Contactos!$J:$J,B$12) -> 1 | C18: =COUNTIFS(Contactos!$N:$N,$A18,Contactos!$J:$J,C$12) -> 47 | D18: =COUNTIFS(Contactos!$N:$N,$A18,Contactos!$J:$J,D$12) -> 0 | E18: =SUM(B18:D18) -> 48
A19: Proveedor industrial (baja afinidad) | B19: =COUNTIFS(Contactos!$N:$N,$A19,Contactos!$J:$J,B$12) -> 0 | C19: =COUNTIFS(Contactos!$N:$N,$A19,Contactos!$J:$J,C$12) -> 0 | D19: =COUNTIFS(Contactos!$N:$N,$A19,Contactos!$J:$J,D$12) -> 163 | E19: =SUM(B19:D19) -> 163
A20: Total | B20: =SUM(B13:B19) -> 281 | C20: =SUM(C13:C19) -> 230 | D20: =SUM(D13:D19) -> 163 | E20: =SUM(E13:E19) -> 674
A22: Estado (pipeline) | B22: Cantidad
A23: Prospecto | B23: =COUNTIF(Contactos!$I:$I,A23) -> 674
A24: Contactado | B24: =COUNTIF(Contactos!$I:$I,A24) -> 0
A25: Reunión | B25: =COUNTIF(Contactos!$I:$I,A25) -> 0
A26: Propuesta | B26: =COUNTIF(Contactos!$I:$I,A26) -> 0
A27: Cliente | B27: =COUNTIF(Contactos!$I:$I,A27) -> 0
A28: No interesado | B28: =COUNTIF(Contactos!$I:$I,A28) -> 0
A30: Indicadores de calidad de datos | B30: Cantidad
A31: Con email | B31: =COUNTIF(Contactos!$F$2:$F$2000,"?*") -> 623
A32: Con teléfono | B32: =COUNTA(Contactos!$O$2:$O$2000) -> 654
A33: Con contacto nominal | B33: =COUNTIF(Contactos!$B$2:$B$2000,"?*") -> 20
A34: Anunciantes del directorio | B34: =COUNTIF(Contactos!$S:$S,"Sí") -> 21
A35: Con LinkedIn validado | B35: =COUNTIF(Contactos!$G$2:$G$2000,"?*") -> 0

Sheet Eventos
A1: Evento | B1: País | C1: Valor para SafetyMind
A2: Directorio SSO 2026 – Cero Accidentes (22.ª ed.) | B2: Perú | C2: Mapa de ~670 proveedores SST en Perú: contratistas mineros (clientes potenciales), consultoras SST (canal), TI/telecom (partners/competencia), distribuidores EPP (canal hacia minería) y 21 anunciantes con inversión activa en SST.
