Workbook

Sheet Contactos
A1: ID | B1: Nombre | C1: Cargo | D1: Empresa | E1: País | F1: Email | G1: LinkedIn | H1: Origen | I1: Estado | J1: Prioridad | K1: Próxima acción | L1: Notas | M1: Segmento SafetyMind | N1: Stand(s) | O1: N° stands | P1: Pabellón país / zona | Q1: Web | R1: Teléfono(s) | S1: Cruce otros CRM
A2: 1 | D2: Albemarle | E2: Chile | H2: Exponor 2026 | I2: Prospecto | J2: Alta | K2: Mapear Gerente SSOMA/HSE y faenas; proponer piloto | L2: Exponor 2026. Sin contacto publicado. | M2: Minera (cliente final) | N2: Exterior B-65 | O2: 1 | S2: No
A3: 2 | D3: Antofagasta Minerals | E3: Chile | H3: Exponor 2026 | I3: Prospecto | J3: Alta | K3: Mapear Gerente SSOMA/HSE y faenas; proponer piloto | L3: Exponor 2026. Sin contacto publicado. | M3: Minera (cliente final) | N3: Exterior C-70 y 71 | O3: 1 | S3: No
A4: 3 | D4: BHP | E4: Chile | H4: Exponor 2026 | I4: Prospecto | J4: Alta | K4: Mapear Gerente SSOMA/HSE y faenas; proponer piloto | L4: Exponor 2026. Sin contacto publicado. | M4: Minera (cliente final) | N4: Exterior C-78-79-80-81 y 82 | O4: 1 | S4: No
A5: 4 | D5: Capstone Copper Mantos Blancos | E5: Chile | H5: Exponor 2026 | I5: Prospecto | J5: Alta | K5: Mapear Gerente SSOMA/HSE y faenas; proponer piloto | L5: Exponor 2026. Sin contacto publicado. | M5: Minera (cliente final) | N5: Exterior B-45 | O5: 1 | S5: No
A6: 5 | D6: Cerro Alto Minería | E6: Chile | H6: Exponor 2026 | I6: Prospecto | J6: Alta | K6: Mapear Gerente SSOMA/HSE y faenas; proponer piloto | L6: Exponor 2026. Sin contacto publicado. | M6: Minera (cliente final) | N6: Oro-1183 | O6: 1 | S6: No
A7: 6 | D7: Cía. Minera Cordillera Chile SCM | E7: Chile | H7: Exponor 2026 | I7: Prospecto | J7: Alta | K7: Mapear Gerente SSOMA/HSE y faenas; proponer piloto | L7: Exponor 2026. Sin contacto publicado. | M7: Minera (cliente final) | N7: Oro-1178 | O7: 1 | S7: No
A8: 7 | D8: Codelco | E8: Chile | H8: Exponor 2026 | I8: Prospecto | J8: Alta | K8: Mapear Gerente SSOMA/HSE y faenas; proponer piloto | L8: Exponor 2026. Sin contacto publicado. | M8: Minera (cliente final) | N8: Exterior B-52 | O8: 1 | S8: No
A9: 8 | D9: Compañía Minera CCL | E9: Chile | H9: Exponor 2026 | I9: Prospecto | J9: Alta | K9: Mapear Gerente SSOMA/HSE y faenas; proponer piloto | L9: Exponor 2026. Sin contacto publicado. | M9: Minera (cliente final) | N9: Litio-945 | O9: 1 | P9: EstaremosEnExponor | S9: No
A10: 9 | D10: Glencore | E10: Chile | H10: Exponor 2026 | I10: Prospecto | J10: Alta | K10: Mapear Gerente SSOMA/HSE y faenas; proponer piloto | L10: Exponor 2026. Sin contacto publicado. | M10: Minera (cliente final) | N10: Exterior B-37 | O10: 1 | S10: No
A11: 10 | D11: Minera El Abra | E11: Chile | H11: Exponor 2026 | I11: Prospecto | J11: Alta | K11: Mapear Gerente SSOMA/HSE y faenas; proponer piloto | L11: Exponor 2026. Sin contacto publicado. | M11: Minera (cliente final) | N11: Exterior B-51 | O11: 1 | S11: No
A12: 11 | D12: Novandina Litio | E12: Chile | H12: Exponor 2026 | I12: Prospecto | J12: Alta | K12: Mapear Gerente SSOMA/HSE y faenas; proponer piloto | L12: Exponor 2026. Sin contacto publicado. | M12: Minera (cliente final) | N12: Exterior B-36 | O12: 1 | S12: No
A13: 12 | D13: Sierra Gorda SCM | E13: Chile | H13: Exponor 2026 | I13: Prospecto | J13: Alta | K13: Mapear Gerente SSOMA/HSE y faenas; proponer piloto | L13: Exponor 2026. Sin contacto publicado. | M13: Minera (cliente final) | N13: Exterior B-39 | O13: 1 | S13: No
A14: 13 | D14: SQM | E14: Chile | H14: Exponor 2026 | I14: Prospecto | J14: Alta | K14: Mapear Gerente SSOMA/HSE y faenas; proponer piloto | L14: Exponor 2026. Sin contacto publicado. | M14: Minera (cliente final) | N14: Exterior B-36 | O14: 1 | S14: No
A15: 14 | D15: Teck Resourses Chile | E15: Chile | H15: Exponor 2026 | I15: Prospecto | J15: Alta | K15: Mapear Gerente SSOMA/HSE y faenas; proponer piloto | L15: Exponor 2026. Sin contacto publicado. | M15: Minera (cliente final) | N15: Exterior B-053A | O15: 1 | S15: No
A16: 15 | D16: All Drill Chile SpA | E16: Chile | H16: Exponor 2026 | I16: Prospecto | J16: Alta | K16: Identificar Gerente HSE/SSOMA en LinkedIn y proponer demo | L16: Exponor 2026. Sin contacto publicado. | M16: Cliente potencial – contratista / operación de alto riesgo | N16: Oro-1099 | O16: 1 | S16: No
A17: 16 | D17: Alo Rental | E17: Chile | H17: Exponor 2026 | I17: Prospecto | J17: Alta | K17: Identificar Gerente HSE/SSOMA en LinkedIn y proponer demo | L17: Exponor 2026. Sin contacto publicado. | M17: Cliente potencial – contratista / operación de alto riesgo | N17: Cobalto-1370 | O17: 1 | S17: No
A18: 17 | D18: Andamios At-Pac | E18: Chile | H18: Exponor 2026 | I18: Prospecto | J18: Alta | K18: Identificar Gerente HSE/SSOMA en LinkedIn y proponer demo | L18: Exponor 2026. Sin contacto publicado. | M18: Cliente potencial – contratista / operación de alto riesgo | N18: Exterior E-140 | O18: 1 | S18: No
A19: 18 | D19: BCM Servicios Mineros | E19: Chile | H19: Exponor 2026 | I19: Prospecto | J19: Alta | K19: Identificar Gerente HSE/SSOMA en LinkedIn y proponer demo | L19: Exponor 2026. Sin contacto publicado. | M19: Cliente potencial – contratista / operación de alto riesgo | N19: Yodo-706 | O19: 1 | S19: No
A20: 19 | D20: Boga Andamios y Servicios SpA | E20: Chile | H20: Exponor 2026 | I20: Prospecto | J20: Alta | K20: Identificar Gerente HSE/SSOMA en LinkedIn y proponer demo | L20: Exponor 2026. Sin contacto publicado. | M20: Cliente potencial – contratista / operación de alto riesgo | N20: Oro-1137 | O20: 1 | S20: No
A21: 20 | D21: Bus 4x4 Group | E21: Australia | H21: Exponor 2026 | I21: Prospecto | J21: Alta | K21: Identificar Gerente HSE/SSOMA en LinkedIn y proponer demo | L21: Exponor 2026. Sin contacto publicado. | M21: Cliente potencial – contratista / operación de alto riesgo | N21: Yodo-666 | O21: 1 | P21: Australia | S21: No
A22: 21 | D22: Buses Hualpén | E22: Chile | H22: Exponor 2026 | I22: Prospecto | J22: Alta | K22: Identificar Gerente HSE/SSOMA en LinkedIn y proponer demo | L22: Exponor 2026. Sin contacto publicado. | M22: Cliente potencial – contratista / operación de alto riesgo | N22: Molibdeno-1275 | O22: 1 | S22: No
A23: 22 | D23: C&V International | E23: Perú | F23: ventas@cvinternational.com.pe | H23: Exponor 2026 | I23: Prospecto | J23: Alta | K23: Identificar Gerente HSE/SSOMA en LinkedIn y proponer demo | L23: Exponor 2026. También en CRM Directorio SSO 2026 (ID 18). | M23: Cliente potencial – contratista / operación de alto riesgo | N23: Plata-564A | O23: 1 | P23: Perú | Q23: www.cvinternational.com.pe | R23: 5156714 | S23: Directorio SSO (ID 18)
A24: 23 | D24: Cas Servicios Industriales | E24: Chile | H24: Exponor 2026 | I24: Prospecto | J24: Alta | K24: Identificar Gerente HSE/SSOMA en LinkedIn y proponer demo | L24: Exponor 2026. Sin contacto publicado. | M24: Cliente potencial – contratista / operación de alto riesgo | N24: Litio-963 | O24: 1 | S24: No
A25: 24 | D25: Cemtec - Latam Mining Services | E25: Chile | H25: Exponor 2026 | I25: Prospecto | J25: Alta | K25: Identificar Gerente HSE/SSOMA en LinkedIn y proponer demo | L25: Exponor 2026. Sin contacto publicado. | M25: Cliente potencial – contratista / operación de alto riesgo | N25: Cobalto-1404 | O25: 1 | S25: No
A26: 25 | D26: Christensen | E26: Chile | H26: Exponor 2026 | I26: Prospecto | J26: Alta | K26: Identificar Gerente HSE/SSOMA en LinkedIn y proponer demo | L26: Exponor 2026. Sin contacto publicado. | M26: Cliente potencial – contratista / operación de alto riesgo | N26: Exterior D-109 | O26: 1 | S26: No
A27: 26 | D27: Complejo Portuario Mejillones | E27: Chile | H27: Exponor 2026 | I27: Prospecto | J27: Alta | K27: Identificar Gerente HSE/SSOMA en LinkedIn y proponer demo | L27: Exponor 2026. Sin contacto publicado. | M27: Cliente potencial – contratista / operación de alto riesgo | N27: Yodo-799 | O27: 1 | S27: No
A28: 27 | D28: Conciencia Logística | E28: Chile | H28: Exponor 2026 | I28: Prospecto | J28: Alta | K28: Identificar Gerente HSE/SSOMA en LinkedIn y proponer demo | L28: Exponor 2026. Sin contacto publicado. | M28: Cliente potencial – contratista / operación de alto riesgo | N28: Molibdeno-1238 | O28: 1 | S28: No
A29: 28 | D29: Confipetrol Chile SpA | E29: Chile | H29: Exponor 2026 | I29: Prospecto | J29: Alta | K29: Identificar Gerente HSE/SSOMA en LinkedIn y proponer demo | L29: Exponor 2026. Sin contacto publicado. | M29: Cliente potencial – contratista / operación de alto riesgo | N29: Hierro-1478 | O29: 1 | S29: No
A30: 29 | D30: Constructora Baical Ltda. - Baical Rental | E30: Chile | H30: Exponor 2026 | I30: Prospecto | J30: Alta | K30: Identificar Gerente HSE/SSOMA en LinkedIn y proponer demo | L30: Exponor 2026. Sin contacto publicado. | M30: Cliente potencial – contratista / operación de alto riesgo | N30: Hierro-1488 | O30: 1 | S30: No
A31: 30 | D31: Constructora El Sauce S.A | E31: Chile | H31: Exponor 2026 | I31: Prospecto | J31: Alta | K31: Identificar Gerente HSE/SSOMA en LinkedIn y proponer demo | L31: Exponor 2026. Sin contacto publicado. | M31: Cliente potencial – contratista / operación de alto riesgo | N31: Exterior C-90 | O31: 1 | S31: No
A32: 31 | D32: Constructora VIC | E32: Chile | H32: Exponor 2026 | I32: Prospecto | J32: Alta | K32: Identificar Gerente HSE/SSOMA en LinkedIn y proponer demo | L32: Exponor 2026. Sin contacto publicado. | M32: Cliente potencial – contratista / operación de alto riesgo | N32: Molibdeno-1220 | O32: 1 | S32: No
A33: 32 | D33: Demolition Plus | E33: Chile | H33: Exponor 2026 | I33: Prospecto | J33: Alta | K33: Identificar Gerente HSE/SSOMA en LinkedIn y proponer demo | L33: Exponor 2026. Sin contacto publicado. | M33: Cliente potencial – contratista / operación de alto riesgo | N33: Litio-1005A | O33: 1 | S33: No
A34: 33 | D34: DMI Projects Global Logistics Ltda | E34: Chile | H34: Exponor 2026 | I34: Prospecto | J34: Alta | K34: Identificar Gerente HSE/SSOMA en LinkedIn y proponer demo | L34: Exponor 2026. Sin contacto publicado. | M34: Cliente potencial – contratista / operación de alto riesgo | N34: Yodo-738 | O34: 1 | S34: No
A35: 34 | D35: DyC Servicios Generales | E35: Chile | H35: Exponor 2026 | I35: Prospecto | J35: Alta | K35: Identificar Gerente HSE/SSOMA en LinkedIn y proponer demo | L35: Exponor 2026. Sin contacto publicado. | M35: Cliente potencial – contratista / operación de alto riesgo | N35: Hierro-1497 | O35: 1 | S35: No
... A39: 38 | D39: Enaex | E39: Chile | H39: Exponor 2026 | I39: Prospecto | J39: Alta | K39: Identificar Gerente HSE/SSOMA en LinkedIn y proponer demo | L39: Exponor 2026. Sin contacto publicado. | M39: Cliente potencial – contratista / operación de alto riesgo | N39: Cobre-181-182-220 y 221 | O39: 1 | S39: No
A40: 39 | D40: Famesa Explosivos Chile | E40: Perú | F40: ventas@famesa.com.pe | H40: Exponor 2026 | I40: Prospecto | J40: Alta | K40: Identificar Gerente HSE/SSOMA en LinkedIn y proponer demo | L40: Exponor 2026. También en CRM Directorio SSO 2026 (ID 60). También expone en ExpoMina 2026 (ID 19). | M40: Cliente potencial – contratista / operación de alto riesgo | N40: Plata-571 y 573 | O40: 1 | P40: Perú | Q40: www.famesa.com.pe | R40: 6139800 | S40: Directorio SSO (ID 60); ExpoMina (ID 19)
A41: 40 | D41: FCAB | E41: Chile | H41: Exponor 2026 | I41: Prospecto | J41: Alta | K41: Identificar Gerente HSE/SSOMA en LinkedIn y proponer demo | L41: Exponor 2026. Sin contacto publicado. | M41: Cliente potencial – contratista / operación de alto riesgo | N41: Exterior B-54 | O41: 1 | S41: No
A42: 41 | D42: Ferronor S.A | E42: Chile | H42: Exponor 2026 | I42: Prospecto | J42: Alta | K42: Identificar Gerente HSE/SSOMA en LinkedIn y proponer demo | L42: Exponor 2026. Sin contacto publicado. | M42: Cliente potencial – contratista / operación de alto riesgo | N42: Hierro-1452 | O42: 1 | S42: No
A43: 42 | D43: FG Logistica SpA | E43: Chile | H43: Exponor 2026 | I43: Prospecto | J43: Alta | K43: Identificar Gerente HSE/SSOMA en LinkedIn y proponer demo | L43: Exponor 2026. Sin contacto publicado. | M43: Cliente potencial – contratista / operación de alto riesgo | N43: Cobalto-1393 | O43: 1 | S43: No
A44: 43 | D44: Grúas Kunza | E44: Chile | H44: Exponor 2026 | I44: Prospecto | J44: Alta | K44: Identificar Gerente HSE/SSOMA en LinkedIn y proponer demo | L44: Exponor 2026. Sin contacto publicado. | M44: Cliente potencial – contratista / operación de alto riesgo | N44: Exterior B-64 | O44: 1 | S44: No
A45: 44 | D45: Grupo Eulen Chile | E45: Chile | H45: Exponor 2026 | I45: Prospecto | J45: Alta | K45: Identificar Gerente HSE/SSOMA en LinkedIn y proponer demo | L45: Exponor 2026. Sin contacto publicado. | M45: Cliente potencial – contratista / operación de alto riesgo | N45: Plata-322 | O45: 1 | S45: No
A46: 45 | D46: HS Rodados Mantenimiento y Servicios SpA | E46: Chile | H46: Exponor 2026 | I46: Prospecto | J46: Alta | K46: Identificar Gerente HSE/SSOMA en LinkedIn y proponer demo | L46: Exponor 2026. Sin contacto publicado. | M46: Cliente potencial – contratista / operación de alto riesgo | N46: Oro-1111 | O46: 1 | P46: EstaremosEnExponor | S46: No
A47: 46 | D47: Icil Icafal | E47: Chile | H47: Exponor 2026 | I47: Prospecto | J47: Alta | K47: Identificar Gerente HSE/SSOMA en LinkedIn y proponer demo | L47: Exponor 2026. Sin contacto publicado. | M47: Cliente potencial – contratista / operación de alto riesgo | N47: Litio-1009 | O47: 1 | S47: No
A48: 47 | D48: Incimmet | E48: Perú | F48: comercial_peru@incimmet.com | H48: Exponor 2026 | I48: Prospecto | J48: Alta | K48: Identificar Gerente HSE/SSOMA en LinkedIn y proponer demo | L48: Exponor 2026. También en CRM Directorio SSO 2026 (ID 80). | M48: Cliente potencial – contratista / operación de alto riesgo | N48: Plata-577A | O48: 1 | P48: Perú | Q48: www.incimmet.com | R48: 963701111 | S48: Directorio SSO (ID 80)
A49: 48 | D49: Independent Drilling Supplies | E49: Chile | H49: Exponor 2026 | I49: Prospecto | J49: Alta | K49: Identificar Gerente HSE/SSOMA en LinkedIn y proponer demo | L49: Exponor 2026. Sin contacto publicado. | M49: Cliente potencial – contratista / operación de alto riesgo | N49: Litio-938 | O49: 1 | S49: No
A50: 49 | D50: Inppa Servicios Industriales SpA | E50: Chile | H50: Exponor 2026 | I50: Prospecto | J50: Alta | K50: Identificar Gerente HSE/SSOMA en LinkedIn y proponer demo | L50: Exponor 2026. Sin contacto publicado. | M50: Cliente potencial – contratista / operación de alto riesgo | N50: Exterior E-137 | O50: 1 | S50: No
A51: 50 | D51: Jofre Transporte Logístico | E51: Chile | H51: Exponor 2026 | I51: Prospecto | J51: Alta | K51: Identificar Gerente HSE/SSOMA en LinkedIn y proponer demo | L51: Exponor 2026. Sin contacto publicado. | M51: Cliente potencial – contratista / operación de alto riesgo | N51: Litio-912 | O51: 1 | P51: EstaremosEnExponor | S51: No
A52: 51 | D52: Kaltire | E52: Chile | H52: Exponor 2026 | I52: Prospecto | J52: Alta | K52: Identificar Gerente HSE/SSOMA en LinkedIn y proponer demo | L52: Exponor 2026. Sin contacto publicado. | M52: Cliente potencial – contratista / operación de alto riesgo | N52: Exterior D-104 | O52: 1 | S52: No
A53: 52 | D53: Layher del Pacifico | E53: Chile | H53: Exponor 2026 | I53: Prospecto | J53: Alta | K53: Identificar Gerente HSE/SSOMA en LinkedIn y proponer demo | L53: Exponor 2026. Sin contacto publicado. | M53: Cliente potencial – contratista / operación de alto riesgo | N53: Exterior D-107 | O53: 1 | S53: No
A54: 53 | D54: LOA Rental SpA | E54: Chile | H54: Exponor 2026 | I54: Prospecto | J54: Alta | K54: Identificar Gerente HSE/SSOMA en LinkedIn y proponer demo | L54: Exponor 2026. Sin contacto publicado. | M54: Cliente potencial – contratista / operación de alto riesgo | N54: Exterior A-31 | O54: 1 | S54: No
A55: 54 | D55: M4ts Mining Support | E55: Chile | H55: Exponor 2026 | I55: Prospecto | J55: Alta | K55: Identificar Gerente HSE/SSOMA en LinkedIn y proponer demo | L55: Exponor 2026. Sin contacto publicado. | M55: Cliente potencial – contratista / operación de alto riesgo | N55: Yodo-777 y 778 | O55: 1 | S55: No
A56: 55 | D56: Mammoet Chile | E56: Chile | H56: Exponor 2026 | I56: Prospecto | J56: Alta | K56: Identificar Gerente HSE/SSOMA en LinkedIn y proponer demo | L56: Exponor 2026. Sin contacto publicado. | M56: Cliente potencial – contratista / operación de alto riesgo | N56: Cobre-128 | O56: 1 | S56: No
A57: 56 | D57: Minabus | E57: Chile | H57: Exponor 2026 | I57: Prospecto | J57: Alta | K57: Identificar Gerente HSE/SSOMA en LinkedIn y proponer demo | L57: Exponor 2026. Sin contacto publicado. | M57: Cliente potencial – contratista / operación de alto riesgo | N57: Cobalto-1432 | O57: 1 | S57: No
A58: 57 | D58: Moverent | E58: Chile | H58: Exponor 2026 | I58: Prospecto | J58: Alta | K58: Identificar Gerente HSE/SSOMA en LinkedIn y proponer demo | L58: Exponor 2026. Sin contacto publicado. | M58: Cliente potencial – contratista / operación de alto riesgo | N58: Molibdeno-1215A | O58: 1 | S58: No
A59: 58 | D59: Orica | E59: Chile | H59: Exponor 2026 | I59: Prospecto | J59: Alta | K59: Identificar Gerente HSE/SSOMA en LinkedIn y proponer demo | L59: Exponor 2026. Sin contacto publicado. | M59: Cliente potencial – contratista / operación de alto riesgo | N59: Oro-1174 | O59: 1 | S59: No
A60: 59 | D60: Puerto de Antofagasta | E60: Chile | H60: Exponor 2026 | I60: Prospecto | J60: Alta | K60: Identificar Gerente HSE/SSOMA en LinkedIn y proponer demo | L60: Exponor 2026. Sin contacto publicado. | M60: Cliente potencial – contratista / operación de alto riesgo | N60: Cobalto-1437 y 1438 | O60: 1 | S60: No
A61: 60 | D61: RAM Rental & Quality SpA | E61: Chile | H61: Exponor 2026 | I61: Prospecto | J61: Alta | K61: Identificar Gerente HSE/SSOMA en LinkedIn y proponer demo | L61: Exponor 2026. Sin contacto publicado. | M61: Cliente potencial – contratista / operación de alto riesgo | N61: Molibdeno-1246 | O61: 1 | S61: No
A62: 61 | D62: RMI Construcción E Ingeniería | E62: Chile | H62: Exponor 2026 | I62: Prospecto | J62: Alta | K62: Identificar Gerente HSE/SSOMA en LinkedIn y proponer demo | L62: Exponor 2026. Sin contacto publicado. | M62: Cliente potencial – contratista / operación de alto riesgo | N62: Molibdeno-1316 | O62: 1 | S62: No
A63: 62 | D63: Rockblast | E63: Chile | H63: Exponor 2026 | I63: Prospecto | J63: Alta | K63: Identificar Gerente HSE/SSOMA en LinkedIn y proponer demo | L63: Exponor 2026. Sin contacto publicado. | M63: Cliente potencial – contratista / operación de alto riesgo | N63: Cobre-225-226-261 y 262 | O63: 1 | S63: No
A64: 63 | D64: Rodotrans | E64: Chile | H64: Exponor 2026 | I64: Prospecto | J64: Alta | K64: Identificar Gerente HSE/SSOMA en LinkedIn y proponer demo | L64: Exponor 2026. Sin contacto publicado. | M64: Cliente potencial – contratista / operación de alto riesgo | N64: Yodo-763 | O64: 1 | S64: No
A65: 64 | D65: Sacyr | E65: Alemania | H65: Exponor 2026 | I65: Prospecto | J65: Alta | K65: Identificar Gerente HSE/SSOMA en LinkedIn y proponer demo | L65: Exponor 2026. Sin contacto publicado. | M65: Cliente potencial – contratista / operación de alto riesgo | N65: Cobre-95 | O65: 1 | P65: Alemania | S65: No
A66: 65 | D66: Serviall | E66: Chile | H66: Exponor 2026 | I66: Prospecto | J66: Alta | K66: Identificar Gerente HSE/SSOMA en LinkedIn y proponer demo | L66: Exponor 2026. Sin contacto publicado. | M66: Cliente potencial – contratista / operación de alto riesgo | N66: Exterior B-50 | O66: 1 | S66: No
A67: 66 | D67: Sigdo Koppers | E67: Chile | H67: Exponor 2026 | I67: Prospecto | J67: Alta | K67: Identificar Gerente HSE/SSOMA en LinkedIn y proponer demo | L67: Exponor 2026. Sin contacto publicado. | M67: Cliente potencial – contratista / operación de alto riesgo | N67: Exterior C-96 | O67: 1 | S67: No
A68: 67 | D68: Sitrans Ltda | E68: Chile | H68: Exponor 2026 | I68: Prospecto | J68: Alta | K68: Identificar Gerente HSE/SSOMA en LinkedIn y proponer demo | L68: Exponor 2026. Sin contacto publicado. | M68: Cliente potencial – contratista / operación de alto riesgo | N68: Litio-934 | O68: 1 | S68: No
A69: 68 | D69: Smart Rental Equipments SpA | E69: Chile | H69: Exponor 2026 | I69: Prospecto | J69: Alta | K69: Identificar Gerente HSE/SSOMA en LinkedIn y proponer demo | L69: Exponor 2026. Startup (zona Lanza tu Innovación). Sin contacto publicado. | M69: Cliente potencial – contratista / operación de alto riesgo | N69: Exterior E-152 | O69: 1 | P69: Lanza tu Innovación | S69: No
A70: 69 | D70: Smartlift | E70: Chile | H70: Exponor 2026 | I70: Prospecto | J70: Alta | K70: Identificar Gerente HSE/SSOMA en LinkedIn y proponer demo | L70: Exponor 2026. Sin contacto publicado. | M70: Cliente potencial – contratista / operación de alto riesgo | N70: Yodo-641A | O70: 1 | S70: No
A71: 70 | D71: Soletanche Bachy | E71: Francia | H71: Exponor 2026 | I71: Prospecto | J71: Alta | K71: Identificar Gerente HSE/SSOMA en LinkedIn y proponer demo | L71: Exponor 2026. Sin contacto publicado. | M71: Cliente potencial – contratista / operación de alto riesgo | N71: Cobre-163 | O71: 1 | P71: Francia | S71: No
A72: 71 | D72: Sotraser S.A | E72: Chile | H72: Exponor 2026 | I72: Prospecto | J72: Alta | K72: Identificar Gerente HSE/SSOMA en LinkedIn y proponer demo | L72: Exponor 2026. Sin contacto publicado. | M72: Cliente potencial – contratista / operación de alto riesgo | N72: Exterior B-60A | O72: 1 | S72: No
A73: 72 | D73: South Cranes | E73: Chile | H73: Exponor 2026 | I73: Prospecto | J73: Alta | K73: Identificar Gerente HSE/SSOMA en LinkedIn y proponer demo | L73: Exponor 2026. Sin contacto publicado. | M73: Cliente potencial – contratista / operación de alto riesgo | N73: Molibdeno-1211 | O73: 1 | S73: No
A74: 73 | D74: Stracon | E74: Chile | F74: info@stracon.com | H74: Exponor 2026 | I74: Prospecto | J74: Alta | K74: Identificar Gerente HSE/SSOMA en LinkedIn y proponer demo | L74: Exponor 2026. También en CRM Directorio SSO 2026 (ID 146); contacto heredado = filial Perú. | M74: Cliente potencial – contratista / operación de alto riesgo | N74: Cobalto-1345 | O74: 1 | Q74: www.stracon.com | R74: 2080230 | S74: Directorio SSO (ID 146)
A75: 74 | D75: Swastic Drilling Co & Maquinet SpA | E75: Chile | H75: Exponor 2026 | I75: Prospecto | J75: Alta | K75: Identificar Gerente HSE/SSOMA en LinkedIn y proponer demo | L75: Exponor 2026. Sin contacto publicado. | M75: Cliente potencial – contratista / operación de alto riesgo | N75: Molibdeno-1252 y 1253 | O75: 1 | S75: No
A76: 75 | D76: T-Port Logistics | E76: Chile | H76: Exponor 2026 | I76: Prospecto | J76: Alta | K76: Identificar Gerente HSE/SSOMA en LinkedIn y proponer demo | L76: Exponor 2026. Pyme regional (pabellón AIA). Sin contacto publicado. | M76: Cliente potencial – contratista / operación de alto riesgo | N76: Litio-830 y 831 | O76: 1 | P76: AIA-Pyme | S76: No
A77: 76 | D77: Thiess | E77: Chile | H77: Exponor 2026 | I77: Prospecto | J77: Alta | K77: Identificar Gerente HSE/SSOMA en LinkedIn y proponer demo | L77: Exponor 2026. Sin contacto publicado. | M77: Cliente potencial – contratista / operación de alto riesgo | N77: Molibdeno-1318 | O77: 1 | S77: No
A78: 77 | D78: TKA Cranes | E78: Brasil | H78: Exponor 2026 | I78: Prospecto | J78: Alta | K78: Identificar Gerente HSE/SSOMA en LinkedIn y proponer demo | L78: Exponor 2026. Sin contacto publicado. | M78: Cliente potencial – contratista / operación de alto riesgo | N78: Yodo-819 | O78: 1 | P78: Brasil | S78: No
A79: 78 | D79: Todo Izaje S.A. - Bimpac | E79: Chile | H79: Exponor 2026 | I79: Prospecto | J79: Alta | K79: Identificar Gerente HSE/SSOMA en LinkedIn y proponer demo | L79: Exponor 2026. Sin contacto publicado. | M79: Cliente potencial – contratista / operación de alto riesgo | N79: Yodo-656 y 685 | O79: 1 | S79: No
A80: 79 | D80: Transportes Bello | E80: Chile | H80: Exponor 2026 | I80: Prospecto | J80: Alta | K80: Identificar Gerente HSE/SSOMA en LinkedIn y proponer demo | L80: Exponor 2026. Sin contacto publicado. | M80: Cliente potencial – contratista / operación de alto riesgo | N80: Exterior E-141 y 142 | O80: 1 | S80: No
A81: 80 | D81: Transportes Santa Eva | E81: Chile | H81: Exponor 2026 | I81: Prospecto | J81: Alta | K81: Identificar Gerente HSE/SSOMA en LinkedIn y proponer demo | L81: Exponor 2026. Sin contacto publicado. | M81: Cliente potencial – contratista / operación de alto riesgo | N81: Molibdeno-1214 | O81: 1 | S81: No
A82: 81 | D82: Transportes y Servicios Mercosur y Cía. Ltda | E82: Chile | H82: Exponor 2026 | I82: Prospecto | J82: Alta | K82: Identificar Gerente HSE/SSOMA en LinkedIn y proponer demo | L82: Exponor 2026. Sin contacto publicado. | M82: Cliente potencial – contratista / operación de alto riesgo | N82: Oro-1195 | O82: 1 | S82: No
A83: 82 | D83: Ulog Soluciones Logísticas y Ultramar | E83: Chile | H83: Exponor 2026 | I83: Prospecto | J83: Alta | K83: Identificar Gerente HSE/SSOMA en LinkedIn y proponer demo | L83: Exponor 2026. Sin contacto publicado. | M83: Cliente potencial – contratista / operación de alto riesgo | N83: Exterior A-24 | O83: 1 | S83: No
A84: 83 | D84: Unidad Construcción y Servicios SpA | E84: Chile | H84: Exponor 2026 | I84: Prospecto | J84: Alta | K84: Identificar Gerente HSE/SSOMA en LinkedIn y proponer demo | L84: Exponor 2026. Sin contacto publicado. | M84: Cliente potencial – contratista / operación de alto riesgo | N84: Oro-1138 | O84: 1 | S84: No
A85: 84 | D85: Vertex Rental SpA | E85: Chile | H85: Exponor 2026 | I85: Prospecto | J85: Alta | K85: Identificar Gerente HSE/SSOMA en LinkedIn y proponer demo | L85: Exponor 2026. Sin contacto publicado. | M85: Cliente potencial – contratista / operación de alto riesgo | N85: Litio-1007 | O85: 1 | S85: No
A86: 85 | D86: Vertical Mine Chile SpA | E86: Chile | H86: Exponor 2026 | I86: Prospecto | J86: Alta | K86: Identificar Gerente HSE/SSOMA en LinkedIn y proponer demo | L86: Exponor 2026. Sin contacto publicado. | M86: Cliente potencial – contratista / operación de alto riesgo | N86: Plata-435 | O86: 1 | S86: No
A87: 86 | D87: Wic Logistics | E87: Chile | H87: Exponor 2026 | I87: Prospecto | J87: Alta | K87: Identificar Gerente HSE/SSOMA en LinkedIn y proponer demo | L87: Exponor 2026. Sin contacto publicado. | M87: Cliente potencial – contratista / operación de alto riesgo | N87: Molibdeno-1242 | O87: 1 | S87: No
A88: 87 | D88: Rukian Tech | E88: Chile | H88: Exponor 2026 | I88: Prospecto | J88: Alta | K88: Mapear oferta: evaluar integración o competencia | L88: Exponor 2026. Varios stands (mayor inversión). Startup (zona Lanza tu Innovación). Sin contacto publicado. | M88: Partner tecnológico / competidor | N88: Litio-919, Exterior E-159 | O88: 2 | P88: EstaremosEnExponor, Lanza tu Innovación | S88: No
A89: 88 | D89: Amperxgroup - Software 4 Tech | E89: Chile | H89: Exponor 2026 | I89: Prospecto | J89: Alta | K89: Mapear oferta: evaluar integración o competencia | L89: Exponor 2026. Sin contacto publicado. | M89: Partner tecnológico / competidor | N89: Cobalto-1372 | O89: 1 | S89: No
A90: 89 | D90: AMV Latam | E90: Chile | H90: Exponor 2026 | I90: Prospecto | J90: Alta | K90: Mapear oferta: evaluar integración o competencia | L90: Exponor 2026. Startup (zona Lanza tu Innovación). Sin contacto publicado. | M90: Partner tecnológico / competidor | N90: Exterior E-168 | O90: 1 | P90: Lanza tu Innovación | S90: No
A91: 90 | D91: Atacamacopter | E91: Chile | H91: Exponor 2026 | I91: Prospecto | J91: Alta | K91: Mapear oferta: evaluar integración o competencia | L91: Exponor 2026. Sin contacto publicado. | M91: Partner tecnológico / competidor | N91: Yodo-788 | O91: 1 | S91: No
A92: 91 | D92: Automining | E92: Chile | H92: Exponor 2026 | I92: Prospecto | J92: Alta | K92: Mapear oferta: evaluar integración o competencia | L92: Exponor 2026. Sin contacto publicado. | M92: Partner tecnológico / competidor | N92: Litio-896 | O92: 1 | S92: No
A93: 92 | D93: Axis Communicationes | E93: Chile | H93: Exponor 2026 | I93: Prospecto | J93: Alta | K93: Mapear oferta: evaluar integración o competencia | L93: Exponor 2026. Sin contacto publicado. | M93: Partner tecnológico / competidor | N93: Cobre-184 | O93: 1 | S93: No
A94: 93 | D94: Bee3 Mining Tech | E94: Perú | H94: Exponor 2026 | I94: Prospecto | J94: Alta | K94: Mapear oferta: evaluar integración o competencia | L94: Exponor 2026. Sin contacto publicado. | M94: Partner tecnológico / competidor | N94: Plata-564 | O94: 1 | P94: Perú | S94: No
A95: 94 | D95: BQSense SpA | E95: Chile | H95: Exponor 2026 | I95: Prospecto | J95: Alta | K95: Mapear oferta: evaluar integración o competencia | L95: Exponor 2026. Startup (zona Lanza tu Innovación). Sin contacto publicado. | M95: Partner tecnológico / competidor | N95: Exterior E-167 | O95: 1 | P95: Lanza tu Innovación | S95: No
A96: 95 | D96: Buk | E96: Chile | H96: Exponor 2026 | I96: Prospecto | J96: Alta | K96: Mapear oferta: evaluar integración o competencia | L96: Exponor 2026. Sin contacto publicado. | M96: Partner tecnológico / competidor | N96: Cobalto-1416 | O96: 1 | S96: No
A97: 96 | D97: Changsha Looking Intelligence Technology Co.,Ltd | E97: China | H97: Exponor 2026 | I97: Prospecto | J97: Alta | K97: Mapear oferta: evaluar integración o competencia | L97: Exponor 2026. Sin contacto publicado. | M97: Partner tecnológico / competidor | N97: Plata-331 | O97: 1 | P97: China | S97: No
A98: 97 | D98: Cloudcsp Soluciones Tecnológicas | E98: Chile | H98: Exponor 2026 | I98: Prospecto | J98: Alta | K98: Mapear oferta: evaluar integración o competencia | L98: Exponor 2026. Pyme regional (pabellón AIA). Sin contacto publicado. | M98: Partner tecnológico / competidor | N98: Litio-827 | O98: 1 | P98: AIA-Pyme | S98: No
A99: 98 | D99: CMS Condition Monitoring Solutions | E99: Chile | H99: Exponor 2026 | I99: Prospecto | J99: Alta | K99: Mapear oferta: evaluar integración o competencia | L99: Exponor 2026. Sin contacto publicado. | M99: Partner tecnológico / competidor | N99: Yodo-765 | O99: 1 | S99: No
A100: 99 | D100: Convergint | E100: Chile | H100: Exponor 2026 | I100: Prospecto | J100: Alta | K100: Mapear oferta: evaluar integración o competencia | L100: Exponor 2026. Sin contacto publicado. | M100: Partner tecnológico / competidor | N100: Plata-344 | O100: 1 | S100: No
A101: 100 | D101: CP Comunicaciones | E101: Chile | H101: Exponor 2026 | I101: Prospecto | J101: Alta | K101: Mapear oferta: evaluar integración o competencia | L101: Exponor 2026. Sin contacto publicado. | M101: Partner tecnológico / competidor | N101: Oro-1123 | O101: 1 | P101: EstaremosEnExponor | S101: No
A102: 101 | D102: Datamine | E102: Chile | H102: Exponor 2026 | I102: Prospecto | J102: Alta | K102: Mapear oferta: evaluar integración o competencia | L102: Exponor 2026. Sin contacto publicado. | M102: Partner tecnológico / competidor | N102: Yodo-764 | O102: 1 | S102: No
A103: 102 | D103: Datascope.io | E103: Chile | H103: Exponor 2026 | I103: Prospecto | J103: Alta | K103: Mapear oferta: evaluar integración o competencia | L103: Exponor 2026. Sin contacto publicado. | M103: Partner tecnológico / competidor | N103: Cobalto-1410 | O103: 1 | S103: No
...

Sheet Oportunidades
A1: ID oportunidad | B1: ID contacto | C1: Empresa | D1: Necesidad | E1: Solución propuesta | F1: Etapa | G1: Valor estimado | H1: Probabilidad | I1: Próxima acción | J1: Fecha

Sheet Resumen
A1: Evento/Fuente | B1: País | C1: Cantidad
A2: Exponor 2026 | B2: Chile | C2: =COUNTIFS(Contactos!$H:$H,$A2,Contactos!$E:$E,$B2) -> 850
A3: Exponor 2026 | B3: China | C3: =COUNTIFS(Contactos!$H:$H,$A3,Contactos!$E:$E,$B3) -> 180
A4: Exponor 2026 | B4: Alemania | C4: =COUNTIFS(Contactos!$H:$H,$A4,Contactos!$E:$E,$B4) -> 66
A5: Exponor 2026 | B5: Estados Unidos | C5: =COUNTIFS(Contactos!$H:$H,$A5,Contactos!$E:$E,$B5) -> 50
A6: Exponor 2026 | B6: Canadá | C6: =COUNTIFS(Contactos!$H:$H,$A6,Contactos!$E:$E,$B6) -> 38
A7: Exponor 2026 | B7: Perú | C7: =COUNTIFS(Contactos!$H:$H,$A7,Contactos!$E:$E,$B7) -> 29
A8: Exponor 2026 | B8: Brasil | C8: =COUNTIFS(Contactos!$H:$H,$A8,Contactos!$E:$E,$B8) -> 20
A9: Exponor 2026 | B9: Australia | C9: =COUNTIFS(Contactos!$H:$H,$A9,Contactos!$E:$E,$B9) -> 18
A10: Exponor 2026 | B10: Francia | C10: =COUNTIFS(Contactos!$H:$H,$A10,Contactos!$E:$E,$B10) -> 17
A11: Exponor 2026 | B11: Italia | C11: =COUNTIFS(Contactos!$H:$H,$A11,Contactos!$E:$E,$B11) -> 17
A12: Exponor 2026 | B12: España | C12: =COUNTIFS(Contactos!$H:$H,$A12,Contactos!$E:$E,$B12) -> 13
A13: Exponor 2026 | B13: Argentina | C13: =COUNTIFS(Contactos!$H:$H,$A13,Contactos!$E:$E,$B13) -> 12
... A25: Exponor 2026 | B25: Hungría | C25: =COUNTIFS(Contactos!$H:$H,$A25,Contactos!$E:$E,$B25) -> 1
A26: Total | C26: =SUM(C2:C25) -> 1375
A28: Segmento SafetyMind | B28: Alta | C28: Media | D28: Baja | E28: Total
A29: Minera (cliente final) | B29: =COUNTIFS(Contactos!$M:$M,$A29,Contactos!$J:$J,B$28) -> 14 | C29: =COUNTIFS(Contactos!$M:$M,$A29,Contactos!$J:$J,C$28) -> 0 | D29: =COUNTIFS(Contactos!$M:$M,$A29,Contactos!$J:$J,D$28) -> 0 | E29: =SUM(B29:D29) -> 14
A30: Cliente potencial – contratista / operación de alto riesgo | B30: =COUNTIFS(Contactos!$M:$M,$A30,Contactos!$J:$J,B$28) -> 72 | C30: =COUNTIFS(Contactos!$M:$M,$A30,Contactos!$J:$J,C$28) -> 0 | D30: =COUNTIFS(Contactos!$M:$M,$A30,Contactos!$J:$J,D$28) -> 0 | E30: =SUM(B30:D30) -> 72
A31: Partner tecnológico / competidor | B31: =COUNTIFS(Contactos!$M:$M,$A31,Contactos!$J:$J,B$28) -> 90 | C31: =COUNTIFS(Contactos!$M:$M,$A31,Contactos!$J:$J,C$28) -> 0 | D31: =COUNTIFS(Contactos!$M:$M,$A31,Contactos!$J:$J,D$28) -> 0 | E31: =SUM(B31:D31) -> 90
A32: Canal / aliado – consultoría SST | B32: =COUNTIFS(Contactos!$M:$M,$A32,Contactos!$J:$J,B$28) -> 38 | C32: =COUNTIFS(Contactos!$M:$M,$A32,Contactos!$J:$J,C$28) -> 0 | D32: =COUNTIFS(Contactos!$M:$M,$A32,Contactos!$J:$J,D$28) -> 0 | E32: =SUM(B32:D32) -> 38
A33: Partner OEM – equipos mineros | B33: =COUNTIFS(Contactos!$M:$M,$A33,Contactos!$J:$J,B$28) -> 0 | C33: =COUNTIFS(Contactos!$M:$M,$A33,Contactos!$J:$J,C$28) -> 30 | D33: =COUNTIFS(Contactos!$M:$M,$A33,Contactos!$J:$J,D$28) -> 0 | E33: =SUM(B33:D33) -> 30
A34: Canal / distribuidor EPP | B34: =COUNTIFS(Contactos!$M:$M,$A34,Contactos!$J:$J,B$28) -> 0 | C34: =COUNTIFS(Contactos!$M:$M,$A34,Contactos!$J:$J,C$28) -> 17 | D34: =COUNTIFS(Contactos!$M:$M,$A34,Contactos!$J:$J,D$28) -> 0 | E34: =SUM(B34:D34) -> 17
A35: Aliado complementario – seguridad | B35: =COUNTIFS(Contactos!$M:$M,$A35,Contactos!$J:$J,B$28) -> 0 | C35: =COUNTIFS(Contactos!$M:$M,$A35,Contactos!$J:$J,C$28) -> 21 | D35: =COUNTIFS(Contactos!$M:$M,$A35,Contactos!$J:$J,D$28) -> 0 | E35: =SUM(B35:D35) -> 21
A36: Aliado complementario – salud | B36: =COUNTIFS(Contactos!$M:$M,$A36,Contactos!$J:$J,B$28) -> 0 | C36: =COUNTIFS(Contactos!$M:$M,$A36,Contactos!$J:$J,C$28) -> 7 | D36: =COUNTIFS(Contactos!$M:$M,$A36,Contactos!$J:$J,D$28) -> 0 | E36: =SUM(B36:D36) -> 7
A37: Institución / gremio / pabellón país | B37: =COUNTIFS(Contactos!$M:$M,$A37,Contactos!$J:$J,B$28) -> 0 | C37: =COUNTIFS(Contactos!$M:$M,$A37,Contactos!$J:$J,C$28) -> 59 | D37: =COUNTIFS(Contactos!$M:$M,$A37,Contactos!$J:$J,D$28) -> 0 | E37: =SUM(B37:D37) -> 59
A38: Proveedor industrial (equipos/insumos) | B38: =COUNTIFS(Contactos!$M:$M,$A38,Contactos!$J:$J,B$28) -> 0 | C38: =COUNTIFS(Contactos!$M:$M,$A38,Contactos!$J:$J,C$28) -> 0 | D38: =COUNTIFS(Contactos!$M:$M,$A38,Contactos!$J:$J,D$28) -> 1027 | E38: =SUM(B38:D38) -> 1027
A39: Total | B39: =SUM(B29:B38) -> 214 | C39: =SUM(C29:C38) -> 134 | D39: =SUM(D29:D38) -> 1027 | E39: =SUM(E29:E38) -> 1375
A41: Estado (pipeline) | B41: Cantidad
A42: Prospecto | B42: =COUNTIF(Contactos!$I:$I,A42) -> 1375
A43: Contactado | B43: =COUNTIF(Contactos!$I:$I,A43) -> 0
A44: Reunión | B44: =COUNTIF(Contactos!$I:$I,A44) -> 0
A45: Propuesta | B45: =COUNTIF(Contactos!$I:$I,A45) -> 0
A46: Cliente | B46: =COUNTIF(Contactos!$I:$I,A46) -> 0
A47: No interesado | B47: =COUNTIF(Contactos!$I:$I,A47) -> 0
A49: Indicadores | B49: Cantidad
A50: Registros originales (stands) | B50: 1382
A51: Empresas únicas | B51: =COUNTA(Contactos!$D$2:$D$3000) -> 1375
A52: También en ExpoMina 2026 | B52: =COUNTIF(Contactos!$S$2:$S$3000,"*ExpoMina*") -> 96
A53: También en Directorio SSO | B53: =COUNTIF(Contactos!$S$2:$S$3000,"*Directorio*") -> 21
A54: Startups (Lanza tu Innovación) | B54: =COUNTIF(Contactos!$P$2:$P$3000,"*Lanza tu Innovación*") -> 32
A55: Con 2+ stands | B55: =COUNTIF(Contactos!$O$2:$O$3000,">1") -> 6

Sheet Eventos
A1: Evento | B1: País | C1: Valor para SafetyMind
A2: Directorio SSO 2026 – Cero Accidentes (22.ª ed.) | B2: Perú | C2: Mapa de ~670 proveedores SST en Perú (ver CRM_Directorio_SSO_2026).
A3: ExpoMina Perú 2026 | B3: Perú | C3: Feria minera: mineras, contratistas, OEM, tecnología y proveedores (ver CRM_ExpoMina_2026).
A4: Exponor 2026 (Antofagasta) | B4: Chile | C4: Principal feria minera del norte de Chile: mineras (Codelco, BHP, AMSA, SQM, Albemarle), contratistas, OEM, startups y pabellones país; base para reuniones en stand y prospección post-evento.
