Workbook

Sheet Contactos
A1: ID | B1: Nombre | C1: Cargo | D1: Empresa | E1: País | F1: Email | G1: LinkedIn | H1: Origen | I1: Estado | J1: Prioridad | K1: Próxima acción | L1: Notas | M1: Segmento SafetyMind | N1: Stand(s) | O1: N° stands | P1: Rubro AquaSur | Q1: Descripción | R1: Teléfono(s) | S1: Cruce otros CRM
A2: 1 | D2: AQUACHILE | E2: Chile | H2: AquaSur 2026 | I2: Prospecto | J2: Alta | K2: Mapear Gerente de Personas/SSOMA y centros de cultivo; proponer piloto (buceo, cosecha, wellboat) | L2: AquaSur 2026. Sin contacto publicado. | M2: Cliente final – productor acuícola | N2: N-32 | O2: 1 | P2: Producción acuícola, pesquera y alimentos › Productores / procesadores acuícolas | Q2: AquaChile empresa nacida en el sur de Chile Líder en la producción de salmón a nivel nacional y mundial. Conformada por un equipo de personas apasionadas y comprometidas, convencidas de que la innovación es parte esencial del ADN. En AquaChile existe un profundo orgullo por su origen, por su gente y por el rol que cumple llevando salmón chileno de alta calidad a los mercados internacionales | S2: No
A3: 2 | D3: BLUMAR | E3: Chile | H3: AquaSur 2026 | I3: Prospecto | J3: Alta | K3: Mapear Gerente de Personas/SSOMA y centros de cultivo; proponer piloto (buceo, cosecha, wellboat) | L3: AquaSur 2026. Sin stand asignado en el listado. Sin contacto publicado. | M3: Cliente final – productor acuícola | N3: Sin stand | O3: 0 | P3: Producción acuícola, pesquera y alimentos › Productores / procesadores acuícolas | Q3: Blumar es una compañía chilena con más de 75 años de trayectoria en pesca y acuicultura. Integra toda su cadena productiva, desde la captura y elaboración de harina y aceite de pescado hasta la salmonicultura en el sur austral. Con presencia en Chile y mercados internacionales, impulsa una operación sostenible, innovadora y comprometida con el cuidado del océano y el trabajo con las comunidades. | S3: No
A4: 3 | D4: ALO RENTAL | E4: Chile | H4: AquaSur 2026 | I4: Prospecto | J4: Alta | K4: Identificar Gerente HSE/Prevención en LinkedIn y proponer demo (faenas marítimas de alto riesgo) | L4: AquaSur 2026. También expone en Exponor 2026 (ID 16). Sin contacto publicado. | M4: Cliente potencial – contratista / operación de alto riesgo | N4: AD-04 | O4: 1 | P4: Equipos e insumos industriales › Ingeniería / mantenimiento | Q4: En ALO Group, hemos liderado el sector de soluciones para trabajos en altura desde 2004, ofreciendo servicios integrales que garantizan seguridad y eficiencia en cada proyecto. Nos dedicamos a elevar personas y proyectos, brindando certeza y confianza a través de soluciones integrales en plataformas para trabajo en altura y manipuladores telescópicos. | S4: Exponor (ID 16)
A5: 4 | D5: ASENAV | E5: Chile | H5: AquaSur 2026 | I5: Prospecto | J5: Alta | K5: Identificar Gerente HSE/Prevención en LinkedIn y proponer demo (faenas marítimas de alto riesgo) | L5: AquaSur 2026. Sin contacto publicado. | M5: Cliente potencial – contratista / operación de alto riesgo | N5: A-36 | O5: 1 | P5: Infraestructura marina y equipamiento acuícola › Servicios / equipos marítimos | Q5: ASENAV es un astillero chileno con más de 50 años de experiencia en el diseño y construcción de embarcaciones especializadas. Destaca por su ingeniería propia, soluciones a medida y altos estándares de calidad, innovación y sostenibilidad, atendiendo clientes de la industria acuícola y marítima a nivel internacional. | S5: No
A6: 5 | D6: ASMAR SHIPYARDS | E6: Chile | H6: AquaSur 2026 | I6: Prospecto | J6: Alta | K6: Identificar Gerente HSE/Prevención en LinkedIn y proponer demo (faenas marítimas de alto riesgo) | L6: AquaSur 2026. Sin contacto publicado. | M6: Cliente potencial – contratista / operación de alto riesgo | N6: J-49 | O6: 1 | P6: Infraestructura marina y equipamiento acuícola › Jaulas / flotación / estructuras | Q6: Astilleros y Maestranzas de la Armada – ASMAR, es un astillero estatal chileno, cuya actividad principal es satisfacer las necesidades de mantenimiento y construcción de buques para la Armada de Chile. Además, ASMAR repara, carena, transforma y moderniza buques pesqueros y mercantes, junto a plataformas de ensilajes, pontones y otros artefactos navales. | S6: No
A7: 6 | D7: BELATOR | E7: Chile | H7: AquaSur 2026 | I7: Prospecto | J7: Alta | K7: Identificar Gerente HSE/Prevención en LinkedIn y proponer demo (faenas marítimas de alto riesgo) | L7: AquaSur 2026. Sin contacto publicado. | M7: Cliente potencial – contratista / operación de alto riesgo | N7: M-36 | O7: 1 | P7: Servicios empresariales y consultoría › Servicios operacionales / abastecimiento | Q7: Aseguramos la continuidad operacional del negocio gracias al alto nivel de nuestros operadores, y a la optimización de los procesos a través de tecnología de vanguardia que permite prevenir posibles riesgos. Siendo lo primordial la seguridad anticipativa de la mano del modelo de seguridad basada en la supervivencia urbana. | S7: No
A8: 7 | D8: COMERCIAL INDUSTRIAL TERRAMAR SPA - WALBUSCH S.A | E8: Chile | H8: AquaSur 2026 | I8: Prospecto | J8: Alta | K8: Identificar Gerente HSE/Prevención en LinkedIn y proponer demo (faenas marítimas de alto riesgo) | L8: AquaSur 2026. Sin contacto publicado. | M8: Cliente potencial – contratista / operación de alto riesgo | N8: B-18 | O8: 1 | P8: Infraestructura marina y equipamiento acuícola › Redes / cabos / fondeo | Q8: Walbusch S.A. Desde 1996, hemos sido pioneros en servicios marítimos para la industria salmonicultura, adaptándonos a las crecientes demandas del sector. Con una amplia experiencia en el montaje de sistemas de fondeo. | S8: No
A9: 8 | D9: DIVING AUSTRAL | E9: Chile | H9: AquaSur 2026 | I9: Prospecto | J9: Alta | K9: Identificar Gerente HSE/Prevención en LinkedIn y proponer demo (faenas marítimas de alto riesgo) | L9: AquaSur 2026. Sin contacto publicado. | M9: Cliente potencial – contratista / operación de alto riesgo | N9: S-16 | O9: 1 | P9: Instituciones, medios y certificación › Certificación / bienestar animal | Q9: Somos una empresa especializada en ingeniería y construcción submarina, que entrega soluciones integrales en los ámbitos industrial, portuario y energético. Operamos bajo altos estándares de seguridad y calidad, con buzos certificados y respaldo técnico. Contamos con certificación Oil Spill Response (OSR), que acredita nuestra capacidad operativa ante emergencias ambientales en el medio marino. | S9: No
A10: 9 | D10: DYC INGENIERIA | E10: Chile | H10: AquaSur 2026 | I10: Prospecto | J10: Alta | K10: Identificar Gerente HSE/Prevención en LinkedIn y proponer demo (faenas marítimas de alto riesgo) | L10: AquaSur 2026. Sin contacto publicado. | M10: Cliente potencial – contratista / operación de alto riesgo | N10: G-24 | O10: 1 | P10: Transporte y logística › Transporte acuícola / wellboats | Q10: Trabajos de Ingenieria en Electronica y Automatizacion Industrial en Piscicultura, plantas de proceso de salmones y Wellboat. | S10: No
A11: 10 | D11: FABRIMAQ | E11: Chile | H11: AquaSur 2026 | I11: Prospecto | J11: Alta | K11: Identificar Gerente HSE/Prevención en LinkedIn y proponer demo (faenas marítimas de alto riesgo) | L11: AquaSur 2026. Sin contacto publicado. | M11: Cliente potencial – contratista / operación de alto riesgo | N11: C-02 | O11: 1 | P11: Transporte y logística › Transporte acuícola / wellboats | Q11: FABRIMAQ es una empresa de ingeniería fabricación y servicios de maestranza orientada a la industria acuícola y alimenticia. Desarrolla proyectos llave en mano para el manejo de peces, sistemas de bombeo, transporte y procesos productivos, aplicados a Pisciculturas, Wellboats y Plantas de Proceso, integrando ingeniería, modelamiento 3D, fabricación en acero inoxidable y soluciones en HDPE. | S11: No
A12: 11 | D12: FYT TRANSPORTES | E12: Chile | H12: AquaSur 2026 | I12: Prospecto | J12: Alta | K12: Identificar Gerente HSE/Prevención en LinkedIn y proponer demo (faenas marítimas de alto riesgo) | L12: AquaSur 2026. Sin contacto publicado. | M12: Cliente potencial – contratista / operación de alto riesgo | N12: ST-96 | O12: 1 | P12: Transporte y logística › Transporte especializado / grúas | Q12: Nos dedicamos al transporte especial, tenemos distintas grúas, y también tenemos movimiento de tierra, contamos con moto niveladora y demás, | S12: No
A13: 12 | D13: Kafra Robotica spa | E13: Chile | H13: AquaSur 2026 | I13: Prospecto | J13: Alta | K13: Identificar Gerente HSE/Prevención en LinkedIn y proponer demo (faenas marítimas de alto riesgo) | L13: AquaSur 2026. Sin contacto publicado. | M13: Cliente potencial – contratista / operación de alto riesgo | N13: ST-102 | O13: 1 | P13: Instituciones, medios y certificación › Certificación / bienestar animal | Q13: Somos una empresa dedicada a la robotica submarina, instalacion de sistema de oxigenación , certificacion de cebtro de cultivo los servicios que contamos son los siguientes: *Inspección y costura de red lobera y pecera. *inspeccion de lineas de fondeos y certificación *extracción de mortalidad y observación de alimentación. *instalacion y desmontaje de oxigenación. | S13: No
... A84: 83 | D84: Acuiestudios SpA | E84: Chile | H84: AquaSur 2026 | I84: Prospecto | J84: Alta | K84: Explorar alianza comercial / reventa a sus clientes salmoneros | L84: AquaSur 2026. Sin contacto publicado. | M84: Canal / aliado – consultoría SST | N84: ST-128 | O84: 1 | P84: Producción acuícola, pesquera y alimentos › Productores / procesadores acuícolas | Q84: Empresa especializada en asesorías en el ámbito sanitario, productivo, ambiental, comercio exterior y jurídico de la pesca y acuicultura, altamente comprometida con el desarrollo de esta actividad estratégica del país. Para esto contamos con un equipo de trabajo multidisciplinario de reconocida trayectoria a nivel nacional e internacional. | S84: No
A85: 84 | D85: CINDER CAPACITACION | E85: Chile | H85: AquaSur 2026 | I85: Prospecto | J85: Alta | K85: Explorar alianza comercial / reventa a sus clientes salmoneros | L85: AquaSur 2026. Sin contacto publicado. | M85: Canal / aliado – consultoría SST | N85: ST-126 | O85: 1 | P85: Servicios empresariales y consultoría › Consultoría / capacitación | S85: No
A86: 85 | D86: Enroka | E86: Chile | H86: AquaSur 2026 | I86: Prospecto | J86: Alta | K86: Explorar alianza comercial / reventa a sus clientes salmoneros | L86: AquaSur 2026. Sin contacto publicado. | M86: Canal / aliado – consultoría SST | N86: ST-124 | O86: 1 | P86: Servicios empresariales y consultoría › Reclutamiento / staffing | Q86: Ayudamos a empresas medianas y grandes a gestionar el envejecimiento laboral y la salida planificada de talentos +50 en cargos críticos, al ofrecer programas de Age Management que trabajan con la organización y con las personas, asegurando continuidad operacional, bienestar organizacional y transferencia estratégica de conocimiento. | S86: No
A87: 86 | D87: FERNANDEZ Y ALEUY CAPACITACION | E87: Chile | H87: AquaSur 2026 | I87: Prospecto | J87: Alta | K87: Explorar alianza comercial / reventa a sus clientes salmoneros | L87: AquaSur 2026. Sin contacto publicado. | M87: Canal / aliado – consultoría SST | N87: N-38 | O87: 1 | P87: Servicios empresariales y consultoría › Consultoría / capacitación | Q87: Grupo CONFIAL es una consultora estratégica y OTEC de alto nivel, especializada en capacitación, liderazgo y gestión de personas para la industria productiva. Contamos con equipos senior y más de 20 años de experiencia, entregando soluciones aplicadas, medibles y alineadas a resultados del negocio. | S87: No
A88: 87 | D88: INCAR | E88: Chile | H88: AquaSur 2026 | I88: Prospecto | J88: Alta | K88: Explorar alianza comercial / reventa a sus clientes salmoneros | L88: AquaSur 2026. Sin contacto publicado. | M88: Canal / aliado – consultoría SST | N88: ST-78 | O88: 1 | P88: Instituciones, medios y certificación › Certificación / bienestar animal | Q88: El Centro de Investigación Aplicada INCAR² desarrolla soluciones científicas y tecnológicas para los principales desafíos de la acuicultura chilena, creando vacunas, herramientas para reducir el uso de antimicrobianos, modelos ambientales y estrategias de resiliencia climática, con foco en soluciones sostenibles, competitividad, bienestar animal y transferencia efectiva al sector productivo. | S88: No
A89: 88 | D89: INTERTEK | E89: Chile | H89: AquaSur 2026 | I89: Prospecto | J89: Alta | K89: Explorar alianza comercial / reventa a sus clientes salmoneros | L89: AquaSur 2026. Sin contacto publicado. | M89: Canal / aliado – consultoría SST | N89: D-11 | O89: 1 | P89: Instituciones, medios y certificación › Certificación / bienestar animal | Q89: Intertek es un proveedor líder en Aseguramiento Total de la Calidad para las industrias al rededor del mundo. A través de nuestra red de más de 44,000 colaboradores, más de 1,000 laboratorios y oficinas en más de 100 países, brindamos soluciones innovadoras y hechas a la medida en Aseguramiento, Pruebas, Inspección y Certificación para las operaciones y cadenas de suministro de nuestros clientes. | S89: No
A90: 89 | D90: LEYTON INSURANCE | E90: Chile | H90: AquaSur 2026 | I90: Prospecto | J90: Alta | K90: Explorar alianza comercial / reventa a sus clientes salmoneros | L90: AquaSur 2026. Sin contacto publicado. | M90: Canal / aliado – consultoría SST | N90: P-36 | O90: 1 | P90: Finanzas, seguros y leasing › Seguros | Q90: LEYTON & ASOCIADOS Corredores de Seguros es especialista en Seguros para riesgos productivos e industriales de alta complejidad, tales como Plantas y Equipos, Seguro de Crédito, Responsabilidad Civil Corporativa, Naves Marítimas, Aéreas y otros Riesgos Facultativos, para lo que contamos con la colaboración Aseguradores en el «Mercado» nacional e internacional. | S90: No
A91: 90 | D91: OTIC CCC | E91: Chile | H91: AquaSur 2026 | I91: Prospecto | J91: Alta | K91: Explorar alianza comercial / reventa a sus clientes salmoneros | L91: AquaSur 2026. Sin contacto publicado. | M91: Canal / aliado – consultoría SST | N91: M-15 | O91: 1 | P91: Servicios empresariales y consultoría › Consultoría / capacitación | Q91: El OTIC CChC es el aliado líder de la industria salmonera en el sur de Chile. Acompañamos a las empresas del rubro en una gestión experta de la franquicia tributaria, conectándolas con capacitación pertinente, eficiente y de alto impacto para fortalecer la productividad, seguridad y sostenibilidad de sus equipos. | S91: No
A92: 91 | D92: PROFISUR | E92: Chile | H92: AquaSur 2026 | I92: Prospecto | J92: Alta | K92: Explorar alianza comercial / reventa a sus clientes salmoneros | L92: AquaSur 2026. Sin contacto publicado. | M92: Canal / aliado – consultoría SST | N92: B-10 | O92: 1 | P92: Servicios empresariales y consultoría › Reclutamiento / staffing | Q92: Profisur entrega soluciones integrales a la industria acuícola mediante la selección, gestión y dirección de personal calificado para plantas de proceso. Coordinamos su traslado, equipamiento y condiciones de trabajo, asegurando operaciones seguras, eficientes y alineadas a los objetivos productivos, con foco en la sustentabilidad y el cuidado de las personas. | S92: No
A93: 92 | D93: SAMS ENTERPRISE | E93: Reino Unido | H93: AquaSur 2026 | I93: Prospecto | J93: Alta | K93: Explorar alianza comercial / reventa a sus clientes salmoneros | L93: AquaSur 2026. Sin contacto publicado. | M93: Canal / aliado – consultoría SST | N93: E-24 | O93: 1 | P93: Producción acuícola, pesquera y alimentos › Productores / procesadores acuícolas | Q93: SAMS Enterprise es el brazo comercial de la Scottish Association for Marine Science, dedicado a transformar la investigación marina de vanguardia en soluciones reales que beneficien a las personas y al planeta. Nuestro trabajo en acuicultura, y especialmente en el cultivo de salmón, respalda prácticas sostenibles, rentables y resilientes, al mismo tiempo que positiva para las comunidades locales. | S93: No
A94: 93 | D94: SGS CHILE | E94: Chile | F94: pe.info@sgs.com | H94: AquaSur 2026 | I94: Prospecto | J94: Alta | K94: Explorar alianza comercial / reventa a sus clientes salmoneros | L94: AquaSur 2026. También en CRM Directorio SSO 2026 (ID 254); contacto heredado = filial Perú. | M94: Canal / aliado – consultoría SST | N94: J-12 | O94: 1 | P94: Instituciones, medios y certificación › Certificación / bienestar animal | Q94: SGS es líder mundial en inspección, ensayos y certificación. Apoyamos a la industria acuícola con servicios para inocuidad, calidad, sostenibilidad y cumplimiento normativo: análisis ambientales y de agua, control sanitario, certificaciones y soluciones para una producción responsable, sostenible y eficiente. | R94: 5171900 / 999979079 | S94: Directorio SSO (ID 254)
A95: 94 | D95: SINGULARES SPA | E95: Chile | H95: AquaSur 2026 | I95: Prospecto | J95: Alta | K95: Explorar alianza comercial / reventa a sus clientes salmoneros | L95: AquaSur 2026. Sin contacto publicado. | M95: Canal / aliado – consultoría SST | N95: J-19 | O95: 1 | P95: Servicios empresariales y consultoría › Consultoría / capacitación | Q95: Singulares SpA es una consultora estratégica certificada como Empresa B, con más de 15 años de experiencia acompañando a empresas a crecer con foco en resultados, personas y sostenibilidad. Diseñamos e implementamos soluciones en estrategia, gestión, liderazgo y talento, generando impacto real en la competitividad y el desarrollo de organizaciones de la industria acuícola y productiva. | S95: No
A96: 95 | D96: SMART TRAINING | E96: Chile | H96: AquaSur 2026 | I96: Prospecto | J96: Alta | K96: Explorar alianza comercial / reventa a sus clientes salmoneros | L96: AquaSur 2026. Sin contacto publicado. | M96: Canal / aliado – consultoría SST | N96: N-31 | O96: 1 | P96: Servicios empresariales y consultoría › Consultoría / capacitación | Q96: Smartraining es una OTEC especializada en academias corporativas con tecnología educativa avanzada y aprendizaje experiencial. Mediante franquicia tributaria SENCE, capacita a empresas del sector salmonero con programas 100% financiados, enfocados en seguridad, productividad, cumplimiento normativo y sostenibilidad, asegurando aprendizaje efectivo y aplicable en el puesto de trabajo. | S96: No
A97: 96 | D97: STIM CHILE | E97: Chile | H97: AquaSur 2026 | I97: Prospecto | J97: Alta | K97: Explorar alianza comercial / reventa a sus clientes salmoneros | L97: AquaSur 2026. Sin contacto publicado. | M97: Canal / aliado – consultoría SST | N97: E-32 | O97: 1 | P97: Servicios empresariales y consultoría › Consultoría / capacitación | Q97: STIM Chile es una filial de una empresa global especializada en salud y bienestar de peces para la acuicultura, con foco en la salmonicultura. Desde Puerto Montt, impulsa soluciones y tecnologías innovadoras que mejoran el rendimiento, bienestar y sostenibilidad de la producción acuícola, respaldadas por investigación y desarrollo científico. | S97: No
A98: 97 | D98: UNIVERSIDAD DE CHILE | E98: Chile | H98: AquaSur 2026 | I98: Prospecto | J98: Alta | K98: Explorar alianza comercial / reventa a sus clientes salmoneros | L98: AquaSur 2026. Sin contacto publicado. | M98: Canal / aliado – consultoría SST | N98: J-41 | O98: 1 | P98: Servicios empresariales y consultoría › Consultoría / capacitación | Q98: El Proyecto PHAGENET, corresponde a una iniciativa Anillo Tecnológico de ANID, código ACT240045. Este núcleo integra especialistas de distintas áreas y universidades del país, comprometidos con impulsar la investigación aplicada, la innovación biotecnológica y la transferencia de conocimiento al entorno productivo. | S98: No
A99: 98 | D99: UNIVERSIDAD DE CONCEPCIÓN | E99: Chile | H99: AquaSur 2026 | I99: Prospecto | J99: Alta | K99: Explorar alianza comercial / reventa a sus clientes salmoneros | L99: AquaSur 2026. Sin contacto publicado. | M99: Canal / aliado – consultoría SST | N99: N-12 | O99: 1 | P99: Energía, climatización e iluminación › Energía / combustibles / electrificación | Q99: El Centro para la Industria 4.0 (C4i) conecta investigación aplicada con desafíos de la industria nacional, apoyando a empresas mediante extensionismo, implementación tecnológica e I+D. En acuicultura desarrolla IA y visión computacional, IoT y monitoreo en tiempo real, diseño y manufactura avanzada, y AR/XR para operación y mantenimiento. Además, CAD/CAM y energía limpia para operaciones. | S99: No
A100: 99 | D100: WSP GLOBAL | E100: Chile | H100: AquaSur 2026 | I100: Prospecto | J100: Alta | K100: Explorar alianza comercial / reventa a sus clientes salmoneros | L100: AquaSur 2026. Sin contacto publicado. | M100: Canal / aliado – consultoría SST | N100: E-46 | O100: 1 | P100: Servicios empresariales y consultoría › Consultoría / capacitación | Q100: WSP es una de las principales empresas de servicios profesionales del mundo, que cuenta con un equipo de más de 77,000 destacados ingenieros, asesores y científicos. Su propósito es dar forma a las comunidades y avanzar a la humanidad mediante el enfoque Future Ready®, impulsado por el compromiso de generar un impacto positivo y apoyar a sus clientes a innovar y enfrentar desafíos reales. | S100: No
A101: 100 | D101: MANPOWER GROUP | E101: Chile | H101: AquaSur 2026 | I101: Prospecto | J101: Alta | K101: Explorar alianza comercial / reventa a sus clientes salmoneros | L101: AquaSur 2026. Sin stand asignado en el listado. Sin contacto publicado. | M101: Canal / aliado – consultoría SST | N101: Sin stand | O101: 0 | P101: Servicios empresariales y consultoría › Reclutamiento / staffing | Q101: ManpowerGroup es líder global en soluciones de talento humano, con más de 70 años de experiencia y presencia en más de 70 países. En Chile apoyamos a empresas en la atracción, gestión y desarrollo del talento, combinando enfoque consultivo B2B, conocimiento del mercado laboral y especialización en talento tecnológico para impulsar su crecimiento y adaptación. | S101: No
A102: 101 | D102: ANCORA | E102: Chile | H102: AquaSur 2026 | I102: Prospecto | J102: Media | K102: Explorar integración con equipos (visión + telemetría en pontones, wellboats, jaulas) | L102: AquaSur 2026. Varios stands (mayor inversión). Sin contacto publicado. | M102: Partner OEM – equipos acuícolas y marinos | N102: D-45, D-44 | O102: 2 | P102: Automatización, robótica y monitoreo › ROV / robótica | Infraestructura marina y equipamiento acuícola › Servicios / equipos marítimos | Q102: ANCORA CHILE, en una nueva etapa de crecimiento y consolidación en la industria marítima continuamos liderando con innovación y soluciones de alta calidad, brindando un servicio integral que responde a las exigencias del sector y a la evolución de las necesidades de nuestros clientes. En la actualidad representamos alrededor de 16 marcas exclusivas, proveedores integrales de equipamiento naval. | S102: No
A103: 102 | D103: PATAGONIA IMPORTACIONES | E103: Chile | H103: AquaSur 2026 | I103: Prospecto | J103: Media | K103: Explorar integración con equipos (visión + telemetría en pontones, wellboats, jaulas) | L103: AquaSur 2026. Varios stands (mayor inversión). Sin contacto publicado. | M103: Partner OEM – equipos acuícolas y marinos | N103: B-50, AD-06 | O103: 2 | P103: Infraestructura marina y equipamiento acuícola › Servicios / equipos marítimos | Q103: Venta de Motores Marinos, Gruas Marinas, Grupos Generadores, Cajas Marinas, Accesorios Marinos, Electronica Naval y Repuestos en General | S103: No
A104: 103 | D104: ABB S.A. | E104: Chile | F104: contact.center@pe.abb.com | H104: AquaSur 2026 | I104: Prospecto | J104: Media | K104: Explorar integración con equipos (visión + telemetría en pontones, wellboats, jaulas) | L104: AquaSur 2026. También expone en Exponor 2026 (ID 361). También en CRM Directorio SSO 2026 (ID 512); contacto heredado = filial Perú. | M104: Partner OEM – equipos acuícolas y marinos | N104: G-48 | O104: 1 | P104: Automatización, robótica y monitoreo › Automatización / control | Q104: En ABB hacemos un futuro más eficiente y sostenible en el uso de los recursos. Conectando su dominio de la ingeniería y de la digitalización, ABB contribuye a que las industrias funcionen a alto rendimiento, al tiempo que mejoran su eficiencia, productividad y sostenibilidad, para superar sus resultados. En ABB, lo llamamos “Engineered to Outrun”. | R104: 4155100 | S104: Exponor (ID 361); Directorio SSO (ID 512)
A105: 104 | D105: ADRIA WINCH | E105: Chile | H105: AquaSur 2026 | I105: Prospecto | J105: Media | K105: Explorar integración con equipos (visión + telemetría en pontones, wellboats, jaulas) | L105: AquaSur 2026. Sin contacto publicado. | M105: Partner OEM – equipos acuícolas y marinos | N105: P-20 | O105: 1 | P105: Infraestructura marina y equipamiento acuícola › Servicios / equipos marítimos | Q105: Adria Winch d.o.o. is a Croatian manufacturer of deck machinery and winches for maritime, offshore, naval and energy sectors. Founded in 1993 and based in Split, the company delivers robust, custom-engineered solutions worldwide, trusted for reliability in demanding operating environments. | S105: No
A106: 105 | D106: BADINOTTI | E106: Chile | H106: AquaSur 2026 | I106: Prospecto | J106: Media | K106: Explorar integración con equipos (visión + telemetría en pontones, wellboats, jaulas) | L106: AquaSur 2026. Sin contacto publicado. | M106: Partner OEM – equipos acuícolas y marinos | N106: A-28 | O106: 1 | P106: Infraestructura marina y equipamiento acuícola › Jaulas / flotación / estructuras | Q106: Soluciones fiables para sistemas de contención en el agua y servicios relacionados | S106: No
A107: 106 | D107: BOSSAQUA | E107: Nueva Zelanda | H107: AquaSur 2026 | I107: Prospecto | J107: Media | K107: Explorar integración con equipos (visión + telemetría en pontones, wellboats, jaulas) | L107: AquaSur 2026. Sin contacto publicado. | M107: Partner OEM – equipos acuícolas y marinos | N107: J-14 | O107: 1 | P107: Infraestructura marina y equipamiento acuícola › Jaulas / flotación / estructuras | Q107: We design and manufacture AutoBoss™, specialised net washing equipment for the global Aquaculture industry. We focus on designing and producing world-class net washing equipment, with a strong emphasis on research and design. Our V4 model has generated exponential growth and significant offshore market penetration and is the ONLY self-contained autonomous net-cleaning solution in the market. | S107: No
A108: 107 | D108: BZ NAVAL ENGINEERING | E108: Chile | H108: AquaSur 2026 | I108: Prospecto | J108: Media | K108: Explorar integración con equipos (visión + telemetría en pontones, wellboats, jaulas) | L108: AquaSur 2026. Sin contacto publicado. | M108: Partner OEM – equipos acuícolas y marinos | N108: G-44 | O108: 1 | P108: Infraestructura marina y equipamiento acuícola › Servicios / equipos marítimos | Q108: BZ Naval ofrece soluciones para el ámbito Marítimo, Portuario y Astilleros. proporcionando servicios de Ingeniería, Concesiones Marítimas y representaciones de reconocidas compañías internacionales. Estará junto a HamiltonJet, pionera en propulsión por chorro de agua (waterjet), que también presentará sus sistemas híbridos-eléctricos para clientes que buscan una propulsión eficiente y ecológica. | S108: No
A109: 108 | D109: CFLOW FISH | E109: Chile | H109: AquaSur 2026 | I109: Prospecto | J109: Media | K109: Explorar integración con equipos (visión + telemetría en pontones, wellboats, jaulas) | L109: AquaSur 2026. Sin contacto publicado. | M109: Partner OEM – equipos acuícolas y marinos | N109: G-30 | O109: 1 | P109: Infraestructura marina y equipamiento acuícola › Jaulas / flotación / estructuras | Q109: Compañía noruega con más de 20 años de trayectoria global. Nos especializamos en diseñar soluciones estratégicas e innovadoras que transforman y optimizan los procesos productivos de nuestros clientes. | S109: No
A110: 109 | D110: DERCOMAQ S.A. | E110: Chile | H110: AquaSur 2026 | I110: Prospecto | J110: Media | K110: Explorar integración con equipos (visión + telemetría en pontones, wellboats, jaulas) | L110: AquaSur 2026. Sin contacto publicado. | M110: Partner OEM – equipos acuícolas y marinos | N110: J-36 | O110: 1 | P110: Equipos e insumos industriales › Construcción / estructuras | Q110: Dercomaq es una empresa líder en la comercialización de maquinaria, camiones, repuestos y soluciones integrales para los sectores agrícola, construcción, minería y transporte. con una amplia red de sucursales en Chile, Representa marcas de prestigio internacional y ofrece servicios de postventa, arriendo de equipos y soporte técnico especializado. | S110: No
A111: 110 | D111: DISTRIBUIDORA CUMMINS CHILE S.A. | E111: Chile | H111: AquaSur 2026 | I111: Prospecto | J111: Media | K111: Explorar integración con equipos (visión + telemetría en pontones, wellboats, jaulas) | L111: AquaSur 2026. Sin contacto publicado. | M111: Partner OEM – equipos acuícolas y marinos | N111: L-34 | O111: 1 | P111: Energía, climatización e iluminación › Energía / combustibles / electrificación | Q111: Cummins Chile es la filial y distribuidor oficial de Cummins en el país. Provee soluciones de energía y potencia, con venta, servicio y soporte técnico de motores diésel, grupos electrógenos, repuestos y componentes, además de arriendo de equipos y contratos de mantenimiento para sectores como minería, transporte, energía e industria. | S111: No
A112: 111 | D112: ELECTRORIDERS | E112: Chile | H112: AquaSur 2026 | I112: Prospecto | J112: Media | K112: Explorar integración con equipos (visión + telemetría en pontones, wellboats, jaulas) | L112: AquaSur 2026. Sin contacto publicado. | M112: Partner OEM – equipos acuícolas y marinos | N112: P-03 | O112: 1 | P112: Automatización, robótica y monitoreo › Sensores / instrumentación / monitoreo | Q112: ElectroRiders es una empresa chilena de ingeniería y soluciones tecnológicas especializada en propulsión eléctrica marina para acuicultura. Desarrollamos sistemas de baterías, motores fuera de borda eléctricos y reconversiones de embarcaciones de apoyo, integrando electrónica de potencia, control y monitoreo. Enfocados en eficiencia, seguridad y reducción de emisiones, ruido y costos operacionales | S112: No
A113: 112 | D113: FEEDING SYSTEMS SL | E113: España | H113: AquaSur 2026 | I113: Prospecto | J113: Media | K113: Explorar integración con equipos (visión + telemetría en pontones, wellboats, jaulas) | L113: AquaSur 2026. Sin contacto publicado. | M113: Partner OEM – equipos acuícolas y marinos | N113: A-06 | O113: 1 | P113: Nutrición y alimentación acuícola › Alimentos balanceados / procesamiento | Q113: En FishFarmFeeder diseñamos y fabricamos sistemas automáticos de alimentación para peces y camarones desde 2008. Somos especialistas en soluciones adaptadas a todas las etapas de cultivo —desde la cría hasta el engorde— y en todo tipo de instalaciones, tanto en tierra como en mar | S113: No
A114: 113 | D114: FERNANDEZ JOVE | E114: España | H114: AquaSur 2026 | I114: Prospecto | J114: Media | K114: Explorar integración con equipos (visión + telemetría en pontones, wellboats, jaulas) | L114: AquaSur 2026. Sin contacto publicado. | M114: Partner OEM – equipos acuícolas y marinos | N114: H-51 | O114: 1 | P114: Infraestructura marina y equipamiento acuícola › Servicios / equipos marítimos | Q114: FJ | Fernández Jove, fabricante e integrador español con 50 años de experiencia, desarrolla sistemas de control remoto, soluciones hidráulicas y válvulas Saval de alto rendimiento. Distribuye HTS para sellado de cables y tuberías. Su enfoque en ingeniería, calidad e innovación lo convierte en un socio fiable en los sectores naval, marítimo e industrial. | S114: No
A115: 114 | D115: FINNING CHILE S.A | E115: Chile | H115: AquaSur 2026 | I115: Prospecto | J115: Media | K115: Explorar integración con equipos (visión + telemetría en pontones, wellboats, jaulas) | L115: AquaSur 2026. Sin contacto publicado. | M115: Partner OEM – equipos acuícolas y marinos | N115: E-48 | O115: 1 | P115: Energía, climatización e iluminación › Energía / combustibles / electrificación | Q115: Finning es el mayor distribuidor mundial de Caterpillar y lleva más de 90 años prestando un servicio inigualable. Vendemos, alquilamos y proporcionamos piezas y servicio para equipos y motores a clientes de diversas industrias, incluyendo minería, construcción, petróleo, silvicultura y una amplia gama de aplicaciones de sistemas de energía. | S115: No
A116: 115 | D116: FJORD MARITIME | E116: Chile | H116: AquaSur 2026 | I116: Prospecto | J116: Media | K116: Explorar integración con equipos (visión + telemetría en pontones, wellboats, jaulas) | L116: AquaSur 2026. Sin contacto publicado. | M116: Partner OEM – equipos acuícolas y marinos | N116: J-09 | O116: 1 | P116: Energía, climatización e iluminación › Energía / combustibles / electrificación | Q116: Empresa de tecnología con énfasis en la sustentabilidad, se enfoca en la reducción de CO2 a través del manejo y optimización del uso de la energía y ahorro en el uso de combustibles fósiles, asegurando energía limpia y estable, a través de su sistema Fjord hybrid para la industria acuícola | S116: No
... A156: 155 | D156: B2B MEDIA GROUP SPA | E156: Chile | H156: AquaSur 2026 | I156: Prospecto | J156: Media | K156: Networking institucional; identificar contacto | L156: AquaSur 2026. Sin contacto publicado. | M156: Institución / gremio / pabellón país | N156: B-23 | O156: 1 | P156: Instituciones, medios y certificación › Medios especializados | Q156: Medios AQUA, a través de www.aqua.cl y Revista AQUA, es el principal medio especializado en acuicultura y pesca en Chile y Latinoamérica. Con más de 37 años de trayectoria, conecta a empresas, ejecutivos y proveedores con información estratégica del sector. Su plataforma integra portal web, newsletter y revista impresa y digital, llegando directamente a tomadores de decisión de la industria. | S156: No
A157: 156 | D157: BOMBEROS DE PUERTO VARAS | E157: Chile | H157: AquaSur 2026 | I157: Prospecto | J157: Media | K157: Networking institucional; identificar contacto | L157: AquaSur 2026. Sin contacto publicado. | M157: Institución / gremio / pabellón país | N157: AD-05 | O157: 1 | P157: Instituciones, medios y certificación › Asociaciones / sector público | S157: No
A158: 157 | D158: BOTE SALVAVIDAS | E158: Chile | H158: AquaSur 2026 | I158: Prospecto | J158: Media | K158: Networking institucional; identificar contacto | L158: AquaSur 2026. Sin contacto publicado. | M158: Institución / gremio / pabellón país | N158: P-08 | O158: 1 | P158: Seguridad, protección y emergencia › Protección industrial / seguridad | Q158: El Cuerpo de Voluntarios de los Botes Salvavidas de Puerto Montt salvaguarda la vida y la integridad de las personas en entornos acuáticos. Con 23 años de experiencia en emergencias comunales, regionales y nacionales, incluyendo terremotos, tsunamis y erupciones volcánicas, somos una organización 100% voluntaria dedicada a la prevención, seguridad y rescate de la comunidad. | S158: No
A159: 158 | D159: CAMARA CHILENO SUIZA DE COMERCIO A.G. | E159: Chile | H159: AquaSur 2026 | I159: Prospecto | J159: Media | K159: Networking institucional; identificar contacto | L159: AquaSur 2026. Sin contacto publicado. | M159: Institución / gremio / pabellón país | N159: L-18 | O159: 1 | P159: Instituciones, medios y certificación › Asociaciones / sector público | Q159: Creamos valor para la sociedad chilena, siendo puente de negocios y de buenas prácticas, promoviendo el sello suizo y fomentando la sostenibilidad para las futuras generaciones. | S159: No
A160: 159 | D160: CERTIFIED HUMANE | E160: Brasil | H160: AquaSur 2026 | I160: Prospecto | J160: Media | K160: Networking institucional; identificar contacto | L160: AquaSur 2026. Sin contacto publicado. | M160: Institución / gremio / pabellón país | N160: J-16 | O160: 1 | P160: Instituciones, medios y certificación › Certificación / bienestar animal | Q160: Programa de certificación de bienestar de animales de granja presente en más de 30 países | S160: No
A161: 160 | D161: CLUB INNOVACION ACUICOLA | E161: Chile | H161: AquaSur 2026 | I161: Prospecto | J161: Media | K161: Networking institucional; identificar contacto | L161: AquaSur 2026. Sin contacto publicado. | M161: Institución / gremio / pabellón país | N161: P-02 | O161: 1 | P161: Equipos e insumos industriales › Construcción / estructuras | Q161: Club Innovación Acuícola fortalece la capacidad individual y asociativa de sus miembros para innovar, sobre la base de la construcción de capital social al interior del club y en los ecosistemas de I+D+i nacional y extranjeros, para el desarrollo de una acuicultura competitiva y sostenible. | S161: No
A162: 161 | D162: CORFO - SALMON SUSTENTABLE | E162: Chile | H162: AquaSur 2026 | I162: Prospecto | J162: Media | K162: Networking institucional; identificar contacto | L162: AquaSur 2026. Sin contacto publicado. | M162: Institución / gremio / pabellón país | N162: S-28 | O162: 1 | P162: Energía, climatización e iluminación › Energía / combustibles / electrificación | Q162: Corfo Los Lagos impulsa el desarrollo productivo, la innovación y el emprendimiento con foco en sostenibilidad. En el sector acuícola apoya programas que fortalecen la competitividad mediante tecnología, economía circular, eficiencia energética, diversificación y desarrollo de proveedores, promoviendo una industria más sostenible y con mayor valor agregado. | S162: No
A163: 162 | D163: DANISH EMBASSY | E163: Dinamarca | H163: AquaSur 2026 | I163: Prospecto | J163: Media | K163: Networking institucional; identificar contacto | L163: AquaSur 2026. Sin contacto publicado. | M163: Institución / gremio / pabellón país | N163: D-26 | O163: 1 | P163: Producción acuícola, pesquera y alimentos › Productores / procesadores acuícolas | Q163: Danish Export - Fish Tech is an export network gathering Danish export companies specialized in innovative and sustainable solutions as well as services for the international aquaculture, fish processing and commercial fisheries industries. Danish Export - Fish Tech/Pavilion of Denmark at Aqua Sur is your one point of contact to strong Danish competences and know-how within the target industries. | S163: No
A164: 163 | D164: DIRECTEMAR | E164: Chile | H164: AquaSur 2026 | I164: Prospecto | J164: Media | K164: Networking institucional; identificar contacto | L164: AquaSur 2026. Sin contacto publicado. | M164: Institución / gremio / pabellón país | N164: R-16 | O164: 1 | P164: Agua, ambiente y sostenibilidad › Servicios ambientales / mitigación | Q164: DIRECTEMAR es el organismo de la Armada de Chile, que cautela el cumplimiento de leyes y acuerdos internacionales, para proteger la vida humana en el mar, ríos y lagos; preservar el medio ambiente acuático y recursos naturales marinos; ejerce la policía marítima, fiscaliza y regula las actividades dentro de su jurisdicción, con el propósito de contribuir al desarrollo marítimo de la nación. | S164: No
A165: 164 | D165: EL CONQUISTADOR | E165: Chile | H165: AquaSur 2026 | I165: Prospecto | J165: Media | K165: Networking institucional; identificar contacto | L165: AquaSur 2026. Sin contacto publicado. | M165: Institución / gremio / pabellón país | N165: GA-32 | O165: 1 | P165: Automatización, robótica y monitoreo › ROV / robótica | Q165: Poseemos 6 estaciones de Radio el Conquistador Fm desde Osorno a Quellon Poseemos 4 estaciones de Radio Cooperativa, Provincia de Llanquihue y Provincia de Chiloe | S165: No
A166: 165 | D166: Endeavor Aquatech Cluster | E166: Chile | H166: AquaSur 2026 | I166: Prospecto | J166: Media | K166: Networking institucional; identificar contacto | L166: AquaSur 2026. Sin contacto publicado. | M166: Institución / gremio / pabellón país | N166: N-46, Sin stand | O166: 1 | P166: Instituciones, medios y certificación › Asociaciones / sector público | Nutrición y alimentación acuícola › Ingredientes / aditivos / probióticos | Salud animal, biotecnología y laboratorio › Biotecnología aplicada | Agua, ambiente y sostenibilidad › Tratamiento de agua / efluentes | Q166: Codebreaker Bioscience transforms the microbiome into actionable biological intelligence. By sequencing DNA and integrating production data, we improve animal survival and performance while reducing risk, using the animal as the ultimate sensor. This enables producers to optimize resources, make better decisions, and increase productivity and sustainability through precise biological control. | S166: No
A167: 166 | D167: FACH - FUERZA AEREA DE CHILE | E167: Chile | H167: AquaSur 2026 | I167: Prospecto | J167: Media | K167: Networking institucional; identificar contacto | L167: AquaSur 2026. Sin contacto publicado. | M167: Institución / gremio / pabellón país | N167: ST-120 | O167: 1 | P167: Instituciones, medios y certificación › Asociaciones / sector público | S167: No
A168: 167 | D168: GLOBAL AQUA | E168: Noruega | H168: AquaSur 2026 | I168: Prospecto | J168: Media | K168: Networking institucional; identificar contacto | L168: AquaSur 2026. Sin contacto publicado. | M168: Institución / gremio / pabellón país | N168: M-41 | O168: 1 | P168: Producción acuícola, pesquera y alimentos › Productores / procesadores acuícolas | Q168: The new international arena for aquaculture! Global Aqua is the new global meeting place for aquaculture, where producers, technology leaders, researchers, decision-makers, and investors come together to accelerate the solutions the world needs to secure the future supply of healthy and responsibly produced seafood. | S168: No
A169: 168 | D169: HAVEXPO | E169: Noruega | H169: AquaSur 2026 | I169: Prospecto | J169: Media | K169: Networking institucional; identificar contacto | L169: AquaSur 2026. Sin contacto publicado. | M169: Institución / gremio / pabellón país | N169: M39B | O169: 1 | P169: Producción acuícola, pesquera y alimentos › Productores / procesadores acuícolas | Q169: HavExpo 2026 will be bigger and better than before. HavExpo 2026 promises to be the best trade fair for the aquaculture and fisheries industries to date with significant expansions and improvements based on experience and feedback from previous events. The area has been used for four annual trade fairs since 2014. | S169: No
A170: 169 | D170: INFO SALMON | E170: Chile | H170: AquaSur 2026 | I170: Prospecto | J170: Media | K170: Networking institucional; identificar contacto | L170: AquaSur 2026. Sin contacto publicado. | M170: Institución / gremio / pabellón país | N170: L-22 | O170: 1 | P170: Instituciones, medios y certificación › Medios especializados | Q170: InfoSALMON es la plataforma líder en medios de comunicación acuícolas a nivel mundial, con información estratégica y multicanal para CEOs y tomadores de decisión de toda la cadena de valor. InfoSALMON is the world’s leading aquaculture media platform, delivering strategic, multichannel intelligence for CEOs and decision-makers across the entire value chain. | S170: No
A171: 170 | D171: MUNDO ACUICOLA | E171: Chile | H171: AquaSur 2026 | I171: Prospecto | J171: Media | K171: Networking institucional; identificar contacto | L171: AquaSur 2026. Sin contacto publicado. | M171: Institución / gremio / pabellón país | N171: F-10 | O171: 1 | P171: Instituciones, medios y certificación › Medios especializados | Q171: Mundo Acuícola es un medio especializado en acuicultura y pesca con 26 años de trayectoria. Integra revista impresa y digital, portal web y app móvil. Su plataforma tecnológica ofrece contenidos dinámicos, interacción en redes y notificaciones en tiempo real, conectando a la industria con información oportuna y de alto valor. | S171: No
A172: 171 | D172: MUNICIPALIDAD DE PUERTO MONTT | E172: Chile | H172: AquaSur 2026 | I172: Prospecto | J172: Media | K172: Networking institucional; identificar contacto | L172: AquaSur 2026. Sin contacto publicado. | M172: Institución / gremio / pabellón país | N172: GA-46 | O172: 1 | P172: Instituciones, medios y certificación › Asociaciones / sector público | S172: No
A173: 172 | D173: MUNICIPALIDAD DE PUERTO VARAS | E173: Chile | H173: AquaSur 2026 | I173: Prospecto | J173: Media | K173: Networking institucional; identificar contacto | L173: AquaSur 2026. Sin contacto publicado. | M173: Institución / gremio / pabellón país | N173: GA-42 | O173: 1 | P173: Instituciones, medios y certificación › Asociaciones / sector público | Q173: La oficina Municipal de información turística de Puerto Varas asesora al visitante en materia del destino Puerto Varas y de la zona ZOIT cuenca lago Llanquihue. | S173: No
A174: 173 | D174: Pabellón Brasil (MAPA) | E174: Chile | H174: AquaSur 2026 | I174: Prospecto | J174: Media | K174: Networking institucional; identificar contacto | L174: AquaSur 2026. Sin contacto publicado. | M174: Institución / gremio / pabellón país | N174: N-22 | O174: 1 | P174: Infraestructura marina y equipamiento acuícola › Redes / cabos / fondeo | Q174: El Ministerio de Agricultura e Pecuária (MAPA) impulsa políticas que fortalecen la agropecuaria y el agronegocio en Brasil, integrando dimensiones económicas, tecnológicas, sanitarias, científicas y ambientales. Promueve innovación, sostenibilidad y competitividad, garantizando la seguridad alimentaria, consolidando el sector productivo y ampliando la presencia internacional del país. | S174: No
A175: 174 | D175: PROCHILE | E175: Chile | H175: AquaSur 2026 | I175: Prospecto | J175: Media | K175: Networking institucional; identificar contacto | L175: AquaSur 2026. Sin contacto publicado. | M175: Institución / gremio / pabellón país | N175: S-24 | O175: 1 | P175: Instituciones, medios y certificación › Asociaciones / sector público | Q175: ProChile es la institución del Ministerio de Relaciones Exteriores que promueve la internacionalización de las empresas chilenas, a través de acciones de promoción de bienes y servicios, junto al apoyo de la atracción de la inversión extranjera, el turismo y el fortalecimiento de la imagen país. Cuenta con oficinas regionales a lo largo de Chile y una red de Oficinas en el extranjero. | S175: No
A176: 175 | D176: RADIO PATAGONIA | E176: Chile | H176: AquaSur 2026 | I176: Prospecto | J176: Media | K176: Networking institucional; identificar contacto | L176: AquaSur 2026. Sin contacto publicado. | M176: Institución / gremio / pabellón país | N176: GA-52 | O176: 1 | P176: Instituciones, medios y certificación › Medios especializados | Q176: Patagonia Radio es una emisora del sur de Chile con base en Puerto Montt. Entrega información local, actualidad, entrevistas, cultura y música, conectando a la Región de Los Lagos con una mirada cercana, plural y comprometida con su comunidad. | S176: No
A177: 176 | D177: REVISTA PUERTO A PUERTO | E177: Chile | H177: AquaSur 2026 | I177: Prospecto | J177: Media | K177: Networking institucional; identificar contacto | L177: AquaSur 2026. Sin contacto publicado. | M177: Institución / gremio / pabellón país | N177: R-18 | O177: 1 | P177: Instituciones, medios y certificación › Medios especializados | Q177: REVISTA PUERTO A PUERTO ES UN MEDIO DIGITAL E IMPRESO, CON 20 AÑOS DE TRAYECTORIA. PUBLICAMOS 4 EDICIONES EN EL AÑO. 6000 EJEMPLARES CADA IMPRESION. PUBLICAMOS TEMAS MISCELANEOS DE CARACTER TRANSVERSAL. CON SUSCRIPCION EN TODO CHILE, Y EN ARGENTINA BARICLOCHE-PUERTO MADRYN- USHUAIA-RIO GRANDE. GRAN TIRAJE EN LAS REGIONES DE LOS LAGOS- AYSEN-MAGALLANES. OFICINAS EN PUERTO MONTT - PUNTA ARENAS | S177: No
A178: 177 | D178: SALMONEXPERT | E178: Chile | H178: AquaSur 2026 | I178: Prospecto | J178: Media | K178: Networking institucional; identificar contacto | L178: AquaSur 2026. Sin contacto publicado. | M178: Institución / gremio / pabellón país | N178: E-35 | O178: 1 | P178: Instituciones, medios y certificación › Medios especializados | Q178: Somos un medio de comunicación independiente, técnico y objetivo, con más de 15 años de trayectoria informando sobre la industria del salmón en Chile y el mundo. Forma parte del grupo Oceanspace Media, holding internacional de medios especializados en pesca, acuicultura, logística y construcción de barcos con presencia en Chile, Noruega, Escocia y Dinamarca, cuya primera publicación data de 1976. | S178: No
A179: 178 | D179: SERNAPESCA | E179: Chile | H179: AquaSur 2026 | I179: Prospecto | J179: Media | K179: Networking institucional; identificar contacto | L179: AquaSur 2026. Sin contacto publicado. | M179: Institución / gremio / pabellón país | N179: P-22 | O179: 1 | P179: Producción acuícola, pesquera y alimentos › Productores / procesadores acuícolas | Q179: El Servicio Nacional de Pesca y Acuicultura es una entidad dependiente del Ministerio de Economía, Fomento y Turismo, cuya misión es “contribuir a la sustentabilidad del sector y a la protección de los recursos hidrobiológicos y su medio ambiente, a través de una fiscalización integral y gestión sanitaria que influye en el comportamiento sectorial promoviendo el cumplimiento de las normas”. | S179: No
A180: 179 | D180: VC MAGAZINE | E180: Chile | H180: AquaSur 2026 | I180: Prospecto | J180: Media | K180: Networking institucional; identificar contacto | L180: AquaSur 2026. Sin contacto publicado. | M180: Institución / gremio / pabellón país | N180: S-25 | O180: 1 | P180: Instituciones, medios y certificación › Medios especializados | Q180: Medio de comunicación multisectorial y multiplataforma de alcance nacional que visibiliza cómo empresas, industrias, emprendimientos y territorios generan impacto económico, social y ambiental positivo en Chile. A través de contenidos editoriales, reportajes, entrevistas y cobertura en distintos formatos —revista impresa y digital, plataformas audiovisuales y redes sociales. | S180: No
A181: 180 | D181: VERTICE TV | E181: Chile | H181: AquaSur 2026 | I181: Prospecto | J181: Media | K181: Networking institucional; identificar contacto | L181: AquaSur 2026. Sin contacto publicado. | M181: Institución / gremio / pabellón país | N181: S-18 | O181: 1 | P181: Instituciones, medios y certificación › Medios especializados | Q181: Vértice Media es un grupo de multimedios que integra Vértice TV, canal de televisión abierta, con su noticiero especializado El Pulso Acuícola. Además, cuenta con diarios digitales regionales y portal web. Desarrolla contenidos multiplataforma, producción audiovisual (videos, spots, podcast) y servicios de streaming para eventos y seminarios. | S181: No
A182: 181 | D182: AQUABENCH | E182: Chile | H182: AquaSur 2026 | I182: Prospecto | J182: Media | K182: Networking institucional; identificar contacto | L182: AquaSur 2026. Sin stand asignado en el listado. Sin contacto publicado. | M182: Institución / gremio / pabellón país | N182: Sin stand | O182: 0 | P182: Producción acuícola, pesquera y alimentos › Productores / procesadores acuícolas | Q182: Alianza Yelcho: Iniciativa público-privada pionera en la salmonicultura. Buscamos nuevas soluciones inmunológicas que controlen eficazmente la Piscirickettsiosis (SRS) que afecta al salmón de cultivo en Chile, para disminuir el uso de antibióticos. | S182: No
A183: 182 | D183: EILERS | E183: Chile | H183: AquaSur 2026 | I183: Prospecto | J183: Baja | K183: Nutrir con contenido; sin acción comercial inmediata | L183: AquaSur 2026. Varios stands (mayor inversión). Sin contacto publicado. | M183: Proveedor industrial (equipos/insumos) | N183: A-13, B-14 | O183: 2 | P183: Equipos e insumos industriales › Maquinaria / insumos industriales | Q183: Con más de 30 años de experiencia, somos un referente en la distribución de equipos y productos marinos de la más alta calidad, de mercados tan prestigiosos como Alemania, Corea, Estados Unidos e Italia. Nuestro compromiso con la excelencia nos impulsa a brindar un servicio personalizado, apoyado por un equipo de expertos dispuestos a asesorarles en cada paso del camino. | S183: No
A184: 183 | D184: GREENVOLUTION | E184: Chile | H184: AquaSur 2026 | I184: Prospecto | J184: Baja | K184: Nutrir con contenido; sin acción comercial inmediata | L184: AquaSur 2026. Varios stands (mayor inversión). Sin contacto publicado. | M184: Proveedor industrial (equipos/insumos) | N184: ST-76, ST-77 | O184: 2 | P184: Nutrición y alimentación acuícola › Ingredientes / aditivos / probióticos | Q184: En Greenvolution nos dedicamos a la formulación y elaboración de mezclas de aditivos funcionales sostenibles que optimizan el bienestar, la eficiencia productiva y el cumplimiento de los más altos estándares internacionales de calidad. Nuestra misión es transformar la industria a través de soluciones innovadoras que mejoren la salud y productividad de los animales y reduzcan el impacto ambiental. | S184: No
... A196: 195 | D196: ALUMICHEM | E196: Dinamarca | H196: AquaSur 2026 | I196: Prospecto | J196: Baja | K196: Nutrir con contenido; sin acción comercial inmediata | L196: AquaSur 2026. Sin contacto publicado. | M196: Proveedor industrial (equipos/insumos) | N196: C-20 | O196: 1 | P196: Agua, ambiente y sostenibilidad › Tratamiento de agua / efluentes | Q196: Meet your RAS water discharge limits Alumichem delivers high-performance, turnkey water treatment solutions for land-based fish farms of all species. Engineered to meet strict discharge requirements, our solutions are powered by 40+ years of proven expertise and a global network of specialists in water treatment chemicals, equipment, and consulting. | S196: No
A197: 196 | D197: AMBIENTE OZONO | E197: Chile | H197: AquaSur 2026 | I197: Prospecto | J197: Baja | K197: Nutrir con contenido; sin acción comercial inmediata | L197: AquaSur 2026. Sin contacto publicado. | M197: Proveedor industrial (equipos/insumos) | N197: P-07 | O197: 1 | P197: Agua, ambiente y sostenibilidad › Ozono / desinfección | S197: No
A198: 197 | D198: AMBIPAR | E198: Chile | H198: AquaSur 2026 | I198: Prospecto | J198: Baja | K198: Nutrir con contenido; sin acción comercial inmediata | L198: AquaSur 2026. Sin contacto publicado. | M198: Proveedor industrial (equipos/insumos) | N198: N-18 | O198: 1 | P198: Agua, ambiente y sostenibilidad › Servicios ambientales / mitigación | Q198: Ambipar es una empresa líder global en soluciones medioambientales que impulsa la transformación ecológica de organizaciones y territorios. Integra gestión de residuos, economía circular, respuesta a emergencias y soluciones sostenibles para proteger el medio ambiente, garantizar la continuidad operativa y generar impacto positivo en las personas y el planeta. | S198: No
A199: 198 | D199: AMRISA | E199: Chile | H199: AquaSur 2026 | I199: Prospecto | J199: Baja | K199: Nutrir con contenido; sin acción comercial inmediata | L199: AquaSur 2026. Sin contacto publicado. | M199: Proveedor industrial (equipos/insumos) | N199: K-42 | O199: 1 | P199: Equipos e insumos industriales › Ingeniería / mantenimiento | Q199: Ingeniería y diseño de plantas frigoríficas industriales y marinas | S199: No
A200: 199 | D200: ANAM - ECORILES | E200: Chile | H200: AquaSur 2026 | I200: Prospecto | J200: Baja | K200: Nutrir con contenido; sin acción comercial inmediata | L200: AquaSur 2026. Sin contacto publicado. | M200: Proveedor industrial (equipos/insumos) | N200: M-02 | O200: 1 | P200: Salud animal, biotecnología y laboratorio › Diagnóstico / laboratorio | Q200: ANAM y Ecoriles son filiales del grupo Aguas y Veolia. ANAM destaca por sus laboratorios acreditados y servicios de análisis de agua, aire, suelos y residuos, con más de 20 años de experiencia. Ecoriles se especializa en tratamiento de aguas industriales, con enfoque en economía circular y continuidad operacional para diversas industrias. | S200: No
A201: 200 | D201: ANDRITZ | E201: Chile | H201: AquaSur 2026 | I201: Prospecto | J201: Baja | K201: Nutrir con contenido; sin acción comercial inmediata | L201: AquaSur 2026. Sin contacto publicado. | M201: Proveedor industrial (equipos/insumos) | N201: J-06 | O201: 1 | P201: Equipos e insumos industriales › Soldadura / termofusión | Q201: ANDRITZ es un grupo tecnológico global que ofrece soluciones innovadoras para la industria acuícola. Con más de 180 años de experiencia, actúa como un socio confiable, entregando soluciones integrales desde el análisis de materias primas hasta procesos de alta capacidad como molienda, extrusión, secado y peletización, además de tecnologías de automatización. | S201: No
A202: 201 | D202: ANGELNET | E202: Polonia | H202: AquaSur 2026 | I202: Prospecto | J202: Baja | K202: Nutrir con contenido; sin acción comercial inmediata | L202: AquaSur 2026. Sin contacto publicado. | M202: Proveedor industrial (equipos/insumos) | N202: GA-23 | O202: 1 | P202: Infraestructura marina y equipamiento acuícola › Redes / cabos / fondeo | Q202: Angelnet is a family company which manufactures twisted ropes, braided lines and fishing gear. Angelnet offers ropes for such sectors as fishing, aquaculture, building, industry and many others. Our focus is the production of floatlines and sinking weight down braided and twisted ropes. We also specialize in rigging these ropes for nets by hands or by machinery with splicing and hand-sewing. | S202: No
A203: 202 | D203: ANPHOTEROL | E203: Chile | H203: AquaSur 2026 | I203: Prospecto | J203: Baja | K203: Nutrir con contenido; sin acción comercial inmediata | L203: AquaSur 2026. Sin contacto publicado. | M203: Proveedor industrial (equipos/insumos) | N203: K-18 | O203: 1 | P203: Salud animal, biotecnología y laboratorio › Diagnóstico / laboratorio | Q203: Laboratorio Kasem desarrolla y comercializa soluciones de primeros auxilios orientadas a la protección y cuidado de las personas que trabajan diariamente con sustancias peligrosas. Sus productos están diseñados para la atención inmediata de emergencias químicas, contribuyendo a detener el avance de las quemaduras químicas, destacando entre ellos ANPHOTEROL® como solución especializada. | S203: No
A204: 203 | D204: ANTALIS | E204: Chile | H204: AquaSur 2026 | I204: Prospecto | J204: Baja | K204: Nutrir con contenido; sin acción comercial inmediata | L204: AquaSur 2026. Sin contacto publicado. | M204: Proveedor industrial (equipos/insumos) | N204: D-12 | O204: 1 | P204: Envases, embalaje y materiales › Packaging / materiales | Q204: Antalis forma parte del grupo japonés Kokusai Pulp & Paper, líder mundial en papel, embalaje y comunicación visual. Es el primer distribuidor B2B de papel y embalaje industrial en Europa, Canadá y Latinoamérica. Con sede en París, opera en 31 países, atiende a más de 100.000 clientes y cuenta con 4.000 empleados y 83 centros eco-responsables. | S204: No
A205: 204 | D205: APOLLO - IMPEX | E205: Chile | H205: AquaSur 2026 | I205: Prospecto | J205: Baja | K205: Nutrir con contenido; sin acción comercial inmediata | L205: AquaSur 2026. Sin contacto publicado. | M205: Proveedor industrial (equipos/insumos) | N205: D-54 | O205: 1 | P205: Equipos e insumos industriales › Bombas / válvulas / tuberías | Q205: Fabricacion de clasificadoras de peces y ovas , Filtros rotatorios , Bombas y contadoras de Peces | S205: No
A206: 205 | D206: AQUA PHARMA / AQUATIQ | E206: Chile | H206: AquaSur 2026 | I206: Prospecto | J206: Baja | K206: Nutrir con contenido; sin acción comercial inmediata | L206: AquaSur 2026. Sin contacto publicado. | M206: Proveedor industrial (equipos/insumos) | N206: K-28 | O206: 1 | P206: Finanzas, seguros y leasing › Seguros | Q206: Aqua Pharma es una empresa especializada en soluciones sanitarias y tratamientos para la acuicultura, enfocada en la salud y bienestar de peces y camarones. Ofrece productos y servicios innovadores, seguros y sustentables, apoyando una producción acuícola eficiente y responsable a nivel global. | S206: No
A207: 206 | D207: AQUAFIND | E207: Chile | H207: AquaSur 2026 | I207: Prospecto | J207: Baja | K207: Nutrir con contenido; sin acción comercial inmediata | L207: AquaSur 2026. Sin contacto publicado. | M207: Proveedor industrial (equipos/insumos) | N207: A-30 | O207: 1 | P207: Automatización, robótica y monitoreo › ROV / robótica | Q207: Empresa provedora de equipos de segunda mano o reuso en la industria acuicola en Noruega y Chile. | S207: No
A208: 207 | D208: AQUALABO | E208: Francia | H208: AquaSur 2026 | I208: Prospecto | J208: Baja | K208: Nutrir con contenido; sin acción comercial inmediata | L208: AquaSur 2026. Sin contacto publicado. | M208: Proveedor industrial (equipos/insumos) | N208: A-20 | O208: 1 | P208: Equipos e insumos industriales › Maquinaria / insumos industriales | Q208: Experiencia en el tratamiento del agua Desde el diseño hasta la instalación de sus equipos AQUALABO diseña, fabrica y comercializa una amplia gama de equipos e instrumentos para el control y el análisis del agua. Nuestra filosofía, nuestro valor añadido: el control del agua se vuelve sencillo, económico, innovador y de bajo consumo. | S208: No
A209: 208 | D209: AQUALIFE | E209: Estados Unidos | H209: AquaSur 2026 | I209: Prospecto | J209: Baja | K209: Nutrir con contenido; sin acción comercial inmediata | L209: AquaSur 2026. Sin contacto publicado. | M209: Proveedor industrial (equipos/insumos) | N209: D-43 | O209: 1 | P209: Equipos e insumos industriales › Bombas / válvulas / tuberías | Q209: Magic Valley Heli-Arc is the manufacturer of world-renowned Aqua-Life Products. From the world's #1 rated fish and shrimp transfer or harvesting systems, to the extensive Aqua-Life Fish Pump line offering 37 models of both submersible and non-submersible pumps. Aqua-Life has the solutions to meet the needs of today's fast-growing Aquaculture Industry. | S209: No
... A219: 218 | D219: AZING | E219: Chile | H219: AquaSur 2026 | I219: Prospecto | J219: Baja | K219: Nutrir con contenido; sin acción comercial inmediata | L219: AquaSur 2026. Sin contacto publicado. | M219: Proveedor industrial (equipos/insumos) | N219: G-04 | O219: 1 | P219: Energía, climatización e iluminación › Energía / combustibles / electrificación | Q219: AZ Ingeniería es una empresa especializada en el tratamiento y valorización de subproductos animales. Diseñamos y fabricamos equipos industriales a medida, integrando soluciones de cocción, secado, evaporación y control ambiental con un enfoque en eficiencia energética, sostenibilidad y alto rendimiento operativo. | S219: No
A220: 219 | D220: BANCO SANTANDER | E220: Chile | H220: AquaSur 2026 | I220: Prospecto | J220: Baja | K220: Nutrir con contenido; sin acción comercial inmediata | L220: AquaSur 2026. Sin contacto publicado. | M220: Proveedor industrial (equipos/insumos) | N220: COWORK-P | O220: 1 | P220: Finanzas, seguros y leasing › Banca / servicios financieros | S220: No
A221: 220 | D221: BEKAERT | E221: Chile | H221: AquaSur 2026 | I221: Prospecto | J221: Baja | K221: Nutrir con contenido; sin acción comercial inmediata | L221: AquaSur 2026. Sin contacto publicado. | M221: Proveedor industrial (equipos/insumos) | N221: C-50 | O221: 1 | P221: Transporte y logística › Transporte especializado / grúas | Q221: Bekaert se posiciona como el mayor fabricante de cables de acero del mundo, con fuerte presencia en los sectores de Oil & Gas, Grúas, Minería, Industria y Pesca. Además de cables de acero, Bekaert fabrica eslingas sintéticas, estrobos, lubricantes, advanced cords y cuenta con una división de servicios llamada Ropes 360. | S221: No
A222: 221 | D222: BENCHMARK | E222: Chile | H222: AquaSur 2026 | I222: Prospecto | J222: Baja | K222: Nutrir con contenido; sin acción comercial inmediata | L222: AquaSur 2026. Sin contacto publicado. | M222: Proveedor industrial (equipos/insumos) | N222: M-40 | O222: 1 | P222: Salud animal, biotecnología y laboratorio › Genética / reproducción | Q222: Benchmark Genetics Chile, es parte de Benchmark Genetics global. Empresa líder en la producción de ovas de salmón atlántico en Noruega e Islandia; a su vez, ofrece servicios genéticos a la acuicultura mundial. En Chile, BMK ofrece: Diseño y gestión de programas de reproducción, Servicios de criopreservación, Servicios de genotipificado y Análisis bioeconómicos a la industria acuícola. | S222: No
A223: 222 | D223: BIOCHEMTECH SPA | E223: Chile | H223: AquaSur 2026 | I223: Prospecto | J223: Baja | K223: Nutrir con contenido; sin acción comercial inmediata | L223: AquaSur 2026. Sin contacto publicado. | M223: Proveedor industrial (equipos/insumos) | N223: C-43 | O223: 1 | P223: Agua, ambiente y sostenibilidad › Tratamiento de agua / efluentes | Q223: Biochem Technology es una empresa chilena que ofrece soluciones integrales para el tratamiento y purificación de aguas. Suministra insumos, equipos y proyectos de pretratamiento, DAF, ultrafiltración, nanofiltración, ósmosis inversa, desalación y tratamiento de lodos para plantas de aguas servidas, potables e industriales, con asesoría especializada y enfoque sustentable. | S223: No
A224: 223 | D224: BIOLED SPA | E224: Chile | H224: AquaSur 2026 | I224: Prospecto | J224: Baja | K224: Nutrir con contenido; sin acción comercial inmediata | L224: AquaSur 2026. Sin contacto publicado. | M224: Proveedor industrial (equipos/insumos) | N224: J-22 | O224: 1 | P224: Instituciones, medios y certificación › Certificación / bienestar animal | Q224: Bioled Photoperiod es una empresa tecnológica de gran escala especializada en la técnica del fotoperiodo para la acuicultura. Con base científica sólida, desarrolla sistemas de iluminación LED y control automatizado que optimizan la producción de manera sustentable. Cuenta con certificaciones internacionales y enfoca sus desarrollos y asesorías en el bienestar y la fisiología de los peces. | S224: No
A225: 224 | D225: BIOLIFT | E225: Chile | H225: AquaSur 2026 | I225: Prospecto | J225: Baja | K225: Nutrir con contenido; sin acción comercial inmediata | L225: AquaSur 2026. Sin contacto publicado. | M225: Proveedor industrial (equipos/insumos) | N225: M-37 | O225: 1 | P225: Agua, ambiente y sostenibilidad › Tratamiento de agua / efluentes | Q225: BioLift es una empresa enfocada en la prevención de impactos en los fondos marinos asociados a la acuicultura. Implementa tecnologías para capturar lodos antes de que se acumulen, reduciendo materia orgánica y riesgo de anaerobiosis, evitando INFAs negativas, mejorando el desempeño ambiental de los centros y valorizando los residuos en soluciones energéticas y productivas sostenibles. | S225: No
A226: 225 | D226: BIOSUR COMERCIAL | E226: Chile | H226: AquaSur 2026 | I226: Prospecto | J226: Baja | K226: Nutrir con contenido; sin acción comercial inmediata | L226: AquaSur 2026. Sin contacto publicado. | M226: Proveedor industrial (equipos/insumos) | N226: M-10 | O226: 1 | P226: Salud animal, biotecnología y laboratorio › Diagnóstico / laboratorio | Q226: BIOSUR es una empresa especializada en tratamiento de agua, separación centrífuga y transferencia de calor para industrias y sector sanitario. Ofrecemos ingeniería, servicio técnico, postventa y montaje, acompañando al cliente desde el diagnóstico hasta la operación. | S226: No
A227: 226 | D227: BIOTEC | E227: Chile | H227: AquaSur 2026 | I227: Prospecto | J227: Baja | K227: Nutrir con contenido; sin acción comercial inmediata | L227: AquaSur 2026. Sin contacto publicado. | M227: Proveedor industrial (equipos/insumos) | N227: C-37 | O227: 1 | P227: Servicios empresariales y consultoría › Consultoría / capacitación | Q227: Somos una compañía enfocada en el desarrollo de programas y soluciones Integrales para garantizar la Inocuidad Alimentaria y proteger la Higiene Industrial. Con más de 30 años de experiencia, innovación, acompañamiento constante y calidad técnica, estamos hoy junto a nuestros clientes, en cada una de sus plantas, monitoreando la seguridad de sus productos, procesos, personas e infraestructura. | S227: No
A228: 227 | D228: BOANERGES | E228: Chile | H228: AquaSur 2026 | I228: Prospecto | J228: Baja | K228: Nutrir con contenido; sin acción comercial inmediata | L228: AquaSur 2026. Sin contacto publicado. | M228: Proveedor industrial (equipos/insumos) | N228: H-33 | O228: 1 | P228: Equipos e insumos industriales › Ingeniería / mantenimiento | Q228: Pioneros en Chile desde 2013: Ofrecemos servicios de Mantenimiento Industrial Especializado en el rubro salmonero, fabricamos componentes para tu planta de procesos salmonero de calidad, alta durabilidad, apto a las exigencias sanitarias y de producción. Aseguramos la producción de calidad de tu planta salmonera. | S228: No
A229: 228 | D229: BOMBAS GRUNDFOS CHILE LTDA. | E229: Chile | H229: AquaSur 2026 | I229: Prospecto | J229: Baja | K229: Nutrir con contenido; sin acción comercial inmediata | L229: AquaSur 2026. Sin contacto publicado. | M229: Proveedor industrial (equipos/insumos) | N229: D-27 | O229: 1 | P229: Equipos e insumos industriales › Bombas / válvulas / tuberías | Q229: Grundfos is a global leader in energy-efficient pump solutions, redefining the future of water management. With electronic pump systems, Grundfos ensures high performance and energy efficiency while cutting emissions. In aquaculture, with over 20 years of expertise, our broad range of pumps meets all your needs, whether for seawater, freshwater, reuse, cleaning, or temperature control. | S229: No
...

Sheet Oportunidades
A1: ID oportunidad | B1: ID contacto | C1: Empresa | D1: Necesidad | E1: Solución propuesta | F1: Etapa | G1: Valor estimado | H1: Probabilidad | I1: Próxima acción | J1: Fecha

Sheet Resumen
A1: Evento/Fuente | B1: País | C1: Cantidad
A2: AquaSur 2026 | B2: Chile | C2: =COUNTIFS(Contactos!$H:$H,$A2,Contactos!$E:$E,$B2) -> 422
A3: AquaSur 2026 | B3: Dinamarca | C3: =COUNTIFS(Contactos!$H:$H,$A3,Contactos!$E:$E,$B3) -> 19
A4: AquaSur 2026 | B4: China | C4: =COUNTIFS(Contactos!$H:$H,$A4,Contactos!$E:$E,$B4) -> 18
A5: AquaSur 2026 | B5: Noruega | C5: =COUNTIFS(Contactos!$H:$H,$A5,Contactos!$E:$E,$B5) -> 14
A6: AquaSur 2026 | B6: Estados Unidos | C6: =COUNTIFS(Contactos!$H:$H,$A6,Contactos!$E:$E,$B6) -> 11
A7: AquaSur 2026 | B7: España | C7: =COUNTIFS(Contactos!$H:$H,$A7,Contactos!$E:$E,$B7) -> 5
A8: AquaSur 2026 | B8: Canadá | C8: =COUNTIFS(Contactos!$H:$H,$A8,Contactos!$E:$E,$B8) -> 4
A9: AquaSur 2026 | B9: Brasil | C9: =COUNTIFS(Contactos!$H:$H,$A9,Contactos!$E:$E,$B9) -> 2
A10: AquaSur 2026 | B10: Corea del Sur | C10: =COUNTIFS(Contactos!$H:$H,$A10,Contactos!$E:$E,$B10) -> 2
A11: AquaSur 2026 | B11: India | C11: =COUNTIFS(Contactos!$H:$H,$A11,Contactos!$E:$E,$B11) -> 2
A12: AquaSur 2026 | B12: Italia | C12: =COUNTIFS(Contactos!$H:$H,$A12,Contactos!$E:$E,$B12) -> 2
A13: AquaSur 2026 | B13: Suecia | C13: =COUNTIFS(Contactos!$H:$H,$A13,Contactos!$E:$E,$B13) -> 2
... A26: AquaSur 2026 | B26: Suiza | C26: =COUNTIFS(Contactos!$H:$H,$A26,Contactos!$E:$E,$B26) -> 1
A27: Total | C27: =SUM(C2:C26) -> 517
A29: Segmento SafetyMind | B29: Alta | C29: Media | D29: Baja | E29: Total
A30: Cliente final – productor acuícola | B30: =COUNTIFS(Contactos!$M:$M,$A30,Contactos!$J:$J,B$29) -> 2 | C30: =COUNTIFS(Contactos!$M:$M,$A30,Contactos!$J:$J,C$29) -> 0 | D30: =COUNTIFS(Contactos!$M:$M,$A30,Contactos!$J:$J,D$29) -> 0 | E30: =SUM(B30:D30) -> 2
A31: Cliente potencial – contratista / operación de alto riesgo | B31: =COUNTIFS(Contactos!$M:$M,$A31,Contactos!$J:$J,B$29) -> 21 | C31: =COUNTIFS(Contactos!$M:$M,$A31,Contactos!$J:$J,C$29) -> 0 | D31: =COUNTIFS(Contactos!$M:$M,$A31,Contactos!$J:$J,D$29) -> 0 | E31: =SUM(B31:D31) -> 21
A32: Partner tecnológico / competidor | B32: =COUNTIFS(Contactos!$M:$M,$A32,Contactos!$J:$J,B$29) -> 59 | C32: =COUNTIFS(Contactos!$M:$M,$A32,Contactos!$J:$J,C$29) -> 0 | D32: =COUNTIFS(Contactos!$M:$M,$A32,Contactos!$J:$J,D$29) -> 0 | E32: =SUM(B32:D32) -> 59
A33: Canal / aliado – consultoría SST | B33: =COUNTIFS(Contactos!$M:$M,$A33,Contactos!$J:$J,B$29) -> 18 | C33: =COUNTIFS(Contactos!$M:$M,$A33,Contactos!$J:$J,C$29) -> 0 | D33: =COUNTIFS(Contactos!$M:$M,$A33,Contactos!$J:$J,D$29) -> 0 | E33: =SUM(B33:D33) -> 18
A34: Partner OEM – equipos acuícolas y marinos | B34: =COUNTIFS(Contactos!$M:$M,$A34,Contactos!$J:$J,B$29) -> 0 | C34: =COUNTIFS(Contactos!$M:$M,$A34,Contactos!$J:$J,C$29) -> 28 | D34: =COUNTIFS(Contactos!$M:$M,$A34,Contactos!$J:$J,D$29) -> 0 | E34: =SUM(B34:D34) -> 28
A35: Canal / distribuidor EPP | B35: =COUNTIFS(Contactos!$M:$M,$A35,Contactos!$J:$J,B$29) -> 0 | C35: =COUNTIFS(Contactos!$M:$M,$A35,Contactos!$J:$J,C$29) -> 15 | D35: =COUNTIFS(Contactos!$M:$M,$A35,Contactos!$J:$J,D$29) -> 0 | E35: =SUM(B35:D35) -> 15
A36: Aliado complementario – seguridad | B36: =COUNTIFS(Contactos!$M:$M,$A36,Contactos!$J:$J,B$29) -> 0 | C36: =COUNTIFS(Contactos!$M:$M,$A36,Contactos!$J:$J,C$29) -> 7 | D36: =COUNTIFS(Contactos!$M:$M,$A36,Contactos!$J:$J,D$29) -> 0 | E36: =SUM(B36:D36) -> 7
A37: Aliado complementario – salud | B37: =COUNTIFS(Contactos!$M:$M,$A37,Contactos!$J:$J,B$29) -> 0 | C37: =COUNTIFS(Contactos!$M:$M,$A37,Contactos!$J:$J,C$29) -> 1 | D37: =COUNTIFS(Contactos!$M:$M,$A37,Contactos!$J:$J,D$29) -> 0 | E37: =SUM(B37:D37) -> 1
A38: Institución / gremio / pabellón país | B38: =COUNTIFS(Contactos!$M:$M,$A38,Contactos!$J:$J,B$29) -> 0 | C38: =COUNTIFS(Contactos!$M:$M,$A38,Contactos!$J:$J,C$29) -> 30 | D38: =COUNTIFS(Contactos!$M:$M,$A38,Contactos!$J:$J,D$29) -> 0 | E38: =SUM(B38:D38) -> 30
A39: Proveedor industrial (equipos/insumos) | B39: =COUNTIFS(Contactos!$M:$M,$A39,Contactos!$J:$J,B$29) -> 0 | C39: =COUNTIFS(Contactos!$M:$M,$A39,Contactos!$J:$J,C$29) -> 0 | D39: =COUNTIFS(Contactos!$M:$M,$A39,Contactos!$J:$J,D$29) -> 336 | E39: =SUM(B39:D39) -> 336
A40: Total | B40: =SUM(B30:B39) -> 100 | C40: =SUM(C30:C39) -> 81 | D40: =SUM(D30:D39) -> 336 | E40: =SUM(E30:E39) -> 517
A42: Estado (pipeline) | B42: Cantidad
A43: Prospecto | B43: =COUNTIF(Contactos!$I:$I,A43) -> 517
A44: Contactado | B44: =COUNTIF(Contactos!$I:$I,A44) -> 0
A45: Reunión | B45: =COUNTIF(Contactos!$I:$I,A45) -> 0
A46: Propuesta | B46: =COUNTIF(Contactos!$I:$I,A46) -> 0
A47: Cliente | B47: =COUNTIF(Contactos!$I:$I,A47) -> 0
A48: No interesado | B48: =COUNTIF(Contactos!$I:$I,A48) -> 0
A50: Indicadores | B50: Cantidad
A51: Registros originales | B51: 528
A52: Empresas únicas | B52: =COUNTA(Contactos!$D$2:$D$3000) -> 517
A53: También en Exponor 2026 | B53: =COUNTIF(Contactos!$S$2:$S$3000,"*Exponor*") -> 55
A54: También en ExpoMina 2026 | B54: =COUNTIF(Contactos!$S$2:$S$3000,"*ExpoMina*") -> 8
A55: También en Directorio SSO | B55: =COUNTIF(Contactos!$S$2:$S$3000,"*Directorio*") -> 3
A56: Con 2+ stands | B56: =COUNTIF(Contactos!$O$2:$O$3000,">1") -> 7

Sheet Eventos
A1: Evento | B1: País | C1: Valor para SafetyMind
A2: Directorio SSO 2026 – Cero Accidentes (22.ª ed.) | B2: Perú | C2: Mapa de ~670 proveedores SST en Perú (ver CRM_Directorio_SSO_2026).
A3: ExpoMina Perú 2026 | B3: Perú | C3: Feria minera: mineras, contratistas, OEM, tecnología y proveedores (ver CRM_ExpoMina_2026).
A4: Exponor 2026 (Antofagasta) | B4: Chile | C4: Feria minera del norte de Chile (ver CRM_Exponor_2026).
A5: AquaSur 2026 (Puerto Montt) | B5: Chile | C5: Feria acuícola: salmoneras, contratistas marítimos (buceo, wellboats, astilleros), tecnología acuícola (IA, ROV, IoT) y proveedores; nueva vertical para SafetyMind.
