Workbook

Sheet Contactos
A1: ID | B1: Nombre | C1: Cargo | D1: Empresa | E1: País | F1: Email | G1: LinkedIn | H1: Origen | I1: Estado | J1: Prioridad | K1: Próxima acción | L1: Notas | M1: Segmento SafetyMind | N1: Bloque temático | O1: Tipo presentación | P1: Ponencia | Q1: Co-presentadores | R1: Verificación LinkedIn | S1: Cruce otros CRM
A2: 1 | B2: Andrea Quevedo | C2: Jefe de Transformación Digital y Proyectos | D2: Alpayana | E2: Perú | G2: https://www.linkedin.com/in/andreaquevedos/ | H2: Minería 5.0 2026 – Encuentro de Metalurgia | I2: Prospecto | J2: Alta | K2: Contactar post-ponencia; mapear a Gerente SSO/Operaciones y proponer piloto SafetyMind | L2: Conferencista Minería 5.0 2026 (Encuentro de Metalurgia). Lidera scoop semiautónomo y automatización en planta. | M2: Cliente final – minera | N2: Minería 5.0 | O2: Individual | P2: Wiraq: scoop semiautónomo / Automatización y control de la dosificación de reactivos en flotación / Creadores digitales: formando talento para liderar la transformación en la era de la Minería 5.0 | R2: Coincide con el nombre | S2: No
A3: 2 | B3: Iván Velásquez | C3: Gerente Corporativo de Control de Gestión y Excelencia Operacional | D3: Compañía Minera Lincuna S.A. | E3: Perú | H3: Minería 5.0 2026 – Encuentro de Metalurgia | I3: Prospecto | J3: Alta | K3: Contactar post-ponencia; mapear a Gerente SSO/Operaciones y proponer piloto SafetyMind | L3: Conferencista Minería 5.0 2026 (Encuentro de Metalurgia). | M3: Cliente final – minera | N3: Excelencia operacional | O3: Individual | P3: Nuevo enfoque de gestión de costos en minería y su conexión con la excelencia operacional | R3: Sin LinkedIn | S3: No
A4: 3 | B4: Marcelo Santillana | C4: Director | D4: Compañía Minera Poderosa | E4: Perú | H4: Minería 5.0 2026 – Encuentro de Metalurgia | I4: Prospecto | J4: Alta | K4: Contactar post-ponencia; mapear a Gerente SSO/Operaciones y proponer piloto SafetyMind | L4: Conferencista Minería 5.0 2026 (Encuentro de Metalurgia). Nombre y organización venían invertidos en la fuente. | M4: Cliente final – minera | N4: Excelencia operacional | O4: Individual | P4: Los proyectos en Poderosa | R4: Sin LinkedIn | S4: No
A5: 4 | B5: Ruddy Morales | C5: Superintendente Corporativo de Excelencia | D5: Consorcio Minero Horizonte | E5: Perú | G5: https://www.linkedin.com/in/ruddy-morales-opx/ | H5: Minería 5.0 2026 – Encuentro de Metalurgia | I5: Prospecto | J5: Alta | K5: Contactar post-ponencia; mapear a Gerente SSO/Operaciones y proponer piloto SafetyMind | L5: Conferencista Minería 5.0 2026 (Encuentro de Metalurgia). Hoja de ruta de transformación (caso CMH). Presentación conjunta. | M5: Cliente final – minera | N5: Excelencia operacional | O5: Conjunta | P5: Creando una hoja de ruta para la transformación: caso CMH | Q5: Glasson Fonseca | R5: Coincide con el nombre | S5: No
A6: 5 | B6: Glasson Fonseca | C6: Gerente Corporativo de Transformación | D6: Consorcio Minero Horizonte | E6: Perú | H6: Minería 5.0 2026 – Encuentro de Metalurgia | I6: Prospecto | J6: Alta | K6: Contactar post-ponencia; mapear a Gerente SSO/Operaciones y proponer piloto SafetyMind | L6: Conferencista Minería 5.0 2026 (Encuentro de Metalurgia). Hoja de ruta de transformación (caso CMH). Presentación conjunta. | M6: Cliente final – minera | N6: Excelencia operacional | O6: Conjunta | P6: Creando una hoja de ruta para la transformación: caso CMH | Q6: Ruddy Morales | R6: Sin LinkedIn | S6: No
A7: 6 | B7: David Bayona | C7: Director de Proyectos | D7: Hot Chili Limited | E7: Chile | G7: https://www.linkedin.com/in/david-bayona-inche/ | H7: Minería 5.0 2026 – Encuentro de Metalurgia | I7: Prospecto | J7: Alta | K7: Contactar post-ponencia; mapear a Gerente SSO/Operaciones y proponer piloto SafetyMind | L7: Conferencista Minería 5.0 2026 (Encuentro de Metalurgia). Proyecto Costa Fuego (Chile). | M7: Cliente final – minera | N7: Excelencia operacional | O7: Individual | P7: Inteligencia artificial en la gestión de megaproyectos mineros | R7: Coincide con el nombre | S7: No
A8: 7 | B8: Luis Rojas | C8: Gerente de Tecnologías de Información | D8: Hudbay Perú | E8: Perú | G8: https://www.linkedin.com/in/luiseduardorojas/ | H8: Minería 5.0 2026 – Encuentro de Metalurgia | I8: Prospecto | J8: Alta | K8: Contactar post-ponencia; mapear a Gerente SSO/Operaciones y proponer piloto SafetyMind | L8: Conferencista Minería 5.0 2026 (Encuentro de Metalurgia). | M8: Cliente final – minera | N8: Minería 5.0 | O8: Individual | P8: Cultura digital en la minería: transformando personas, procesos y decisiones | R8: Coincide con el nombre | S8: No
A9: 8 | B9: Jorge Infantes | C9: Superintendente Planta Concentradora | D9: Marcobre | E9: Perú | H9: Minería 5.0 2026 – Encuentro de Metalurgia | I9: Prospecto | J9: Alta | K9: Contactar post-ponencia; mapear a Gerente SSO/Operaciones y proponer piloto SafetyMind | L9: Conferencista Minería 5.0 2026 (Encuentro de Metalurgia). Optimus AI en planta concentradora (Grupo Minsur). Presentación conjunta. | M9: Cliente final – minera | N9: Excelencia operacional | O9: Conjunta | P9: Optimus AI, inteligencia artificial operacional para maximizar la recuperación de cobre fino | Q9: Luis Chacón | R9: Sin LinkedIn | S9: No
A10: 9 | B10: Luis Chacón | C10: Analítica Avanzada | D10: Marcobre | E10: Perú | H10: Minería 5.0 2026 – Encuentro de Metalurgia | I10: Prospecto | J10: Alta | K10: Contactar post-ponencia; mapear a Gerente SSO/Operaciones y proponer piloto SafetyMind | L10: Conferencista Minería 5.0 2026 (Encuentro de Metalurgia). Optimus AI en planta concentradora (Grupo Minsur). Presentación conjunta. | M10: Cliente final – minera | N10: Excelencia operacional | O10: Conjunta | P10: Optimus AI, inteligencia artificial operacional para maximizar la recuperación de cobre fino | Q10: Jorge Infantes | R10: Sin LinkedIn | S10: No
A11: 10 | B11: Andrew Hulme | C11: General Manager & SSE | D11: Sibanye-Stillwater | E11: Sudáfrica | G11: https://www.linkedin.com/in/andrew-hulme-gaicd-09ba3654/ | H11: Minería 5.0 2026 – Encuentro de Metalurgia | I11: Prospecto | J11: Alta | K11: Contactar post-ponencia; mapear a Gerente SSO/Operaciones y proponer piloto SafetyMind | L11: Conferencista Minería 5.0 2026 (Encuentro de Metalurgia). | M11: Cliente final – minera | N11: Excelencia operacional | O11: Individual | P11: Donde la estrategia se encuentra con la ejecución. Cómo maximizar tus activos y procesos mediante la minimización de la variabilidad | R11: Coincide con el nombre | S11: No
A12: 11 | B12: Raúl Benavides | C12: Presidente del Directorio | D12: Sociedad Minera El Brocal S.A.A. | E12: Perú | G12: https://www.linkedin.com/in/raul-benavides-93479450/ | H12: Minería 5.0 2026 – Encuentro de Metalurgia | I12: Prospecto | J12: Alta | K12: Contactar post-ponencia; mapear a Gerente SSO/Operaciones y proponer piloto SafetyMind | L12: Conferencista Minería 5.0 2026 (Encuentro de Metalurgia). PRIORIDAD: ponencia sobre IA para prevenir accidentes (encaje directo con SafetyMind). Grupo Buenaventura. Presentación conjunta. | M12: Cliente final – minera | N12: Excelencia operacional | O12: Conjunta | P12: Aplicaciones de la inteligencia artificial para prevenir accidentes y mejorar la productividad en las operaciones mineras | Q12: Homar Lozano | R12: Coincide con el nombre | S12: No
A13: 12 | B13: Homar Lozano | C13: Co-autor | D13: Sociedad Minera El Brocal S.A.A. | E13: Perú | H13: Minería 5.0 2026 – Encuentro de Metalurgia | I13: Prospecto | J13: Alta | K13: Contactar post-ponencia; mapear a Gerente SSO/Operaciones y proponer piloto SafetyMind | L13: Conferencista Minería 5.0 2026 (Encuentro de Metalurgia). PRIORIDAD: ponencia sobre IA para prevenir accidentes (encaje directo con SafetyMind). Grupo Buenaventura. Presentación conjunta. | M13: Cliente final – minera | N13: Excelencia operacional | O13: Conjunta | P13: Aplicaciones de la inteligencia artificial para prevenir accidentes y mejorar la productividad en las operaciones mineras | Q13: Raúl Benavides | R13: Sin LinkedIn | S13: No
A14: 13 | B14: Terry Williams | C14: Director Ejecutivo | D14: New Project Perú SAC | E14: Perú | H14: Minería 5.0 2026 – Encuentro de Metalurgia | I14: Prospecto | J14: Alta | K14: Inteligencia competitiva: revisar ponencia y oferta; evaluar si es competidor o integrable | L14: Conferencista Minería 5.0 2026 (Encuentro de Metalurgia). IoT-IA para tracking, seguridad activa y control de acceso en minería subterránea: posible competidor. | M14: Competidor / tecnología de seguridad | N14: Minería 5.0 | O14: Individual | P14: Ecosistema IoT–IA para tracking, seguridad activa y control de acceso en minería subterránea | R14: Sin LinkedIn | S14: No
A15: 14 | B15: Vicente Rojas | C15: Gerente Tecnología & IA | D15: Empírica | E15: Perú | G15: https://www.linkedin.com/in/vicente-rojas-ojeda/ | H15: Minería 5.0 2026 – Encuentro de Metalurgia | I15: Prospecto | J15: Media | K15: Explorar integración/alianza (datos de planta, IIoT, analítica) | L15: Conferencista Minería 5.0 2026 (Encuentro de Metalurgia). | M15: Partner tecnológico (IA, IIoT, datos) | N15: Minería 5.0 | O15: Individual | P15: Integración geometalúrgica y analítica avanzada en molienda SAG | R15: Coincide con el nombre | S15: No
A16: 15 | B16: Juan Pablo Rodriguez | C16: Gerente Fundición/Refinería y Balance Metalúrgico | D16: Empírica | E16: Perú | H16: Minería 5.0 2026 – Encuentro de Metalurgia | I16: Prospecto | J16: Media | K16: Explorar integración/alianza (datos de planta, IIoT, analítica) | L16: Conferencista Minería 5.0 2026 (Encuentro de Metalurgia). Misma empresa que Vicente Rojas (unificado "EMPIRICA"/"EMPÍRICA"). | M16: Partner tecnológico (IA, IIoT, datos) | N16: Excelencia operacional | O16: Individual | P16: Aspectos relevantes en el proceso de balance metalúrgico para minerales de cobre | R16: Sin LinkedIn | S16: No
A17: 16 | B17: Leonardo Forero | C17: Investigador IA | D17: MGM Corporate Resources | E17: Perú | H17: Minería 5.0 2026 – Encuentro de Metalurgia | I17: Prospecto | J17: Media | K17: Explorar integración/alianza (datos de planta, IIoT, analítica) | L17: Conferencista Minería 5.0 2026 (Encuentro de Metalurgia). Caso aplicado en Compañía de Minas Buenaventura (deep learning en imágenes geo-mineras). Presentación conjunta. | M17: Partner tecnológico (IA, IIoT, datos) | N17: Minería 5.0 | O17: Conjunta | P17: Aplicación de deep learning para la segmentación semántica de imágenes geo-mineras mediante DeepLabv3+ en Compañía de Minas Buenaventura | Q17: Eloy Paredes, Angela Donaires | R17: Sin LinkedIn | S17: No
A18: 17 | B18: Eloy Paredes | C18: Consultor Senior | D18: MGM Corporate Resources | E18: Perú | H18: Minería 5.0 2026 – Encuentro de Metalurgia | I18: Prospecto | J18: Media | K18: Explorar integración/alianza (datos de planta, IIoT, analítica) | L18: Conferencista Minería 5.0 2026 (Encuentro de Metalurgia). Caso aplicado en Compañía de Minas Buenaventura (deep learning en imágenes geo-mineras). Presentación conjunta. | M18: Partner tecnológico (IA, IIoT, datos) | N18: Minería 5.0 | O18: Conjunta | P18: Aplicación de deep learning para la segmentación semántica de imágenes geo-mineras mediante DeepLabv3+ en Compañía de Minas Buenaventura | Q18: Leonardo Forero, Angela Donaires | R18: Sin LinkedIn | S18: No
A19: 18 | B19: Angela Donaires | C19: Especialista en Deep Learning | D19: MGM Corporate Resources | E19: Perú | H19: Minería 5.0 2026 – Encuentro de Metalurgia | I19: Prospecto | J19: Media | K19: Explorar integración/alianza (datos de planta, IIoT, analítica) | L19: Conferencista Minería 5.0 2026 (Encuentro de Metalurgia). Caso aplicado en Compañía de Minas Buenaventura (deep learning en imágenes geo-mineras). Presentación conjunta. | M19: Partner tecnológico (IA, IIoT, datos) | N19: Minería 5.0 | O19: Conjunta | P19: Aplicación de deep learning para la segmentación semántica de imágenes geo-mineras mediante DeepLabv3+ en Compañía de Minas Buenaventura | Q19: Leonardo Forero, Eloy Paredes | R19: Sin LinkedIn | S19: No
A20: 19 | B20: Angel Navarro | C20: Sales & Configuration Manager | D20: Procetradi SAC | E20: Perú | G20: https://www.linkedin.com/in/angel-alfonso-navarro-la-rosa/ | H20: Minería 5.0 2026 – Encuentro de Metalurgia | I20: Prospecto | J20: Media | K20: Explorar integración/alianza (datos de planta, IIoT, analítica) | L20: Conferencista Minería 5.0 2026 (Encuentro de Metalurgia). Centros integrados de operaciones. | M20: Partner tecnológico (IA, IIoT, datos) | N20: Minería 5.0 | O20: Individual | P20: Centros integrados de operaciones para una minería sin silos de información | R20: Coincide con el nombre | S20: No
A21: 20 | B21: Lucas Torres | C21: Team Lead, Technical Solutions, Mining | D21: Seequent | E21: Perú | G21: https://www.linkedin.com/in/lucas-torres-ortiz-77884494/ | H21: Minería 5.0 2026 – Encuentro de Metalurgia | I21: Prospecto | J21: Media | K21: Explorar integración/alianza (datos de planta, IIoT, analítica) | L21: Conferencista Minería 5.0 2026 (Encuentro de Metalurgia). | M21: Partner tecnológico (IA, IIoT, datos) | N21: Minería 5.0 | O21: Individual | P21: Inteligencia artificial para la geociencia: driver de Seequent y la optimización minera | R21: Coincide con el nombre | S21: No
A22: 21 | B22: Danilo Sturiza | C22: COO y Founder | D22: Smart Mining | E22: Perú | G22: https://www.linkedin.com/in/danilosturiza/ | H22: Minería 5.0 2026 – Encuentro de Metalurgia | I22: Prospecto | J22: Media | K22: Explorar integración/alianza (datos de planta, IIoT, analítica) | L22: Conferencista Minería 5.0 2026 (Encuentro de Metalurgia). IIoT para mantenimiento y espesamiento. Presentación conjunta. | M22: Partner tecnológico (IA, IIoT, datos) | N22: Minería 5.0 | O22: Conjunta | P22: De la condición al desempeño: inteligencia IIoT para mantenimiento y optimización operacional en espesamiento de concentrado | Q22: Claudia Castillo | R22: Coincide con el nombre | S22: No
A23: 22 | B23: Claudia Castillo | C23: Advisor | D23: Smart Mining | E23: Perú | H23: Minería 5.0 2026 – Encuentro de Metalurgia | I23: Prospecto | J23: Media | K23: Explorar integración/alianza (datos de planta, IIoT, analítica) | L23: Conferencista Minería 5.0 2026 (Encuentro de Metalurgia). IIoT para mantenimiento y espesamiento. Presentación conjunta. | M23: Partner tecnológico (IA, IIoT, datos) | N23: Minería 5.0 | O23: Conjunta | P23: De la condición al desempeño: inteligencia IIoT para mantenimiento y optimización operacional en espesamiento de concentrado | Q23: Danilo Sturiza | R23: Sin LinkedIn | S23: No
A24: 23 | B24: Leonel Aguilar | C24: Gerente Posventa Sudamérica | D24: Watergenics SAC | E24: Perú | G24: https://www.linkedin.com/in/leonel-aguilar-681371a7/ | H24: Minería 5.0 2026 – Encuentro de Metalurgia | I24: Prospecto | J24: Media | K24: Explorar integración/alianza (datos de planta, IIoT, analítica) | L24: Conferencista Minería 5.0 2026 (Encuentro de Metalurgia). Monitoreo de agua en tiempo real. | M24: Partner tecnológico (IA, IIoT, datos) | N24: Minería 5.0 | O24: Individual | P24: Monitoreo inteligente de calidad de agua en tiempo real | R24: Coincide con el nombre | S24: No
A25: 24 | B25: Arturo Vásquez | C25: Gerente Regional de Desarrollo de Negocios para Latinoamérica | D25: Epiroc | E25: Perú | G25: https://www.linkedin.com/in/arturovasquez/ | H25: Minería 5.0 2026 – Encuentro de Metalurgia | I25: Prospecto | J25: Media | K25: Explorar alianza con representante local (equipos y talleres) | L25: Conferencista Minería 5.0 2026 (Encuentro de Metalurgia). Empresa también en: Directorio SSO (ID 51); Expo San Juan (ID 117). | M25: Partner OEM – equipos mineros | N25: Minería 5.0 | O25: Individual | P25: Autonomía minera: de la eficiencia operacional a la ventaja competitiva | R25: Verificar (handle genérico) | S25: Directorio SSO (ID 51); Expo San Juan (ID 117)
A26: 25 | B26: Hyder Mamani | C26: Especialista en Circuitos de Molienda | D26: Weir Minerals Perú | E26: Perú | G26: https://www.linkedin.com/in/hyder-mamani-83769617/ | H26: Minería 5.0 2026 – Encuentro de Metalurgia | I26: Prospecto | J26: Media | K26: Explorar alianza con representante local (equipos y talleres) | L26: Conferencista Minería 5.0 2026 (Encuentro de Metalurgia). Empresa también en: Expo San Juan (ID 146). | M26: Partner OEM – equipos mineros | N26: Minería 5.0 | O26: Individual | P26: Agentes de inteligencia artificial aplicados a la validación, simulación y optimización de circuitos de molienda | R26: Coincide con el nombre | S26: Expo San Juan (ID 146)
A27: 26 | B27: Luis Reynafarge | C27: Experto en Excelencia Operacional | D27: Independiente | E27: Perú | G27: https://www.linkedin.com/in/luisreynafarge/ | H27: Minería 5.0 2026 – Encuentro de Metalurgia | I27: Prospecto | J27: Media | K27: Explorar alianza comercial / canal de formación | L27: Conferencista Minería 5.0 2026 (Encuentro de Metalurgia). Consultor Lean + IA multiagente. | M27: Canal / aliado – consultoría y formación | N27: Excelencia operacional | O27: Individual | P27: Cultura Lean e inteligencia artificial multiagente, la evolución del sistema de producción hacia la minería conectada | R27: Coincide con el nombre | S27: No
A28: 27 | B28: Alessandra Morante | C28: CEO | D28: Innovation Academy & Experience | E28: Perú | G28: https://www.linkedin.com/in/alessandramorantepr/ | H28: Minería 5.0 2026 – Encuentro de Metalurgia | I28: Prospecto | J28: Media | K28: Explorar alianza comercial / canal de formación | L28: Conferencista Minería 5.0 2026 (Encuentro de Metalurgia). Organización corregida (la fuente ponía a Alessandra Morante como organización). Presentación conjunta. | M28: Canal / aliado – consultoría y formación | N28: Minería 5.0 | O28: Conjunta | P28: El nuevo mindset minero: anticipar, cuestionar, innovar | Q28: Angela Barreda | R28: Coincide con el nombre | S28: No
A29: 28 | B29: Angela Barreda | C29: Co-presentadora | D29: Innovation Academy & Experience | E29: Perú | H29: Minería 5.0 2026 – Encuentro de Metalurgia | I29: Prospecto | J29: Media | K29: Explorar alianza comercial / canal de formación | L29: Conferencista Minería 5.0 2026 (Encuentro de Metalurgia). Organización corregida (la fuente ponía a Alessandra Morante como organización). Presentación conjunta. | M29: Canal / aliado – consultoría y formación | N29: Minería 5.0 | O29: Conjunta | P29: El nuevo mindset minero: anticipar, cuestionar, innovar | Q29: Alessandra Morante | R29: Sin LinkedIn | S29: No
A30: 29 | B30: Ivan Quintanilla | C30: Director | D30: Supply Talent Consulting | E30: Perú | H30: Minería 5.0 2026 – Encuentro de Metalurgia | I30: Prospecto | J30: Media | K30: Explorar alianza comercial / canal de formación | L30: Conferencista Minería 5.0 2026 (Encuentro de Metalurgia). Título de la ponencia venía truncado en la fuente; corregido desde el texto original. | M30: Canal / aliado – consultoría y formación | N30: Excelencia operacional | O30: Individual | P30: Modelo de expediting "on time" basado en aprendizaje automático para la cadena de suministro minera | R30: Sin LinkedIn | S30: No
A31: 30 | B31: Carlos Calderón | C31: Director de la Academia de IA, Datos y Ciencias de la Computación | D31: UTEC | E31: Perú | G31: https://www.linkedin.com/in/carloscalderon/ | H31: Minería 5.0 2026 – Encuentro de Metalurgia | I31: Prospecto | J31: Media | K31: Vincular para I+D, casos de estudio o validación académica | L31: Conferencista Minería 5.0 2026 (Encuentro de Metalurgia). | M31: Academia / investigación | N31: Minería 5.0 | O31: Individual | P31: Robótica e IA física para el mundo empresarial: al borde de una invasión robótica en todos los rincones del planeta | R31: Verificar (handle genérico) | S31: No
A32: 31 | B32: Thierry de Saint Pierre | C32: Profesor investigador | D32: Universidad San Sebastián | E32: Chile | G32: https://www.linkedin.com/in/thierry-de-saint-pierre-04149a7/ | H32: Minería 5.0 2026 – Encuentro de Metalurgia | I32: Prospecto | J32: Media | K32: Vincular para I+D, casos de estudio o validación académica | L32: Conferencista Minería 5.0 2026 (Encuentro de Metalurgia). Dr.; nombre y organización venían invertidos en la fuente. | M32: Academia / investigación | N32: Minería 5.0 | O32: Individual | P32: Un framework para la inteligencia artificial en minería | R32: Coincide con el nombre | S32: No
A33: 32 | B33: Fernando Velásquez | C33: Gerente General | D33: Feedback Economic Investments and B… | E33: Perú | G33: https://www.linkedin.com/in/fernandovelasquez/ | H33: Minería 5.0 2026 – Encuentro de Metalurgia | I33: Prospecto | J33: Baja | K33: Mantener en red (posible champion o talento) | L33: Conferencista Minería 5.0 2026 (Encuentro de Metalurgia). Nombre de la organización viene truncado en la fuente. Tema blockchain/tokenización (fuera de foco). | M33: Profesional independiente / talento | N33: Minería 5.0 | O33: Individual | P33: TMC 5.0: arquitectura híbrida de IA y blockchain para tokenización y verificación de activos mineros | R33: Verificar (handle genérico) | S33: No
A34: 33 | B34: Martin Miranda | C34: Asistente de Supervisor General de Mantenimiento Eléctrico Mina | D34: Investigador independiente | E34: Perú | H34: Minería 5.0 2026 – Encuentro de Metalurgia | I34: Prospecto | J34: Baja | K34: Mantener en red (posible champion o talento) | L34: Conferencista Minería 5.0 2026 (Encuentro de Metalurgia). Trabaja en mina; desarrolló visión artificial para conteo de camiones: posible champion interno. | M34: Profesional independiente / talento | N34: Minería 5.0 | O34: Individual | P34: Mine Vision AI: visión artificial para el conteo automático de camiones en chancado primario, sin inversión adicional en hardware ni licencias | R34: Sin LinkedIn | S34: No
A35: 34 | B35: Diego Rey | C35: Investigador independiente | D35: Investigador independiente | E35: Perú | H35: Minería 5.0 2026 – Encuentro de Metalurgia | I35: Prospecto | J35: Baja | K35: Mantener en red (posible champion o talento) | L35: Conferencista Minería 5.0 2026 (Encuentro de Metalurgia). Predicción de fallas de motor de camión minero. | M35: Profesional independiente / talento | N35: Excelencia operacional | O35: Individual | P35: Diseño de un sistema de predicción de fallas de motor de camión minero basado en algoritmos de aprendizaje | R35: Sin LinkedIn | S35: No

Sheet Oportunidades
A1: ID oportunidad | B1: ID contacto | C1: Empresa | D1: Necesidad | E1: Solución propuesta | F1: Etapa | G1: Valor estimado | H1: Probabilidad | I1: Próxima acción | J1: Fecha

Sheet Resumen
A1: Segmento SafetyMind | B1: Alta | C1: Media | D1: Baja | E1: Total
A2: Cliente final – minera | B2: =COUNTIFS(Contactos!$M:$M,$A2,Contactos!$J:$J,B$1) -> 12 | C2: =COUNTIFS(Contactos!$M:$M,$A2,Contactos!$J:$J,C$1) -> 0 | D2: =COUNTIFS(Contactos!$M:$M,$A2,Contactos!$J:$J,D$1) -> 0 | E2: =SUM(B2:D2) -> 12
A3: Competidor / tecnología de seguridad | B3: =COUNTIFS(Contactos!$M:$M,$A3,Contactos!$J:$J,B$1) -> 1 | C3: =COUNTIFS(Contactos!$M:$M,$A3,Contactos!$J:$J,C$1) -> 0 | D3: =COUNTIFS(Contactos!$M:$M,$A3,Contactos!$J:$J,D$1) -> 0 | E3: =SUM(B3:D3) -> 1
A4: Partner tecnológico (IA, IIoT, datos) | B4: =COUNTIFS(Contactos!$M:$M,$A4,Contactos!$J:$J,B$1) -> 0 | C4: =COUNTIFS(Contactos!$M:$M,$A4,Contactos!$J:$J,C$1) -> 10 | D4: =COUNTIFS(Contactos!$M:$M,$A4,Contactos!$J:$J,D$1) -> 0 | E4: =SUM(B4:D4) -> 10
A5: Partner OEM – equipos mineros | B5: =COUNTIFS(Contactos!$M:$M,$A5,Contactos!$J:$J,B$1) -> 0 | C5: =COUNTIFS(Contactos!$M:$M,$A5,Contactos!$J:$J,C$1) -> 2 | D5: =COUNTIFS(Contactos!$M:$M,$A5,Contactos!$J:$J,D$1) -> 0 | E5: =SUM(B5:D5) -> 2
A6: Canal / aliado – consultoría y formación | B6: =COUNTIFS(Contactos!$M:$M,$A6,Contactos!$J:$J,B$1) -> 0 | C6: =COUNTIFS(Contactos!$M:$M,$A6,Contactos!$J:$J,C$1) -> 4 | D6: =COUNTIFS(Contactos!$M:$M,$A6,Contactos!$J:$J,D$1) -> 0 | E6: =SUM(B6:D6) -> 4
A7: Academia / investigación | B7: =COUNTIFS(Contactos!$M:$M,$A7,Contactos!$J:$J,B$1) -> 0 | C7: =COUNTIFS(Contactos!$M:$M,$A7,Contactos!$J:$J,C$1) -> 2 | D7: =COUNTIFS(Contactos!$M:$M,$A7,Contactos!$J:$J,D$1) -> 0 | E7: =SUM(B7:D7) -> 2
A8: Profesional independiente / talento | B8: =COUNTIFS(Contactos!$M:$M,$A8,Contactos!$J:$J,B$1) -> 0 | C8: =COUNTIFS(Contactos!$M:$M,$A8,Contactos!$J:$J,C$1) -> 0 | D8: =COUNTIFS(Contactos!$M:$M,$A8,Contactos!$J:$J,D$1) -> 3 | E8: =SUM(B8:D8) -> 3
A9: Total | B9: =SUM(B2:B8) -> 13 | C9: =SUM(C2:C8) -> 18 | D9: =SUM(D2:D8) -> 3 | E9: =SUM(E2:E8) -> 34
A11: Indicadores | B11: Cantidad
A12: Filas en archivo original | B12: 27
A13: Personas (tras separar presentaciones conjuntas) | B13: =COUNTA(Contactos!$B$2:$B$500) -> 34
A14: Organizaciones únicas | B14: =SUMPRODUCT(1/COUNTIF(Contactos!$D$2:$D$35,Contactos!$D$2:$D$35)) -> 25
A15: Con LinkedIn | B15: =COUNTIF(Contactos!$G$2:$G$500,"?*") -> 18
A16: LinkedIn a verificar | B16: =COUNTIF(Contactos!$R$2:$R$500,"Verificar*") -> 3
A17: Contactos de empresas ya presentes en otros CRM | B17: =COUNTIF(Contactos!$S$2:$S$500,"*(ID*") -> 2

Sheet Log depuración
A1: Fila origen | B1: Corrección | C1: Valor original | D1: Valor final
A2: 2 | B2: Fila marcada para revisión (RequiereRevision=Sí) | C2: Dr. Thierry de Saint Pierre | D2: Corregida: nombre y organización estaban invertidos
A3: 2 | B3: Organización normalizada | C3: Dr. Thierry de Saint Pierre | D3: Universidad San Sebastián
A4: 4 | B4: Organización normalizada | C4: EPIROC | D4: Epiroc
A5: 5 | B5: Organización normalizada | C5: HUDBAY PERÚ | D5: Hudbay Perú
A6: 6 | B6: Fila marcada para revisión (RequiereRevision=Sí) | C6: Angela Barreda | D6: Separada en 2 contactos: Alessandra Morante, Angela Barreda
A7: 6 | B7: Organización normalizada | C7: Alessandra Morante | D7: Innovation Academy & Experience
A8: 7 | B8: Fila marcada para revisión (RequiereRevision=Sí) | C8: Danilo Sturiza | Claudia Castillo | D8: Separada en 2 contactos: Danilo Sturiza, Claudia Castillo
A9: 7 | B9: Organización normalizada | C9: SMART MINING | D9: Smart Mining
A10: 8 | B10: Organización normalizada | C10: EMPIRICA | D10: Empírica
A11: 9 | B11: Organización normalizada | C11: INVESTIGADOR INDEPENDIENTE | D11: Investigador independiente
A12: 10 | B12: Organización normalizada | C12: NEW PROJECT PERU SAC | D12: New Project Perú SAC
A13: 11 | B13: Organización normalizada | C13: PROCETRADI S.A.C. | D13: Procetradi SAC
... A36: 28 | B36: Organización normalizada | C36: SUPPLY TALENT CONSULTING | D36: Supply Talent Consulting

Sheet Eventos
A1: Evento | B1: País | C1: Valor para SafetyMind
A2: Minería 5.0 2026 – Encuentro de Metalurgia | B2: Perú | C2: Conferencistas sobre IA, IIoT y excelencia operacional en minería: tomadores de decisión de mineras peruanas (El Brocal, Marcobre, CMH, Poderosa, Alpayana, Hudbay, Lincuna) y proveedores tecnológicos. El Brocal presenta IA para prevenir accidentes.
